Workbook
Name \0: #REF!
Name \01: #REF!
Name \A: #REF!
Name \A1: #REF!
Name \B: #REF!
Name \B: #REF!
Name \c: #REF!
Name \ddefrgfre: #REF!
Name \e: #REF!
Name \I: #REF!
Name \NOTES: #N/A
Name \P: #REF!
Name \P: #REF!
Name \Q: #REF!
Name \Q: #REF!
Name \s: #REF!
Name \v: #REF!
Name \X: #REF!
Name \z: #REF!
Name ________________pl11: 'P&L-Budget 2025'!________________pl11
Name ________________pl11: #N/A
Name _____________pl11: 'P&L-Budget 2025'!_____________pl11
Name _____________pl11: #N/A
Name ____________pl11: 'P&L-Budget 2025'!____________pl11
Name ____________pl11: #N/A
Name ___________pl11: 'P&L-Budget 2025'!___________pl11
Name ___________pl11: #N/A
Name ________ADD1: #REF!
Name ________ADD1: #REF!
Name ________ADD2: #REF!
Name ________ADD2: #REF!
Name ________ANX8: #REF!
Name ________pg3: #REF!
Name ________pg5: #REF!
Name ________pg7: #REF!
Name ________pg9: #REF!
Name ________SS96: #REF!
Name _______ADD1: #REF!
Name _______ADD2: #REF!
Name _______ANX8: #REF!
Name _______COL04: #N/A
Name _______COL07: #N/A
Name _______eva97: #REF!
Name _______eva97: #REF!
Name _______fcf97: #REF!
Name _______fcf97: #REF!
Name _______mva97: #REF!
Name _______pg3: #REF!
Name _______pg3: #REF!
Name _______pg5: #REF!
Name _______pg5: #REF!
Name _______pg7: #REF!
Name _______pg7: #REF!
Name _______pg9: #REF!
Name _______pg9: #REF!
Name _______roe97: #REF!
Name _______SCH1: #REF!
Name _______SCH10: #REF!
Name _______SCH13: #REF!
Name _______SCH3: #REF!

Sheet SSC Recharge Summary
A1: India Shared Services
A2: 45658 | B2: January, 2025 | D2: 1 | E2: =3+1+7 -> 11 | F2: 1 | G2: 30 | H2: 3 | I2: 3 | J2: =1+1 -> 2 | K2: 15 | L2: 17 | M2: 1 | N2: =18+9 -> 27 | O2: =13+13+1 -> 27 | P2: 1 | Q2: 4 | R2: =1+1 -> 2 | S2: =4+3 -> 7 | T2: 1 | U2: =1+1+2 -> 4 | V2: 1 | W2: =1+1 -> 2 | X2: =2+2+3 -> 7 | Y2: =4+2+7 -> 13 | Z2: 4
D3: CMI | E3: CMI | F3: CMI | N3: GCC +Jibe | R3: Germany | T3: 13th Floor
B4: Business Unit Name | C4: Expense Type | D4: Crew Management | E4: Cruise Management | F4: Accounts | G4: Accounts | H4: Admin | I4: Agency Services | J4: Commercial | K4: Consultancy Services | L4: Environmental Compliance | M4: Environmental Compliance | N4: IT | O4: Procurement | P4: Procurement | Q4: Ship Management | R4: Ship Management | S4: Ship Management | T4: Ship Management | U4: Ship Management | V4: Ship Management | W4: Ship Management | X4: Ship Management | Y4: Ship Management | Z4: Ship Management | AA4: Technical Services | AB4: Ship Management | AC4: Ship Management | AD4: Actual
B5: Division Name | D5: Group Marine HR | E5: Miami Ship Management | F5: CMI Accounts Payables | G5: Fleet Accounts | H5: Administration | I5: Agency Hub | J5: Commercial | K5: Fleet Performance | L5: Carbon Emission Services | M5: Other Environmental Compliance | N5: Group IT | O5: Galleymasters | P5: Sourcing | Q5: Antwerp Dry | R5: Goes Dry | S5: Group Operations | T5: Group Shared Service Center | U5: Hamburg Dry | V5: Hong Kong Dry 1 | W5: JV Ardmore | X5: Singapore Dry | Y5: Singapore Tanker 1 | Z5: Singapore Tanker 2 | AA5: AE Technical Services | AB5: Hong Kong Dry 2 | AC5: Hong Kong Dry 3 | AD5: Total
A7: A | B7: PERSONNEL EXPENSES
B8: Salaries & Wages | C8: Fixed | D8: 6313.72 | E8: 16347.8 | F8: 1643.79 | G8: 29043.29 | H8: 2239.97 | I8: 2256.14 | J8: 7056.17 | K8: 39208.36 | L8: 17844.41 | M8: 4645.25 | N8: 36370.33 | O8: 20535.24 | P8: 3422.24 | Q8: 6549.82 | R8: 1316.03 | S8: 14282.4 | T8: 7330.55 | U8: 3505.1 | V8: 1625.39 | W8: 6195.08 | X8: 15528.55 | Y8: 24979.43 | Z8: 4581.77 | AA8: 826.95 | AB8: 0 | AC8: 0 | AD8: =SUM(D8:AA8) -> 273647.78
B9: Provision for Bonus, Leave & Other Employment Costs | C9: Fixed | D9: 483.74 | E9: 1252.5 | F9: 125.94 | G9: 2233.66 | H9: 171.64 | I9: 172.87 | J9: 540.61 | K9: 3055.21 | L9: 653.74 | M9: 170.33 | N9: 2780.99 | O9: 1596.5 | P9: 262.21 | Q9: 434.51 | R9: 81.59 | S9: 1094.27 | T9: 86.89 | U9: 377.45 | V9: 124.52 | W9: 444.51 | X9: 1198.53 | Y9: 1765.18 | Z9: 626.76 | AA9: 30.32 | AB9: 0 | AC9: 0 | AD9: =SUM(D9:AA9) -> 19764.47
B10: Consultants & Contractors | C10: Fixed | D10: 0 | E10: 0 | F10: 0 | G10: 0 | H10: 0 | I10: 0 | J10: 0 | K10: 0 | L10: 0 | M10: -608.36 | N10: 3344.15 | O10: 0 | P10: 0 | Q10: 0 | R10: 0 | S10: 655.35 | T10: 0 | U10: 0 | V10: 0 | W10: 0 | X10: 0 | Y10: 0 | Z10: 0 | AA10: 0 | AB10: 0 | AC10: 0 | AD10: =SUM(D10:AA10) -> 3391.14
B11: Pension Fund & Social Securities | C11: Fixed | D11: 434.26 | E11: 1017.43 | F11: 94.83 | G11: 1814.75 | H11: 130.79 | I11: 131.66 | J11: 474.57 | K11: 2634.98 | L11: 1247.53 | M11: 349.29 | N11: 2369.94 | O11: 1272.76 | P11: 235.76 | Q11: 431.96 | R11: 79.6 | S11: 945.66 | T11: 522.85 | U11: 195.02 | V11: 93.81 | W11: 422.37 | X11: 1027.41 | Y11: 1671.28 | Z11: 235.91 | AA11: 52.55 | AB11: 0 | AC11: 0 | AD11: =SUM(D11:AA11) -> 17886.97
B12: Staff Allowances & Benefits | C12: Fixed | D12: 36.52 | E12: 1445.56 | F12: 43.99 | G12: 1319.61 | H12: 109.52 | I12: 109.52 | J12: 73.03 | K12: 547.64 | L12: 620.65 | M12: 36.52 | N12: 985.74 | O12: 985.76 | P12: 36.52 | Q12: 146.04 | R12: 73.03 | S12: 255.56 | T12: 36.52 | U12: 146.04 | V12: 36.52 | W12: 73.03 | X12: 255.54 | Y12: 474.61 | Z12: 146.04 | AA12: 36.52 | AB12: 0 | AC12: 0 | AD12: =SUM(D12:AA12) -> 8030.03
B13: Medical Expenses | C13: Variable | D13: 0 | E13: 0 | F13: 0 | G13: 0 | H13: 0 | I13: 0 | J13: 0 | K13: 0 | L13: 0 | M13: 0 | N13: 0 | O13: 0 | P13: 0 | Q13: 0 | R13: 0 | S13: 0 | T13: 0 | U13: 0 | V13: 0 | W13: 0 | X13: 0 | Y13: 0 | Z13: 0 | AA13: 0 | AB13: 0 | AC13: 0 | AD13: =SUM(D13:AA13) -> 0
B14: Staff Recruitment / Relocation | C14: Variable | D14: -0.45 | E14: -5.01 | F14: -0.46 | G14: -13.66 | H14: -1.37 | I14: -1.37 | J14: -0.9 | K14: 24.79 | L14: -7.74 | M14: -0.45 | N14: -1.84 | O14: -12.28 | P14: -0.45 | Q14: -1.82 | R14: 9.53 | S14: -3.19 | T14: 348.58 | U14: 8.63 | V14: -0.45 | W14: -0.9 | X14: -3.18 | Y14: 14.96 | Z14: -1.82 | AA14: -0.45 | AB14: 0 | AC14: 0 | AD14: =SUM(D14:AA14) -> 348.7
B15: Staff Functions | C15: Variable | D15: 37.57 | E15: 413.36 | F15: 37.58 | G15: 1127.39 | H15: 112.74 | I15: 112.74 | J15: 75.14 | K15: 563.68 | L15: 638.84 | M15: 37.57 | N15: 1014.7 | O15: 1014.63 | P15: 37.57 | Q15: 150.32 | R15: 75.14 | S15: 263.06 | T15: 37.57 | U15: 150.3 | V15: 37.57 | W15: 75.14 | X15: 263.04 | Y15: 488.53 | Z15: 150.32 | AA15: 37.57 | AB15: 0 | AC15: 0 | AD15: =SUM(D15:AA15) -> 6952.07
B16: Course & Training | C16: Variable | D16: 0 | E16: 0 | F16: 0 | G16: 0 | H16: 0 | I16: 0 | J16: 0 | K16: 0 | L16: 0 | M16: 0 | N16: 1876.8 | O16: 0 | P16: 0 | Q16: 0 | R16: 0 | S16: 0 | T16: 0 | U16: 0 | V16: 0 | W16: 0 | X16: 0 | Y16: 0 | Z16: 0 | AA16: 0 | AB16: 0 | AC16: 0 | AD16: =SUM(D16:AA16) -> 1876.8
B17: Joint Venture Personnel Cost Recharges | C17: Fixed | D17: 0 | E17: 0 | F17: 0 | G17: 0 | H17: 0 | I17: 0 | J17: 0 | K17: 0 | L17: 0 | M17: 0 | N17: 0 | O17: 0 | P17: 0 | Q17: 0 | R17: 0 | S17: 0 | T17: 0 | U17: 0 | V17: 0 | W17: 0 | X17: 0 | Y17: 0 | Z17: 0 | AA17: 0 | AB17: 0 | AC17: 0 | AD17: =SUM(D17:AA17) -> 0
B18: Intra-group Personnel Cost Recharges | C18: Fixed | D18: 0 | E18: 0 | F18: 0 | G18: 0 | H18: 0 | I18: 0 | J18: 0 | K18: 0 | L18: 0 | M18: 0 | N18: 0 | O18: 0 | P18: 0 | Q18: 0 | R18: 0 | S18: 0 | T18: 0 | U18: 0 | V18: 0 | W18: 0 | X18: 0 | Y18: 0 | Z18: 0 | AA18: 0 | AB18: 0 | AC18: 0 | AD18: =SUM(D18:AA18) -> 0
AD19: =SUM(AD8:AD18) -> 331897.96
A20: B | B20: OFFICE EXPENSES
B21: Rent - Depreciation | C21: Fixed | D21: =+working!C8 -> 131.16383 | E21: =+working!D8 -> 1442.8021 | F21: =+working!E8 -> 131.16383 | G21: =+working!F8 -> 3934.9148 | H21: =+working!G8 -> 393.49148 | I21: =+working!H8 -> 393.49148 | J21: =+working!I8 -> 262.32765 | K21: =+working!J8 -> 1967.4574 | ... Z21: =+working!Y8 -> 524.6553 | AA21: 124.36981 | AB21: 0 | AC21: 0 | AD21: =SUM(D21:AA21) -> 24127.35
B22: Rent - Lease Interest | C22: Fixed | D22: 0 | E22: 0 | F22: 0 | G22: 0 | H22: 0 | I22: 0 | J22: 0 | K22: 0 | L22: 0 | M22: 0 | N22: 0 | O22: 0 | P22: 0 | Q22: 0 | R22: 0 | S22: 0 | T22: 0 | U22: 0 | V22: 0 | W22: 0 | X22: 0 | Y22: 0 | Z22: 0 | AA22: 0 | AB22: 0 | AC22: 0 | AD22: =SUM(D22:AA22) -> 0
B23: Rates & Management Fees | C23: Fixed | D23: 15.58 | E23: 171.38 | F23: 15.58 | G23: 467.47 | H23: 46.73 | I23: 46.73 | J23: 31.16 | K23: 384.51 | L23: 264.88 | M23: 15.58 | N23: 420.6 | O23: 420.71 | P23: 0 | Q23: 62.3 | R23: 31.16 | S23: 109.04 | T23: 4098.63 | U23: 62.31 | V23: 15.58 | W23: 31.16 | X23: 109.05 | Y23: 202.53 | Z23: 62.3 | AA23: 15.58 | AB23: 0 | AC23: 0 | AD23: =SUM(D23:AA23) -> 7100.55
B24: Light & Power | C24: Fixed | D24: 5.88 | E24: 64.75 | F24: 5.88 | G24: 176.49 | H24: 17.67 | I24: 17.67 | J24: 11.76 | K24: 88.3 | L24: 100.1 | M24: 5.88 | N24: 158.93 | O24: 158.93 | P24: 0 | Q24: 23.54 | R24: 11.76 | S24: 41.2 | T24: 342.85 | U24: 23.54 | V24: 5.88 | W24: 11.76 | X24: 41.21 | Y24: 76.51 | Z24: 23.54 | AA24: 5.88 | AB24: 0 | AC24: 0 | AD24: =SUM(D24:AA24) -> 1419.91
B25: Office Supplies & Cleaning | C25: Variable | D25: 8.04 | E25: 88.46 | F25: 8.05 | G25: 241.37 | H25: 24.13 | I25: 24.13 | J25: 16.08 | K25: 120.65 | L25: 136.72 | M25: 8.04 | N25: 217.14 | O25: 217.13 | P25: 0 | Q25: 32.17 | R25: 16.08 | S25: 56.29 | T25: 8.04 | U25: 32.15 | V25: 8.04 | W25: 16.08 | X25: 56.28 | Y25: 104.54 | Z25: 32.17 | AA25: 8.04 | AB25: 0 | AC25: 0 | AD25: =SUM(D25:AA25) -> 1479.82
B26: Archive Storage / Warehouse | C26: Fixed | D26: 0.56 | E26: 6.14 | F26: 0.56 | G26: 16.83 | H26: 1.67 | I26: 1.67 | J26: 1.11 | K26: 8.39 | L26: 9.5 | M26: 0.56 | N26: 15.08 | O26: 15.08 | P26: 0 | Q26: 2.23 | R26: 1.11 | S26: 3.9 | T26: 0.56 | U26: 2.23 | V26: 0.56 | W26: 1.11 | X26: 3.9 | Y26: 7.25 | Z26: 2.23 | AA26: 0.56 | AB26: 0 | AC26: 0 | AD26: =SUM(D26:AA26) -> 102.79
B27: Office Repairs & Maintenance | C27: Fixed | D27: 2.76 | E27: 30.36 | F27: 2.76 | G27: 82.73 | H27: 8.28 | I27: 8.28 | J27: 5.52 | K27: 37.92 | L27: 46.87 | M27: 2.76 | N27: 74.49 | O27: 74.49 | P27: 0 | Q27: 11.04 | R27: 5.52 | S27: 19.32 | T27: 2.76 | U27: 11.03 | V27: 2.53 | W27: 5.52 | X27: 19.3 | Y27: 35.87 | Z27: 11.04 | AA27: 2.76 | AB27: 0 | AC27: 0 | AD27: =SUM(D27:AA27) -> 503.91
B28: Intra-group rental cost recharges | C28: Fixed | D28: 61.71 | E28: 678.76 | F28: 61.7 | G28: 1851.08 | H28: 185.12 | I28: 185.12 | J28: 123.42 | K28: 925.58 | L28: 1048.99 | M28: 61.71 | N28: 1666.04 | O28: 1666.05 | P28: 0 | Q28: 246.82 | R28: 123.42 | S28: 431.93 | T28: 61.71 | U28: 246.83 | V28: 61.71 | W28: 123.42 | X28: 431.93 | Y28: 802.16 | Z28: 246.82 | AA28: 61.71 | AB28: 0 | AC28: 0 | AD28: =SUM(D28:AA28) -> 11353.74
AD29: =SUM(AD21:AD28) -> 46088.07
A30: C | B30: ADMINISTRATIVE EXPENSES
B31: IT - Software & Applications | C31: Variable | D31: 42.96 | E31: 472.54 | F31: 42.95 | G31: 1288.59 | H31: 128.87 | I31: 128.87 | J31: 85.93 | K31: 644.36 | L31: 730.26 | M31: 42.96 | N31: 1159.84 | O31: 1159.87 | P31: 42.96 | Q31: 171.84 | R31: 85.93 | S31: 300.71 | T31: 42.96 | U31: 171.84 | V31: 42.96 | W31: 85.93 | X31: 300.68 | Y31: 558.45 | Z31: 171.84 | AA31: 42.96 | AB31: 0 | AC31: 0 | AD31: =SUM(D31:AA31) -> 7947.06
B32: IT - Communications | C32: Variable | D32: 22.55 | E32: 248.14 | F32: 23.57 | G32: 707.2 | H32: 76.75 | I32: 67.66 | J32: 45.1 | K32: 175.33 | L32: 392.97 | M32: 22.55 | N32: 690.99 | O32: 641.24 | P32: -6.96 | Q32: 90.22 | R32: 45.1 | S32: 157.88 | T32: 22.55 | U32: 90.2 | V32: 11.68 | W32: 45.1 | X32: 157.86 | Y32: 293.25 | Z32: 90.22 | AA32: 22.55 | AB32: 0 | AC32: 0 | AD32: =SUM(D32:AA32) -> 4133.7
B33: IT - IT Services | C33: Variable | D33: 3.33 | E33: 36.61 | F33: 3.32 | G33: 99.73 | H33: 9.99 | I33: 9.99 | J33: 6.66 | K33: 9.56 | L33: 56.57 | M33: 3.33 | N33: 459.3 | O33: 89.86 | P33: 0.64 | Q33: 13.32 | R33: 6.66 | S33: 23.3 | T33: 3.33 | U33: 13.32 | V33: 0.64 | W33: 6.66 | X33: 23.3 | Y33: 43.27 | Z33: 13.32 | AA33: 3.33 | AB33: 0 | AC33: 0 | AD33: =SUM(D33:AA33) -> 939.34
B34: IT - Network & Infrastructure Services | C34: Variable | D34: 0 | E34: 0 | F34: 0 | G34: 0 | H34: 0 | I34: 0 | J34: 0 | K34: 0 | L34: 0 | M34: 0 | N34: 0 | O34: 0 | P34: 0 | Q34: 0 | R34: 0 | S34: 0 | T34: 0 | U34: 0 | V34: 0 | W34: 0 | X34: 0 | Y34: 0 | Z34: 0 | AA34: 0 | AB34: 0 | AC34: 0 | AD34: =SUM(D34:AA34) -> 0
B35: Insurance | C35: Fixed | D35: 0.26 | E35: 2.77 | F35: 0.25 | G35: 7.51 | H35: 0.75 | I35: 0.75 | J35: 0.51 | K35: 3.78 | L35: 4.29 | M35: 0.26 | N35: 6.82 | O35: 6.82 | P35: 0 | Q35: 1.01 | R35: 0.51 | S35: 1.76 | T35: 114.91 | U35: 1.02 | V35: 0.26 | W35: 0.51 | X35: 1.77 | Y35: 3.28 | Z35: 1.01 | AA35: 0.26 | AB35: 0 | AC35: 0 | AD35: =SUM(D35:AA35) -> 161.07
B36: Marketing, Branding & Communications | C36: Variable | D36: 0 | E36: 0 | F36: 0 | G36: 0 | H36: 0 | I36: 0 | J36: 0 | K36: 0 | L36: 0 | M36: 0 | N36: 0 | O36: 0 | P36: 0 | Q36: 0 | R36: 0 | S36: 0 | T36: 0 | U36: 0 | V36: 0 | W36: 0 | X36: 0 | Y36: 0 | Z36: 0 | AA36: 0 | AB36: 0 | AC36: 0 | AD36: =SUM(D36:AA36) -> 0
B37: Overseas Travelling | C37: Variable | D37: 2757.23 | E37: 0 | F37: 0 | G37: 0 | H37: 0 | I37: 0 | J37: 0 | K37: 673.8 | L37: 0 | M37: 0 | N37: 0 | O37: 0 | P37: 0 | Q37: 0 | R37: 0 | S37: 0 | T37: 2970.37 | U37: 0 | V37: 384.24 | W37: 0 | X37: 0 | Y37: 62.15 | Z37: 0 | AA37: 0 | AB37: 0 | AC37: 0 | AD37: =SUM(D37:AA37) -> 6847.79
B38: Local Travelling | C38: Variable | D38: 21.39 | E38: 594.86 | F38: 18.25 | G38: 547.57 | H38: 100.96 | I38: 64.17 | J38: 179.19 | K38: 4.94 | L38: 318.94 | M38: 21.39 | N38: 549.07 | O38: 549.08 | P38: 0.01 | Q38: 85.56 | R38: 42.78 | S38: 157.08 | T38: 336.26 | U38: 85.57 | V38: -7.78 | W38: 42.78 | X38: 149.75 | Y38: 278.07 | Z38: 85.56 | AA38: 21.39 | AB38: 0 | AC38: 0 | AD38: =SUM(D38:AA38) -> 4246.84
B39: ISSC Team | C39: Variable | D39: 0 | E39: 0 | F39: 0 | G39: 0 | H39: 0 | I39: 0 | J39: 0 | K39: 0 | L39: 0 | M39: 0 | N39: 0 | O39: 0 | P39: 0 | Q39: 0 | R39: 0 | S39: 0 | T39: 0 | U39: 0 | V39: 0 | W39: 0 | X39: 0 | Y39: 0 | Z39: 0 | AD39: =SUM(D39:AA39) -> 0
B40: Motor Car Expenses | C40: Variable | D40: 198.46 | E40: -138.76 | F40: 2.5 | G40: 74.97 | H40: 0 | I40: 0 | J40: 0 | K40: 0 | L40: 0 | M40: 0 | N40: 0 | O40: 0 | P40: 0 | Q40: 0 | R40: 0 | S40: 0 | T40: 543.23 | U40: 0 | V40: 0 | W40: 0 | X40: 0 | Y40: 0 | Z40: 0 | AA40: 0 | AB40: 0 | AC40: 0 | AD40: =SUM(D40:AA40) -> 680.4
B41: Entertainment | C41: Variable | D41: 0 | E41: 0 | F41: 0 | G41: 0 | H41: 0 | I41: 0 | J41: 0 | K41: 0 | L41: 0 | M41: 0 | N41: 0 | O41: 0 | P41: 0 | Q41: 0 | R41: 0 | S41: 40.53 | T41: 56.99 | U41: 0 | V41: 0 | W41: 0 | X41: 0 | Y41: 0 | Z41: 0 | AA41: 0 | AB41: 0 | AC41: 0 | AD41: =SUM(D41:AA41) -> 97.52
B42: Printing & Stationery | C42: Variable | D42: 13.62 | E42: 121.09 | F42: 12.01 | G42: 360.33 | H42: 33.67 | I42: 40.88 | J42: 27.24 | K42: 204.44 | L42: 197.47 | M42: 13.62 | N42: 319.38 | O42: 321.18 | P42: 5.94 | Q42: 49.12 | R42: 25.44 | S42: 84.6 | T42: 13.62 | U42: 43.68 | V42: 11.82 | W42: 25.44 | X42: 82.79 | Y42: 160.98 | Z42: 43.72 | AA42: 13.62 | AB42: 0 | AC42: 0 | AD42: =SUM(D42:AA42) -> 2225.7
B43: Postage & Courier | C43: Variable | D43: 0.79 | E43: 8.72 | F43: 0.8 | G43: 23.86 | H43: 2.38 | I43: 2.38 | J43: 1.58 | K43: 11.89 | L43: 13.49 | M43: 0.79 | N43: 21.41 | O43: 21.41 | P43: 0.79 | Q43: 3.18 | R43: 1.58 | S43: 5.56 | T43: 0.79 | U43: 3.16 | V43: 0.79 | W43: 1.58 | X43: 5.53 | Y43: 10.31 | Z43: 3.18 | AA43: 0.79 | AB43: 0 | AC43: 0 | AD43: =SUM(D43:AA43) -> 146.74
B44: Corporate Membership & Subscriptions | C44: Variable | D44: 0 | E44: 0 | F44: 0 | G44: 0 | H44: 0 | I44: 0 | J44: 0 | K44: 0 | L44: 0 | M44: 0 | N44: 0 | O44: 0 | P44: 0 | Q44: 0 | R44: 0 | S44: 0 | T44: 0 | U44: 0 | V44: 0 | W44: 0 | X44: 0 | Y44: 0 | Z44: 0 | AA44: 0 | AB44: 0 | AC44: 0 | AD44: =SUM(D44:AA44) -> 0
B45: Audit Fee | C45: Fixed | D45: =(146902/31)/86.21 -> 54.967802 | E45: =(146902/31)/86.21 -> 54.967802 | F45: =(146902/31)/86.21 -> 54.967802 | G45: =(146902/31)/86.21 -> 54.967802 | H45: =(146902/31)/86.21 -> 54.967802 | I45: =(146902/31)/86.21 -> 54.967802 | J45: =(146902/31)/86.21 -> 54.967802 | K45: =(146902/31)/86.21 -> 54.967802 | ... Z45: =(146902/31)/86.21 -> 54.967802 | AA45: 54.967802 | AB45: 0 | AC45: 0 | AD45: =SUM(D45:AA45) -> 1319.2272
B46: Taxation Service Fees | C46: Fixed | D46: 0.96 | E46: 10.52 | F46: 0.95 | G46: 28.52 | H46: 2.85 | I46: 2.87 | J46: 1.93 | K46: 14.33 | L46: 16.24 | M46: 0.96 | N46: 25.8 | O46: 25.81 | P46: 0.96 | Q46: 3.82 | R46: 1.93 | S46: 6.68 | T46: 0.96 | U46: 3.84 | V46: 0.96 | W46: 1.93 | X46: 6.69 | Y46: 12.42 | Z46: 3.82 | AA46: 0.96 | AB46: 0 | AC46: 0 | AD46: =SUM(D46:AA46) -> 176.71
B47: Legal Fees | C47: Variable | D47: 0 | E47: 0 | F47: 0 | G47: 0 | H47: 0 | I47: 0 | J47: 0 | K47: 0 | L47: 0 | M47: 0 | N47: 0 | O47: 0 | P47: 0 | Q47: 0 | R47: 0 | S47: 0 | T47: 0 | U47: 0 | V47: 0 | W47: 0 | X47: 0 | Y47: 0 | Z47: 0 | AA47: 0 | AB47: 0 | AC47: 0 | AD47: =SUM(D47:AA47) -> 0
B48: Professional Fees | C48: Variable | D48: 4.47 | E48: 49.04 | F48: 4.45 | G48: 133.63 | H48: 13.37 | I48: 13.37 | J48: 8.93 | K48: 66.86 | L48: 75.78 | M48: 4.47 | N48: 120.36 | O48: 120.37 | P48: 4.47 | Q48: 17.83 | R48: 8.93 | S48: 31.2 | T48: 4.47 | U48: 17.85 | V48: 4.47 | W48: 8.93 | X48: 31.21 | Y48: 57.95 | Z48: 17.83 | AA48: 4.47 | AB48: 0 | AC48: 0 | AD48: =SUM(D48:AA48) -> 824.71
B49: Compliance Costs, Licence Fees & Certification | C49: Variable | D49: 0 | E49: 0 | F49: 0 | G49: 0 | H49: 0 | I49: 0 | J49: 0 | K49: 0 | L49: 0 | M49: 0 | N49: 0 | O49: 0 | P49: 0 | Q49: 0 | R49: 0 | S49: 0 | T49: 0 | U49: 0 | V49: 0 | W49: 0 | X49: 0 | Y49: 0 | Z49: 0 | AA49: 0 | AB49: 0 | AC49: 0 | AD49: =SUM(D49:AA49) -> 0
B50: Sundry Expenses | C50: Variable | D50: 0 | E50: 0 | F50: 0 | G50: 0 | H50: 0 | I50: 0 | J50: 0 | K50: 0 | L50: 0 | M50: 0 | N50: 0 | O50: 0 | P50: 0 | Q50: 0 | R50: 0 | S50: 0 | T50: 0 | U50: 0 | V50: 0 | W50: 0 | X50: 0 | Y50: 0 | Z50: 0 | AA50: 0 | AB50: 0 | AC50: 0 | AD50: =SUM(D50:AA50) -> 0
B51: Intra-group IT Cost Recharges | C51: Variable | D51: 0 | E51: 0 | F51: 0 | G51: 0 | H51: 0 | I51: 0 | J51: 0 | K51: 0 | L51: 0 | M51: 0 | N51: 0 | O51: 0 | P51: 0 | Q51: 0 | R51: 0 | S51: 0 | T51: 0 | U51: 0 | V51: 0 | W51: 0 | X51: 0 | Y51: 0 | Z51: 0 | AA51: 0 | AB51: 0 | AC51: 0 | AD51: =SUM(D51:AA51) -> 0
B52: Intra-group Administrative Cost Recharges | C52: Variable | D52: 0 | E52: 0 | F52: 0 | G52: 0 | H52: 0 | I52: 0 | J52: 0 | K52: 0 | L52: 0 | M52: 0 | N52: 0 | O52: 0 | P52: 0 | Q52: 0 | R52: 0 | S52: 0 | T52: 0 | U52: 0 | V52: 0 | W52: 0 | X52: 0 | Y52: 0 | Z52: 0 | AA52: 0 | AB52: 0 | AC52: 0 | AD52: =SUM(D52:AA52) -> 0
AD53: =SUM(AD31:AD52) -> 29746.807
A54: D | B54: FINANCIAL EXPENSES
B55: Loan Expenses | C55: Fixed | D55: 0 | E55: 0 | F55: 0 | G55: 0 | H55: 0 | I55: 0 | J55: 0 | K55: 0 | L55: 0 | M55: 0 | N55: 0 | O55: 0 | P55: 0 | Q55: 0 | R55: 0 | S55: 0 | T55: 0 | U55: 0 | V55: 0 | W55: 0 | X55: 0 | Y55: 0 | Z55: 0 | AA55: 0 | AB55: 0 | AC55: 0 | AD55: =SUM(D55:AA55) -> 0
B56: Other Interest Expenses | C56: Fixed | D56: 0 | E56: 0 | F56: 0 | G56: 0 | H56: 0 | I56: 0 | J56: 0 | K56: 0 | L56: 0 | M56: 0 | N56: 0 | O56: 0 | P56: 0 | Q56: 0 | R56: 0 | S56: 0 | T56: 0 | U56: 0 | V56: 0 | W56: 0 | X56: 0 | Y56: 0 | Z56: 0 | AA56: 0 | AB56: 0 | AC56: 0 | AD56: =SUM(D56:AA56) -> 0
B57: Bank Charges | C57: Variable | D57: 0 | E57: 0 | F57: 0 | G57: 0 | H57: 0 | I57: 0 | J57: 0 | K57: 0 | L57: 0 | M57: 0 | N57: 0 | O57: 5.01 | P57: 0 | Q57: 0 | R57: 0 | S57: 0 | T57: 0 | U57: 0 | V57: 0 | W57: 0 | X57: 0 | Y57: -0.01 | Z57: 0 | AA57: 0 | AB57: 0 | AC57: 0 | AD57: =SUM(D57:AA57) -> 5
B58: Exchange Difference | C58: Variable | D58: 0 | E58: 0 | F58: 0 | G58: 0 | H58: 0 | I58: 0 | J58: 0 | K58: 0 | L58: 0 | M58: 0 | N58: 0 | O58: 0 | P58: 0 | Q58: 0 | R58: 0 | S58: 0 | T58: 0 | U58: 0 | V58: 0 | W58: 0 | X58: 0 | Y58: 0 | Z58: 0 | AA58: 0 | AB58: 0 | AC58: 0 | AD58: =SUM(D58:AA58) -> 0
B59: Fair value loss/(gain) on financial instrument/ CCB | C59: Variable | D59: 0 | E59: 0 | F59: 0 | G59: 0 | H59: 0 | I59: 0 | J59: 0 | K59: 0 | L59: 0 | M59: 0 | N59: 0 | O59: 0 | P59: 0 | Q59: 0 | R59: 0 | S59: 0 | T59: 0 | U59: 0 | V59: 0 | W59: 0 | X59: 0 | Y59: 0 | Z59: 0 | AA59: 0 | AB59: 0 | AC59: 0 | AD59: =SUM(D59:AA59) -> 0
AD60: =SUM(AD55:AD59) -> 5
A61: E | B61: OTHER OPERATING EXPENSES
B62: ESG / Donation (e.g. Humanitarian Funds) | C62: Variable | D62: 0 | E62: 0 | F62: 0 | G62: 0 | H62: 0 | I62: 0 | J62: 0 | K62: 0 | L62: 0 | M62: 0 | N62: 0 | O62: 0 | P62: 0 | Q62: 0 | R62: 0 | S62: 0 | T62: 0 | U62: 0 | V62: 0 | W62: 0 | X62: 0 | Y62: 0 | Z62: 0 | AA62: 0 | AB62: 0 | AC62: 0 | AD62: =SUM(D62:AA62) -> 0
B63: Loss/(Gain) on Disposal of Fixed Assets | C63: Variable | D63: 0 | E63: 0 | F63: 0 | G63: 0 | H63: 0 | I63: 0 | J63: 0 | K63: 0 | L63: 0 | M63: 0 | N63: 0 | O63: 0 | P63: 0 | Q63: 0 | R63: 0 | S63: 0 | T63: 0 | U63: 0 | V63: 0 | W63: 0 | X63: 0 | Y63: 0 | Z63: 0 | AA63: 0 | AB63: 0 | AC63: 0 | AD63: =SUM(D63:AA63) -> 0
B64: Depreciation | C64: Fixed | D64: 175 | E64: 1928 | F64: 175 | G64: 5258 | H64: 526 | I64: 526 | J64: 351 | K64: 2629 | L64: 2979 | M64: 175 | N64: 4732 | O64: 4732 | P64: 175 | Q64: 701 | R64: 351 | S64: 1227 | T64: 175 | U64: 701 | V64: 175 | W64: 351 | X64: 1227 | Y64: 2278 | Z64: 701 | AA64: 175.26108 | AB64: 0 | AC64: 0 | AD64: =SUM(D64:AA64) -> 32423.261
B65: Amortisation | C65: Fixed | D65: 0 | E65: 0 | F65: 0 | G65: 0 | H65: 0 | I65: 0 | J65: 0 | K65: 0 | L65: 0 | M65: 0 | N65: 0 | O65: 0 | P65: 0 | Q65: 0 | R65: 0 | S65: 0 | T65: 0 | U65: 0 | V65: 0 | W65: 0 | X65: 0 | Y65: 0 | Z65: 0 | AA65: 0 | AB65: 0 | AC65: 0 | AD65: =SUM(D65:AA65) -> 0
B66: Provision for impairment in value | C66: Variable | D66: 0 | E66: 0 | F66: 0 | G66: 0 | H66: 0 | I66: 0 | J66: 0 | K66: 0 | L66: 0 | M66: 0 | N66: 0 | O66: 0 | P66: 0 | Q66: 0 | R66: 0 | S66: 0 | T66: 0 | U66: 0 | V66: 0 | W66: 0 | X66: 0 | Y66: 0 | Z66: 0 | AA66: 0 | AB66: 0 | AC66: 0 | AD66: =SUM(D66:AA66) -> 0
B67: Provision for Accounts Receivable | C67: Variable | D67: 0 | E67: 0 | F67: 0 | G67: 0 | H67: 0 | I67: 0 | J67: 0 | K67: 0 | L67: 0 | M67: 0 | N67: 0 | O67: 0 | P67: 0 | Q67: 0 | R67: 0 | S67: 0 | T67: 0 | U67: 0 | V67: 0 | W67: 0 | X67: 0 | Y67: 0 | Z67: 0 | AA67: 0 | AB67: 0 | AC67: 0 | AD67: =SUM(D67:AA67) -> 0
B68: Other tax - VAT & GST | C68: Variable | D68: 0 | E68: 0 | F68: 0 | G68: 0 | H68: 0 | I68: 0 | J68: 0 | K68: 0 | L68: 0 | M68: 0 | N68: 0 | O68: 0 | P68: 0 | Q68: 0 | R68: 0 | S68: 0 | T68: 0 | U68: 0 | V68: 0 | W68: 0 | X68: 0 | Y68: 0 | Z68: 0 | AA68: 0 | AB68: 0 | AC68: 0 | AD68: =SUM(D68:AA68) -> 0
B69: Other tax - WHT | C69: Variable | D69: 0 | E69: 0 | F69: 0 | G69: 0 | H69: 0 | I69: 0 | J69: 0 | K69: 0 | L69: 0 | M69: 0 | N69: 0 | O69: 0 | P69: 0 | Q69: 0 | R69: 0 | S69: 0 | T69: 0 | U69: 0 | V69: 0 | W69: 0 | X69: 0 | Y69: 0 | Z69: 0 | AA69: 0 | AB69: 0 | AC69: 0 | AD69: =SUM(D69:AA69) -> 0
AD70: =SUM(AD62:AD69) -> 32423.261
B72: Total Cost (USD) | D72: =SUM(D6:D71) -> 10827.042 | E72: =SUM(E6:E71) -> 26342.79 | F72: =SUM(F6:F71) -> 2510.3816 | G72: =SUM(G6:G71) -> 50880.803 | H72: =SUM(H6:H71) -> 4390.9393 | I72: =SUM(I6:I71) -> 4370.5593 | J72: =SUM(J6:J71) -> 9433.0355 | K72: =SUM(K6:K71) -> 54060.725 | ... AC72: =SUM(AC6:AC71) -> 0 | AD72: =+AD19+AD29+AD53+AD70+AD60 -> 440161.1
C73: Fixed | D73: =ROUND(SUMIF($C$8:$C$69,$C$73,D8:D69)/D72,2) -> 0.71 | E73: =ROUND(SUMIF($C$8:$C$69,$C$73,E8:E69)/E72,2) -> 0.93 | F73: =ROUND(SUMIF($C$8:$C$69,$C$73,F8:F69)/F72,2) -> 0.94 | G73: =ROUND(SUMIF($C$8:$C$69,$C$73,G8:G69)/G72,2) -> 0.91 | H73: =ROUND(SUMIF($C$8:$C$69,$C$73,H8:H69)/H72,2) -> 0.89 | I73: =ROUND(SUMIF($C$8:$C$69,$C$73,I8:I69)/I72,2) -> 0.89 | J73: =ROUND(SUMIF($C$8:$C$69,$C$73,J8:J69)/J72,2) -> 0.95 | K73: =ROUND(SUMIF($C$8:$C$69,$C$73,K8:K69)/K72,2) -> 0.95 | ... AA73: =ROUND(SUMIF($C$8:$C$69,$C$73,AA8:AA69)/AA72,2) -> 0.9 | AD73: =ROUND(SUMIF($C$8:$C$69,$C$73,AD8:AD69)/AD72,2) -> 0.91
C74: Variable | D74: =ROUND(SUMIF($C$8:$C$69,$C$74,D8:D69)/D72,2) -> 0.29 | E74: =ROUND(SUMIF($C$8:$C$69,$C$74,E8:E69)/E72,2) -> 0.07 | F74: =ROUND(SUMIF($C$8:$C$69,$C$74,F8:F69)/F72,2) -> 0.06 | G74: =ROUND(SUMIF($C$8:$C$69,$C$74,G8:G69)/G72,2) -> 0.09 | H74: =ROUND(SUMIF($C$8:$C$69,$C$74,H8:H69)/H72,2) -> 0.11 | I74: =ROUND(SUMIF($C$8:$C$69,$C$74,I8:I69)/I72,2) -> 0.11 | J74: =ROUND(SUMIF($C$8:$C$69,$C$74,J8:J69)/J72,2) -> 0.05 | K74: =ROUND(SUMIF($C$8:$C$69,$C$74,K8:K69)/K72,2) -> 0.05 | ... AA74: =ROUND(SUMIF($C$8:$C$69,$C$74,AA8:AA69)/AA72,2) -> 0.1 | AD74: =ROUND(SUMIF($C$8:$C$69,$C$74,AD8:AD69)/AD72,2) -> 0.09
B77: Headcount | D77: 1 | E77: 11 | F77: 1 | G77: 30 | H77: 3 | I77: 3 | J77: 2 | K77: 15 | L77: 17 | M77: 1 | N77: 27 | O77: 27 | P77: 1 | Q77: 4 | R77: 2 | S77: 7 | T77: 1 | U77: 4 | V77: 1 | W77: 2 | X77: 7 | Y77: 13 | Z77: 4 | AA77: 1 | AD77: =SUM(D77:AA77) -> 185
B78: Average Salaries and Wages per employee | D78: =(+D8+D9+D10+D11)/D77 -> 7231.72 | E78: =(+E8+E9+E10+E11)/E77 -> 1692.5209 | F78: =(+F8+F9+F10+F11)/F77 -> 1864.56 | G78: =(+G8+G9+G10+G11)/G77 -> 1103.0567 | H78: =(+H8+H9+H10+H11)/H77 -> 847.46667 | I78: =(+I8+I9+I10+I11)/I77 -> 853.55667 | J78: =(+J8+J9+J10+J11)/J77 -> 4035.675 | K78: =(+K8+K9+K10+K11)/K77 -> 2993.2367 | ... Z78: =(+Z8+Z9+Z10+Z11)/Z77 -> 1361.11 | AA78: 909.82 | AD78: =(+AD8+AD9+AD10+AD11)/AD77 -> 1701.029
B79: Average Personnel expenses per employee | D79: =SUM(D12:D18)/D77 -> 73.64 | E79: =SUM(E12:E18)/E77 -> 168.53727 | F79: =SUM(F12:F18)/F77 -> 81.11 | G79: =SUM(G12:G18)/G77 -> 81.111333 | H79: =SUM(H12:H18)/H77 -> 73.63 | I79: =SUM(I12:I18)/I77 -> 73.63 | J79: =SUM(J12:J18)/J77 -> 73.635 | K79: =SUM(K12:K18)/K77 -> 75.740667 | ... Z79: =SUM(Z12:Z18)/Z77 -> 73.635 | AA79: 73.64 | AD79: =SUM(AD12:AD18)/AD77 -> 93.014054
B80: Average Office expenses per employee | D80: =SUM(D21:D28)/D77 -> 225.69383 | E80: =SUM(E21:E28)/E77 -> 225.69564 | F80: =SUM(F21:F28)/F77 -> 225.69383 | G80: =SUM(G21:G28)/G77 -> 225.69616 | H80: =SUM(H21:H28)/H77 -> 225.69716 | I80: =SUM(I21:I28)/I77 -> 225.69716 | J80: =SUM(J21:J28)/J77 -> 225.68883 | K80: =SUM(K21:K28)/K77 -> 235.52049 | ... Z80: =SUM(Z21:Z28)/Z77 -> 225.68883 | AA80: 218.89981 | AD80: =SUM(AD21:AD28)/AD77 -> 249.1247
B81: Average IT expenses per employee | D81: =SUM(D31:D34)/D77 -> 68.84 | E81: =SUM(E31:E34)/E77 -> 68.844545 | F81: =SUM(F31:F34)/F77 -> 69.84 | G81: =SUM(G31:G34)/G77 -> 69.850667 | H81: =SUM(H31:H34)/H77 -> 71.87 | I81: =SUM(I31:I34)/I77 -> 68.84 | J81: =SUM(J31:J34)/J77 -> 68.845 | K81: =SUM(K31:K34)/K77 -> 55.283333 | ... Z81: =SUM(Z31:Z34)/Z77 -> 68.845 | AA81: 68.84 | AD81: =SUM(AD31:AD34)/AD77 -> 70.378919
B82: Average Administrative expenses per employee | D82: =SUM(D35:D52)/D77 -> 3052.1478 | E82: =SUM(E35:E52)/E77 -> 63.927982 | F82: =SUM(F35:F52)/F77 -> 94.177802 | G82: =SUM(G35:G52)/G77 -> 41.04526 | H82: =SUM(H35:H52)/H77 -> 69.649267 | I82: =SUM(I35:I52)/I77 -> 59.795934 | J82: =SUM(J35:J52)/J77 -> 137.1739 | K82: =SUM(K35:K52)/K77 -> 69.00052 | ... Z82: =SUM(Z35:Z52)/Z77 -> 52.52195 | AA82: 96.457802 | AD82: =SUM(AD35:AD52)/AD77 -> 90.414634
B83: Average financial and other operative expenses per employee | D83: =(SUM(D62:D69)+SUM(D55:D59))/D77 -> 175 | E83: =(SUM(E62:E69)+SUM(E55:E59))/E77 -> 175.27273 | F83: =(SUM(F62:F69)+SUM(F55:F59))/F77 -> 175 | G83: =(SUM(G62:G69)+SUM(G55:G59))/G77 -> 175.26667 | H83: =(SUM(H62:H69)+SUM(H55:H59))/H77 -> 175.33333 | I83: =(SUM(I62:I69)+SUM(I55:I59))/I77 -> 175.33333 | J83: =(SUM(J62:J69)+SUM(J55:J59))/J77 -> 175.5 | K83: =(SUM(K62:K69)+SUM(K55:K59))/K77 -> 175.26667 | ... Z83: =(SUM(Z62:Z69)+SUM(Z55:Z59))/Z77 -> 175.25 | AA83: 175.26108 | AD83: =(SUM(AD62:AD69)+SUM(AD55:AD59))/AD77 -> 175.2879
B84: Average TOTAL expenses per employee | D84: =+D72/D77 -> 10827.042 | E84: =+E72/E77 -> 2394.7991 | F84: =+F72/F77 -> 2510.3816 | G84: =+G72/G77 -> 1696.0268 | H84: =+H72/H77 -> 1463.6464 | I84: =+I72/I77 -> 1456.8531 | J84: =+J72/J77 -> 4716.5177 | K84: =+K72/K77 -> 3604.0483 | ... Z84: =+Z72/Z77 -> 1957.0508 | AA84: 1542.9187 | AD84: =+AD72/AD77 -> 2379.2492
B86: Personnal Expenses % of overall ISSC cost | D86: =SUM(D8:D16)/D72 -> 0.67473279 | E86: =SUM(E8:E16)/E72 -> 0.77712498 | F86: =SUM(F8:F16)/F72 -> 0.77504949 | G86: =SUM(G8:G16)/G72 -> 0.69820125 | H86: =SUM(H8:H16)/H72 -> 0.62931638 | I86: =SUM(I8:I16)/I72 -> 0.63643113 | J86: =SUM(J8:J16)/J72 -> 0.87125931 | K86: =SUM(K8:K16)/K72 -> 0.85153612 | ... Z86: =SUM(Z8:Z16)/Z72 -> 0.73311588 | AA86: 0.63740235 | AD86: =SUM(AD8:AD16)/AD72 -> 0.75403747
B87: Other Personnel expenses as % Salaries and Wages | D87: =+D79/D78 -> 0.010182916 | E87: =+E79/E78 -> 0.099577661 | F87: =+F79/F78 -> 0.04350088 | G87: =+G79/G78 -> 0.073533242 | H87: =+H79/H78 -> 0.086882473 | I87: =+I79/I78 -> 0.08626258 | J87: =+J79/J78 -> 0.018246018 | K87: =+K79/K78 -> 0.025303935 | ... Z87: =+Z79/Z78 -> 0.054099228 | AA87: 0.080939087 | AD87: =+AD79/AD78 -> 0.054681052
B88: Office expenses as % Salaries and Wages | D88: =+D80/D78 -> 0.031208872 | E88: =+E80/E78 -> 0.13334881 | F88: =+F80/F78 -> 0.12104401 | G88: =+G80/G78 -> 0.20460976 | H88: =+H80/H78 -> 0.26631981 | I88: =+I80/I78 -> 0.26441965 | J88: =+J80/J78 -> 0.055923439 | K88: =+K80/K78 -> 0.07868422 | ... Z88: =+Z80/Z78 -> 0.16581233 | AA88: 0.24059684 | AD88: =+AD80/AD78 -> 0.1464553
B89: IT as % Salaries and Wages | D89: =+D81/D78 -> 0.0095191739 | E89: =+E81/E78 -> 0.040675743 | F89: =+F81/F78 -> 0.037456558 | G89: =+G81/G78 -> 0.06332464 | H89: =+H81/H78 -> 0.084805695 | I89: =+I81/I78 -> 0.080650767 | J89: =+J81/J78 -> 0.017059104 | K89: =+K81/K78 -> 0.018469416 | ... Z89: =+Z81/Z78 -> 0.050580041 | AA89: 0.075663318 | AD89: =+AD81/AD78 -> 0.041374321
B90: Administrative expenses as % of Salaries and Wages | D90: =+D82/D78 -> 0.42205005 | E90: =+E82/E78 -> 0.037770867 | F90: =+F82/F78 -> 0.050509397 | G90: =+G82/G78 -> 0.037210473 | H90: =+H82/H78 -> 0.082185259 | I90: =+I82/I78 -> 0.070055025 | J90: =+J82/J78 -> 0.033990324 | K90: =+K82/K78 -> 0.023052143 | ... Z90: =+Z82/Z78 -> 0.038587587 | AA90: 0.10601856 | AD90: =+AD82/AD78 -> 0.053152906
B91: Financial and other operative as % of Salaries and Wages | D91: =+D83/D78 -> 0.024198946 | E91: =+E83/E78 -> 0.1035572 | F91: =+F83/F78 -> 0.093855923 | G91: =+G83/G78 -> 0.15889181 | H91: =+H83/H78 -> 0.20689113 | I91: =+I83/I78 -> 0.20541499 | J91: =+J83/J78 -> 0.043487149 | K91: =+K83/K78 -> 0.058554229 | ... Z91: =+Z83/Z78 -> 0.12875521 | AA91: 0.1926327 | AD91: =+AD83/AD78 -> 0.10304816
B92: TOTAL expenses except Salaries and Wages as % Salaries and Wages | D92: =SUM(D79:D83)/D78 -> 0.49715996 | E92: =SUM(E79:E83)/E78 -> 0.41493028 | F92: =SUM(F79:F83)/F78 -> 0.34636677 | G92: =SUM(G79:G83)/G78 -> 0.53756992 | H92: =SUM(H79:H83)/H78 -> 0.72708436 | I92: =SUM(I79:I83)/I78 -> 0.70680302 | J92: =SUM(J79:J83)/J78 -> 0.16870603 | K92: =SUM(K79:K83)/K78 -> 0.20406394 | ... Z92: =SUM(Z79:Z83)/Z78 -> 0.4378344 | AA92: 0.69585049 | AD92: =SUM(AD79:AD83)/AD78 -> 0.39871173
A95: 45689 | B95: February, 2025
B97: Business Unit Name | D97: Crew Management | E97: Cruise Management | F97: Accounts | G97: Accounts | H97: Admin | I97: Agency Services | J97: Commercial | K97: Consultancy Services | L97: Environmental Compliance | M97: Environmental Compliance | N97: IT | O97: Procurement | P97: Procurement | Q97: Ship Management | R97: Ship Management | S97: Ship Management | T97: Ship Management | U97: Ship Management | V97: Ship Management | W97: Ship Management | X97: Ship Management | Y97: Ship Management | Z97: Ship Management | AA97: Technical Services | AB97: Ship Management | AC97: Ship Management | AD97: Actual
B98: Division Name | D98: Group Marine HR | E98: Miami Ship Management | F98: CMI Accounts Payables | G98: Fleet Accounts | H98: Administration | I98: Agency Hub | J98: Commercial | K98: Fleet Performance | L98: Carbon Emission Services | M98: Other Environmental Compliance | N98: Group IT | O98: Galleymasters | P98: Sourcing | Q98: Antwerp Dry | R98: Goes Dry | S98: Group Operations | T98: Group Shared Service Center | U98: Hamburg Dry | V98: Hong Kong Dry 1 | W98: JV Ardmore | X98: Singapore Dry | Y98: Singapore Tanker 1 | Z98: Singapore Tanker 2 | AA98: AE Technical Services | AB98: Hong Kong Dry 2 | AC98: Hong Kong Dry 3 | AD98: Total
A100: A | B100: PERSONNEL EXPENSES
B101: Salaries & Wages | C101: =VLOOKUP(B101,$B$8:$C$69,2,0) -> Fixed | D101: 6696.27 | E101: 17506.92 | F101: 1755.28 | G101: 29960.69 | H101: 2368.32 | I101: 2804.64 | J101: 7490.98 | K101: 42352.58 | L101: 19178.81 | M101: 4884.42 | N101: 38754.56 | O101: 21720.47 | P101: 3654.35 | Q101: 12043.42 | R101: 1386.01 | S101: 14964.12 | T101: 7519.45 | U101: 3699.95 | V101: 1735.64 | W101: 6581.46 | X101: 17549 | Y101: 26893.36 | Z101: 4800.33 | AA101: 974.37 | AB101: 526.08 | AC101: 505.62 | AD101: =SUM(D101:AC101) -> 298307.1
B102: Provision for Bonus, Leave & Other Employment Costs | C102: =VLOOKUP(B102,$B$8:$C$69,2,0) -> Fixed | D102: 494.8 | E102: 1287.32 | F102: 129.26 | G102: 2253.55 | H102: 175.29 | I102: 191.92 | J102: 553.23 | K102: 3152.13 | L102: 703.22 | M102: 179.1 | N102: 2851.38 | O102: 1630.03 | P102: 269.11 | Q102: 633.66 | R102: 83.76 | S102: 1112.55 | T102: 95.96 | U102: 381.68 | V102: 127.8 | W102: 456.13 | X102: 1265.22 | Y102: 1825.37 | Z102: 629.38 | AA102: 35.73 | AB102: 19.29 | AC102: 18.54 | AD102: =SUM(D102:AC102) -> 20555.41
B103: Consultants & Contractors | C103: =VLOOKUP(B103,$B$8:$C$69,2,0) -> Fixed | D103: 0 | E103: 0 | F103: 0 | G103: 0 | H103: 0 | I103: 0 | J103: 0 | K103: 0 | L103: 0 | M103: 0 | N103: 4522.04 | O103: 0 | P103: 0 | Q103: 0 | R103: 0 | S103: 341.71 | T103: 0 | U103: 0 | V103: 0 | W103: 0 | X103: 0 | Y103: 0 | Z103: 0 | AA103: 4367.46 | AB103: 0 | AC103: 0 | AD103: =SUM(D103:AC103) -> 9231.21
B104: Pension Fund & Social Securities | C104: =VLOOKUP(B104,$B$8:$C$69,2,0) -> Fixed | D104: 463.4 | E104: 1085.27 | F104: 102.02 | G104: 1874.8 | H104: 138.7 | I104: 166.86 | J104: 506.81 | K104: 2857.81 | L104: 1340.33 | M104: 367.25 | N104: 2535.94 | O104: 1354.02 | P104: 253.48 | Q104: 833.57 | R104: 83.97 | S104: 994.57 | T104: 537.34 | U104: 205.62 | V104: 100.88 | W104: 451.08 | X104: 1164.1 | Y104: 1800.15 | Z104: 244.45 | AA104: 61.76 | AB104: 34.07 | AC104: 32.46 | AD104: =SUM(D104:AC104) -> 19590.71
B105: Staff Allowances & Benefits | C105: =VLOOKUP(B105,$B$8:$C$69,2,0) -> Fixed | D105: 30.45 | E105: 1481.27 | F105: 26.63 | G105: 772.23 | H105: 91.35 | I105: 121.81 | J105: 60.89 | K105: 456.74 | L105: 456.74 | M105: 30.45 | N105: 822.1 | O105: 822.14 | P105: 30.45 | Q105: 182.7 | R105: 60.89 | S105: 213.16 | T105: 30.45 | U105: 121.8 | V105: 30.45 | W105: 60.89 | X105: 243.62 | Y105: 453.18 | Z105: 121.81 | AA105: 30.45 | AB105: 60.89 | AC105: 30.45 | AD105: =SUM(D105:AC105) -> 6843.99
B106: Staff Recruitment / Relocation | C106: =VLOOKUP(B106,$B$8:$C$69,2,0) -> Variable | D106: 0 | E106: 0 | F106: 0 | G106: 0 | H106: 0 | I106: 0 | J106: 0 | K106: 49.29 | L106: 0 | M106: 0 | N106: 0 | O106: 0 | P106: 0 | Q106: 90.85 | R106: 0 | S106: 0 | T106: 0 | U106: 0 | V106: 0 | W106: 0 | X106: 10.32 | Y106: 74.51 | Z106: 10.32 | AA106: 0 | AB106: 20.63 | AC106: 0 | AD106: =SUM(D106:AC106) -> 255.92
B107: Staff Functions | C107: =VLOOKUP(B107,$B$8:$C$69,2,0) -> Variable | D107: 0 | E107: 0.71 | F107: -0.95 | G107: -27.53 | H107: 0.19 | I107: 30.65 | J107: 0.14 | K107: 0.96 | L107: -59.83 | M107: 1261.02 | N107: 1.63 | O107: 1.72 | P107: 0.07 | Q107: 61.17 | R107: 0.14 | S107: 0.45 | T107: 0.07 | U107: 0.26 | V107: 0.07 | W107: 0.14 | X107: 30.9 | Y107: 0.83 | Z107: 0.25 | AA107: 0.07 | AB107: 60.92 | AC107: 30.46 | AD107: =SUM(D107:AC107) -> 1394.51
B108: Course & Training | C108: Variable | D108: 0 | E108: 0 | F108: 0 | G108: 0 | H108: 0 | I108: 0 | J108: 0 | K108: 0 | L108: 0 | M108: 0 | N108: 0 | O108: 0 | P108: 0 | Q108: 0 | R108: 0 | S108: 0 | T108: 0 | U108: 0 | V108: 0 | W108: 0 | X108: 0 | Y108: 0 | Z108: 0 | AA108: 0 | AB108: 0 | AC108: 0 | AD108: =SUM(D108:AC108) -> 0
AD109: =SUM(AD101:AD108) -> 356178.85
...

Sheet ISSC Spend_KPI's
A1: Category: Overall Cost Insights | F1: 45658 | H1: 45689 | J1: 45717 | K1: 45748 | L1: 45778 | M1: 45809 | N1: 45839 | O1: 45870 | P1: 45901 | Q1: 45931 | R1: 45962 | S1: 45992
A2: KPI | B2: Description | C2: Remark | D2: Formula (Excel) | F2: Total (All BU) | H2: Total (All BU)
D3: Headcount | F3: =+'SSC Recharge Summary'!AD77 -> 185 | H3: =+'SSC Recharge Summary'!AD154 -> 189
A4: 1. Total ISSC Spend | B4: Aggregate spend across all categories | F4: =+'SSC Recharge Summary'!AD72 -> 440161.1 | H4: =+'SSC Recharge Summary'!AD149 -> 448023.2
A5: 2. Spend vs. Budget Variance | B5: Variance between actual spend and the allocated budget ( BU & overall) | C5: Pls add budget provided by ISSC | D5: Actual minus Budget | F5: =+F4-'P&L-Budget 2025'!MB264 -> 1805.5196 | H5: =+H4-'P&L-Budget 2025'!MC264 -> 24303.47
D6: Variance Remarks
A7: 3. Fixed vs. Variable Cost Ratio | B7: Proportion of Fixed costs Vs. Vriable costs | F7: ='SSC Recharge Summary'!AD73&" "&":" &" "&'SSC Recharge Summary'!AD74 -> 0.91 : 0.09 | H7: ='SSC Recharge Summary'!AD150&" "&":" &" "&'SSC Recharge Summary'!AD151 -> 0.94 : 0.06
A8: 4. Cost Per FTE (Desk Cost) | B8: Total SSC cost divided by the number of ISSC HC | F8: =F4/F3 -> 2379.2492 | H8: =+H4/H3 -> 2370.4931
A9: Employee-Related Costs
A10: KPI | B10: Description | D10: Formula (Excel)
A11: 1. Employee Cost as % of Total ISSC Spend | B11: Proportion of overall Employee Cost relative to the total ISSC spend | F11: =SUM('SSC Recharge Summary'!AD8:AD18)/F4 -> 0.75403747 | H11: =SUM('SSC Recharge Summary'!AD101:AD108)/H4 -> 0.7950009
A12: 2. Training Cost per Employee | B12: Total training-related costs divided by the number of ISSC HC trained
A13: IT & Technology Costs
A14: KPI | B14: Description | D14: Formula (Excel)
A15: 1. IT Spend as % of Total ISSC Spend | B15: Proportion of overall IT expenses relative to the total ISSC spend | F15: =SUM('SSC Recharge Summary'!AD31:AD34)/'ISSC Spend_KPI''s'!F4 -> 0.029580306 | H15: =SUM('SSC Recharge Summary'!AD121:AD123)/H4 -> 0.026190496
A16: Facility & Office Costs
A17: KPI | B17: Description | D17: Formula (Excel)
A18: 1. Total Facility Spend | B18: Total rent, utilities, and maintenance costs | F18: =SUM('SSC Recharge Summary'!AD21:AD28) -> 46088.07 | H18: =+'SSC Recharge Summary'!AD119 -> 36724.24
A19: 2. Facility Spend as % of Total Spend | B19: Proportion of overall Facility Spend relative to the total ISSC spend | F19: =F18/F4 -> 0.10470728 | H19: =H18/H4 -> 0.081969505
A20: 3. Average Cost per Employee | B20: Total Facility Spend / Number of Employees | F20: =F18/F3 -> 249.1247 | H20: =+H18/H3 -> 194.30815
A21: 4. Space Utilization | B21: percentage of space that is actively used versus the total available space | C21: Admin
A22: 5. Admin Cost per FTE | B22: Total administrative expenses divided by the number of employees | F22: =SUM('SSC Recharge Summary'!AD35:AD52)/F3 -> 90.414634 | H22: =SUM('SSC Recharge Summary'!AD125:AD139)/H3 -> 66.955771
A23: Travel & Transportation Costs
A24: KPI | B24: Description | D24: Formula (Excel)
A25: 1. Travel Spend per Employee | B25: Total travel-related costs divided by the number of employees who traveled.(Domestic/International) | F25: =SUM('SSC Recharge Summary'!AD37:AD38)/F3 -> 59.970973 | H25: =SUM('SSC Recharge Summary'!AD127:AD128)/H3 -> 48.112593
A26: 2. Overall Travel Cost | F26: =SUM('SSC Recharge Summary'!AD37:AD38) -> 11094.63 | H26: =SUM('SSC Recharge Summary'!AD127:AD128) -> 9093.28
A27: 3.Travel Cost as % of Total ISSC Spend | F27: =F26/F4 -> 0.02520584 | H27: =+H26/H4 -> 0.020296449

Sheet P&L-Budget 2025
B1: ANGLO-EASTERN MARITIME SERVICES PRIVATE LIMITED | P1: =+P11 -> Budget-2025 | AD1: =+AD11 -> Budget-2025 | AR1: =+AR11 -> Budget-2025 | BF1: =+BF11 -> Budget-2025 | BT1: =+BT11 -> #REF! | CH1: =+CH11 -> #REF! | CV1: =+CV11 -> #REF! | DJ1: =+DJ11 -> #REF! | DX1: =+DX11 -> #REF! | EL1: =+EL11 -> #REF! | EZ1: =+EZ11 -> #REF! | FN1: =+FN11 -> #REF! | GB1: =+GB11 -> #REF! | GP1: =+GP11 -> #REF! | HD1: =+HD11 -> Total | HR1: =+HR11 -> #REF! | IF1: =+IF11 -> #REF! | IT1: =+IT11 -> #REF! | JH1: =+JH11 -> #REF! | JV1: =+JV11 -> #REF! | KJ1: =+KJ11 -> #REF! | KX1: =+KX11 -> Total | LL1: =+LL11 -> Total | LZ1: =+LZ11 -> Total | MB1: =+LZ1 -> Total | MC1: =+MB1 -> Total | MD1: =+MC1 -> Total | ME1: =+MD1 -> Total | MF1: =+ME1 -> Total | MG1: =+MF1 -> Total | MH1: =+MG1 -> Total | MI1: =+MH1 -> Total | MJ1: =+MI1 -> Total | ... MN1: =+MM1 -> Total
B2: Budget 2025 | P2: 1 | AD2: 2 | AR2: 3 | BF2: 4 | BT2: 6 | CH2: 8 | CV2: 11 | DJ2: 12 | DX2: 13 | EL2: 14 | EZ2: 15 | FN2: 16 | GB2: 17 | GP2: 19 | HD2: 30 | HR2: 20 | IF2: 21 | IT2: 22 | JH2: 23 | JV2: 24 | KJ2: 25 | KX2: 28 | LL2: 29 | LZ2: 31
B8: BU | D8: Accounts | P8: =+D8 -> Accounts | R8: Admin | AD8: =+R8 -> Admin | AF8: Agency Services | AR8: =AF8 -> Agency Services | AT8: Commercial | BF8: =AT8 -> Commercial | BH8: Consultancy Services | BT8: =+BH8 -> Consultancy Services | BV8: Crew Management | CH8: =+BV8 -> Crew Management | CJ8: Cruise Management | CV8: =+CJ8 -> Cruise Management | CX8: IT | DJ8: =+CX8 -> IT | DL8: Procurement | DX8: =+DL8 -> Procurement | DZ8: Procurement | EL8: =+DZ8 -> Procurement | EN8: Ship Management | EZ8: =+EN8 -> Ship Management | FB8: Ship Management | FN8: =+FB8 -> Ship Management | FP8: Ship Management | GB8: =+FP8 -> Ship Management | GD8: Ship Management | GP8: =+GD8 -> Ship Management | GR8: Vacant Seats | HD8: =+GR8 -> Vacant Seats | HF8: Ship Management | HR8: =+HF8 -> Ship Management | HT8: Ship Management | IF8: =+HT8 -> Ship Management | IH8: Ship Management | IT8: =+IH8 -> Ship Management | IV8: Ship Management | JH8: =+IV8 -> Ship Management | JJ8: Ship Management | JV8: =+JJ8 -> Ship Management | JX8: Ship Management | KJ8: =+JX8 -> Ship Management | KL8: Accounts | KX8: =+KL8 -> Accounts | KZ8: Accounts | LL8: =+KZ8 -> Accounts | LZ8: =+LN8 -> 0 | MB8: =LN11 -> 45688 | MC8: =LO11 -> 45716 | MD8: =LP11 -> 45747 | ME8: =LQ11 -> 45777 | MF8: =LR11 -> 45808 | MG8: =LS11 -> 45838 | MH8: =LT11 -> 45869 | MI8: =LU11 -> 45900 | ... MN8: =LZ11 -> Total
B9: Division | D9: Fleet Accounts | P9: =+D9 -> Fleet Accounts | R9: Administration | AD9: =+R9 -> Administration | AF9: Agency Hub | AR9: =AF9 -> Agency Hub | AT9: Commercial | BF9: =AT9 -> Commercial | BH9: Fleet Performance | BT9: =+BH9 -> Fleet Performance | BV9: Group Marine HR | CH9: =+BV9 -> Group Marine HR | CJ9: Miami Ship Management | CV9: =+CJ9 -> Miami Ship Management | CX9: Group IT | DJ9: =+CX9 -> Group IT | DL9: Galleymasters | DX9: =+DL9 -> Galleymasters | DZ9: Sourcing | EL9: =+DZ9 -> Sourcing | EN9: Antwerp Dry | EZ9: =+EN9 -> Antwerp Dry | FB9: Goes Dry | FN9: =+FB9 -> Goes Dry | FP9: Group Operations | GB9: =+FP9 -> Group Operations | GD9: Group Shared Service Center | GP9: =+GD9 -> Group Shared Service Center | GR9: Vacant Seats | HD9: =+GR9 -> Vacant Seats | HF9: Hamburg Dry | HR9: =+HF9 -> Hamburg Dry | HT9: Hong Kong Dry 1 | IF9: =+HT9 -> Hong Kong Dry 1 | IH9: JV Ardmore | IT9: =+IH9 -> JV Ardmore | IV9: Singapore Dry | JH9: =+IV9 -> Singapore Dry | JJ9: Singapore Tanker 1 | JV9: =+JJ9 -> Singapore Tanker 1 | JX9: Singapore Tanker 2 | KJ9: =+JX9 -> Singapore Tanker 2 | KL9: Accounts Payables | KX9: =+KL9 -> Accounts Payables | KZ9: CMI Accounts Payables | LL9: =+KZ9 -> CMI Accounts Payables | LZ9: =+LN9 -> 0 | MB9: All Divisions | MC9: =MB9 -> All Divisions | MD9: =MC9 -> All Divisions | ME9: =MD9 -> All Divisions | MF9: =ME9 -> All Divisions | MG9: =MF9 -> All Divisions | MH9: =MG9 -> All Divisions | MI9: =MH9 -> All Divisions | MJ9: =MI9 -> All Divisions | ... MN9: =MM9 -> All Divisions
B10: Amount (INR) | D10: INR | E10: INR | F10: INR | G10: INR | H10: INR | I10: INR | J10: INR | K10: INR | L10: INR | M10: INR | N10: INR | O10: INR | P10: INR | R10: INR | S10: INR | T10: INR | U10: INR | V10: INR | W10: INR | X10: INR | Y10: INR | Z10: INR | AA10: INR | AB10: INR | AC10: INR | AD10: INR | AF10: INR | AG10: INR | AH10: INR | AI10: INR | AJ10: INR | AK10: INR | AL10: INR | AM10: INR | AN10: INR | AO10: INR | AP10: INR | AQ10: INR | AR10: INR | AT10: INR | AU10: INR | AV10: INR | AW10: INR | AX10: INR | AY10: INR | AZ10: INR | BA10: INR | BB10: INR | BC10: INR | BD10: INR | BE10: INR | BF10: INR | BH10: INR | BI10: INR | BJ10: INR | BK10: INR | BL10: INR | BM10: INR | BN10: INR | BO10: INR | BP10: INR | BQ10: INR | BR10: INR | BS10: INR | BT10: INR | BV10: INR | BW10: INR | BX10: INR | BY10: INR | BZ10: INR | CA10: INR | CB10: INR | CC10: INR | CD10: INR | CE10: INR | CF10: INR | CG10: INR | CH10: INR | CJ10: INR | CK10: INR | CL10: INR | CM10: INR | CN10: INR | CO10: INR | CP10: INR | CQ10: INR | CR10: INR | CS10: INR | CT10: INR | CU10: INR | CV10: INR | CX10: INR | CY10: INR | CZ10: INR | DA10: INR | DB10: INR | DC10: INR | DD10: INR | DE10: INR | DF10: INR | DG10: INR | DH10: INR | DI10: INR | DJ10: INR | DL10: INR | DM10: INR | DN10: INR | DO10: INR | DP10: INR | DQ10: INR | DR10: INR | DS10: INR | DT10: INR | DU10: INR | DV10: INR | DW10: INR | DX10: INR | DZ10: INR | EA10: INR | EB10: INR | EC10: INR | ED10: INR | EE10: INR | EF10: INR | EG10: INR | EH10: INR | EI10: INR | EJ10: INR | EK10: INR | EL10: INR | EN10: INR | EO10: INR | EP10: INR | EQ10: INR | ER10: INR | ES10: INR | ET10: INR | EU10: INR | EV10: INR | EW10: INR | EX10: INR | EY10: INR | EZ10: INR | FB10: INR | FC10: INR | FD10: INR | FE10: INR | FF10: INR | FG10: INR | FH10: INR | FI10: INR | FJ10: INR | FK10: INR | FL10: INR | FM10: INR | FN10: INR | FP10: INR | FQ10: INR | FR10: INR | FS10: INR | FT10: INR | FU10: INR | FV10: INR | FW10: INR | FX10: INR | FY10: INR | FZ10: INR | GA10: INR | GB10: INR | GD10: INR | GE10: INR | GF10: INR | GG10: INR | GH10: INR | GI10: INR | GJ10: INR | GK10: INR | GL10: INR | GM10: INR | GN10: INR | GO10: INR | GP10: INR | GR10: INR | GS10: INR | GT10: INR | GU10: INR | GV10: INR | GW10: INR | GX10: INR | GY10: INR | GZ10: INR | HA10: INR | HB10: INR | HC10: INR | HD10: INR | HF10: INR | HG10: INR | HH10: INR | HI10: INR | HJ10: INR | HK10: INR | HL10: INR | HM10: INR | HN10: INR | HO10: INR | HP10: INR | HQ10: INR | HR10: INR | HT10: INR | HU10: INR | HV10: INR | HW10: INR | HX10: INR | HY10: INR | HZ10: INR | IA10: INR | IB10: INR | IC10: INR | ID10: INR | IE10: INR | IF10: INR | IH10: INR | II10: INR | IJ10: INR | IK10: INR | IL10: INR | IM10: INR | IN10: INR | IO10: INR | IP10: INR | IQ10: INR | IR10: INR | IS10: INR | IT10: INR | IV10: INR | IW10: INR | IX10: INR | IY10: INR | IZ10: INR | JA10: INR | JB10: INR | JC10: INR | JD10: INR | JE10: INR | JF10: INR | JG10: INR | JH10: INR | JJ10: INR | JK10: INR | JL10: INR | JM10: INR | JN10: INR | JO10: INR | JP10: INR | JQ10: INR | JR10: INR | JS10: INR | JT10: INR | JU10: INR | JV10: INR | JX10: INR | JY10: INR | JZ10: INR | KA10: INR | KB10: INR | KC10: INR | KD10: INR | KE10: INR | KF10: INR | KG10: INR | KH10: INR | KI10: INR | KJ10: INR | KL10: INR | KM10: INR | KN10: INR | KO10: INR | KP10: INR | KQ10: INR | KR10: INR | KS10: INR | KT10: INR | KU10: INR | KV10: INR | KW10: INR | KX10: INR | KZ10: INR | LA10: INR | LB10: INR | LC10: INR | LD10: INR | LE10: INR | LF10: INR | LG10: INR | LH10: INR | LI10: INR | LJ10: INR | LK10: INR | LL10: INR | LN10: INR | LO10: INR | LP10: INR | LQ10: INR | LR10: INR | LS10: INR | LT10: INR | LU10: INR | LV10: INR | LW10: INR | LX10: INR | LY10: INR | LZ10: INR | MB10: INR | MC10: =MB10 -> INR | MD10: =MC10 -> INR | ME10: =MD10 -> INR | MF10: =ME10 -> INR | MG10: =MF10 -> INR | MH10: =MG10 -> INR | MI10: =MH10 -> INR | MJ10: =MI10 -> INR | ... MN10: =MM10 -> INR
B11: Month (2025) | D11: 45688 | E11: 45716 | F11: 45747 | G11: 45777 | H11: 45808 | I11: 45838 | J11: 45869 | K11: 45900 | L11: 45930 | M11: 45961 | N11: 45991 | O11: 46022 | P11: Budget-2025 | R11: 45688 | S11: 45716 | T11: 45747 | U11: 45777 | V11: 45808 | W11: 45838 | X11: 45869 | Y11: 45900 | Z11: 45930 | AA11: 45961 | AB11: 45991 | AC11: 46022 | AD11: =+P11 -> Budget-2025 | AF11: 45688 | AG11: 45716 | AH11: 45747 | AI11: 45777 | AJ11: 45808 | AK11: 45838 | AL11: 45869 | AM11: 45900 | AN11: 45930 | AO11: 45961 | AP11: 45991 | AQ11: 46022 | AR11: =AD11 -> Budget-2025 | AT11: 45688 | AU11: 45716 | AV11: 45747 | AW11: 45777 | AX11: 45808 | AY11: 45838 | AZ11: 45869 | BA11: 45900 | BB11: 45930 | BC11: 45961 | BD11: 45991 | BE11: 46022 | BF11: =AR11 -> Budget-2025 | BH11: 45688 | BI11: 45716 | BJ11: 45747 | BK11: 45777 | BL11: 45808 | BM11: 45838 | BN11: 45869 | BO11: 45900 | BP11: 45930 | BQ11: 45961 | BR11: 45991 | BS11: 46022 | BT11: =+#REF! -> #REF! | BV11: 45688 | BW11: 45716 | BX11: 45747 | BY11: 45777 | BZ11: 45808 | CA11: 45838 | CB11: 45869 | CC11: 45900 | CD11: 45930 | CE11: 45961 | CF11: 45991 | CG11: 46022 | CH11: =+#REF! -> #REF! | CJ11: 45688 | CK11: 45716 | CL11: 45747 | CM11: 45777 | CN11: 45808 | CO11: 45838 | CP11: 45869 | CQ11: 45900 | CR11: 45930 | CS11: 45961 | CT11: 45991 | CU11: 46022 | CV11: =+#REF! -> #REF! | CX11: 45688 | CY11: 45716 | CZ11: 45747 | DA11: 45777 | DB11: 45808 | DC11: 45838 | DD11: 45869 | DE11: 45900 | DF11: 45930 | DG11: 45961 | DH11: 45991 | DI11: 46022 | DJ11: =+CV11 -> #REF! | DL11: 45688 | DM11: 45716 | DN11: 45747 | DO11: 45777 | DP11: 45808 | DQ11: 45838 | DR11: 45869 | DS11: 45900 | DT11: 45930 | DU11: 45961 | DV11: 45991 | DW11: 46022 | DX11: =+DJ11 -> #REF! | DZ11: 45688 | EA11: 45716 | EB11: 45747 | EC11: 45777 | ED11: 45808 | EE11: 45838 | EF11: 45869 | EG11: 45900 | EH11: 45930 | EI11: 45961 | EJ11: 45991 | EK11: 46022 | EL11: =+DX11 -> #REF! | EN11: 45688 | EO11: 45716 | EP11: 45747 | EQ11: 45777 | ER11: 45808 | ES11: 45838 | ET11: 45869 | EU11: 45900 | EV11: 45930 | EW11: 45961 | EX11: 45991 | EY11: 46022 | EZ11: =+EL11 -> #REF! | FB11: 45688 | FC11: 45716 | FD11: 45747 | FE11: 45777 | FF11: 45808 | FG11: 45838 | FH11: 45869 | FI11: 45900 | FJ11: 45930 | FK11: 45961 | FL11: 45991 | FM11: 46022 | FN11: =+EZ11 -> #REF! | FP11: 45688 | FQ11: 45716 | FR11: 45747 | FS11: 45777 | FT11: 45808 | FU11: 45838 | FV11: 45869 | FW11: 45900 | FX11: 45930 | FY11: 45961 | FZ11: 45991 | GA11: 46022 | GB11: =+FN11 -> #REF! | GD11: 45688 | GE11: 45716 | GF11: 45747 | GG11: 45777 | GH11: 45808 | GI11: 45838 | GJ11: 45869 | GK11: 45900 | GL11: 45930 | GM11: 45961 | GN11: 45991 | GO11: 46022 | GP11: =+#REF! -> #REF! | GR11: 45688 | GS11: 45716 | GT11: 45747 | GU11: 45777 | GV11: 45808 | GW11: 45838 | GX11: 45869 | GY11: 45900 | GZ11: 45930 | HA11: 45961 | HB11: 45991 | HC11: 46022 | HD11: =+LL11 -> Total | HF11: 45688 | HG11: 45716 | HH11: 45747 | HI11: 45777 | HJ11: 45808 | HK11: 45838 | HL11: 45869 | HM11: 45900 | HN11: 45930 | HO11: 45961 | HP11: 45991 | HQ11: 46022 | HR11: =+GP11 -> #REF! | HT11: 45688 | HU11: 45716 | HV11: 45747 | HW11: 45777 | HX11: 45808 | HY11: 45838 | HZ11: 45869 | IA11: 45900 | IB11: 45930 | IC11: 45961 | ID11: 45991 | IE11: 46022 | IF11: =+HR11 -> #REF! | IH11: 45688 | II11: 45716 | IJ11: 45747 | IK11: 45777 | IL11: 45808 | IM11: 45838 | IN11: 45869 | IO11: 45900 | IP11: 45930 | IQ11: 45961 | IR11: 45991 | IS11: 46022 | IT11: =+IF11 -> #REF! | IV11: 45688 | IW11: 45716 | IX11: 45747 | IY11: 45777 | IZ11: 45808 | JA11: 45838 | JB11: 45869 | JC11: 45900 | JD11: 45930 | JE11: 45961 | JF11: 45991 | JG11: 46022 | JH11: =+IT11 -> #REF! | JJ11: 45688 | JK11: 45716 | JL11: 45747 | JM11: 45777 | JN11: 45808 | JO11: 45838 | JP11: 45869 | JQ11: 45900 | JR11: 45930 | JS11: 45961 | JT11: 45991 | JU11: 46022 | JV11: =+JH11 -> #REF! | JX11: 45688 | JY11: 45716 | JZ11: 45747 | KA11: 45777 | KB11: 45808 | KC11: 45838 | KD11: 45869 | KE11: 45900 | KF11: 45930 | KG11: 45961 | KH11: 45991 | KI11: 46022 | KJ11: =+JV11 -> #REF! | KL11: 45688 | KM11: 45716 | KN11: 45747 | KO11: 45777 | KP11: 45808 | KQ11: 45838 | KR11: 45869 | KS11: 45900 | KT11: 45930 | KU11: 45961 | KV11: 45991 | KW11: 46022 | KX11: Total | KZ11: 45688 | LA11: 45716 | LB11: 45747 | LC11: 45777 | LD11: 45808 | LE11: 45838 | LF11: 45869 | LG11: 45900 | LH11: 45930 | LI11: 45961 | LJ11: 45991 | LK11: 46022 | LL11: =+KX11 -> Total | LN11: 45688 | LO11: 45716 | LP11: 45747 | LQ11: 45777 | LR11: 45808 | LS11: 45838 | LT11: 45869 | LU11: 45900 | LV11: 45930 | LW11: 45961 | LX11: 45991 | LY11: 46022 | LZ11: =+HD11 -> Total | MB11: Total | MC11: =MB11 -> Total | MD11: =MC11 -> Total | ME11: =MD11 -> Total | MF11: =ME11 -> Total | MG11: =MF11 -> Total | MH11: =MG11 -> Total | MI11: =MH11 -> Total | MJ11: =MI11 -> Total | ... MN11: =MM11 -> Total
B12: Unique BU-Division Name | D12: Accounts-Fleet Accounts | E12: Accounts-Fleet Accounts | F12: Accounts-Fleet Accounts | G12: Accounts-Fleet Accounts | H12: Accounts-Fleet Accounts | I12: Accounts-Fleet Accounts | J12: Accounts-Fleet Accounts | K12: Accounts-Fleet Accounts | L12: Accounts-Fleet Accounts | M12: Accounts-Fleet Accounts | N12: Accounts-Fleet Accounts | O12: Accounts-Fleet Accounts | P12: Accounts-Fleet Accounts | R12: Admin-Administration | S12: Admin-Administration | T12: Admin-Administration | U12: Admin-Administration | V12: Admin-Administration | W12: Admin-Administration | X12: Admin-Administration | Y12: Admin-Administration | Z12: Admin-Administration | AA12: Admin-Administration | AB12: Admin-Administration | AC12: Admin-Administration | AD12: Admin-Administration | AF12: Agency Services-Agency Hub | AG12: Agency Services-Agency Hub | AH12: Agency Services-Agency Hub | AI12: Agency Services-Agency Hub | AJ12: Agency Services-Agency Hub | AK12: Agency Services-Agency Hub | AL12: Agency Services-Agency Hub | AM12: Agency Services-Agency Hub | AN12: Agency Services-Agency Hub | AO12: Agency Services-Agency Hub | AP12: Agency Services-Agency Hub | AQ12: Agency Services-Agency Hub | AR12: Agency Services-Agency Hub | AT12: Commercial-Commercial | AU12: Commercial-Commercial | AV12: Commercial-Commercial | AW12: Commercial-Commercial | AX12: Commercial-Commercial | AY12: Commercial-Commercial | AZ12: Commercial-Commercial | BA12: Commercial-Commercial | BB12: Commercial-Commercial | BC12: Commercial-Commercial | BD12: Commercial-Commercial | BE12: Commercial-Commercial | BF12: Commercial-Commercial | BH12: Consultancy Services-Fleet Performance | BI12: Consultancy Services-Fleet Performance | BJ12: Consultancy Services-Fleet Performance | BK12: Consultancy Services-Fleet Performance | BL12: Consultancy Services-Fleet Performance | BM12: Consultancy Services-Fleet Performance | BN12: Consultancy Services-Fleet Performance | BO12: Consultancy Services-Fleet Performance | BP12: Consultancy Services-Fleet Performance | BQ12: Consultancy Services-Fleet Performance | BR12: Consultancy Services-Fleet Performance | BS12: Consultancy Services-Fleet Performance | BT12: Consultancy Services-Fleet Performance | BV12: Crew Management-Group Marine HR | BW12: Crew Management-Group Marine HR | BX12: Crew Management-Group Marine HR | BY12: Crew Management-Group Marine HR | BZ12: Crew Management-Group Marine HR | CA12: Crew Management-Group Marine HR | CB12: Crew Management-Group Marine HR | CC12: Crew Management-Group Marine HR | CD12: Crew Management-Group Marine HR | CE12: Crew Management-Group Marine HR | CF12: Crew Management-Group Marine HR | CG12: Crew Management-Group Marine HR | CH12: Crew Management-Group Marine HR | CJ12: Cruise Management-Miami Ship Management | CK12: Cruise Management-Miami Ship Management | CL12: Cruise Management-Miami Ship Management | CM12: Cruise Management-Miami Ship Management | CN12: Cruise Management-Miami Ship Management | CO12: Cruise Management-Miami Ship Management | CP12: Cruise Management-Miami Ship Management | CQ12: Cruise Management-Miami Ship Management | CR12: Cruise Management-Miami Ship Management | CS12: Cruise Management-Miami Ship Management | CT12: Cruise Management-Miami Ship Management | CU12: Cruise Management-Miami Ship Management | CV12: Cruise Management-Miami Ship Management | CX12: IT-Group IT | CY12: IT-Group IT | CZ12: IT-Group IT | DA12: IT-Group IT | DB12: IT-Group IT | DC12: IT-Group IT | DD12: IT-Group IT | DE12: IT-Group IT | DF12: IT-Group IT | DG12: IT-Group IT | DH12: IT-Group IT | DI12: IT-Group IT | DJ12: IT-Group IT | DL12: Procurement-Galleymasters | DM12: Procurement-Galleymasters | DN12: Procurement-Galleymasters | DO12: Procurement-Galleymasters | DP12: Procurement-Galleymasters | DQ12: Procurement-Galleymasters | DR12: Procurement-Galleymasters | DS12: Procurement-Galleymasters | DT12: Procurement-Galleymasters | DU12: Procurement-Galleymasters | DV12: Procurement-Galleymasters | DW12: Procurement-Galleymasters | DX12: Procurement-Galleymasters | DZ12: Procurement-Sourcing | EA12: Procurement-Sourcing | EB12: Procurement-Sourcing | EC12: Procurement-Sourcing | ED12: Procurement-Sourcing | EE12: Procurement-Sourcing | EF12: Procurement-Sourcing | EG12: Procurement-Sourcing | EH12: Procurement-Sourcing | EI12: Procurement-Sourcing | EJ12: Procurement-Sourcing | EK12: Procurement-Sourcing | EL12: Procurement-Sourcing | EN12: Ship Management-Antwerp Dry | EO12: Ship Management-Antwerp Dry | EP12: Ship Management-Antwerp Dry | EQ12: Ship Management-Antwerp Dry | ER12: Ship Management-Antwerp Dry | ES12: Ship Management-Antwerp Dry | ET12: Ship Management-Antwerp Dry | EU12: Ship Management-Antwerp Dry | EV12: Ship Management-Antwerp Dry | EW12: Ship Management-Antwerp Dry | EX12: Ship Management-Antwerp Dry | EY12: Ship Management-Antwerp Dry | EZ12: Ship Management-Antwerp Dry | FB12: Ship Management-Goes Dry | FC12: Ship Management-Goes Dry | FD12: Ship Management-Goes Dry | FE12: Ship Management-Goes Dry | FF12: Ship Management-Goes Dry | FG12: Ship Management-Goes Dry | FH12: Ship Management-Goes Dry | FI12: Ship Management-Goes Dry | FJ12: Ship Management-Goes Dry | FK12: Ship Management-Goes Dry | FL12: Ship Management-Goes Dry | FM12: Ship Management-Goes Dry | FN12: Ship Management-Goes Dry | FP12: Ship Management-Group Operations | FQ12: Ship Management-Group Operations | FR12: Ship Management-Group Operations | FS12: Ship Management-Group Operations | FT12: Ship Management-Group Operations | FU12: Ship Management-Group Operations | FV12: Ship Management-Group Operations | FW12: Ship Management-Group Operations | FX12: Ship Management-Group Operations | FY12: Ship Management-Group Operations | FZ12: Ship Management-Group Operations | GA12: Ship Management-Group Operations | GB12: Ship Management-Group Operations | GD12: Ship Management-Group Shared Service Center | GE12: Ship Management-Group Shared Service Center | GF12: Ship Management-Group Shared Service Center | GG12: Ship Management-Group Shared Service Center | GH12: Ship Management-Group Shared Service Center | GI12: Ship Management-Group Shared Service Center | GJ12: Ship Management-Group Shared Service Center | GK12: Ship Management-Group Shared Service Center | GL12: Ship Management-Group Shared Service Center | GM12: Ship Management-Group Shared Service Center | GN12: Ship Management-Group Shared Service Center | GO12: Ship Management-Group Shared Service Center | GP12: Ship Management-Group Shared Service Center | GR12: Vacant Seats | GS12: Vacant Seats | GT12: Vacant Seats | GU12: Vacant Seats | GV12: Vacant Seats | GW12: Vacant Seats | GX12: Vacant Seats | GY12: Vacant Seats | GZ12: Vacant Seats | HA12: Vacant Seats | HB12: Vacant Seats | HC12: Vacant Seats | HD12: Vacant Seats | HF12: Ship Management-Hamburg Dry | HG12: Ship Management-Hamburg Dry | HH12: Ship Management-Hamburg Dry | HI12: Ship Management-Hamburg Dry | HJ12: Ship Management-Hamburg Dry | HK12: Ship Management-Hamburg Dry | HL12: Ship Management-Hamburg Dry | HM12: Ship Management-Hamburg Dry | HN12: Ship Management-Hamburg Dry | HO12: Ship Management-Hamburg Dry | HP12: Ship Management-Hamburg Dry | HQ12: Ship Management-Hamburg Dry | HR12: Ship Management-Hamburg Dry | HT12: Ship Management-Hong Kong Dry 1 | HU12: Ship Management-Hong Kong Dry 1 | HV12: Ship Management-Hong Kong Dry 1 | HW12: Ship Management-Hong Kong Dry 1 | HX12: Ship Management-Hong Kong Dry 1 | HY12: Ship Management-Hong Kong Dry 1 | HZ12: Ship Management-Hong Kong Dry 1 | IA12: Ship Management-Hong Kong Dry 1 | IB12: Ship Management-Hong Kong Dry 1 | IC12: Ship Management-Hong Kong Dry 1 | ID12: Ship Management-Hong Kong Dry 1 | IE12: Ship Management-Hong Kong Dry 1 | IF12: Ship Management-Hong Kong Dry 1 | IH12: Ship Management-JV Ardmore | II12: Ship Management-JV Ardmore | IJ12: Ship Management-JV Ardmore | IK12: Ship Management-JV Ardmore | IL12: Ship Management-JV Ardmore | IM12: Ship Management-JV Ardmore | IN12: Ship Management-JV Ardmore | IO12: Ship Management-JV Ardmore | IP12: Ship Management-JV Ardmore | IQ12: Ship Management-JV Ardmore | IR12: Ship Management-JV Ardmore | IS12: Ship Management-JV Ardmore | IT12: Ship Management-JV Ardmore | IV12: Ship Management-Singapore Dry | IW12: Ship Management-Singapore Dry | IX12: Ship Management-Singapore Dry | IY12: Ship Management-Singapore Dry | IZ12: Ship Management-Singapore Dry | JA12: Ship Management-Singapore Dry | JB12: Ship Management-Singapore Dry | JC12: Ship Management-Singapore Dry | JD12: Ship Management-Singapore Dry | JE12: Ship Management-Singapore Dry | JF12: Ship Management-Singapore Dry | JG12: Ship Management-Singapore Dry | JH12: Ship Management-Singapore Dry | JJ12: Ship Management-Singapore Tanker 1 | JK12: Ship Management-Singapore Tanker 1 | JL12: Ship Management-Singapore Tanker 1 | JM12: Ship Management-Singapore Tanker 1 | JN12: Ship Management-Singapore Tanker 1 | JO12: Ship Management-Singapore Tanker 1 | JP12: Ship Management-Singapore Tanker 1 | JQ12: Ship Management-Singapore Tanker 1 | JR12: Ship Management-Singapore Tanker 1 | JS12: Ship Management-Singapore Tanker 1 | JT12: Ship Management-Singapore Tanker 1 | JU12: Ship Management-Singapore Tanker 1 | JV12: Ship Management-Singapore Tanker 1 | JX12: Ship Management-Singapore Tanker 2 | JY12: Ship Management-Singapore Tanker 2 | JZ12: Ship Management-Singapore Tanker 2 | KA12: Ship Management-Singapore Tanker 2 | KB12: Ship Management-Singapore Tanker 2 | KC12: Ship Management-Singapore Tanker 2 | KD12: Ship Management-Singapore Tanker 2 | KE12: Ship Management-Singapore Tanker 2 | KF12: Ship Management-Singapore Tanker 2 | KG12: Ship Management-Singapore Tanker 2 | KH12: Ship Management-Singapore Tanker 2 | KI12: Ship Management-Singapore Tanker 2 | KJ12: Ship Management-Singapore Tanker 2 | KL12: Accounts-Accounts Payables | KM12: Accounts-Accounts Payables | KN12: Accounts-Accounts Payables | KO12: Accounts-Accounts Payables | KP12: Accounts-Accounts Payables | KQ12: Accounts-Accounts Payables | KR12: Accounts-Accounts Payables | KS12: Accounts-Accounts Payables | KT12: Accounts-Accounts Payables | KU12: Accounts-Accounts Payables | KV12: Accounts-Accounts Payables | KW12: Accounts-Accounts Payables | KX12: Accounts-Accounts Payables | KZ12: Accounts-CMI Accounts Payables | LA12: Accounts-CMI Accounts Payables | LB12: Accounts-CMI Accounts Payables | LC12: Accounts-CMI Accounts Payables | LD12: Accounts-CMI Accounts Payables | LE12: Accounts-CMI Accounts Payables | LF12: Accounts-CMI Accounts Payables | LG12: Accounts-CMI Accounts Payables | LH12: Accounts-CMI Accounts Payables | LI12: Accounts-CMI Accounts Payables | LJ12: Accounts-CMI Accounts Payables | LK12: Accounts-CMI Accounts Payables | LL12: Accounts-CMI Accounts Payables | MB12: 30 Divisions | MC12: =MB12 -> 30 Divisions | MD12: =MC12 -> 30 Divisions | ME12: =MD12 -> 30 Divisions | MF12: =ME12 -> 30 Divisions | MG12: =MF12 -> 30 Divisions | MH12: =MG12 -> 30 Divisions | MI12: =MH12 -> 30 Divisions | MJ12: =MI12 -> 30 Divisions | ... MN12: =MM12 -> 30 Divisions
B13: INCOME
B14: Ship Management - Other Income | D14: 0 | E14: 0 | F14: 0 | G14: 0 | H14: 0 | I14: 0 | J14: 0 | K14: 0 | L14: 0 | M14: 0 | N14: 0 | O14: 0 | P14: =+SUBTOTAL(9,D14:O14) -> 0 | R14: 0 | S14: 0 | T14: 0 | U14: 0 | V14: 0 | W14: 0 | X14: 0 | Y14: 0 | Z14: 0 | AA14: 0 | AB14: 0 | AC14: 0 | AD14: =+SUBTOTAL(9,R14:AC14) -> 0 | AF14: 0 | AG14: 0 | AH14: 0 | AI14: 0 | AJ14: 0 | AK14: 0 | AL14: 0 | AM14: 0 | AN14: 0 | AO14: 0 | AP14: 0 | AQ14: 0 | AR14: =+SUBTOTAL(9,AF14:AQ14) -> 0 | AT14: 0 | AU14: 0 | AV14: 0 | AW14: 0 | AX14: 0 | AY14: 0 | AZ14: 0 | BA14: 0 | BB14: 0 | BC14: 0 | BD14: 0 | BE14: 0 | BF14: =+SUBTOTAL(9,AT14:BE14) -> 0 | BH14: 0 | BI14: 0 | BJ14: 0 | BK14: 0 | BL14: 0 | BM14: 0 | BN14: 0 | BO14: 0 | BP14: 0 | BQ14: 0 | BR14: 0 | BS14: 0 | BT14: =+SUBTOTAL(9,BH14:BS14) -> 0 | BV14: 0 | BW14: 0 | BX14: 0 | BY14: 0 | BZ14: 0 | CA14: 0 | CB14: 0 | CC14: 0 | CD14: 0 | CE14: 0 | CF14: 0 | CG14: 0 | CH14: =+SUBTOTAL(9,BV14:CG14) -> 0 | CJ14: 0 | CK14: 0 | CL14: 0 | CM14: 0 | CN14: 0 | CO14: 0 | CP14: 0 | CQ14: 0 | CR14: 0 | CS14: 0 | CT14: 0 | CU14: 0 | CV14: =+SUBTOTAL(9,CJ14:CU14) -> 0 | CX14: 0 | CY14: 0 | CZ14: 0 | DA14: 0 | DB14: 0 | DC14: 0 | DD14: 0 | DE14: 0 | DF14: 0 | DG14: 0 | DH14: 0 | DI14: 0 | DJ14: =+SUBTOTAL(9,CX14:DI14) -> 0 | DL14: 0 | DM14: 0 | DN14: 0 | DO14: 0 | DP14: 0 | DQ14: 0 | DR14: 0 | DS14: 0 | DT14: 0 | DU14: 0 | DV14: 0 | DW14: 0 | DX14: =+SUBTOTAL(9,DL14:DW14) -> 0 | DZ14: 0 | EA14: 0 | EB14: 0 | EC14: 0 | ED14: 0 | EE14: 0 | EF14: 0 | EG14: 0 | EH14: 0 | EI14: 0 | EJ14: 0 | EK14: 0 | EL14: =+SUBTOTAL(9,DZ14:EK14) -> 0 | EN14: 0 | EO14: 0 | EP14: 0 | EQ14: 0 | ER14: 0 | ES14: 0 | ET14: 0 | EU14: 0 | EV14: 0 | EW14: 0 | EX14: 0 | EY14: 0 | EZ14: =+SUBTOTAL(9,EN14:EY14) -> 0 | FB14: 0 | FC14: 0 | FD14: 0 | FE14: 0 | FF14: 0 | FG14: 0 | FH14: 0 | FI14: 0 | FJ14: 0 | FK14: 0 | FL14: 0 | FM14: 0 | FN14: =+SUBTOTAL(9,FB14:FM14) -> 0 | FP14: 0 | FQ14: 0 | FR14: 0 | FS14: 0 | FT14: 0 | FU14: 0 | FV14: 0 | FW14: 0 | FX14: 0 | FY14: 0 | FZ14: 0 | GA14: 0 | GB14: =+SUBTOTAL(9,FP14:GA14) -> 0 | GD14: 0 | GE14: 0 | GF14: 0 | GG14: 0 | GH14: 0 | GI14: 0 | GJ14: 0 | GK14: 0 | GL14: 0 | GM14: 0 | GN14: 0 | GO14: 0 | GP14: =+SUBTOTAL(9,GD14:GO14) -> 0 | GR14: 0 | GS14: 0 | GT14: 0 | GU14: 0 | GV14: 0 | GW14: 0 | GX14: 0 | GY14: 0 | GZ14: 0 | HA14: 0 | HB14: 0 | HC14: 0 | HD14: =+SUBTOTAL(9,GR14:HC14) -> 0 | HF14: 0 | HG14: 0 | HH14: 0 | HI14: 0 | HJ14: 0 | HK14: 0 | HL14: 0 | HM14: 0 | HN14: 0 | HO14: 0 | HP14: 0 | HQ14: 0 | HR14: =+SUBTOTAL(9,HF14:HQ14) -> 0 | HT14: 0 | HU14: 0 | HV14: 0 | HW14: 0 | HX14: 0 | HY14: 0 | HZ14: 0 | IA14: 0 | IB14: 0 | IC14: 0 | ID14: 0 | IE14: 0 | IF14: =+SUBTOTAL(9,HT14:IE14) -> 0 | IH14: 0 | II14: 0 | IJ14: 0 | IK14: 0 | IL14: 0 | IM14: 0 | IN14: 0 | IO14: 0 | IP14: 0 | IQ14: 0 | IR14: 0 | IS14: 0 | IT14: =+SUBTOTAL(9,IH14:IS14) -> 0 | IV14: 0 | IW14: 0 | IX14: 0 | IY14: 0 | IZ14: 0 | JA14: 0 | JB14: 0 | JC14: 0 | JD14: 0 | JE14: 0 | JF14: 0 | JG14: 0 | JH14: =+SUBTOTAL(9,IV14:JG14) -> 0 | JJ14: 0 | JK14: 0 | JL14: 0 | JM14: 0 | JN14: 0 | JO14: 0 | JP14: 0 | JQ14: 0 | JR14: 0 | JS14: 0 | JT14: 0 | JU14: 0 | JV14: =+SUBTOTAL(9,JJ14:JU14) -> 0 | JX14: 0 | JY14: 0 | JZ14: 0 | KA14: 0 | KB14: 0 | KC14: 0 | KD14: 0 | KE14: 0 | KF14: 0 | KG14: 0 | KH14: 0 | KI14: 0 | KJ14: =+SUBTOTAL(9,JX14:KI14) -> 0 | KL14: 0 | KM14: 0 | KN14: 0 | KO14: 0 | KP14: 0 | KQ14: 0 | KR14: 0 | KS14: 0 | KT14: 0 | KU14: 0 | KV14: 0 | KW14: 0 | KX14: =+SUBTOTAL(9,KL14:KW14) -> 0 | KZ14: 0 | LA14: 0 | LB14: 0 | LC14: 0 | LD14: 0 | LE14: 0 | LF14: 0 | LG14: 0 | LH14: 0 | LI14: 0 | LJ14: 0 | LK14: 0 | LL14: =+SUBTOTAL(9,KZ14:LK14) -> 0 | LN14: 0 | LO14: 0 | LP14: 0 | LQ14: 0 | LR14: 0 | LS14: 0 | LT14: 0 | LU14: 0 | LV14: 0 | LW14: 0 | LX14: 0 | LY14: 0 | LZ14: =+SUBTOTAL(9,LN14:LY14) -> 0 | MB14: =SUMIF($D$11:$LY$11,MB$8,$D14:$LY14) -> 0 | MC14: =SUMIF($D$11:$LY$11,MC$8,$D14:$LY14) -> 0 | MD14: =SUMIF($D$11:$LY$11,MD$8,$D14:$LY14) -> 0 | ME14: =SUMIF($D$11:$LY$11,ME$8,$D14:$LY14) -> 0 | MF14: =SUMIF($D$11:$LY$11,MF$8,$D14:$LY14) -> 0 | MG14: =SUMIF($D$11:$LY$11,MG$8,$D14:$LY14) -> 0 | MH14: =SUMIF($D$11:$LY$11,MH$8,$D14:$LY14) -> 0 | MI14: =SUMIF($D$11:$LY$11,MI$8,$D14:$LY14) -> 0 | ... MM14: =SUMIF($D$11:$LY$11,MM$8,$D14:$LY14) -> 0 | MN14: =SUM(MB14:MM14) -> 0
B15: Intercompany Sales | D15: 0 | E15: 0 | F15: 0 | G15: 0 | H15: 0 | I15: 0 | J15: 0 | K15: 0 | L15: 0 | M15: 0 | N15: 0 | O15: 0 | P15: =+SUBTOTAL(9,D15:O15) -> 0 | R15: 0 | S15: 0 | T15: 0 | U15: 0 | V15: 0 | W15: 0 | X15: 0 | Y15: 0 | Z15: 0 | AA15: 0 | AB15: 0 | AC15: 0 | AD15: =+SUBTOTAL(9,R15:AC15) -> 0 | AF15: 0 | AG15: 0 | AH15: 0 | AI15: 0 | AJ15: 0 | AK15: 0 | AL15: 0 | AM15: 0 | AN15: 0 | AO15: 0 | AP15: 0 | AQ15: 0 | AR15: =+SUBTOTAL(9,AF15:AQ15) -> 0 | AT15: 0 | AU15: 0 | AV15: 0 | AW15: 0 | AX15: 0 | AY15: 0 | AZ15: 0 | BA15: 0 | BB15: 0 | BC15: 0 | BD15: 0 | BE15: 0 | BF15: =+SUBTOTAL(9,AT15:BE15) -> 0 | BH15: 0 | BI15: 0 | BJ15: 0 | BK15: 0 | BL15: 0 | BM15: 0 | BN15: 0 | BO15: 0 | BP15: 0 | BQ15: 0 | BR15: 0 | BS15: 0 | BT15: =+SUBTOTAL(9,BH15:BS15) -> 0 | BV15: 0 | BW15: 0 | BX15: 0 | BY15: 0 | BZ15: 0 | CA15: 0 | CB15: 0 | CC15: 0 | CD15: 0 | CE15: 0 | CF15: 0 | CG15: 0 | CH15: =+SUBTOTAL(9,BV15:CG15) -> 0 | CJ15: 0 | CK15: 0 | CL15: 0 | CM15: 0 | CN15: 0 | CO15: 0 | CP15: 0 | CQ15: 0 | CR15: 0 | CS15: 0 | CT15: 0 | CU15: 0 | CV15: =+SUBTOTAL(9,CJ15:CU15) -> 0 | CX15: 0 | CY15: 0 | CZ15: 0 | DA15: 0 | DB15: 0 | DC15: 0 | DD15: 0 | DE15: 0 | DF15: 0 | DG15: 0 | DH15: 0 | DI15: 0 | DJ15: =+SUBTOTAL(9,CX15:DI15) -> 0 | DL15: 0 | DM15: 0 | DN15: 0 | DO15: 0 | DP15: 0 | DQ15: 0 | DR15: 0 | DS15: 0 | DT15: 0 | DU15: 0 | DV15: 0 | DW15: 0 | DX15: =+SUBTOTAL(9,DL15:DW15) -> 0 | DZ15: 0 | EA15: 0 | EB15: 0 | EC15: 0 | ED15: 0 | EE15: 0 | EF15: 0 | EG15: 0 | EH15: 0 | EI15: 0 | EJ15: 0 | EK15: 0 | EL15: =+SUBTOTAL(9,DZ15:EK15) -> 0 | EN15: 0 | EO15: 0 | EP15: 0 | EQ15: 0 | ER15: 0 | ES15: 0 | ET15: 0 | EU15: 0 | EV15: 0 | EW15: 0 | EX15: 0 | EY15: 0 | EZ15: =+SUBTOTAL(9,EN15:EY15) -> 0 | FB15: 0 | FC15: 0 | FD15: 0 | FE15: 0 | FF15: 0 | FG15: 0 | FH15: 0 | FI15: 0 | FJ15: 0 | FK15: 0 | FL15: 0 | FM15: 0 | FN15: =+SUBTOTAL(9,FB15:FM15) -> 0 | FP15: 0 | FQ15: 0 | FR15: 0 | FS15: 0 | FT15: 0 | FU15: 0 | FV15: 0 | FW15: 0 | FX15: 0 | FY15: 0 | FZ15: 0 | GA15: 0 | GB15: =+SUBTOTAL(9,FP15:GA15) -> 0 | GD15: 0 | GE15: 0 | GF15: 0 | GG15: 0 | GH15: 0 | GI15: 0 | GJ15: 0 | GK15: 0 | GL15: 0 | GM15: 0 | GN15: 0 | GO15: 0 | GP15: =+SUBTOTAL(9,GD15:GO15) -> 0 | GR15: 0 | GS15: 0 | GT15: 0 | GU15: 0 | GV15: 0 | GW15: 0 | GX15: 0 | GY15: 0 | GZ15: 0 | HA15: 0 | HB15: 0 | HC15: 0 | HD15: =+SUBTOTAL(9,GR15:HC15) -> 0 | HF15: 0 | HG15: 0 | HH15: 0 | HI15: 0 | HJ15: 0 | HK15: 0 | HL15: 0 | HM15: 0 | HN15: 0 | HO15: 0 | HP15: 0 | HQ15: 0 | HR15: =+SUBTOTAL(9,HF15:HQ15) -> 0 | HT15: 0 | HU15: 0 | HV15: 0 | HW15: 0 | HX15: 0 | HY15: 0 | HZ15: 0 | IA15: 0 | IB15: 0 | IC15: 0 | ID15: 0 | IE15: 0 | IF15: =+SUBTOTAL(9,HT15:IE15) -> 0 | IH15: 0 | II15: 0 | IJ15: 0 | IK15: 0 | IL15: 0 | IM15: 0 | IN15: 0 | IO15: 0 | IP15: 0 | IQ15: 0 | IR15: 0 | IS15: 0 | IT15: =+SUBTOTAL(9,IH15:IS15) -> 0 | IV15: 0 | IW15: 0 | IX15: 0 | IY15: 0 | IZ15: 0 | JA15: 0 | JB15: 0 | JC15: 0 | JD15: 0 | JE15: 0 | JF15: 0 | JG15: 0 | JH15: =+SUBTOTAL(9,IV15:JG15) -> 0 | JJ15: 0 | JK15: 0 | JL15: 0 | JM15: 0 | JN15: 0 | JO15: 0 | JP15: 0 | JQ15: 0 | JR15: 0 | JS15: 0 | JT15: 0 | JU15: 0 | JV15: =+SUBTOTAL(9,JJ15:JU15) -> 0 | JX15: 0 | JY15: 0 | JZ15: 0 | KA15: 0 | KB15: 0 | KC15: 0 | KD15: 0 | KE15: 0 | KF15: 0 | KG15: 0 | KH15: 0 | KI15: 0 | KJ15: =+SUBTOTAL(9,JX15:KI15) -> 0 | KL15: 0 | KM15: 0 | KN15: 0 | KO15: 0 | KP15: 0 | KQ15: 0 | KR15: 0 | KS15: 0 | KT15: 0 | KU15: 0 | KV15: 0 | KW15: 0 | KX15: =+SUBTOTAL(9,KL15:KW15) -> 0 | KZ15: 0 | LA15: 0 | LB15: 0 | LC15: 0 | LD15: 0 | LE15: 0 | LF15: 0 | LG15: 0 | LH15: 0 | LI15: 0 | LJ15: 0 | LK15: 0 | LL15: =+SUBTOTAL(9,KZ15:LK15) -> 0 | LN15: 0 | LO15: 0 | LP15: 0 | LQ15: 0 | LR15: 0 | LS15: 0 | LT15: 0 | LU15: 0 | LV15: 0 | LW15: 0 | LX15: 0 | LY15: 0 | LZ15: =+SUBTOTAL(9,LN15:LY15) -> 0 | MB15: =SUMIF($D$11:$LY$11,MB$8,$D15:$LY15) -> 0 | MC15: =SUMIF($D$11:$LY$11,MC$8,$D15:$LY15) -> 0 | MD15: =SUMIF($D$11:$LY$11,MD$8,$D15:$LY15) -> 0 | ME15: =SUMIF($D$11:$LY$11,ME$8,$D15:$LY15) -> 0 | MF15: =SUMIF($D$11:$LY$11,MF$8,$D15:$LY15) -> 0 | MG15: =SUMIF($D$11:$LY$11,MG$8,$D15:$LY15) -> 0 | MH15: =SUMIF($D$11:$LY$11,MH$8,$D15:$LY15) -> 0 | MI15: =SUMIF($D$11:$LY$11,MI$8,$D15:$LY15) -> 0 | ... MM15: =SUMIF($D$11:$LY$11,MM$8,$D15:$LY15) -> 0 | MN15: =SUM(MB15:MM15) -> 0
B17: TOTAL INCOME | D17: =SUM(D14:D16) -> 0 | E17: =SUM(E14:E16) -> 0 | F17: =SUM(F14:F16) -> 0 | G17: =SUM(G14:G16) -> 0 | H17: =SUM(H14:H16) -> 0 | I17: =SUM(I14:I16) -> 0 | J17: =SUM(J14:J16) -> 0 | K17: =SUM(K14:K16) -> 0 | ... O17: =SUM(O14:O16) -> 0 | P17: =+SUBTOTAL(9,D17:O17) -> 0 | R17: =SUM(R14:R16) -> 0 | S17: =SUM(S14:S16) -> 0 | T17: =SUM(T14:T16) -> 0 | U17: =SUM(U14:U16) -> 0 | V17: =SUM(V14:V16) -> 0 | W17: =SUM(W14:W16) -> 0 | X17: =SUM(X14:X16) -> 0 | Y17: =SUM(Y14:Y16) -> 0 | ... AC17: =SUM(AC14:AC16) -> 0 | AD17: =+SUBTOTAL(9,R17:AC17) -> 0 | AF17: =SUM(AF14:AF16) -> 0 | AG17: =SUM(AG14:AG16) -> 0 | AH17: =SUM(AH14:AH16) -> 0 | AI17: =SUM(AI14:AI16) -> 0 | AJ17: =SUM(AJ14:AJ16) -> 0 | AK17: =SUM(AK14:AK16) -> 0 | AL17: =SUM(AL14:AL16) -> 0 | AM17: =SUM(AM14:AM16) -> 0 | ... AQ17: =SUM(AQ14:AQ16) -> 0 | AR17: =+SUBTOTAL(9,AF17:AQ17) -> 0 | AT17: =SUM(AT14:AT16) -> 0 | AU17: =SUM(AU14:AU16) -> 0 | AV17: =SUM(AV14:AV16) -> 0 | AW17: =SUM(AW14:AW16) -> 0 | AX17: =SUM(AX14:AX16) -> 0 | AY17: =SUM(AY14:AY16) -> 0 | AZ17: =SUM(AZ14:AZ16) -> 0 | BA17: =SUM(BA14:BA16) -> 0 | ... BE17: =SUM(BE14:BE16) -> 0 | BF17: =+SUBTOTAL(9,AT17:BE17) -> 0 | BH17: =SUM(BH14:BH16) -> 0 | BI17: =SUM(BI14:BI16) -> 0 | BJ17: =SUM(BJ14:BJ16) -> 0 | BK17: =SUM(BK14:BK16) -> 0 | BL17: =SUM(BL14:BL16) -> 0 | BM17: =SUM(BM14:BM16) -> 0 | BN17: =SUM(BN14:BN16) -> 0 | BO17: =SUM(BO14:BO16) -> 0 | ... BS17: =SUM(BS14:BS16) -> 0 | BT17: =+SUBTOTAL(9,BH17:BS17) -> 0 | BV17: =SUM(BV14:BV16) -> 0 | BW17: =SUM(BW14:BW16) -> 0 | BX17: =SUM(BX14:BX16) -> 0 | BY17: =SUM(BY14:BY16) -> 0 | BZ17: =SUM(BZ14:BZ16) -> 0 | CA17: =SUM(CA14:CA16) -> 0 | CB17: =SUM(CB14:CB16) -> 0 | CC17: =SUM(CC14:CC16) -> 0 | ... CG17: =SUM(CG14:CG16) -> 0 | CH17: =+SUBTOTAL(9,BV17:CG17) -> 0 | CJ17: =SUM(CJ14:CJ16) -> 0 | CK17: =SUM(CK14:CK16) -> 0 | CL17: =SUM(CL14:CL16) -> 0 | CM17: =SUM(CM14:CM16) -> 0 | CN17: =SUM(CN14:CN16) -> 0 | CO17: =SUM(CO14:CO16) -> 0 | CP17: =SUM(CP14:CP16) -> 0 | CQ17: =SUM(CQ14:CQ16) -> 0 | ... CU17: =SUM(CU14:CU16) -> 0 | CV17: =+SUBTOTAL(9,CJ17:CU17) -> 0 | CX17: =SUM(CX14:CX16) -> 0 | CY17: =SUM(CY14:CY16) -> 0 | CZ17: =SUM(CZ14:CZ16) -> 0 | DA17: =SUM(DA14:DA16) -> 0 | DB17: =SUM(DB14:DB16) -> 0 | DC17: =SUM(DC14:DC16) -> 0 | DD17: =SUM(DD14:DD16) -> 0 | DE17: =SUM(DE14:DE16) -> 0 | ... DI17: =SUM(DI14:DI16) -> 0 | DJ17: =+SUBTOTAL(9,CX17:DI17) -> 0 | DL17: =SUM(DL14:DL16) -> 0 | DM17: =SUM(DM14:DM16) -> 0 | DN17: =SUM(DN14:DN16) -> 0 | DO17: =SUM(DO14:DO16) -> 0 | DP17: =SUM(DP14:DP16) -> 0 | DQ17: =SUM(DQ14:DQ16) -> 0 | DR17: =SUM(DR14:DR16) -> 0 | DS17: =SUM(DS14:DS16) -> 0 | ... DW17: =SUM(DW14:DW16) -> 0 | DX17: =+SUBTOTAL(9,DL17:DW17) -> 0 | DZ17: =SUM(DZ14:DZ16) -> 0 | EA17: =SUM(EA14:EA16) -> 0 | EB17: =SUM(EB14:EB16) -> 0 | EC17: =SUM(EC14:EC16) -> 0 | ED17: =SUM(ED14:ED16) -> 0 | EE17: =SUM(EE14:EE16) -> 0 | EF17: =SUM(EF14:EF16) -> 0 | EG17: =SUM(EG14:EG16) -> 0 | ... EK17: =SUM(EK14:EK16) -> 0 | EL17: =+SUBTOTAL(9,DZ17:EK17) -> 0 | EN17: =SUM(EN14:EN16) -> 0 | EO17: =SUM(EO14:EO16) -> 0 | EP17: =SUM(EP14:EP16) -> 0 | EQ17: =SUM(EQ14:EQ16) -> 0 | ER17: =SUM(ER14:ER16) -> 0 | ES17: =SUM(ES14:ES16) -> 0 | ET17: =SUM(ET14:ET16) -> 0 | EU17: =SUM(EU14:EU16) -> 0 | ... EY17: =SUM(EY14:EY16) -> 0 | EZ17: =+SUBTOTAL(9,EN17:EY17) -> 0 | FB17: =SUM(FB14:FB16) -> 0 | FC17: =SUM(FC14:FC16) -> 0 | FD17: =SUM(FD14:FD16) -> 0 | FE17: =SUM(FE14:FE16) -> 0 | FF17: =SUM(FF14:FF16) -> 0 | FG17: =SUM(FG14:FG16) -> 0 | FH17: =SUM(FH14:FH16) -> 0 | FI17: =SUM(FI14:FI16) -> 0 | ... FM17: =SUM(FM14:FM16) -> 0 | FN17: =+SUBTOTAL(9,FB17:FM17) -> 0 | FP17: =SUM(FP14:FP16) -> 0 | FQ17: =SUM(FQ14:FQ16) -> 0 | FR17: =SUM(FR14:FR16) -> 0 | FS17: =SUM(FS14:FS16) -> 0 | FT17: =SUM(FT14:FT16) -> 0 | FU17: =SUM(FU14:FU16) -> 0 | FV17: =SUM(FV14:FV16) -> 0 | FW17: =SUM(FW14:FW16) -> 0 | ... GA17: =SUM(GA14:GA16) -> 0 | GB17: =+SUBTOTAL(9,FP17:GA17) -> 0 | GD17: =SUM(GD14:GD16) -> 0 | GE17: =SUM(GE14:GE16) -> 0 | GF17: =SUM(GF14:GF16) -> 0 | GG17: =SUM(GG14:GG16) -> 0 | GH17: =SUM(GH14:GH16) -> 0 | GI17: =SUM(GI14:GI16) -> 0 | GJ17: =SUM(GJ14:GJ16) -> 0 | GK17: =SUM(GK14:GK16) -> 0 | ... GO17: =SUM(GO14:GO16) -> 0 | GP17: =+SUBTOTAL(9,GD17:GO17) -> 0 | GR17: =SUM(GR14:GR16) -> 0 | GS17: =SUM(GS14:GS16) -> 0 | GT17: =SUM(GT14:GT16) -> 0 | GU17: =SUM(GU14:GU16) -> 0 | GV17: =SUM(GV14:GV16) -> 0 | GW17: =SUM(GW14:GW16) -> 0 | GX17: =SUM(GX14:GX16) -> 0 | GY17: =SUM(GY14:GY16) -> 0 | ... HC17: =SUM(HC14:HC16) -> 0 | HD17: =+SUBTOTAL(9,GR17:HC17) -> 0 | HF17: =SUM(HF14:HF16) -> 0 | HG17: =SUM(HG14:HG16) -> 0 | HH17: =SUM(HH14:HH16) -> 0 | HI17: =SUM(HI14:HI16) -> 0 | HJ17: =SUM(HJ14:HJ16) -> 0 | HK17: =SUM(HK14:HK16) -> 0 | HL17: =SUM(HL14:HL16) -> 0 | HM17: =SUM(HM14:HM16) -> 0 | ... HQ17: =SUM(HQ14:HQ16) -> 0 | HR17: =+SUBTOTAL(9,HF17:HQ17) -> 0 | HT17: =SUM(HT14:HT16) -> 0 | HU17: =SUM(HU14:HU16) -> 0 | HV17: =SUM(HV14:HV16) -> 0 | HW17: =SUM(HW14:HW16) -> 0 | HX17: =SUM(HX14:HX16) -> 0 | HY17: =SUM(HY14:HY16) -> 0 | HZ17: =SUM(HZ14:HZ16) -> 0 | IA17: =SUM(IA14:IA16) -> 0 | ... IE17: =SUM(IE14:IE16) -> 0 | IF17: =+SUBTOTAL(9,HT17:IE17) -> 0 | IH17: =SUM(IH14:IH16) -> 0 | II17: =SUM(II14:II16) -> 0 | IJ17: =SUM(IJ14:IJ16) -> 0 | IK17: =SUM(IK14:IK16) -> 0 | IL17: =SUM(IL14:IL16) -> 0 | IM17: =SUM(IM14:IM16) -> 0 | IN17: =SUM(IN14:IN16) -> 0 | IO17: =SUM(IO14:IO16) -> 0 | ... IS17: =SUM(IS14:IS16) -> 0 | IT17: =+SUBTOTAL(9,IH17:IS17) -> 0 | IV17: =SUM(IV14:IV16) -> 0 | IW17: =SUM(IW14:IW16) -> 0 | IX17: =SUM(IX14:IX16) -> 0 | IY17: =SUM(IY14:IY16) -> 0 | IZ17: =SUM(IZ14:IZ16) -> 0 | JA17: =SUM(JA14:JA16) -> 0 | JB17: =SUM(JB14:JB16) -> 0 | JC17: =SUM(JC14:JC16) -> 0 | ... JG17: =SUM(JG14:JG16) -> 0 | JH17: =+SUBTOTAL(9,IV17:JG17) -> 0 | JJ17: =SUM(JJ14:JJ16) -> 0 | JK17: =SUM(JK14:JK16) -> 0 | JL17: =SUM(JL14:JL16) -> 0 | JM17: =SUM(JM14:JM16) -> 0 | JN17: =SUM(JN14:JN16) -> 0 | JO17: =SUM(JO14:JO16) -> 0 | JP17: =SUM(JP14:JP16) -> 0 | JQ17: =SUM(JQ14:JQ16) -> 0 | ... JU17: =SUM(JU14:JU16) -> 0 | JV17: =+SUBTOTAL(9,JJ17:JU17) -> 0 | JX17: =SUM(JX14:JX16) -> 0 | JY17: =SUM(JY14:JY16) -> 0 | JZ17: =SUM(JZ14:JZ16) -> 0 | KA17: =SUM(KA14:KA16) -> 0 | KB17: =SUM(KB14:KB16) -> 0 | KC17: =SUM(KC14:KC16) -> 0 | KD17: =SUM(KD14:KD16) -> 0 | KE17: =SUM(KE14:KE16) -> 0 | ... KI17: =SUM(KI14:KI16) -> 0 | KJ17: =+SUBTOTAL(9,JX17:KI17) -> 0 | KL17: =SUM(KL14:KL16) -> 0 | KM17: =SUM(KM14:KM16) -> 0 | KN17: =SUM(KN14:KN16) -> 0 | KO17: =SUM(KO14:KO16) -> 0 | KP17: =SUM(KP14:KP16) -> 0 | KQ17: =SUM(KQ14:KQ16) -> 0 | KR17: =SUM(KR14:KR16) -> 0 | KS17: =SUM(KS14:KS16) -> 0 | ... KW17: =SUM(KW14:KW16) -> 0 | KX17: =+SUBTOTAL(9,KL17:KW17) -> 0 | KZ17: =SUM(KZ14:KZ16) -> 0 | LA17: =SUM(LA14:LA16) -> 0 | LB17: =SUM(LB14:LB16) -> 0 | LC17: =SUM(LC14:LC16) -> 0 | LD17: =SUM(LD14:LD16) -> 0 | LE17: =SUM(LE14:LE16) -> 0 | LF17: =SUM(LF14:LF16) -> 0 | LG17: =SUM(LG14:LG16) -> 0 | ... LK17: =SUM(LK14:LK16) -> 0 | LL17: =+SUBTOTAL(9,KZ17:LK17) -> 0 | LN17: =SUM(LN14:LN16) -> 0 | LO17: =SUM(LO14:LO16) -> 0 | LP17: =SUM(LP14:LP16) -> 0 | LQ17: =SUM(LQ14:LQ16) -> 0 | LR17: =SUM(LR14:LR16) -> 0 | LS17: =SUM(LS14:LS16) -> 0 | LT17: =SUM(LT14:LT16) -> 0 | LU17: =SUM(LU14:LU16) -> 0 | ... LY17: =SUM(LY14:LY16) -> 0 | LZ17: =+SUBTOTAL(9,LN17:LY17) -> 0 | MB17: =SUM(MB14:MB16) -> 0 | MC17: =SUM(MC14:MC16) -> 0 | MD17: =SUM(MD14:MD16) -> 0 | ME17: =SUM(ME14:ME16) -> 0 | MF17: =SUM(MF14:MF16) -> 0 | MG17: =SUM(MG14:MG16) -> 0 | MH17: =SUM(MH14:MH16) -> 0 | MI17: =SUM(MI14:MI16) -> 0 | ... MN17: =SUM(MN14:MN16) -> 0
B19: DIRECT COSTS
B20: Crew Management | D20: 0 | E20: 0 | F20: 0 | G20: 0 | H20: 0 | I20: 0 | J20: 0 | K20: 0 | L20: 0 | M20: 0 | N20: 0 | O20: 0 | P20: =+SUBTOTAL(9,D20:O20) -> 0 | R20: 0 | S20: 0 | T20: 0 | U20: 0 | V20: 0 | W20: 0 | X20: 0 | Y20: 0 | Z20: 0 | AA20: 0 | AB20: 0 | AC20: 0 | AD20: =+SUBTOTAL(9,R20:AC20) -> 0 | AF20: 0 | AG20: 0 | AH20: 0 | AI20: 0 | AJ20: 0 | AK20: 0 | AL20: 0 | AM20: 0 | AN20: 0 | AO20: 0 | AP20: 0 | AQ20: 0 | AR20: =+SUBTOTAL(9,AF20:AQ20) -> 0 | AT20: 0 | AU20: 0 | AV20: 0 | AW20: 0 | AX20: 0 | AY20: 0 | AZ20: 0 | BA20: 0 | BB20: 0 | BC20: 0 | BD20: 0 | BE20: 0 | BF20: =+SUBTOTAL(9,AT20:BE20) -> 0 | BH20: 0 | BI20: 0 | BJ20: 0 | BK20: 0 | BL20: 0 | BM20: 0 | BN20: 0 | BO20: 0 | BP20: 0 | BQ20: 0 | BR20: 0 | BS20: 0 | BT20: =+SUBTOTAL(9,BH20:BS20) -> 0 | BV20: 0 | BW20: 0 | BX20: 0 | BY20: 0 | BZ20: 0 | CA20: 0 | CB20: 0 | CC20: 0 | CD20: 0 | CE20: 0 | CF20: 0 | CG20: 0 | CH20: =+SUBTOTAL(9,BV20:CG20) -> 0 | CJ20: 0 | CK20: 0 | CL20: 0 | CM20: 0 | CN20: 0 | CO20: 0 | CP20: 0 | CQ20: 0 | CR20: 0 | CS20: 0 | CT20: 0 | CU20: 0 | CV20: =+SUBTOTAL(9,CJ20:CU20) -> 0 | CX20: 0 | CY20: 0 | CZ20: 0 | DA20: 0 | DB20: 0 | DC20: 0 | DD20: 0 | DE20: 0 | DF20: 0 | DG20: 0 | DH20: 0 | DI20: 0 | DJ20: =+SUBTOTAL(9,CX20:DI20) -> 0 | DL20: 0 | DM20: 0 | DN20: 0 | DO20: 0 | DP20: 0 | DQ20: 0 | DR20: 0 | DS20: 0 | DT20: 0 | DU20: 0 | DV20: 0 | DW20: 0 | DX20: =+SUBTOTAL(9,DL20:DW20) -> 0 | DZ20: 0 | EA20: 0 | EB20: 0 | EC20: 0 | ED20: 0 | EE20: 0 | EF20: 0 | EG20: 0 | EH20: 0 | EI20: 0 | EJ20: 0 | EK20: 0 | EL20: =+SUBTOTAL(9,DZ20:EK20) -> 0 | EN20: 0 | EO20: 0 | EP20: 0 | EQ20: 0 | ER20: 0 | ES20: 0 | ET20: 0 | EU20: 0 | EV20: 0 | EW20: 0 | EX20: 0 | EY20: 0 | EZ20: =+SUBTOTAL(9,EN20:EY20) -> 0 | FB20: 0 | FC20: 0 | FD20: 0 | FE20: 0 | FF20: 0 | FG20: 0 | FH20: 0 | FI20: 0 | FJ20: 0 | FK20: 0 | FL20: 0 | FM20: 0 | FN20: =+SUBTOTAL(9,FB20:FM20) -> 0 | FP20: 0 | FQ20: 0 | FR20: 0 | FS20: 0 | FT20: 0 | FU20: 0 | FV20: 0 | FW20: 0 | FX20: 0 | FY20: 0 | FZ20: 0 | GA20: 0 | GB20: =+SUBTOTAL(9,FP20:GA20) -> 0 | GD20: 0 | GE20: 0 | GF20: 0 | GG20: 0 | GH20: 0 | GI20: 0 | GJ20: 0 | GK20: 0 | GL20: 0 | GM20: 0 | GN20: 0 | GO20: 0 | GP20: =+SUBTOTAL(9,GD20:GO20) -> 0 | GR20: 0 | GS20: 0 | GT20: 0 | GU20: 0 | GV20: 0 | GW20: 0 | GX20: 0 | GY20: 0 | GZ20: 0 | HA20: 0 | HB20: 0 | HC20: 0 | HD20: =+SUBTOTAL(9,GR20:HC20) -> 0 | HF20: 0 | HG20: 0 | HH20: 0 | HI20: 0 | HJ20: 0 | HK20: 0 | HL20: 0 | HM20: 0 | HN20: 0 | HO20: 0 | HP20: 0 | HQ20: 0 | HR20: =+SUBTOTAL(9,HF20:HQ20) -> 0 | HT20: 0 | HU20: 0 | HV20: 0 | HW20: 0 | HX20: 0 | HY20: 0 | HZ20: 0 | IA20: 0 | IB20: 0 | IC20: 0 | ID20: 0 | IE20: 0 | IF20: =+SUBTOTAL(9,HT20:IE20) -> 0 | IH20: 0 | II20: 0 | IJ20: 0 | IK20: 0 | IL20: 0 | IM20: 0 | IN20: 0 | IO20: 0 | IP20: 0 | IQ20: 0 | IR20: 0 | IS20: 0 | IT20: =+SUBTOTAL(9,IH20:IS20) -> 0 | IV20: 0 | IW20: 0 | IX20: 0 | IY20: 0 | IZ20: 0 | JA20: 0 | JB20: 0 | JC20: 0 | JD20: 0 | JE20: 0 | JF20: 0 | JG20: 0 | JH20: =+SUBTOTAL(9,IV20:JG20) -> 0 | JJ20: 0 | JK20: 0 | JL20: 0 | JM20: 0 | JN20: 0 | JO20: 0 | JP20: 0 | JQ20: 0 | JR20: 0 | JS20: 0 | JT20: 0 | JU20: 0 | JV20: =+SUBTOTAL(9,JJ20:JU20) -> 0 | JX20: 0 | JY20: 0 | JZ20: 0 | KA20: 0 | KB20: 0 | KC20: 0 | KD20: 0 | KE20: 0 | KF20: 0 | KG20: 0 | KH20: 0 | KI20: 0 | KJ20: =+SUBTOTAL(9,JX20:KI20) -> 0 | KL20: 0 | KM20: 0 | KN20: 0 | KO20: 0 | KP20: 0 | KQ20: 0 | KR20: 0 | KS20: 0 | KT20: 0 | KU20: 0 | KV20: 0 | KW20: 0 | KX20: =+SUBTOTAL(9,KL20:KW20) -> 0 | KZ20: 0 | LA20: 0 | LB20: 0 | LC20: 0 | LD20: 0 | LE20: 0 | LF20: 0 | LG20: 0 | LH20: 0 | LI20: 0 | LJ20: 0 | LK20: 0 | LL20: =+SUBTOTAL(9,KZ20:LK20) -> 0 | LN20: 0 | LO20: 0 | LP20: 0 | LQ20: 0 | LR20: 0 | LS20: 0 | LT20: 0 | LU20: 0 | LV20: 0 | LW20: 0 | LX20: 0 | LY20: 0 | LZ20: =+SUBTOTAL(9,LN20:LY20) -> 0 | MB20: =SUMIF($D$11:$LY$11,MB$8,$D20:$LY20) -> 0 | MC20: =SUMIF($D$11:$LY$11,MC$8,$D20:$LY20) -> 0 | MD20: =SUMIF($D$11:$LY$11,MD$8,$D20:$LY20) -> 0 | ME20: =SUMIF($D$11:$LY$11,ME$8,$D20:$LY20) -> 0 | MF20: =SUMIF($D$11:$LY$11,MF$8,$D20:$LY20) -> 0 | MG20: =SUMIF($D$11:$LY$11,MG$8,$D20:$LY20) -> 0 | MH20: =SUMIF($D$11:$LY$11,MH$8,$D20:$LY20) -> 0 | MI20: =SUMIF($D$11:$LY$11,MI$8,$D20:$LY20) -> 0 | ... MM20: =SUMIF($D$11:$LY$11,MM$8,$D20:$LY20) -> 0 | MN20: =SUM(MB20:MM20) -> 0
B21: Cruise Management | D21: 0 | E21: 0 | F21: 0 | G21: 0 | H21: 0 | I21: 0 | J21: 0 | K21: 0 | L21: 0 | M21: 0 | N21: 0 | O21: 0 | P21: =+SUBTOTAL(9,D21:O21) -> 0 | R21: 0 | S21: 0 | T21: 0 | U21: 0 | V21: 0 | W21: 0 | X21: 0 | Y21: 0 | Z21: 0 | AA21: 0 | AB21: 0 | AC21: 0 | AD21: =+SUBTOTAL(9,R21:AC21) -> 0 | AF21: 0 | AG21: 0 | AH21: 0 | AI21: 0 | AJ21: 0 | AK21: 0 | AL21: 0 | AM21: 0 | AN21: 0 | AO21: 0 | AP21: 0 | AQ21: 0 | AR21: =+SUBTOTAL(9,AF21:AQ21) -> 0 | AT21: 0 | AU21: 0 | AV21: 0 | AW21: 0 | AX21: 0 | AY21: 0 | AZ21: 0 | BA21: 0 | BB21: 0 | BC21: 0 | BD21: 0 | BE21: 0 | BF21: =+SUBTOTAL(9,AT21:BE21) -> 0 | BH21: 0 | BI21: 0 | BJ21: 0 | BK21: 0 | BL21: 0 | BM21: 0 | BN21: 0 | BO21: 0 | BP21: 0 | BQ21: 0 | BR21: 0 | BS21: 0 | BT21: =+SUBTOTAL(9,BH21:BS21) -> 0 | BV21: 0 | BW21: 0 | BX21: 0 | BY21: 0 | BZ21: 0 | CA21: 0 | CB21: 0 | CC21: 0 | CD21: 0 | CE21: 0 | CF21: 0 | CG21: 0 | CH21: =+SUBTOTAL(9,BV21:CG21) -> 0 | CJ21: 0 | CK21: 0 | CL21: 0 | CM21: 0 | CN21: 0 | CO21: 0 | CP21: 0 | CQ21: 0 | CR21: 0 | CS21: 0 | CT21: 0 | CU21: 0 | CV21: =+SUBTOTAL(9,CJ21:CU21) -> 0 | CX21: 0 | CY21: 0 | CZ21: 0 | DA21: 0 | DB21: 0 | DC21: 0 | DD21: 0 | DE21: 0 | DF21: 0 | DG21: 0 | DH21: 0 | DI21: 0 | DJ21: =+SUBTOTAL(9,CX21:DI21) -> 0 | DL21: 0 | DM21: 0 | DN21: 0 | DO21: 0 | DP21: 0 | DQ21: 0 | DR21: 0 | DS21: 0 | DT21: 0 | DU21: 0 | DV21: 0 | DW21: 0 | DX21: =+SUBTOTAL(9,DL21:DW21) -> 0 | DZ21: 0 | EA21: 0 | EB21: 0 | EC21: 0 | ED21: 0 | EE21: 0 | EF21: 0 | EG21: 0 | EH21: 0 | EI21: 0 | EJ21: 0 | EK21: 0 | EL21: =+SUBTOTAL(9,DZ21:EK21) -> 0 | EN21: 0 | EO21: 0 | EP21: 0 | EQ21: 0 | ER21: 0 | ES21: 0 | ET21: 0 | EU21: 0 | EV21: 0 | EW21: 0 | EX21: 0 | EY21: 0 | EZ21: =+SUBTOTAL(9,EN21:EY21) -> 0 | FB21: 0 | FC21: 0 | FD21: 0 | FE21: 0 | FF21: 0 | FG21: 0 | FH21: 0 | FI21: 0 | FJ21: 0 | FK21: 0 | FL21: 0 | FM21: 0 | FN21: =+SUBTOTAL(9,FB21:FM21) -> 0 | FP21: 0 | FQ21: 0 | FR21: 0 | FS21: 0 | FT21: 0 | FU21: 0 | FV21: 0 | FW21: 0 | FX21: 0 | FY21: 0 | FZ21: 0 | GA21: 0 | GB21: =+SUBTOTAL(9,FP21:GA21) -> 0 | GD21: 0 | GE21: 0 | GF21: 0 | GG21: 0 | GH21: 0 | GI21: 0 | GJ21: 0 | GK21: 0 | GL21: 0 | GM21: 0 | GN21: 0 | GO21: 0 | GP21: =+SUBTOTAL(9,GD21:GO21) -> 0 | GR21: 0 | GS21: 0 | GT21: 0 | GU21: 0 | GV21: 0 | GW21: 0 | GX21: 0 | GY21: 0 | GZ21: 0 | HA21: 0 | HB21: 0 | HC21: 0 | HD21: =+SUBTOTAL(9,GR21:HC21) -> 0 | HF21: 0 | HG21: 0 | HH21: 0 | HI21: 0 | HJ21: 0 | HK21: 0 | HL21: 0 | HM21: 0 | HN21: 0 | HO21: 0 | HP21: 0 | HQ21: 0 | HR21: =+SUBTOTAL(9,HF21:HQ21) -> 0 | HT21: 0 | HU21: 0 | HV21: 0 | HW21: 0 | HX21: 0 | HY21: 0 | HZ21: 0 | IA21: 0 | IB21: 0 | IC21: 0 | ID21: 0 | IE21: 0 | IF21: =+SUBTOTAL(9,HT21:IE21) -> 0 | IH21: 0 | II21: 0 | IJ21: 0 | IK21: 0 | IL21: 0 | IM21: 0 | IN21: 0 | IO21: 0 | IP21: 0 | IQ21: 0 | IR21: 0 | IS21: 0 | IT21: =+SUBTOTAL(9,IH21:IS21) -> 0 | IV21: 0 | IW21: 0 | IX21: 0 | IY21: 0 | IZ21: 0 | JA21: 0 | JB21: 0 | JC21: 0 | JD21: 0 | JE21: 0 | JF21: 0 | JG21: 0 | JH21: =+SUBTOTAL(9,IV21:JG21) -> 0 | JJ21: 0 | JK21: 0 | JL21: 0 | JM21: 0 | JN21: 0 | JO21: 0 | JP21: 0 | JQ21: 0 | JR21: 0 | JS21: 0 | JT21: 0 | JU21: 0 | JV21: =+SUBTOTAL(9,JJ21:JU21) -> 0 | JX21: 0 | JY21: 0 | JZ21: 0 | KA21: 0 | KB21: 0 | KC21: 0 | KD21: 0 | KE21: 0 | KF21: 0 | KG21: 0 | KH21: 0 | KI21: 0 | KJ21: =+SUBTOTAL(9,JX21:KI21) -> 0 | KL21: 0 | KM21: 0 | KN21: 0 | KO21: 0 | KP21: 0 | KQ21: 0 | KR21: 0 | KS21: 0 | KT21: 0 | KU21: 0 | KV21: 0 | KW21: 0 | KX21: =+SUBTOTAL(9,KL21:KW21) -> 0 | KZ21: 0 | LA21: 0 | LB21: 0 | LC21: 0 | LD21: 0 | LE21: 0 | LF21: 0 | LG21: 0 | LH21: 0 | LI21: 0 | LJ21: 0 | LK21: 0 | LL21: =+SUBTOTAL(9,KZ21:LK21) -> 0 | LN21: 0 | LO21: 0 | LP21: 0 | LQ21: 0 | LR21: 0 | LS21: 0 | LT21: 0 | LU21: 0 | LV21: 0 | LW21: 0 | LX21: 0 | LY21: 0 | LZ21: =+SUBTOTAL(9,LN21:LY21) -> 0 | MB21: =SUMIF($D$11:$LY$11,MB$8,$D21:$LY21) -> 0 | MC21: =SUMIF($D$11:$LY$11,MC$8,$D21:$LY21) -> 0 | MD21: =SUMIF($D$11:$LY$11,MD$8,$D21:$LY21) -> 0 | ME21: =SUMIF($D$11:$LY$11,ME$8,$D21:$LY21) -> 0 | MF21: =SUMIF($D$11:$LY$11,MF$8,$D21:$LY21) -> 0 | MG21: =SUMIF($D$11:$LY$11,MG$8,$D21:$LY21) -> 0 | MH21: =SUMIF($D$11:$LY$11,MH$8,$D21:$LY21) -> 0 | MI21: =SUMIF($D$11:$LY$11,MI$8,$D21:$LY21) -> 0 | ... MM21: =SUMIF($D$11:$LY$11,MM$8,$D21:$LY21) -> 0 | MN21: =SUM(MB21:MM21) -> 0
B22: Travel | D22: 0 | E22: 0 | F22: 0 | G22: 0 | H22: 0 | I22: 0 | J22: 0 | K22: 0 | L22: 0 | M22: 0 | N22: 0 | O22: 0 | P22: =+SUBTOTAL(9,D22:O22) -> 0 | R22: 0 | S22: 0 | T22: 0 | U22: 0 | V22: 0 | W22: 0 | X22: 0 | Y22: 0 | Z22: 0 | AA22: 0 | AB22: 0 | AC22: 0 | AD22: =+SUBTOTAL(9,R22:AC22) -> 0 | AF22: 0 | AG22: 0 | AH22: 0 | AI22: 0 | AJ22: 0 | AK22: 0 | AL22: 0 | AM22: 0 | AN22: 0 | AO22: 0 | AP22: 0 | AQ22: 0 | AR22: =+SUBTOTAL(9,AF22:AQ22) -> 0 | AT22: 0 | AU22: 0 | AV22: 0 | AW22: 0 | AX22: 0 | AY22: 0 | AZ22: 0 | BA22: 0 | BB22: 0 | BC22: 0 | BD22: 0 | BE22: 0 | BF22: =+SUBTOTAL(9,AT22:BE22) -> 0 | BH22: 0 | BI22: 0 | BJ22: 0 | BK22: 0 | BL22: 0 | BM22: 0 | BN22: 0 | BO22: 0 | BP22: 0 | BQ22: 0 | BR22: 0 | BS22: 0 | BT22: =+SUBTOTAL(9,BH22:BS22) -> 0 | BV22: 0 | BW22: 0 | BX22: 0 | BY22: 0 | BZ22: 0 | CA22: 0 | CB22: 0 | CC22: 0 | CD22: 0 | CE22: 0 | CF22: 0 | CG22: 0 | CH22: =+SUBTOTAL(9,BV22:CG22) -> 0 | CJ22: 0 | CK22: 0 | CL22: 0 | CM22: 0 | CN22: 0 | CO22: 0 | CP22: 0 | CQ22: 0 | CR22: 0 | CS22: 0 | CT22: 0 | CU22: 0 | CV22: =+SUBTOTAL(9,CJ22:CU22) -> 0 | CX22: 0 | CY22: 0 | CZ22: 0 | DA22: 0 | DB22: 0 | DC22: 0 | DD22: 0 | DE22: 0 | DF22: 0 | DG22: 0 | DH22: 0 | DI22: 0 | DJ22: =+SUBTOTAL(9,CX22:DI22) -> 0 | DL22: 0 | DM22: 0 | DN22: 0 | DO22: 0 | DP22: 0 | DQ22: 0 | DR22: 0 | DS22: 0 | DT22: 0 | DU22: 0 | DV22: 0 | DW22: 0 | DX22: =+SUBTOTAL(9,DL22:DW22) -> 0 | DZ22: 0 | EA22: 0 | EB22: 0 | EC22: 0 | ED22: 0 | EE22: 0 | EF22: 0 | EG22: 0 | EH22: 0 | EI22: 0 | EJ22: 0 | EK22: 0 | EL22: =+SUBTOTAL(9,DZ22:EK22) -> 0 | EN22: 0 | EO22: 0 | EP22: 0 | EQ22: 0 | ER22: 0 | ES22: 0 | ET22: 0 | EU22: 0 | EV22: 0 | EW22: 0 | EX22: 0 | EY22: 0 | EZ22: =+SUBTOTAL(9,EN22:EY22) -> 0 | FB22: 0 | FC22: 0 | FD22: 0 | FE22: 0 | FF22: 0 | FG22: 0 | FH22: 0 | FI22: 0 | FJ22: 0 | FK22: 0 | FL22: 0 | FM22: 0 | FN22: =+SUBTOTAL(9,FB22:FM22) -> 0 | FP22: 0 | FQ22: 0 | FR22: 0 | FS22: 0 | FT22: 0 | FU22: 0 | FV22: 0 | FW22: 0 | FX22: 0 | FY22: 0 | FZ22: 0 | GA22: 0 | GB22: =+SUBTOTAL(9,FP22:GA22) -> 0 | GD22: 0 | GE22: 0 | GF22: 0 | GG22: 0 | GH22: 0 | GI22: 0 | GJ22: 0 | GK22: 0 | GL22: 0 | GM22: 0 | GN22: 0 | GO22: 0 | GP22: =+SUBTOTAL(9,GD22:GO22) -> 0 | GR22: 0 | GS22: 0 | GT22: 0 | GU22: 0 | GV22: 0 | GW22: 0 | GX22: 0 | GY22: 0 | GZ22: 0 | HA22: 0 | HB22: 0 | HC22: 0 | HD22: =+SUBTOTAL(9,GR22:HC22) -> 0 | HF22: 0 | HG22: 0 | HH22: 0 | HI22: 0 | HJ22: 0 | HK22: 0 | HL22: 0 | HM22: 0 | HN22: 0 | HO22: 0 | HP22: 0 | HQ22: 0 | HR22: =+SUBTOTAL(9,HF22:HQ22) -> 0 | HT22: 0 | HU22: 0 | HV22: 0 | HW22: 0 | HX22: 0 | HY22: 0 | HZ22: 0 | IA22: 0 | IB22: 0 | IC22: 0 | ID22: 0 | IE22: 0 | IF22: =+SUBTOTAL(9,HT22:IE22) -> 0 | IH22: 0 | II22: 0 | IJ22: 0 | IK22: 0 | IL22: 0 | IM22: 0 | IN22: 0 | IO22: 0 | IP22: 0 | IQ22: 0 | IR22: 0 | IS22: 0 | IT22: =+SUBTOTAL(9,IH22:IS22) -> 0 | IV22: 0 | IW22: 0 | IX22: 0 | IY22: 0 | IZ22: 0 | JA22: 0 | JB22: 0 | JC22: 0 | JD22: 0 | JE22: 0 | JF22: 0 | JG22: 0 | JH22: =+SUBTOTAL(9,IV22:JG22) -> 0 | JJ22: 0 | JK22: 0 | JL22: 0 | JM22: 0 | JN22: 0 | JO22: 0 | JP22: 0 | JQ22: 0 | JR22: 0 | JS22: 0 | JT22: 0 | JU22: 0 | JV22: =+SUBTOTAL(9,JJ22:JU22) -> 0 | JX22: 0 | JY22: 0 | JZ22: 0 | KA22: 0 | KB22: 0 | KC22: 0 | KD22: 0 | KE22: 0 | KF22: 0 | KG22: 0 | KH22: 0 | KI22: 0 | KJ22: =+SUBTOTAL(9,JX22:KI22) -> 0 | KL22: 0 | KM22: 0 | KN22: 0 | KO22: 0 | KP22: 0 | KQ22: 0 | KR22: 0 | KS22: 0 | KT22: 0 | KU22: 0 | KV22: 0 | KW22: 0 | KX22: =+SUBTOTAL(9,KL22:KW22) -> 0 | KZ22: 0 | LA22: 0 | LB22: 0 | LC22: 0 | LD22: 0 | LE22: 0 | LF22: 0 | LG22: 0 | LH22: 0 | LI22: 0 | LJ22: 0 | LK22: 0 | LL22: =+SUBTOTAL(9,KZ22:LK22) -> 0 | LN22: 0 | LO22: 0 | LP22: 0 | LQ22: 0 | LR22: 0 | LS22: 0 | LT22: 0 | LU22: 0 | LV22: 0 | LW22: 0 | LX22: 0 | LY22: 0 | LZ22: =+SUBTOTAL(9,LN22:LY22) -> 0 | MB22: =SUMIF($D$11:$LY$11,MB$8,$D22:$LY22) -> 0 | MC22: =SUMIF($D$11:$LY$11,MC$8,$D22:$LY22) -> 0 | MD22: =SUMIF($D$11:$LY$11,MD$8,$D22:$LY22) -> 0 | ME22: =SUMIF($D$11:$LY$11,ME$8,$D22:$LY22) -> 0 | MF22: =SUMIF($D$11:$LY$11,MF$8,$D22:$LY22) -> 0 | MG22: =SUMIF($D$11:$LY$11,MG$8,$D22:$LY22) -> 0 | MH22: =SUMIF($D$11:$LY$11,MH$8,$D22:$LY22) -> 0 | MI22: =SUMIF($D$11:$LY$11,MI$8,$D22:$LY22) -> 0 | ... MM22: =SUMIF($D$11:$LY$11,MM$8,$D22:$LY22) -> 0 | MN22: =SUM(MB22:MM22) -> 0
B23: Training | D23: 0 | E23: 0 | F23: 0 | G23: 0 | H23: 0 | I23: 0 | J23: 0 | K23: 0 | L23: 0 | M23: 0 | N23: 0 | O23: 0 | P23: =+SUBTOTAL(9,D23:O23) -> 0 | R23: 0 | S23: 0 | T23: 0 | U23: 0 | V23: 0 | W23: 0 | X23: 0 | Y23: 0 | Z23: 0 | AA23: 0 | AB23: 0 | AC23: 0 | AD23: =+SUBTOTAL(9,R23:AC23) -> 0 | AF23: 0 | AG23: 0 | AH23: 0 | AI23: 0 | AJ23: 0 | AK23: 0 | AL23: 0 | AM23: 0 | AN23: 0 | AO23: 0 | AP23: 0 | AQ23: 0 | AR23: =+SUBTOTAL(9,AF23:AQ23) -> 0 | AT23: 0 | AU23: 0 | AV23: 0 | AW23: 0 | AX23: 0 | AY23: 0 | AZ23: 0 | BA23: 0 | BB23: 0 | BC23: 0 | BD23: 0 | BE23: 0 | BF23: =+SUBTOTAL(9,AT23:BE23) -> 0 | BH23: 0 | BI23: 0 | BJ23: 0 | BK23: 0 | BL23: 0 | BM23: 0 | BN23: 0 | BO23: 0 | BP23: 0 | BQ23: 0 | BR23: 0 | BS23: 0 | BT23: =+SUBTOTAL(9,BH23:BS23) -> 0 | BV23: 0 | BW23: 0 | BX23: 0 | BY23: 0 | BZ23: 0 | CA23: 0 | CB23: 0 | CC23: 0 | CD23: 0 | CE23: 0 | CF23: 0 | CG23: 0 | CH23: =+SUBTOTAL(9,BV23:CG23) -> 0 | CJ23: 0 | CK23: 0 | CL23: 0 | CM23: 0 | CN23: 0 | CO23: 0 | CP23: 0 | CQ23: 0 | CR23: 0 | CS23: 0 | CT23: 0 | CU23: 0 | CV23: =+SUBTOTAL(9,CJ23:CU23) -> 0 | CX23: 0 | CY23: 0 | CZ23: 0 | DA23: 0 | DB23: 0 | DC23: 0 | DD23: 0 | DE23: 0 | DF23: 0 | DG23: 0 | DH23: 0 | DI23: 0 | DJ23: =+SUBTOTAL(9,CX23:DI23) -> 0 | DL23: 0 | DM23: 0 | DN23: 0 | DO23: 0 | DP23: 0 | DQ23: 0 | DR23: 0 | DS23: 0 | DT23: 0 | DU23: 0 | DV23: 0 | DW23: 0 | DX23: =+SUBTOTAL(9,DL23:DW23) -> 0 | DZ23: 0 | EA23: 0 | EB23: 0 | EC23: 0 | ED23: 0 | EE23: 0 | EF23: 0 | EG23: 0 | EH23: 0 | EI23: 0 | EJ23: 0 | EK23: 0 | EL23: =+SUBTOTAL(9,DZ23:EK23) -> 0 | EN23: 0 | EO23: 0 | EP23: 0 | EQ23: 0 | ER23: 0 | ES23: 0 | ET23: 0 | EU23: 0 | EV23: 0 | EW23: 0 | EX23: 0 | EY23: 0 | EZ23: =+SUBTOTAL(9,EN23:EY23) -> 0 | FB23: 0 | FC23: 0 | FD23: 0 | FE23: 0 | FF23: 0 | FG23: 0 | FH23: 0 | FI23: 0 | FJ23: 0 | FK23: 0 | FL23: 0 | FM23: 0 | FN23: =+SUBTOTAL(9,FB23:FM23) -> 0 | FP23: 0 | FQ23: 0 | FR23: 0 | FS23: 0 | FT23: 0 | FU23: 0 | FV23: 0 | FW23: 0 | FX23: 0 | FY23: 0 | FZ23: 0 | GA23: 0 | GB23: =+SUBTOTAL(9,FP23:GA23) -> 0 | GD23: 0 | GE23: 0 | GF23: 0 | GG23: 0 | GH23: 0 | GI23: 0 | GJ23: 0 | GK23: 0 | GL23: 0 | GM23: 0 | GN23: 0 | GO23: 0 | GP23: =+SUBTOTAL(9,GD23:GO23) -> 0 | GR23: 0 | GS23: 0 | GT23: 0 | GU23: 0 | GV23: 0 | GW23: 0 | GX23: 0 | GY23: 0 | GZ23: 0 | HA23: 0 | HB23: 0 | HC23: 0 | HD23: =+SUBTOTAL(9,GR23:HC23) -> 0 | HF23: 0 | HG23: 0 | HH23: 0 | HI23: 0 | HJ23: 0 | HK23: 0 | HL23: 0 | HM23: 0 | HN23: 0 | HO23: 0 | HP23: 0 | HQ23: 0 | HR23: =+SUBTOTAL(9,HF23:HQ23) -> 0 | HT23: 0 | HU23: 0 | HV23: 0 | HW23: 0 | HX23: 0 | HY23: 0 | HZ23: 0 | IA23: 0 | IB23: 0 | IC23: 0 | ID23: 0 | IE23: 0 | IF23: =+SUBTOTAL(9,HT23:IE23) -> 0 | IH23: 0 | II23: 0 | IJ23: 0 | IK23: 0 | IL23: 0 | IM23: 0 | IN23: 0 | IO23: 0 | IP23: 0 | IQ23: 0 | IR23: 0 | IS23: 0 | IT23: =+SUBTOTAL(9,IH23:IS23) -> 0 | IV23: 0 | IW23: 0 | IX23: 0 | IY23: 0 | IZ23: 0 | JA23: 0 | JB23: 0 | JC23: 0 | JD23: 0 | JE23: 0 | JF23: 0 | JG23: 0 | JH23: =+SUBTOTAL(9,IV23:JG23) -> 0 | JJ23: 0 | JK23: 0 | JL23: 0 | JM23: 0 | JN23: 0 | JO23: 0 | JP23: 0 | JQ23: 0 | JR23: 0 | JS23: 0 | JT23: 0 | JU23: 0 | JV23: =+SUBTOTAL(9,JJ23:JU23) -> 0 | JX23: 0 | JY23: 0 | JZ23: 0 | KA23: 0 | KB23: 0 | KC23: 0 | KD23: 0 | KE23: 0 | KF23: 0 | KG23: 0 | KH23: 0 | KI23: 0 | KJ23: =+SUBTOTAL(9,JX23:KI23) -> 0 | KL23: 0 | KM23: 0 | KN23: 0 | KO23: 0 | KP23: 0 | KQ23: 0 | KR23: 0 | KS23: 0 | KT23: 0 | KU23: 0 | KV23: 0 | KW23: 0 | KX23: =+SUBTOTAL(9,KL23:KW23) -> 0 | KZ23: 0 | LA23: 0 | LB23: 0 | LC23: 0 | LD23: 0 | LE23: 0 | LF23: 0 | LG23: 0 | LH23: 0 | LI23: 0 | LJ23: 0 | LK23: 0 | LL23: =+SUBTOTAL(9,KZ23:LK23) -> 0 | LN23: 0 | LO23: 0 | LP23: 0 | LQ23: 0 | LR23: 0 | LS23: 0 | LT23: 0 | LU23: 0 | LV23: 0 | LW23: 0 | LX23: 0 | LY23: 0 | LZ23: =+SUBTOTAL(9,LN23:LY23) -> 0 | MB23: =SUMIF($D$11:$LY$11,MB$8,$D23:$LY23) -> 0 | MC23: =SUMIF($D$11:$LY$11,MC$8,$D23:$LY23) -> 0 | MD23: =SUMIF($D$11:$LY$11,MD$8,$D23:$LY23) -> 0 | ME23: =SUMIF($D$11:$LY$11,ME$8,$D23:$LY23) -> 0 | MF23: =SUMIF($D$11:$LY$11,MF$8,$D23:$LY23) -> 0 | MG23: =SUMIF($D$11:$LY$11,MG$8,$D23:$LY23) -> 0 | MH23: =SUMIF($D$11:$LY$11,MH$8,$D23:$LY23) -> 0 | MI23: =SUMIF($D$11:$LY$11,MI$8,$D23:$LY23) -> 0 | ... MM23: =SUMIF($D$11:$LY$11,MM$8,$D23:$LY23) -> 0 | MN23: =SUM(MB23:MM23) -> 0
B24: School Expenses | D24: 0 | E24: 0 | F24: 0 | G24: 0 | H24: 0 | I24: 0 | J24: 0 | K24: 0 | L24: 0 | M24: 0 | N24: 0 | O24: 0 | P24: =+SUBTOTAL(9,D24:O24) -> 0 | R24: 0 | S24: 0 | T24: 0 | U24: 0 | V24: 0 | W24: 0 | X24: 0 | Y24: 0 | Z24: 0 | AA24: 0 | AB24: 0 | AC24: 0 | AD24: =+SUBTOTAL(9,R24:AC24) -> 0 | AF24: 0 | AG24: 0 | AH24: 0 | AI24: 0 | AJ24: 0 | AK24: 0 | AL24: 0 | AM24: 0 | AN24: 0 | AO24: 0 | AP24: 0 | AQ24: 0 | AR24: =+SUBTOTAL(9,AF24:AQ24) -> 0 | AT24: 0 | AU24: 0 | AV24: 0 | AW24: 0 | AX24: 0 | AY24: 0 | AZ24: 0 | BA24: 0 | BB24: 0 | BC24: 0 | BD24: 0 | BE24: 0 | BF24: =+SUBTOTAL(9,AT24:BE24) -> 0 | BH24: 0 | BI24: 0 | BJ24: 0 | BK24: 0 | BL24: 0 | BM24: 0 | BN24: 0 | BO24: 0 | BP24: 0 | BQ24: 0 | BR24: 0 | BS24: 0 | BT24: =+SUBTOTAL(9,BH24:BS24) -> 0 | BV24: 0 | BW24: 0 | BX24: 0 | BY24: 0 | BZ24: 0 | CA24: 0 | CB24: 0 | CC24: 0 | CD24: 0 | CE24: 0 | CF24: 0 | CG24: 0 | CH24: =+SUBTOTAL(9,BV24:CG24) -> 0 | CJ24: 0 | CK24: 0 | CL24: 0 | CM24: 0 | CN24: 0 | CO24: 0 | CP24: 0 | CQ24: 0 | CR24: 0 | CS24: 0 | CT24: 0 | CU24: 0 | CV24: =+SUBTOTAL(9,CJ24:CU24) -> 0 | CX24: 0 | CY24: 0 | CZ24: 0 | DA24: 0 | DB24: 0 | DC24: 0 | DD24: 0 | DE24: 0 | DF24: 0 | DG24: 0 | DH24: 0 | DI24: 0 | DJ24: =+SUBTOTAL(9,CX24:DI24) -> 0 | DL24: 0 | DM24: 0 | DN24: 0 | DO24: 0 | DP24: 0 | DQ24: 0 | DR24: 0 | DS24: 0 | DT24: 0 | DU24: 0 | DV24: 0 | DW24: 0 | DX24: =+SUBTOTAL(9,DL24:DW24) -> 0 | DZ24: 0 | EA24: 0 | EB24: 0 | EC24: 0 | ED24: 0 | EE24: 0 | EF24: 0 | EG24: 0 | EH24: 0 | EI24: 0 | EJ24: 0 | EK24: 0 | EL24: =+SUBTOTAL(9,DZ24:EK24) -> 0 | EN24: 0 | EO24: 0 | EP24: 0 | EQ24: 0 | ER24: 0 | ES24: 0 | ET24: 0 | EU24: 0 | EV24: 0 | EW24: 0 | EX24: 0 | EY24: 0 | EZ24: =+SUBTOTAL(9,EN24:EY24) -> 0 | FB24: 0 | FC24: 0 | FD24: 0 | FE24: 0 | FF24: 0 | FG24: 0 | FH24: 0 | FI24: 0 | FJ24: 0 | FK24: 0 | FL24: 0 | FM24: 0 | FN24: =+SUBTOTAL(9,FB24:FM24) -> 0 | FP24: 0 | FQ24: 0 | FR24: 0 | FS24: 0 | FT24: 0 | FU24: 0 | FV24: 0 | FW24: 0 | FX24: 0 | FY24: 0 | FZ24: 0 | GA24: 0 | GB24: =+SUBTOTAL(9,FP24:GA24) -> 0 | GD24: 0 | GE24: 0 | GF24: 0 | GG24: 0 | GH24: 0 | GI24: 0 | GJ24: 0 | GK24: 0 | GL24: 0 | GM24: 0 | GN24: 0 | GO24: 0 | GP24: =+SUBTOTAL(9,GD24:GO24) -> 0 | GR24: 0 | GS24: 0 | GT24: 0 | GU24: 0 | GV24: 0 | GW24: 0 | GX24: 0 | GY24: 0 | GZ24: 0 | HA24: 0 | HB24: 0 | HC24: 0 | HD24: =+SUBTOTAL(9,GR24:HC24) -> 0 | HF24: 0 | HG24: 0 | HH24: 0 | HI24: 0 | HJ24: 0 | HK24: 0 | HL24: 0 | HM24: 0 | HN24: 0 | HO24: 0 | HP24: 0 | HQ24: 0 | HR24: =+SUBTOTAL(9,HF24:HQ24) -> 0 | HT24: 0 | HU24: 0 | HV24: 0 | HW24: 0 | HX24: 0 | HY24: 0 | HZ24: 0 | IA24: 0 | IB24: 0 | IC24: 0 | ID24: 0 | IE24: 0 | IF24: =+SUBTOTAL(9,HT24:IE24) -> 0 | IH24: 0 | II24: 0 | IJ24: 0 | IK24: 0 | IL24: 0 | IM24: 0 | IN24: 0 | IO24: 0 | IP24: 0 | IQ24: 0 | IR24: 0 | IS24: 0 | IT24: =+SUBTOTAL(9,IH24:IS24) -> 0 | IV24: 0 | IW24: 0 | IX24: 0 | IY24: 0 | IZ24: 0 | JA24: 0 | JB24: 0 | JC24: 0 | JD24: 0 | JE24: 0 | JF24: 0 | JG24: 0 | JH24: =+SUBTOTAL(9,IV24:JG24) -> 0 | JJ24: 0 | JK24: 0 | JL24: 0 | JM24: 0 | JN24: 0 | JO24: 0 | JP24: 0 | JQ24: 0 | JR24: 0 | JS24: 0 | JT24: 0 | JU24: 0 | JV24: =+SUBTOTAL(9,JJ24:JU24) -> 0 | JX24: 0 | JY24: 0 | JZ24: 0 | KA24: 0 | KB24: 0 | KC24: 0 | KD24: 0 | KE24: 0 | KF24: 0 | KG24: 0 | KH24: 0 | KI24: 0 | KJ24: =+SUBTOTAL(9,JX24:KI24) -> 0 | KL24: 0 | KM24: 0 | KN24: 0 | KO24: 0 | KP24: 0 | KQ24: 0 | KR24: 0 | KS24: 0 | KT24: 0 | KU24: 0 | KV24: 0 | KW24: 0 | KX24: =+SUBTOTAL(9,KL24:KW24) -> 0 | KZ24: 0 | LA24: 0 | LB24: 0 | LC24: 0 | LD24: 0 | LE24: 0 | LF24: 0 | LG24: 0 | LH24: 0 | LI24: 0 | LJ24: 0 | LK24: 0 | LL24: =+SUBTOTAL(9,KZ24:LK24) -> 0 | LN24: 0 | LO24: 0 | LP24: 0 | LQ24: 0 | LR24: 0 | LS24: 0 | LT24: 0 | LU24: 0 | LV24: 0 | LW24: 0 | LX24: 0 | LY24: 0 | LZ24: =+SUBTOTAL(9,LN24:LY24) -> 0 | MB24: =SUMIF($D$11:$LY$11,MB$8,$D24:$LY24) -> 0 | MC24: =SUMIF($D$11:$LY$11,MC$8,$D24:$LY24) -> 0 | MD24: =SUMIF($D$11:$LY$11,MD$8,$D24:$LY24) -> 0 | ME24: =SUMIF($D$11:$LY$11,ME$8,$D24:$LY24) -> 0 | MF24: =SUMIF($D$11:$LY$11,MF$8,$D24:$LY24) -> 0 | MG24: =SUMIF($D$11:$LY$11,MG$8,$D24:$LY24) -> 0 | MH24: =SUMIF($D$11:$LY$11,MH$8,$D24:$LY24) -> 0 | MI24: =SUMIF($D$11:$LY$11,MI$8,$D24:$LY24) -> 0 | ... MM24: =SUMIF($D$11:$LY$11,MM$8,$D24:$LY24) -> 0 | MN24: =SUM(MB24:MM24) -> 0
B25: Care Training Centre Expenses | D25: 0 | E25: 0 | F25: 0 | G25: 0 | H25: 0 | I25: 0 | J25: 0 | K25: 0 | L25: 0 | M25: 0 | N25: 0 | O25: 0 | P25: =+SUBTOTAL(9,D25:O25) -> 0 | R25: 0 | S25: 0 | T25: 0 | U25: 0 | V25: 0 | W25: 0 | X25: 0 | Y25: 0 | Z25: 0 | AA25: 0 | AB25: 0 | AC25: 0 | AD25: =+SUBTOTAL(9,R25:AC25) -> 0 | AF25: 0 | AG25: 0 | AH25: 0 | AI25: 0 | AJ25: 0 | AK25: 0 | AL25: 0 | AM25: 0 | AN25: 0 | AO25: 0 | AP25: 0 | AQ25: 0 | AR25: =+SUBTOTAL(9,AF25:AQ25) -> 0 | AT25: 0 | AU25: 0 | AV25: 0 | AW25: 0 | AX25: 0 | AY25: 0 | AZ25: 0 | BA25: 0 | BB25: 0 | BC25: 0 | BD25: 0 | BE25: 0 | BF25: =+SUBTOTAL(9,AT25:BE25) -> 0 | BH25: 0 | BI25: 0 | BJ25: 0 | BK25: 0 | BL25: 0 | BM25: 0 | BN25: 0 | BO25: 0 | BP25: 0 | BQ25: 0 | BR25: 0 | BS25: 0 | BT25: =+SUBTOTAL(9,BH25:BS25) -> 0 | BV25: 0 | BW25: 0 | BX25: 0 | BY25: 0 | BZ25: 0 | CA25: 0 | CB25: 0 | CC25: 0 | CD25: 0 | CE25: 0 | CF25: 0 | CG25: 0 | CH25: =+SUBTOTAL(9,BV25:CG25) -> 0 | CJ25: 0 | CK25: 0 | CL25: 0 | CM25: 0 | CN25: 0 | CO25: 0 | CP25: 0 | CQ25: 0 | CR25: 0 | CS25: 0 | CT25: 0 | CU25: 0 | CV25: =+SUBTOTAL(9,CJ25:CU25) -> 0 | CX25: 0 | CY25: 0 | CZ25: 0 | DA25: 0 | DB25: 0 | DC25: 0 | DD25: 0 | DE25: 0 | DF25: 0 | DG25: 0 | DH25: 0 | DI25: 0 | DJ25: =+SUBTOTAL(9,CX25:DI25) -> 0 | DL25: 0 | DM25: 0 | DN25: 0 | DO25: 0 | DP25: 0 | DQ25: 0 | DR25: 0 | DS25: 0 | DT25: 0 | DU25: 0 | DV25: 0 | DW25: 0 | DX25: =+SUBTOTAL(9,DL25:DW25) -> 0 | DZ25: 0 | EA25: 0 | EB25: 0 | EC25: 0 | ED25: 0 | EE25: 0 | EF25: 0 | EG25: 0 | EH25: 0 | EI25: 0 | EJ25: 0 | EK25: 0 | EL25: =+SUBTOTAL(9,DZ25:EK25) -> 0 | EN25: 0 | EO25: 0 | EP25: 0 | EQ25: 0 | ER25: 0 | ES25: 0 | ET25: 0 | EU25: 0 | EV25: 0 | EW25: 0 | EX25: 0 | EY25: 0 | EZ25: =+SUBTOTAL(9,EN25:EY25) -> 0 | FB25: 0 | FC25: 0 | FD25: 0 | FE25: 0 | FF25: 0 | FG25: 0 | FH25: 0 | FI25: 0 | FJ25: 0 | FK25: 0 | FL25: 0 | FM25: 0 | FN25: =+SUBTOTAL(9,FB25:FM25) -> 0 | FP25: 0 | FQ25: 0 | FR25: 0 | FS25: 0 | FT25: 0 | FU25: 0 | FV25: 0 | FW25: 0 | FX25: 0 | FY25: 0 | FZ25: 0 | GA25: 0 | GB25: =+SUBTOTAL(9,FP25:GA25) -> 0 | GD25: 0 | GE25: 0 | GF25: 0 | GG25: 0 | GH25: 0 | GI25: 0 | GJ25: 0 | GK25: 0 | GL25: 0 | GM25: 0 | GN25: 0 | GO25: 0 | GP25: =+SUBTOTAL(9,GD25:GO25) -> 0 | GR25: 0 | GS25: 0 | GT25: 0 | GU25: 0 | GV25: 0 | GW25: 0 | GX25: 0 | GY25: 0 | GZ25: 0 | HA25: 0 | HB25: 0 | HC25: 0 | HD25: =+SUBTOTAL(9,GR25:HC25) -> 0 | HF25: 0 | HG25: 0 | HH25: 0 | HI25: 0 | HJ25: 0 | HK25: 0 | HL25: 0 | HM25: 0 | HN25: 0 | HO25: 0 | HP25: 0 | HQ25: 0 | HR25: =+SUBTOTAL(9,HF25:HQ25) -> 0 | HT25: 0 | HU25: 0 | HV25: 0 | HW25: 0 | HX25: 0 | HY25: 0 | HZ25: 0 | IA25: 0 | IB25: 0 | IC25: 0 | ID25: 0 | IE25: 0 | IF25: =+SUBTOTAL(9,HT25:IE25) -> 0 | IH25: 0 | II25: 0 | IJ25: 0 | IK25: 0 | IL25: 0 | IM25: 0 | IN25: 0 | IO25: 0 | IP25: 0 | IQ25: 0 | IR25: 0 | IS25: 0 | IT25: =+SUBTOTAL(9,IH25:IS25) -> 0 | IV25: 0 | IW25: 0 | IX25: 0 | IY25: 0 | IZ25: 0 | JA25: 0 | JB25: 0 | JC25: 0 | JD25: 0 | JE25: 0 | JF25: 0 | JG25: 0 | JH25: =+SUBTOTAL(9,IV25:JG25) -> 0 | JJ25: 0 | JK25: 0 | JL25: 0 | JM25: 0 | JN25: 0 | JO25: 0 | JP25: 0 | JQ25: 0 | JR25: 0 | JS25: 0 | JT25: 0 | JU25: 0 | JV25: =+SUBTOTAL(9,JJ25:JU25) -> 0 | JX25: 0 | JY25: 0 | JZ25: 0 | KA25: 0 | KB25: 0 | KC25: 0 | KD25: 0 | KE25: 0 | KF25: 0 | KG25: 0 | KH25: 0 | KI25: 0 | KJ25: =+SUBTOTAL(9,JX25:KI25) -> 0 | KL25: 0 | KM25: 0 | KN25: 0 | KO25: 0 | KP25: 0 | KQ25: 0 | KR25: 0 | KS25: 0 | KT25: 0 | KU25: 0 | KV25: 0 | KW25: 0 | KX25: =+SUBTOTAL(9,KL25:KW25) -> 0 | KZ25: 0 | LA25: 0 | LB25: 0 | LC25: 0 | LD25: 0 | LE25: 0 | LF25: 0 | LG25: 0 | LH25: 0 | LI25: 0 | LJ25: 0 | LK25: 0 | LL25: =+SUBTOTAL(9,KZ25:LK25) -> 0 | LN25: 0 | LO25: 0 | LP25: 0 | LQ25: 0 | LR25: 0 | LS25: 0 | LT25: 0 | LU25: 0 | LV25: 0 | LW25: 0 | LX25: 0 | LY25: 0 | LZ25: =+SUBTOTAL(9,LN25:LY25) -> 0 | MB25: =SUMIF($D$11:$LY$11,MB$8,$D25:$LY25) -> 0 | MC25: =SUMIF($D$11:$LY$11,MC$8,$D25:$LY25) -> 0 | MD25: =SUMIF($D$11:$LY$11,MD$8,$D25:$LY25) -> 0 | ME25: =SUMIF($D$11:$LY$11,ME$8,$D25:$LY25) -> 0 | MF25: =SUMIF($D$11:$LY$11,MF$8,$D25:$LY25) -> 0 | MG25: =SUMIF($D$11:$LY$11,MG$8,$D25:$LY25) -> 0 | MH25: =SUMIF($D$11:$LY$11,MH$8,$D25:$LY25) -> 0 | MI25: =SUMIF($D$11:$LY$11,MI$8,$D25:$LY25) -> 0 | ... MM25: =SUMIF($D$11:$LY$11,MM$8,$D25:$LY25) -> 0 | MN25: =SUM(MB25:MM25) -> 0
B26: Intercompany Cost of Sales | D26: 0 | E26: 0 | F26: 0 | G26: 0 | H26: 0 | I26: 0 | J26: 0 | K26: 0 | L26: 0 | M26: 0 | N26: 0 | O26: 0 | P26: =+SUBTOTAL(9,D26:O26) -> 0 | R26: 0 | S26: 0 | T26: 0 | U26: 0 | V26: 0 | W26: 0 | X26: 0 | Y26: 0 | Z26: 0 | AA26: 0 | AB26: 0 | AC26: 0 | AD26: =+SUBTOTAL(9,R26:AC26) -> 0 | AF26: 0 | AG26: 0 | AH26: 0 | AI26: 0 | AJ26: 0 | AK26: 0 | AL26: 0 | AM26: 0 | AN26: 0 | AO26: 0 | AP26: 0 | AQ26: 0 | AR26: =+SUBTOTAL(9,AF26:AQ26) -> 0 | AT26: 0 | AU26: 0 | AV26: 0 | AW26: 0 | AX26: 0 | AY26: 0 | AZ26: 0 | BA26: 0 | BB26: 0 | BC26: 0 | BD26: 0 | BE26: 0 | BF26: =+SUBTOTAL(9,AT26:BE26) -> 0 | BH26: 0 | BI26: 0 | BJ26: 0 | BK26: 0 | BL26: 0 | BM26: 0 | BN26: 0 | BO26: 0 | BP26: 0 | BQ26: 0 | BR26: 0 | BS26: 0 | BT26: =+SUBTOTAL(9,BH26:BS26) -> 0 | BV26: 0 | BW26: 0 | BX26: 0 | BY26: 0 | BZ26: 0 | CA26: 0 | CB26: 0 | CC26: 0 | CD26: 0 | CE26: 0 | CF26: 0 | CG26: 0 | CH26: =+SUBTOTAL(9,BV26:CG26) -> 0 | CJ26: 0 | CK26: 0 | CL26: 0 | CM26: 0 | CN26: 0 | CO26: 0 | CP26: 0 | CQ26: 0 | CR26: 0 | CS26: 0 | CT26: 0 | CU26: 0 | CV26: =+SUBTOTAL(9,CJ26:CU26) -> 0 | CX26: 0 | CY26: 0 | CZ26: 0 | DA26: 0 | DB26: 0 | DC26: 0 | DD26: 0 | DE26: 0 | DF26: 0 | DG26: 0 | DH26: 0 | DI26: 0 | DJ26: =+SUBTOTAL(9,CX26:DI26) -> 0 | DL26: 0 | DM26: 0 | DN26: 0 | DO26: 0 | DP26: 0 | DQ26: 0 | DR26: 0 | DS26: 0 | DT26: 0 | DU26: 0 | DV26: 0 | DW26: 0 | DX26: =+SUBTOTAL(9,DL26:DW26) -> 0 | DZ26: 0 | EA26: 0 | EB26: 0 | EC26: 0 | ED26: 0 | EE26: 0 | EF26: 0 | EG26: 0 | EH26: 0 | EI26: 0 | EJ26: 0 | EK26: 0 | EL26: =+SUBTOTAL(9,DZ26:EK26) -> 0 | EN26: 0 | EO26: 0 | EP26: 0 | EQ26: 0 | ER26: 0 | ES26: 0 | ET26: 0 | EU26: 0 | EV26: 0 | EW26: 0 | EX26: 0 | EY26: 0 | EZ26: =+SUBTOTAL(9,EN26:EY26) -> 0 | FB26: 0 | FC26: 0 | FD26: 0 | FE26: 0 | FF26: 0 | FG26: 0 | FH26: 0 | FI26: 0 | FJ26: 0 | FK26: 0 | FL26: 0 | FM26: 0 | FN26: =+SUBTOTAL(9,FB26:FM26) -> 0 | FP26: 0 | FQ26: 0 | FR26: 0 | FS26: 0 | FT26: 0 | FU26: 0 | FV26: 0 | FW26: 0 | FX26: 0 | FY26: 0 | FZ26: 0 | GA26: 0 | GB26: =+SUBTOTAL(9,FP26:GA26) -> 0 | GD26: 0 | GE26: 0 | GF26: 0 | GG26: 0 | GH26: 0 | GI26: 0 | GJ26: 0 | GK26: 0 | GL26: 0 | GM26: 0 | GN26: 0 | GO26: 0 | GP26: =+SUBTOTAL(9,GD26:GO26) -> 0 | GR26: 0 | GS26: 0 | GT26: 0 | GU26: 0 | GV26: 0 | GW26: 0 | GX26: 0 | GY26: 0 | GZ26: 0 | HA26: 0 | HB26: 0 | HC26: 0 | HD26: =+SUBTOTAL(9,GR26:HC26) -> 0 | HF26: 0 | HG26: 0 | HH26: 0 | HI26: 0 | HJ26: 0 | HK26: 0 | HL26: 0 | HM26: 0 | HN26: 0 | HO26: 0 | HP26: 0 | HQ26: 0 | HR26: =+SUBTOTAL(9,HF26:HQ26) -> 0 | HT26: 0 | HU26: 0 | HV26: 0 | HW26: 0 | HX26: 0 | HY26: 0 | HZ26: 0 | IA26: 0 | IB26: 0 | IC26: 0 | ID26: 0 | IE26: 0 | IF26: =+SUBTOTAL(9,HT26:IE26) -> 0 | IH26: 0 | II26: 0 | IJ26: 0 | IK26: 0 | IL26: 0 | IM26: 0 | IN26: 0 | IO26: 0 | IP26: 0 | IQ26: 0 | IR26: 0 | IS26: 0 | IT26: =+SUBTOTAL(9,IH26:IS26) -> 0 | IV26: 0 | IW26: 0 | IX26: 0 | IY26: 0 | IZ26: 0 | JA26: 0 | JB26: 0 | JC26: 0 | JD26: 0 | JE26: 0 | JF26: 0 | JG26: 0 | JH26: =+SUBTOTAL(9,IV26:JG26) -> 0 | JJ26: 0 | JK26: 0 | JL26: 0 | JM26: 0 | JN26: 0 | JO26: 0 | JP26: 0 | JQ26: 0 | JR26: 0 | JS26: 0 | JT26: 0 | JU26: 0 | JV26: =+SUBTOTAL(9,JJ26:JU26) -> 0 | JX26: 0 | JY26: 0 | JZ26: 0 | KA26: 0 | KB26: 0 | KC26: 0 | KD26: 0 | KE26: 0 | KF26: 0 | KG26: 0 | KH26: 0 | KI26: 0 | KJ26: =+SUBTOTAL(9,JX26:KI26) -> 0 | KL26: 0 | KM26: 0 | KN26: 0 | KO26: 0 | KP26: 0 | KQ26: 0 | KR26: 0 | KS26: 0 | KT26: 0 | KU26: 0 | KV26: 0 | KW26: 0 | KX26: =+SUBTOTAL(9,KL26:KW26) -> 0 | KZ26: 0 | LA26: 0 | LB26: 0 | LC26: 0 | LD26: 0 | LE26: 0 | LF26: 0 | LG26: 0 | LH26: 0 | LI26: 0 | LJ26: 0 | LK26: 0 | LL26: =+SUBTOTAL(9,KZ26:LK26) -> 0 | LN26: 0 | LO26: 0 | LP26: 0 | LQ26: 0 | LR26: 0 | LS26: 0 | LT26: 0 | LU26: 0 | LV26: 0 | LW26: 0 | LX26: 0 | LY26: 0 | LZ26: =+SUBTOTAL(9,LN26:LY26) -> 0 | MB26: =SUMIF($D$11:$LY$11,MB$8,$D26:$LY26) -> 0 | MC26: =SUMIF($D$11:$LY$11,MC$8,$D26:$LY26) -> 0 | MD26: =SUMIF($D$11:$LY$11,MD$8,$D26:$LY26) -> 0 | ME26: =SUMIF($D$11:$LY$11,ME$8,$D26:$LY26) -> 0 | MF26: =SUMIF($D$11:$LY$11,MF$8,$D26:$LY26) -> 0 | MG26: =SUMIF($D$11:$LY$11,MG$8,$D26:$LY26) -> 0 | MH26: =SUMIF($D$11:$LY$11,MH$8,$D26:$LY26) -> 0 | MI26: =SUMIF($D$11:$LY$11,MI$8,$D26:$LY26) -> 0 | ... MM26: =SUMIF($D$11:$LY$11,MM$8,$D26:$LY26) -> 0 | MN26: =SUM(MB26:MM26) -> 0
P27: =+SUBTOTAL(9,D27:O27) -> 0 | AD27: =+SUBTOTAL(9,R27:AC27) -> 0 | AR27: =+SUBTOTAL(9,AF27:AQ27) -> 0 | BF27: =+SUBTOTAL(9,AT27:BE27) -> 0 | BT27: =+SUBTOTAL(9,BH27:BS27) -> 0 | CH27: =+SUBTOTAL(9,BV27:CG27) -> 0 | CV27: =+SUBTOTAL(9,CJ27:CU27) -> 0 | DJ27: =+SUBTOTAL(9,CX27:DI27) -> 0 | DX27: =+SUBTOTAL(9,DL27:DW27) -> 0 | EL27: =+SUBTOTAL(9,DZ27:EK27) -> 0 | EZ27: =+SUBTOTAL(9,EN27:EY27) -> 0 | FN27: =+SUBTOTAL(9,FB27:FM27) -> 0 | GB27: =+SUBTOTAL(9,FP27:GA27) -> 0 | GP27: =+SUBTOTAL(9,GD27:GO27) -> 0 | HD27: =+SUBTOTAL(9,GR27:HC27) -> 0 | HR27: =+SUBTOTAL(9,HF27:HQ27) -> 0 | IF27: =+SUBTOTAL(9,HT27:IE27) -> 0 | IT27: =+SUBTOTAL(9,IH27:IS27) -> 0 | JH27: =+SUBTOTAL(9,IV27:JG27) -> 0 | JV27: =+SUBTOTAL(9,JJ27:JU27) -> 0 | KJ27: =+SUBTOTAL(9,JX27:KI27) -> 0 | KX27: =+SUBTOTAL(9,KL27:KW27) -> 0 | LL27: =+SUBTOTAL(9,KZ27:LK27) -> 0 | LZ27: =+SUBTOTAL(9,LN27:LY27) -> 0
B28: TOTAL DIRECT COSTS | D28: =SUM(D20:D27) -> 0 | E28: =SUM(E20:E27) -> 0 | F28: =SUM(F20:F27) -> 0 | G28: =SUM(G20:G27) -> 0 | H28: =SUM(H20:H27) -> 0 | I28: =SUM(I20:I27) -> 0 | J28: =SUM(J20:J27) -> 0 | K28: =SUM(K20:K27) -> 0 | ... O28: =SUM(O20:O27) -> 0 | P28: =+SUBTOTAL(9,D28:O28) -> 0 | R28: =SUM(R20:R27) -> 0 | S28: =SUM(S20:S27) -> 0 | T28: =SUM(T20:T27) -> 0 | U28: =SUM(U20:U27) -> 0 | V28: =SUM(V20:V27) -> 0 | W28: =SUM(W20:W27) -> 0 | X28: =SUM(X20:X27) -> 0 | Y28: =SUM(Y20:Y27) -> 0 | ... AC28: =SUM(AC20:AC27) -> 0 | AD28: =+SUBTOTAL(9,R28:AC28) -> 0 | AF28: =SUM(AF20:AF27) -> 0 | AG28: =SUM(AG20:AG27) -> 0 | AH28: =SUM(AH20:AH27) -> 0 | AI28: =SUM(AI20:AI27) -> 0 | AJ28: =SUM(AJ20:AJ27) -> 0 | AK28: =SUM(AK20:AK27) -> 0 | AL28: =SUM(AL20:AL27) -> 0 | AM28: =SUM(AM20:AM27) -> 0 | ... AQ28: =SUM(AQ20:AQ27) -> 0 | AR28: =+SUBTOTAL(9,AF28:AQ28) -> 0 | AT28: =SUM(AT20:AT27) -> 0 | AU28: =SUM(AU20:AU27) -> 0 | AV28: =SUM(AV20:AV27) -> 0 | AW28: =SUM(AW20:AW27) -> 0 | AX28: =SUM(AX20:AX27) -> 0 | AY28: =SUM(AY20:AY27) -> 0 | AZ28: =SUM(AZ20:AZ27) -> 0 | BA28: =SUM(BA20:BA27) -> 0 | ... BE28: =SUM(BE20:BE27) -> 0 | BF28: =+SUBTOTAL(9,AT28:BE28) -> 0 | BH28: =SUM(BH20:BH27) -> 0 | BI28: =SUM(BI20:BI27) -> 0 | BJ28: =SUM(BJ20:BJ27) -> 0 | BK28: =SUM(BK20:BK27) -> 0 | BL28: =SUM(BL20:BL27) -> 0 | BM28: =SUM(BM20:BM27) -> 0 | BN28: =SUM(BN20:BN27) -> 0 | BO28: =SUM(BO20:BO27) -> 0 | ... BS28: =SUM(BS20:BS27) -> 0 | BT28: =+SUBTOTAL(9,BH28:BS28) -> 0 | BV28: =SUM(BV20:BV27) -> 0 | BW28: =SUM(BW20:BW27) -> 0 | BX28: =SUM(BX20:BX27) -> 0 | BY28: =SUM(BY20:BY27) -> 0 | BZ28: =SUM(BZ20:BZ27) -> 0 | CA28: =SUM(CA20:CA27) -> 0 | CB28: =SUM(CB20:CB27) -> 0 | CC28: =SUM(CC20:CC27) -> 0 | ... CG28: =SUM(CG20:CG27) -> 0 | CH28: =+SUBTOTAL(9,BV28:CG28) -> 0 | CJ28: =SUM(CJ20:CJ27) -> 0 | CK28: =SUM(CK20:CK27) -> 0 | CL28: =SUM(CL20:CL27) -> 0 | CM28: =SUM(CM20:CM27) -> 0 | CN28: =SUM(CN20:CN27) -> 0 | CO28: =SUM(CO20:CO27) -> 0 | CP28: =SUM(CP20:CP27) -> 0 | CQ28: =SUM(CQ20:CQ27) -> 0 | ... CU28: =SUM(CU20:CU27) -> 0 | CV28: =+SUBTOTAL(9,CJ28:CU28) -> 0 | CX28: =SUM(CX20:CX27) -> 0 | CY28: =SUM(CY20:CY27) -> 0 | CZ28: =SUM(CZ20:CZ27) -> 0 | DA28: =SUM(DA20:DA27) -> 0 | DB28: =SUM(DB20:DB27) -> 0 | DC28: =SUM(DC20:DC27) -> 0 | DD28: =SUM(DD20:DD27) -> 0 | DE28: =SUM(DE20:DE27) -> 0 | ... DI28: =SUM(DI20:DI27) -> 0 | DJ28: =+SUBTOTAL(9,CX28:DI28) -> 0 | DL28: =SUM(DL20:DL27) -> 0 | DM28: =SUM(DM20:DM27) -> 0 | DN28: =SUM(DN20:DN27) -> 0 | DO28: =SUM(DO20:DO27) -> 0 | DP28: =SUM(DP20:DP27) -> 0 | DQ28: =SUM(DQ20:DQ27) -> 0 | DR28: =SUM(DR20:DR27) -> 0 | DS28: =SUM(DS20:DS27) -> 0 | ... DW28: =SUM(DW20:DW27) -> 0 | DX28: =+SUBTOTAL(9,DL28:DW28) -> 0 | DZ28: =SUM(DZ20:DZ27) -> 0 | EA28: =SUM(EA20:EA27) -> 0 | EB28: =SUM(EB20:EB27) -> 0 | EC28: =SUM(EC20:EC27) -> 0 | ED28: =SUM(ED20:ED27) -> 0 | EE28: =SUM(EE20:EE27) -> 0 | EF28: =SUM(EF20:EF27) -> 0 | EG28: =SUM(EG20:EG27) -> 0 | ... EK28: =SUM(EK20:EK27) -> 0 | EL28: =+SUBTOTAL(9,DZ28:EK28) -> 0 | EN28: =SUM(EN20:EN27) -> 0 | EO28: =SUM(EO20:EO27) -> 0 | EP28: =SUM(EP20:EP27) -> 0 | EQ28: =SUM(EQ20:EQ27) -> 0 | ER28: =SUM(ER20:ER27) -> 0 | ES28: =SUM(ES20:ES27) -> 0 | ET28: =SUM(ET20:ET27) -> 0 | EU28: =SUM(EU20:EU27) -> 0 | ... EY28: =SUM(EY20:EY27) -> 0 | EZ28: =+SUBTOTAL(9,EN28:EY28) -> 0 | FB28: =SUM(FB20:FB27) -> 0 | FC28: =SUM(FC20:FC27) -> 0 | FD28: =SUM(FD20:FD27) -> 0 | FE28: =SUM(FE20:FE27) -> 0 | FF28: =SUM(FF20:FF27) -> 0 | FG28: =SUM(FG20:FG27) -> 0 | FH28: =SUM(FH20:FH27) -> 0 | FI28: =SUM(FI20:FI27) -> 0 | ... FM28: =SUM(FM20:FM27) -> 0 | FN28: =+SUBTOTAL(9,FB28:FM28) -> 0 | FP28: =SUM(FP20:FP27) -> 0 | FQ28: =SUM(FQ20:FQ27) -> 0 | FR28: =SUM(FR20:FR27) -> 0 | FS28: =SUM(FS20:FS27) -> 0 | FT28: =SUM(FT20:FT27) -> 0 | FU28: =SUM(FU20:FU27) -> 0 | FV28: =SUM(FV20:FV27) -> 0 | FW28: =SUM(FW20:FW27) -> 0 | ... GA28: =SUM(GA20:GA27) -> 0 | GB28: =+SUBTOTAL(9,FP28:GA28) -> 0 | GD28: =SUM(GD20:GD27) -> 0 | GE28: =SUM(GE20:GE27) -> 0 | GF28: =SUM(GF20:GF27) -> 0 | GG28: =SUM(GG20:GG27) -> 0 | GH28: =SUM(GH20:GH27) -> 0 | GI28: =SUM(GI20:GI27) -> 0 | GJ28: =SUM(GJ20:GJ27) -> 0 | GK28: =SUM(GK20:GK27) -> 0 | ... GO28: =SUM(GO20:GO27) -> 0 | GP28: =+SUBTOTAL(9,GD28:GO28) -> 0 | GR28: =SUM(GR20:GR27) -> 0 | GS28: =SUM(GS20:GS27) -> 0 | GT28: =SUM(GT20:GT27) -> 0 | GU28: =SUM(GU20:GU27) -> 0 | GV28: =SUM(GV20:GV27) -> 0 | GW28: =SUM(GW20:GW27) -> 0 | GX28: =SUM(GX20:GX27) -> 0 | GY28: =SUM(GY20:GY27) -> 0 | ... HC28: =SUM(HC20:HC27) -> 0 | HD28: =+SUBTOTAL(9,GR28:HC28) -> 0 | HF28: =SUM(HF20:HF27) -> 0 | HG28: =SUM(HG20:HG27) -> 0 | HH28: =SUM(HH20:HH27) -> 0 | HI28: =SUM(HI20:HI27) -> 0 | HJ28: =SUM(HJ20:HJ27) -> 0 | HK28: =SUM(HK20:HK27) -> 0 | HL28: =SUM(HL20:HL27) -> 0 | HM28: =SUM(HM20:HM27) -> 0 | ... HQ28: =SUM(HQ20:HQ27) -> 0 | HR28: =+SUBTOTAL(9,HF28:HQ28) -> 0 | HT28: =SUM(HT20:HT27) -> 0 | HU28: =SUM(HU20:HU27) -> 0 | HV28: =SUM(HV20:HV27) -> 0 | HW28: =SUM(HW20:HW27) -> 0 | HX28: =SUM(HX20:HX27) -> 0 | HY28: =SUM(HY20:HY27) -> 0 | HZ28: =SUM(HZ20:HZ27) -> 0 | IA28: =SUM(IA20:IA27) -> 0 | ... IE28: =SUM(IE20:IE27) -> 0 | IF28: =+SUBTOTAL(9,HT28:IE28) -> 0 | IH28: =SUM(IH20:IH27) -> 0 | II28: =SUM(II20:II27) -> 0 | IJ28: =SUM(IJ20:IJ27) -> 0 | IK28: =SUM(IK20:IK27) -> 0 | IL28: =SUM(IL20:IL27) -> 0 | IM28: =SUM(IM20:IM27) -> 0 | IN28: =SUM(IN20:IN27) -> 0 | IO28: =SUM(IO20:IO27) -> 0 | ... IS28: =SUM(IS20:IS27) -> 0 | IT28: =+SUBTOTAL(9,IH28:IS28) -> 0 | IV28: =SUM(IV20:IV27) -> 0 | IW28: =SUM(IW20:IW27) -> 0 | IX28: =SUM(IX20:IX27) -> 0 | IY28: =SUM(IY20:IY27) -> 0 | IZ28: =SUM(IZ20:IZ27) -> 0 | JA28: =SUM(JA20:JA27) -> 0 | JB28: =SUM(JB20:JB27) -> 0 | JC28: =SUM(JC20:JC27) -> 0 | ... JG28: =SUM(JG20:JG27) -> 0 | JH28: =+SUBTOTAL(9,IV28:JG28) -> 0 | JJ28: =SUM(JJ20:JJ27) -> 0 | JK28: =SUM(JK20:JK27) -> 0 | JL28: =SUM(JL20:JL27) -> 0 | JM28: =SUM(JM20:JM27) -> 0 | JN28: =SUM(JN20:JN27) -> 0 | JO28: =SUM(JO20:JO27) -> 0 | JP28: =SUM(JP20:JP27) -> 0 | JQ28: =SUM(JQ20:JQ27) -> 0 | ... JU28: =SUM(JU20:JU27) -> 0 | JV28: =+SUBTOTAL(9,JJ28:JU28) -> 0 | JX28: =SUM(JX20:JX27) -> 0 | JY28: =SUM(JY20:JY27) -> 0 | JZ28: =SUM(JZ20:JZ27) -> 0 | KA28: =SUM(KA20:KA27) -> 0 | KB28: =SUM(KB20:KB27) -> 0 | KC28: =SUM(KC20:KC27) -> 0 | KD28: =SUM(KD20:KD27) -> 0 | KE28: =SUM(KE20:KE27) -> 0 | ... KI28: =SUM(KI20:KI27) -> 0 | KJ28: =+SUBTOTAL(9,JX28:KI28) -> 0 | KL28: =SUM(KL20:KL27) -> 0 | KM28: =SUM(KM20:KM27) -> 0 | KN28: =SUM(KN20:KN27) -> 0 | KO28: =SUM(KO20:KO27) -> 0 | KP28: =SUM(KP20:KP27) -> 0 | KQ28: =SUM(KQ20:KQ27) -> 0 | KR28: =SUM(KR20:KR27) -> 0 | KS28: =SUM(KS20:KS27) -> 0 | ... KW28: =SUM(KW20:KW27) -> 0 | KX28: =+SUBTOTAL(9,KL28:KW28) -> 0 | KZ28: =SUM(KZ20:KZ27) -> 0 | LA28: =SUM(LA20:LA27) -> 0 | LB28: =SUM(LB20:LB27) -> 0 | LC28: =SUM(LC20:LC27) -> 0 | LD28: =SUM(LD20:LD27) -> 0 | LE28: =SUM(LE20:LE27) -> 0 | LF28: =SUM(LF20:LF27) -> 0 | LG28: =SUM(LG20:LG27) -> 0 | ... LK28: =SUM(LK20:LK27) -> 0 | LL28: =+SUBTOTAL(9,KZ28:LK28) -> 0 | LN28: =SUM(LN20:LN27) -> 0 | LO28: =SUM(LO20:LO27) -> 0 | LP28: =SUM(LP20:LP27) -> 0 | LQ28: =SUM(LQ20:LQ27) -> 0 | LR28: =SUM(LR20:LR27) -> 0 | LS28: =SUM(LS20:LS27) -> 0 | LT28: =SUM(LT20:LT27) -> 0 | LU28: =SUM(LU20:LU27) -> 0 | ... LY28: =SUM(LY20:LY27) -> 0 | LZ28: =+SUBTOTAL(9,LN28:LY28) -> 0 | MB28: =SUM(MB20:MB27) -> 0 | MC28: =SUM(MC20:MC27) -> 0 | MD28: =SUM(MD20:MD27) -> 0 | ME28: =SUM(ME20:ME27) -> 0 | MF28: =SUM(MF20:MF27) -> 0 | MG28: =SUM(MG20:MG27) -> 0 | MH28: =SUM(MH20:MH27) -> 0 | MI28: =SUM(MI20:MI27) -> 0 | ... MN28: =SUM(MN20:MN27) -> 0
B30: OTHER INCOME
B31: Miscellaneous Income (Others [e.g. Govt subsidy]) | D31: 0 | E31: 0 | F31: 0 | G31: 0 | H31: 0 | I31: 0 | J31: 0 | K31: 0 | L31: 0 | M31: 0 | N31: 0 | O31: 0 | P31: =+SUBTOTAL(9,D31:O31) -> 0 | R31: 0 | S31: 0 | T31: 0 | U31: 0 | V31: 0 | W31: 0 | X31: 0 | Y31: 0 | Z31: 0 | AA31: 0 | AB31: 0 | AC31: 0 | AD31: =+SUBTOTAL(9,R31:AC31) -> 0 | AF31: 0 | AG31: 0 | AH31: 0 | AI31: 0 | AJ31: 0 | AK31: 0 | AL31: 0 | AM31: 0 | AN31: 0 | AO31: 0 | AP31: 0 | AQ31: 0 | AR31: =+SUBTOTAL(9,AF31:AQ31) -> 0 | AT31: 0 | AU31: 0 | AV31: 0 | AW31: 0 | AX31: 0 | AY31: 0 | AZ31: 0 | BA31: 0 | BB31: 0 | BC31: 0 | BD31: 0 | BE31: 0 | BF31: =+SUBTOTAL(9,AT31:BE31) -> 0 | BH31: 0 | BI31: 0 | BJ31: 0 | BK31: 0 | BL31: 0 | BM31: 0 | BN31: 0 | BO31: 0 | BP31: 0 | BQ31: 0 | BR31: 0 | BS31: 0 | BT31: =+SUBTOTAL(9,BH31:BS31) -> 0 | BV31: 0 | BW31: 0 | BX31: 0 | BY31: 0 | BZ31: 0 | CA31: 0 | CB31: 0 | CC31: 0 | CD31: 0 | CE31: 0 | CF31: 0 | CG31: 0 | CH31: =+SUBTOTAL(9,BV31:CG31) -> 0 | CJ31: 0 | CK31: 0 | CL31: 0 | CM31: 0 | CN31: 0 | CO31: 0 | CP31: 0 | CQ31: 0 | CR31: 0 | CS31: 0 | CT31: 0 | CU31: 0 | CV31: =+SUBTOTAL(9,CJ31:CU31) -> 0 | CX31: 0 | CY31: 0 | CZ31: 0 | DA31: 0 | DB31: 0 | DC31: 0 | DD31: 0 | DE31: 0 | DF31: 0 | DG31: 0 | DH31: 0 | DI31: 0 | DJ31: =+SUBTOTAL(9,CX31:DI31) -> 0 | DL31: 0 | DM31: 0 | DN31: 0 | DO31: 0 | DP31: 0 | DQ31: 0 | DR31: 0 | DS31: 0 | DT31: 0 | DU31: 0 | DV31: 0 | DW31: 0 | DX31: =+SUBTOTAL(9,DL31:DW31) -> 0 | DZ31: 0 | EA31: 0 | EB31: 0 | EC31: 0 | ED31: 0 | EE31: 0 | EF31: 0 | EG31: 0 | EH31: 0 | EI31: 0 | EJ31: 0 | EK31: 0 | EL31: =+SUBTOTAL(9,DZ31:EK31) -> 0 | EN31: 0 | EO31: 0 | EP31: 0 | EQ31: 0 | ER31: 0 | ES31: 0 | ET31: 0 | EU31: 0 | EV31: 0 | EW31: 0 | EX31: 0 | EY31: 0 | EZ31: =+SUBTOTAL(9,EN31:EY31) -> 0 | FB31: 0 | FC31: 0 | FD31: 0 | FE31: 0 | FF31: 0 | FG31: 0 | FH31: 0 | FI31: 0 | FJ31: 0 | FK31: 0 | FL31: 0 | FM31: 0 | FN31: =+SUBTOTAL(9,FB31:FM31) -> 0 | FP31: 0 | FQ31: 0 | FR31: 0 | FS31: 0 | FT31: 0 | FU31: 0 | FV31: 0 | FW31: 0 | FX31: 0 | FY31: 0 | FZ31: 0 | GA31: 0 | GB31: =+SUBTOTAL(9,FP31:GA31) -> 0 | GD31: 0 | GE31: 0 | GF31: 0 | GG31: 0 | GH31: 0 | GI31: 0 | GJ31: 0 | GK31: 0 | GL31: 0 | GM31: 0 | GN31: 0 | GO31: 0 | GP31: =+SUBTOTAL(9,GD31:GO31) -> 0 | GR31: 0 | GS31: 0 | GT31: 0 | GU31: 0 | GV31: 0 | GW31: 0 | GX31: 0 | GY31: 0 | GZ31: 0 | HA31: 0 | HB31: 0 | HC31: 0 | HD31: =+SUBTOTAL(9,GR31:HC31) -> 0 | HF31: 0 | HG31: 0 | HH31: 0 | HI31: 0 | HJ31: 0 | HK31: 0 | HL31: 0 | HM31: 0 | HN31: 0 | HO31: 0 | HP31: 0 | HQ31: 0 | HR31: =+SUBTOTAL(9,HF31:HQ31) -> 0 | HT31: 0 | HU31: 0 | HV31: 0 | HW31: 0 | HX31: 0 | HY31: 0 | HZ31: 0 | IA31: 0 | IB31: 0 | IC31: 0 | ID31: 0 | IE31: 0 | IF31: =+SUBTOTAL(9,HT31:IE31) -> 0 | IH31: 0 | II31: 0 | IJ31: 0 | IK31: 0 | IL31: 0 | IM31: 0 | IN31: 0 | IO31: 0 | IP31: 0 | IQ31: 0 | IR31: 0 | IS31: 0 | IT31: =+SUBTOTAL(9,IH31:IS31) -> 0 | IV31: 0 | IW31: 0 | IX31: 0 | IY31: 0 | IZ31: 0 | JA31: 0 | JB31: 0 | JC31: 0 | JD31: 0 | JE31: 0 | JF31: 0 | JG31: 0 | JH31: =+SUBTOTAL(9,IV31:JG31) -> 0 | JJ31: 0 | JK31: 0 | JL31: 0 | JM31: 0 | JN31: 0 | JO31: 0 | JP31: 0 | JQ31: 0 | JR31: 0 | JS31: 0 | JT31: 0 | JU31: 0 | JV31: =+SUBTOTAL(9,JJ31:JU31) -> 0 | JX31: 0 | JY31: 0 | JZ31: 0 | KA31: 0 | KB31: 0 | KC31: 0 | KD31: 0 | KE31: 0 | KF31: 0 | KG31: 0 | KH31: 0 | KI31: 0 | KJ31: =+SUBTOTAL(9,JX31:KI31) -> 0 | KL31: 0 | KM31: 0 | KN31: 0 | KO31: 0 | KP31: 0 | KQ31: 0 | KR31: 0 | KS31: 0 | KT31: 0 | KU31: 0 | KV31: 0 | KW31: 0 | KX31: =+SUBTOTAL(9,KL31:KW31) -> 0 | KZ31: 0 | LA31: 0 | LB31: 0 | LC31: 0 | LD31: 0 | LE31: 0 | LF31: 0 | LG31: 0 | LH31: 0 | LI31: 0 | LJ31: 0 | LK31: 0 | LL31: =+SUBTOTAL(9,KZ31:LK31) -> 0 | LN31: 0 | LO31: 0 | LP31: 0 | LQ31: 0 | LR31: 0 | LS31: 0 | LT31: 0 | LU31: 0 | LV31: 0 | LW31: 0 | LX31: 0 | LY31: 0 | LZ31: =+SUBTOTAL(9,LN31:LY31) -> 0 | MB31: =SUMIF($D$11:$LY$11,MB$8,$D31:$LY31) -> 0 | MC31: =SUMIF($D$11:$LY$11,MC$8,$D31:$LY31) -> 0 | MD31: =SUMIF($D$11:$LY$11,MD$8,$D31:$LY31) -> 0 | ME31: =SUMIF($D$11:$LY$11,ME$8,$D31:$LY31) -> 0 | MF31: =SUMIF($D$11:$LY$11,MF$8,$D31:$LY31) -> 0 | MG31: =SUMIF($D$11:$LY$11,MG$8,$D31:$LY31) -> 0 | MH31: =SUMIF($D$11:$LY$11,MH$8,$D31:$LY31) -> 0 | MI31: =SUMIF($D$11:$LY$11,MI$8,$D31:$LY31) -> 0 | ... MM31: =SUMIF($D$11:$LY$11,MM$8,$D31:$LY31) -> 0 | MN31: =SUM(MB31:MM31) -> 0
B32: Vessel System Income | D32: 0 | E32: 0 | F32: 0 | G32: 0 | H32: 0 | I32: 0 | J32: 0 | K32: 0 | L32: 0 | M32: 0 | N32: 0 | O32: 0 | P32: =+SUBTOTAL(9,D32:O32) -> 0 | R32: 0 | S32: 0 | T32: 0 | U32: 0 | V32: 0 | W32: 0 | X32: 0 | Y32: 0 | Z32: 0 | AA32: 0 | AB32: 0 | AC32: 0 | AD32: =+SUBTOTAL(9,R32:AC32) -> 0 | AF32: 0 | AG32: 0 | AH32: 0 | AI32: 0 | AJ32: 0 | AK32: 0 | AL32: 0 | AM32: 0 | AN32: 0 | AO32: 0 | AP32: 0 | AQ32: 0 | AR32: =+SUBTOTAL(9,AF32:AQ32) -> 0 | AT32: 0 | AU32: 0 | AV32: 0 | AW32: 0 | AX32: 0 | AY32: 0 | AZ32: 0 | BA32: 0 | BB32: 0 | BC32: 0 | BD32: 0 | BE32: 0 | BF32: =+SUBTOTAL(9,AT32:BE32) -> 0 | BH32: 0 | BI32: 0 | BJ32: 0 | BK32: 0 | BL32: 0 | BM32: 0 | BN32: 0 | BO32: 0 | BP32: 0 | BQ32: 0 | BR32: 0 | BS32: 0 | BT32: =+SUBTOTAL(9,BH32:BS32) -> 0 | BV32: 0 | BW32: 0 | BX32: 0 | BY32: 0 | BZ32: 0 | CA32: 0 | CB32: 0 | CC32: 0 | CD32: 0 | CE32: 0 | CF32: 0 | CG32: 0 | CH32: =+SUBTOTAL(9,BV32:CG32) -> 0 | CJ32: 0 | CK32: 0 | CL32: 0 | CM32: 0 | CN32: 0 | CO32: 0 | CP32: 0 | CQ32: 0 | CR32: 0 | CS32: 0 | CT32: 0 | CU32: 0 | CV32: =+SUBTOTAL(9,CJ32:CU32) -> 0 | CX32: 0 | CY32: 0 | CZ32: 0 | DA32: 0 | DB32: 0 | DC32: 0 | DD32: 0 | DE32: 0 | DF32: 0 | DG32: 0 | DH32: 0 | DI32: 0 | DJ32: =+SUBTOTAL(9,CX32:DI32) -> 0 | DL32: 0 | DM32: 0 | DN32: 0 | DO32: 0 | DP32: 0 | DQ32: 0 | DR32: 0 | DS32: 0 | DT32: 0 | DU32: 0 | DV32: 0 | DW32: 0 | DX32: =+SUBTOTAL(9,DL32:DW32) -> 0 | DZ32: 0 | EA32: 0 | EB32: 0 | EC32: 0 | ED32: 0 | EE32: 0 | EF32: 0 | EG32: 0 | EH32: 0 | EI32: 0 | EJ32: 0 | EK32: 0 | EL32: =+SUBTOTAL(9,DZ32:EK32) -> 0 | EN32: 0 | EO32: 0 | EP32: 0 | EQ32: 0 | ER32: 0 | ES32: 0 | ET32: 0 | EU32: 0 | EV32: 0 | EW32: 0 | EX32: 0 | EY32: 0 | EZ32: =+SUBTOTAL(9,EN32:EY32) -> 0 | FB32: 0 | FC32: 0 | FD32: 0 | FE32: 0 | FF32: 0 | FG32: 0 | FH32: 0 | FI32: 0 | FJ32: 0 | FK32: 0 | FL32: 0 | FM32: 0 | FN32: =+SUBTOTAL(9,FB32:FM32) -> 0 | FP32: 0 | FQ32: 0 | FR32: 0 | FS32: 0 | FT32: 0 | FU32: 0 | FV32: 0 | FW32: 0 | FX32: 0 | FY32: 0 | FZ32: 0 | GA32: 0 | GB32: =+SUBTOTAL(9,FP32:GA32) -> 0 | GD32: 0 | GE32: 0 | GF32: 0 | GG32: 0 | GH32: 0 | GI32: 0 | GJ32: 0 | GK32: 0 | GL32: 0 | GM32: 0 | GN32: 0 | GO32: 0 | GP32: =+SUBTOTAL(9,GD32:GO32) -> 0 | GR32: 0 | GS32: 0 | GT32: 0 | GU32: 0 | GV32: 0 | GW32: 0 | GX32: 0 | GY32: 0 | GZ32: 0 | HA32: 0 | HB32: 0 | HC32: 0 | HD32: =+SUBTOTAL(9,GR32:HC32) -> 0 | HF32: 0 | HG32: 0 | HH32: 0 | HI32: 0 | HJ32: 0 | HK32: 0 | HL32: 0 | HM32: 0 | HN32: 0 | HO32: 0 | HP32: 0 | HQ32: 0 | HR32: =+SUBTOTAL(9,HF32:HQ32) -> 0 | HT32: 0 | HU32: 0 | HV32: 0 | HW32: 0 | HX32: 0 | HY32: 0 | HZ32: 0 | IA32: 0 | IB32: 0 | IC32: 0 | ID32: 0 | IE32: 0 | IF32: =+SUBTOTAL(9,HT32:IE32) -> 0 | IH32: 0 | II32: 0 | IJ32: 0 | IK32: 0 | IL32: 0 | IM32: 0 | IN32: 0 | IO32: 0 | IP32: 0 | IQ32: 0 | IR32: 0 | IS32: 0 | IT32: =+SUBTOTAL(9,IH32:IS32) -> 0 | IV32: 0 | IW32: 0 | IX32: 0 | IY32: 0 | IZ32: 0 | JA32: 0 | JB32: 0 | JC32: 0 | JD32: 0 | JE32: 0 | JF32: 0 | JG32: 0 | JH32: =+SUBTOTAL(9,IV32:JG32) -> 0 | JJ32: 0 | JK32: 0 | JL32: 0 | JM32: 0 | JN32: 0 | JO32: 0 | JP32: 0 | JQ32: 0 | JR32: 0 | JS32: 0 | JT32: 0 | JU32: 0 | JV32: =+SUBTOTAL(9,JJ32:JU32) -> 0 | JX32: 0 | JY32: 0 | JZ32: 0 | KA32: 0 | KB32: 0 | KC32: 0 | KD32: 0 | KE32: 0 | KF32: 0 | KG32: 0 | KH32: 0 | KI32: 0 | KJ32: =+SUBTOTAL(9,JX32:KI32) -> 0 | KL32: 0 | KM32: 0 | KN32: 0 | KO32: 0 | KP32: 0 | KQ32: 0 | KR32: 0 | KS32: 0 | KT32: 0 | KU32: 0 | KV32: 0 | KW32: 0 | KX32: =+SUBTOTAL(9,KL32:KW32) -> 0 | KZ32: 0 | LA32: 0 | LB32: 0 | LC32: 0 | LD32: 0 | LE32: 0 | LF32: 0 | LG32: 0 | LH32: 0 | LI32: 0 | LJ32: 0 | LK32: 0 | LL32: =+SUBTOTAL(9,KZ32:LK32) -> 0 | LN32: 0 | LO32: 0 | LP32: 0 | LQ32: 0 | LR32: 0 | LS32: 0 | LT32: 0 | LU32: 0 | LV32: 0 | LW32: 0 | LX32: 0 | LY32: 0 | LZ32: =+SUBTOTAL(9,LN32:LY32) -> 0 | MB32: =SUMIF($D$11:$LY$11,MB$8,$D32:$LY32) -> 0 | MC32: =SUMIF($D$11:$LY$11,MC$8,$D32:$LY32) -> 0 | MD32: =SUMIF($D$11:$LY$11,MD$8,$D32:$LY32) -> 0 | ME32: =SUMIF($D$11:$LY$11,ME$8,$D32:$LY32) -> 0 | MF32: =SUMIF($D$11:$LY$11,MF$8,$D32:$LY32) -> 0 | MG32: =SUMIF($D$11:$LY$11,MG$8,$D32:$LY32) -> 0 | MH32: =SUMIF($D$11:$LY$11,MH$8,$D32:$LY32) -> 0 | MI32: =SUMIF($D$11:$LY$11,MI$8,$D32:$LY32) -> 0 | ... MM32: =SUMIF($D$11:$LY$11,MM$8,$D32:$LY32) -> 0 | MN32: =SUM(MB32:MM32) -> 0
B34: TOTAL OTHER INCOME | D34: =SUM(D31:D33) -> 0 | E34: =SUM(E31:E33) -> 0 | F34: =SUM(F31:F33) -> 0 | G34: =SUM(G31:G33) -> 0 | H34: =SUM(H31:H33) -> 0 | I34: =SUM(I31:I33) -> 0 | J34: =SUM(J31:J33) -> 0 | K34: =SUM(K31:K33) -> 0 | ... O34: =SUM(O31:O33) -> 0 | P34: =+SUBTOTAL(9,D34:O34) -> 0 | R34: =SUM(R31:R33) -> 0 | S34: =SUM(S31:S33) -> 0 | T34: =SUM(T31:T33) -> 0 | U34: =SUM(U31:U33) -> 0 | V34: =SUM(V31:V33) -> 0 | W34: =SUM(W31:W33) -> 0 | X34: =SUM(X31:X33) -> 0 | Y34: =SUM(Y31:Y33) -> 0 | ... AC34: =SUM(AC31:AC33) -> 0 | AD34: =+SUBTOTAL(9,R34:AC34) -> 0 | AF34: =SUM(AF31:AF33) -> 0 | AG34: =SUM(AG31:AG33) -> 0 | AH34: =SUM(AH31:AH33) -> 0 | AI34: =SUM(AI31:AI33) -> 0 | AJ34: =SUM(AJ31:AJ33) -> 0 | AK34: =SUM(AK31:AK33) -> 0 | AL34: =SUM(AL31:AL33) -> 0 | AM34: =SUM(AM31:AM33) -> 0 | ... AQ34: =SUM(AQ31:AQ33) -> 0 | AR34: =+SUBTOTAL(9,AF34:AQ34) -> 0 | AT34: =SUM(AT31:AT33) -> 0 | AU34: =SUM(AU31:AU33) -> 0 | AV34: =SUM(AV31:AV33) -> 0 | AW34: =SUM(AW31:AW33) -> 0 | AX34: =SUM(AX31:AX33) -> 0 | AY34: =SUM(AY31:AY33) -> 0 | AZ34: =SUM(AZ31:AZ33) -> 0 | BA34: =SUM(BA31:BA33) -> 0 | ... BE34: =SUM(BE31:BE33) -> 0 | BF34: =+SUBTOTAL(9,AT34:BE34) -> 0 | BH34: =SUM(BH31:BH33) -> 0 | BI34: =SUM(BI31:BI33) -> 0 | BJ34: =SUM(BJ31:BJ33) -> 0 | BK34: =SUM(BK31:BK33) -> 0 | BL34: =SUM(BL31:BL33) -> 0 | BM34: =SUM(BM31:BM33) -> 0 | BN34: =SUM(BN31:BN33) -> 0 | BO34: =SUM(BO31:BO33) -> 0 | ... BS34: =SUM(BS31:BS33) -> 0 | BT34: =+SUBTOTAL(9,BH34:BS34) -> 0 | BV34: =SUM(BV31:BV33) -> 0 | BW34: =SUM(BW31:BW33) -> 0 | BX34: =SUM(BX31:BX33) -> 0 | BY34: =SUM(BY31:BY33) -> 0 | BZ34: =SUM(BZ31:BZ33) -> 0 | CA34: =SUM(CA31:CA33) -> 0 | CB34: =SUM(CB31:CB33) -> 0 | CC34: =SUM(CC31:CC33) -> 0 | ... CG34: =SUM(CG31:CG33) -> 0 | CH34: =+SUBTOTAL(9,BV34:CG34) -> 0 | CJ34: =SUM(CJ31:CJ33) -> 0 | CK34: =SUM(CK31:CK33) -> 0 | CL34: =SUM(CL31:CL33) -> 0 | CM34: =SUM(CM31:CM33) -> 0 | CN34: =SUM(CN31:CN33) -> 0 | CO34: =SUM(CO31:CO33) -> 0 | CP34: =SUM(CP31:CP33) -> 0 | CQ34: =SUM(CQ31:CQ33) -> 0 | ... CU34: =SUM(CU31:CU33) -> 0 | CV34: =+SUBTOTAL(9,CJ34:CU34) -> 0 | CX34: =SUM(CX31:CX33) -> 0 | CY34: =SUM(CY31:CY33) -> 0 | CZ34: =SUM(CZ31:CZ33) -> 0 | DA34: =SUM(DA31:DA33) -> 0 | DB34: =SUM(DB31:DB33) -> 0 | DC34: =SUM(DC31:DC33) -> 0 | DD34: =SUM(DD31:DD33) -> 0 | DE34: =SUM(DE31:DE33) -> 0 | ... DI34: =SUM(DI31:DI33) -> 0 | DJ34: =+SUBTOTAL(9,CX34:DI34) -> 0 | DL34: =SUM(DL31:DL33) -> 0 | DM34: =SUM(DM31:DM33) -> 0 | DN34: =SUM(DN31:DN33) -> 0 | DO34: =SUM(DO31:DO33) -> 0 | DP34: =SUM(DP31:DP33) -> 0 | DQ34: =SUM(DQ31:DQ33) -> 0 | DR34: =SUM(DR31:DR33) -> 0 | DS34: =SUM(DS31:DS33) -> 0 | ... DW34: =SUM(DW31:DW33) -> 0 | DX34: =+SUBTOTAL(9,DL34:DW34) -> 0 | DZ34: =SUM(DZ31:DZ33) -> 0 | EA34: =SUM(EA31:EA33) -> 0 | EB34: =SUM(EB31:EB33) -> 0 | EC34: =SUM(EC31:EC33) -> 0 | ED34: =SUM(ED31:ED33) -> 0 | EE34: =SUM(EE31:EE33) -> 0 | EF34: =SUM(EF31:EF33) -> 0 | EG34: =SUM(EG31:EG33) -> 0 | ... EK34: =SUM(EK31:EK33) -> 0 | EL34: =+SUBTOTAL(9,DZ34:EK34) -> 0 | EN34: =SUM(EN31:EN33) -> 0 | EO34: =SUM(EO31:EO33) -> 0 | EP34: =SUM(EP31:EP33) -> 0 | EQ34: =SUM(EQ31:EQ33) -> 0 | ER34: =SUM(ER31:ER33) -> 0 | ES34: =SUM(ES31:ES33) -> 0 | ET34: =SUM(ET31:ET33) -> 0 | EU34: =SUM(EU31:EU33) -> 0 | ... EY34: =SUM(EY31:EY33) -> 0 | EZ34: =+SUBTOTAL(9,EN34:EY34) -> 0 | FB34: =SUM(FB31:FB33) -> 0 | FC34: =SUM(FC31:FC33) -> 0 | FD34: =SUM(FD31:FD33) -> 0 | FE34: =SUM(FE31:FE33) -> 0 | FF34: =SUM(FF31:FF33) -> 0 | FG34: =SUM(FG31:FG33) -> 0 | FH34: =SUM(FH31:FH33) -> 0 | FI34: =SUM(FI31:FI33) -> 0 | ... FM34: =SUM(FM31:FM33) -> 0 | FN34: =+SUBTOTAL(9,FB34:FM34) -> 0 | FP34: =SUM(FP31:FP33) -> 0 | FQ34: =SUM(FQ31:FQ33) -> 0 | FR34: =SUM(FR31:FR33) -> 0 | FS34: =SUM(FS31:FS33) -> 0 | FT34: =SUM(FT31:FT33) -> 0 | FU34: =SUM(FU31:FU33) -> 0 | FV34: =SUM(FV31:FV33) -> 0 | FW34: =SUM(FW31:FW33) -> 0 | ... GA34: =SUM(GA31:GA33) -> 0 | GB34: =+SUBTOTAL(9,FP34:GA34) -> 0 | GD34: =SUM(GD31:GD33) -> 0 | GE34: =SUM(GE31:GE33) -> 0 | GF34: =SUM(GF31:GF33) -> 0 | GG34: =SUM(GG31:GG33) -> 0 | GH34: =SUM(GH31:GH33) -> 0 | GI34: =SUM(GI31:GI33) -> 0 | GJ34: =SUM(GJ31:GJ33) -> 0 | GK34: =SUM(GK31:GK33) -> 0 | ... GO34: =SUM(GO31:GO33) -> 0 | GP34: =+SUBTOTAL(9,GD34:GO34) -> 0 | GR34: =SUM(GR31:GR33) -> 0 | GS34: =SUM(GS31:GS33) -> 0 | GT34: =SUM(GT31:GT33) -> 0 | GU34: =SUM(GU31:GU33) -> 0 | GV34: =SUM(GV31:GV33) -> 0 | GW34: =SUM(GW31:GW33) -> 0 | GX34: =SUM(GX31:GX33) -> 0 | GY34: =SUM(GY31:GY33) -> 0 | ... HC34: =SUM(HC31:HC33) -> 0 | HD34: =+SUBTOTAL(9,GR34:HC34) -> 0 | HF34: =SUM(HF31:HF33) -> 0 | HG34: =SUM(HG31:HG33) -> 0 | HH34: =SUM(HH31:HH33) -> 0 | HI34: =SUM(HI31:HI33) -> 0 | HJ34: =SUM(HJ31:HJ33) -> 0 | HK34: =SUM(HK31:HK33) -> 0 | HL34: =SUM(HL31:HL33) -> 0 | HM34: =SUM(HM31:HM33) -> 0 | ... HQ34: =SUM(HQ31:HQ33) -> 0 | HR34: =+SUBTOTAL(9,HF34:HQ34) -> 0 | HT34: =SUM(HT31:HT33) -> 0 | HU34: =SUM(HU31:HU33) -> 0 | HV34: =SUM(HV31:HV33) -> 0 | HW34: =SUM(HW31:HW33) -> 0 | HX34: =SUM(HX31:HX33) -> 0 | HY34: =SUM(HY31:HY33) -> 0 | HZ34: =SUM(HZ31:HZ33) -> 0 | IA34: =SUM(IA31:IA33) -> 0 | ... IE34: =SUM(IE31:IE33) -> 0 | IF34: =+SUBTOTAL(9,HT34:IE34) -> 0 | IH34: =SUM(IH31:IH33) -> 0 | II34: =SUM(II31:II33) -> 0 | IJ34: =SUM(IJ31:IJ33) -> 0 | IK34: =SUM(IK31:IK33) -> 0 | IL34: =SUM(IL31:IL33) -> 0 | IM34: =SUM(IM31:IM33) -> 0 | IN34: =SUM(IN31:IN33) -> 0 | IO34: =SUM(IO31:IO33) -> 0 | ... IS34: =SUM(IS31:IS33) -> 0 | IT34: =+SUBTOTAL(9,IH34:IS34) -> 0 | IV34: =SUM(IV31:IV33) -> 0 | IW34: =SUM(IW31:IW33) -> 0 | IX34: =SUM(IX31:IX33) -> 0 | IY34: =SUM(IY31:IY33) -> 0 | IZ34: =SUM(IZ31:IZ33) -> 0 | JA34: =SUM(JA31:JA33) -> 0 | JB34: =SUM(JB31:JB33) -> 0 | JC34: =SUM(JC31:JC33) -> 0 | ... JG34: =SUM(JG31:JG33) -> 0 | JH34: =+SUBTOTAL(9,IV34:JG34) -> 0 | JJ34: =SUM(JJ31:JJ33) -> 0 | JK34: =SUM(JK31:JK33) -> 0 | JL34: =SUM(JL31:JL33) -> 0 | JM34: =SUM(JM31:JM33) -> 0 | JN34: =SUM(JN31:JN33) -> 0 | JO34: =SUM(JO31:JO33) -> 0 | JP34: =SUM(JP31:JP33) -> 0 | JQ34: =SUM(JQ31:JQ33) -> 0 | ... JU34: =SUM(JU31:JU33) -> 0 | JV34: =+SUBTOTAL(9,JJ34:JU34) -> 0 | JX34: =SUM(JX31:JX33) -> 0 | JY34: =SUM(JY31:JY33) -> 0 | JZ34: =SUM(JZ31:JZ33) -> 0 | KA34: =SUM(KA31:KA33) -> 0 | KB34: =SUM(KB31:KB33) -> 0 | KC34: =SUM(KC31:KC33) -> 0 | KD34: =SUM(KD31:KD33) -> 0 | KE34: =SUM(KE31:KE33) -> 0 | ... KI34: =SUM(KI31:KI33) -> 0 | KJ34: =+SUBTOTAL(9,JX34:KI34) -> 0 | KL34: =SUM(KL31:KL33) -> 0 | KM34: =SUM(KM31:KM33) -> 0 | KN34: =SUM(KN31:KN33) -> 0 | KO34: =SUM(KO31:KO33) -> 0 | KP34: =SUM(KP31:KP33) -> 0 | KQ34: =SUM(KQ31:KQ33) -> 0 | KR34: =SUM(KR31:KR33) -> 0 | KS34: =SUM(KS31:KS33) -> 0 | ... KW34: =SUM(KW31:KW33) -> 0 | KX34: =+SUBTOTAL(9,KL34:KW34) -> 0 | KZ34: =SUM(KZ31:KZ33) -> 0 | LA34: =SUM(LA31:LA33) -> 0 | LB34: =SUM(LB31:LB33) -> 0 | LC34: =SUM(LC31:LC33) -> 0 | LD34: =SUM(LD31:LD33) -> 0 | LE34: =SUM(LE31:LE33) -> 0 | LF34: =SUM(LF31:LF33) -> 0 | LG34: =SUM(LG31:LG33) -> 0 | ... LK34: =SUM(LK31:LK33) -> 0 | LL34: =+SUBTOTAL(9,KZ34:LK34) -> 0 | LN34: =SUM(LN31:LN33) -> 0 | LO34: =SUM(LO31:LO33) -> 0 | LP34: =SUM(LP31:LP33) -> 0 | LQ34: =SUM(LQ31:LQ33) -> 0 | LR34: =SUM(LR31:LR33) -> 0 | LS34: =SUM(LS31:LS33) -> 0 | LT34: =SUM(LT31:LT33) -> 0 | LU34: =SUM(LU31:LU33) -> 0 | ... LY34: =SUM(LY31:LY33) -> 0 | LZ34: =+SUBTOTAL(9,LN34:LY34) -> 0 | MB34: =SUM(MB31:MB33) -> 0 | MC34: =SUM(MC31:MC33) -> 0 | MD34: =SUM(MD31:MD33) -> 0 | ME34: =SUM(ME31:ME33) -> 0 | MF34: =SUM(MF31:MF33) -> 0 | MG34: =SUM(MG31:MG33) -> 0 | MH34: =SUM(MH31:MH33) -> 0 | MI34: =SUM(MI31:MI33) -> 0 | ... MN34: =SUM(MN31:MN33) -> 0
B36: OPERATING EXPENSES
B37: PERSONNEL EXPENSES
B38: Salaries & Wages | D38: 2631519 | E38: 2631519 | F38: 2631519 | G38: 2631519 | H38: 2631519 | I38: 2631519 | J38: 2631519 | K38: 2631519 | L38: 2631519 | M38: 2631519 | N38: 2631519 | O38: 2631519 | P38: =+SUBTOTAL(9,D38:O38) -> 31578228 | R38: 212989 | S38: 212989 | T38: 212989 | U38: 212989 | V38: 212989 | W38: 212989 | X38: 212989 | Y38: 212989 | Z38: 212989 | AA38: 212989 | AB38: 212989 | AC38: 212989 | AD38: =+SUBTOTAL(9,R38:AC38) -> 2555868 | AF38: 214527 | AG38: 214527 | AH38: 214527 | AI38: 214527 | AJ38: 214527 | AK38: 214527 | AL38: 214527 | AM38: 214527 | AN38: 214527 | AO38: 214527 | AP38: 214527 | AQ38: 214527 | AR38: =+SUBTOTAL(9,AF38:AQ38) -> 2574324 | AT38: 670941 | AU38: 670941 | AV38: 670941 | AW38: 670941 | AX38: 670941 | AY38: 670941 | AZ38: 670941 | BA38: 670941 | BB38: 670941 | BC38: 670941 | BD38: 670941 | BE38: 670941 | BF38: =+SUBTOTAL(9,AT38:BE38) -> 8051292 | BH38: 3850090 | BI38: 3850090 | BJ38: 3850090 | BK38: 3850090 | BL38: 3850090 | BM38: 3850090 | BN38: 3850090 | BO38: 3850090 | BP38: 3850090 | BQ38: 3850090 | BR38: 3850090 | BS38: 3850090 | BT38: =+SUBTOTAL(9,BH38:BS38) -> 46201080 | BV38: 600345 | BW38: 600345 | BX38: 600345 | BY38: 600345 | BZ38: 600345 | CA38: 600345 | CB38: 600345 | CC38: 600345 | CD38: 600345 | CE38: 600345 | CF38: 600345 | CG38: 600345 | CH38: =+SUBTOTAL(9,BV38:CG38) -> 7204140 | CJ38: 1554444 | CK38: 1554444 | CL38: 1554444 | CM38: 1554444 | CN38: 1554444 | CO38: 1554444 | CP38: 1554444 | CQ38: 1554444 | CR38: 1554444 | CS38: 1554444 | CT38: 1554444 | CU38: 1554444 | CV38: =+SUBTOTAL(9,CJ38:CU38) -> 18653328 | CX38: 3445127 | CY38: 3445127 | CZ38: 3445127 | DA38: 3445127 | DB38: 3445127 | DC38: 3445127 | DD38: 3445127 | DE38: 3445127 | DF38: 3445127 | DG38: 3445127 | DH38: 3445127 | DI38: 3445127 | DJ38: =+SUBTOTAL(9,CX38:DI38) -> 41341524 | DL38: 2007756 | DM38: 2007756 | DN38: 2007756 | DO38: 2007756 | DP38: 2007756 | DQ38: 2007756 | DR38: 2007756 | DS38: 2007756 | DT38: 2007756 | DU38: 2007756 | DV38: 2007756 | DW38: 2007756 | DX38: =+SUBTOTAL(9,DL38:DW38) -> 24093072 | DZ38: 325406 | EA38: 325406 | EB38: 325406 | EC38: 325406 | ED38: 325406 | EE38: 325406 | EF38: 325406 | EG38: 325406 | EH38: 325406 | EI38: 325406 | EJ38: 325406 | EK38: 325406 | EL38: =+SUBTOTAL(9,DZ38:EK38) -> 3904872 | EN38: 462618 | EO38: 462618 | EP38: 462618 | EQ38: 462618 | ER38: 462618 | ES38: 462618 | ET38: 462618 | EU38: 462618 | EV38: 462618 | EW38: 462618 | EX38: 462618 | EY38: 462618 | EZ38: =+SUBTOTAL(9,EN38:EY38) -> 5551416 | FB38: 79363 | FC38: 79363 | FD38: 79363 | FE38: 79363 | FF38: 79363 | FG38: 79363 | FH38: 79363 | FI38: 79363 | FJ38: 79363 | FK38: 79363 | FL38: 79363 | FM38: 79363 | FN38: =+SUBTOTAL(9,FB38:FM38) -> 952356 | FP38: 1358053 | FQ38: 1358053 | FR38: 1358053 | FS38: 1358053 | FT38: 1358053 | FU38: 1358053 | FV38: 1358053 | FW38: 1358053 | FX38: 1358053 | FY38: 1358053 | FZ38: 1358053 | GA38: 1358053 | GB38: =+SUBTOTAL(9,FP38:GA38) -> 16296636 | GD38: 723125 | GE38: 723125 | GF38: 723125 | GG38: 723125 | GH38: 723125 | GI38: 723125 | GJ38: 723125 | GK38: 723125 | GL38: 723125 | GM38: 723125 | GN38: 723125 | GO38: 723125 | GP38: =+SUBTOTAL(9,GD38:GO38) -> 8677500 | GR38: -1096797.9 | GS38: -1096797.9 | GT38: -1096797.9 | GU38: -1096797.9 | GV38: -1096797.9 | GW38: -1096797.9 | GX38: -1096797.9 | GY38: -1096797.9 | GZ38: -1096797.9 | HA38: -1096797.9 | HB38: -1096797.9 | HC38: -1096797.9 | HD38: =+SUBTOTAL(9,GR38:HC38)*0 -> 0 | HF38: 592480 | HG38: 592480 | HH38: 592480 | HI38: 592480 | HJ38: 592480 | HK38: 592480 | HL38: 592480 | HM38: 592480 | HN38: 592480 | HO38: 592480 | HP38: 592480 | HQ38: 592480 | HR38: =+SUBTOTAL(9,HF38:HQ38) -> 7109760 | HT38: 154552 | HU38: 154552 | HV38: 154552 | HW38: 154552 | HX38: 154552 | HY38: 154552 | HZ38: 154552 | IA38: 154552 | IB38: 154552 | IC38: 154552 | ID38: 154552 | IE38: 154552 | IF38: =+SUBTOTAL(9,HT38:IE38) -> 1854624 | IH38: 517372 | II38: 517372 | IJ38: 517372 | IK38: 517372 | IL38: 517372 | IM38: 517372 | IN38: 517372 | IO38: 517372 | IP38: 517372 | IQ38: 517372 | IR38: 517372 | IS38: 517372 | IT38: =+SUBTOTAL(9,IH38:IS38) -> 6208464 | IV38: 1497536 | IW38: 1497536 | IX38: 1497536 | IY38: 1497536 | IZ38: 1497536 | JA38: 1497536 | JB38: 1497536 | JC38: 1497536 | JD38: 1497536 | JE38: 1497536 | JF38: 1497536 | JG38: 1497536 | JH38: =+SUBTOTAL(9,IV38:JG38) -> 17970432 | JJ38: 2021408 | JK38: 2021408 | JL38: 2021408 | JM38: 2021408 | JN38: 2021408 | JO38: 2021408 | JP38: 2021408 | JQ38: 2021408 | JR38: 2021408 | JS38: 2021408 | JT38: 2021408 | JU38: 2021408 | JV38: =+SUBTOTAL(9,JJ38:JU38) -> 24256896 | JX38: 1091919 | JY38: 1091919 | JZ38: 1091919 | KA38: 1091919 | KB38: 1091919 | KC38: 1091919 | KD38: 1091919 | KE38: 1091919 | KF38: 1091919 | KG38: 1091919 | KH38: 1091919 | KI38: 1091919 | KJ38: =+SUBTOTAL(9,JX38:KI38) -> 13103028 | KL38: 150250 | KM38: 150250 | KN38: 150250 | KO38: 150250 | KP38: 150250 | KQ38: 150250 | KR38: 150250 | KS38: 150250 | KT38: 150250 | KU38: 150250 | KV38: 150250 | KW38: 150250 | KX38: =+SUBTOTAL(9,KL38:KW38) -> 1803000 | KZ38: 156301 | LA38: 156301 | LB38: 156301 | LC38: 156301 | LD38: 156301 | LE38: 156301 | LF38: 156301 | LG38: 156301 | LH38: 156301 | LI38: 156301 | LJ38: 156301 | LK38: 156301 | LL38: =+SUBTOTAL(9,KZ38:LK38) -> 1875612 | LN38: 0 | LO38: 0 | LP38: 0 | LQ38: 0 | LR38: 0 | LS38: 0 | LT38: 0 | LU38: 0 | LV38: 0 | LW38: 0 | LX38: 0 | LY38: 0 | LZ38: =+SUBTOTAL(9,LN38:LY38) -> 0 | MB38: =SUMIF($D$11:$LY$11,MB$8,$D38:$LY38) -> 23221323 | MC38: =SUMIF($D$11:$LY$11,MC$8,$D38:$LY38) -> 23221323 | MD38: =SUMIF($D$11:$LY$11,MD$8,$D38:$LY38) -> 23221323 | ME38: =SUMIF($D$11:$LY$11,ME$8,$D38:$LY38) -> 23221323 | MF38: =SUMIF($D$11:$LY$11,MF$8,$D38:$LY38) -> 23221323 | MG38: =SUMIF($D$11:$LY$11,MG$8,$D38:$LY38) -> 23221323 | MH38: =SUMIF($D$11:$LY$11,MH$8,$D38:$LY38) -> 23221323 | MI38: =SUMIF($D$11:$LY$11,MI$8,$D38:$LY38) -> 23221323 | ... MM38: =SUMIF($D$11:$LY$11,MM$8,$D38:$LY38) -> 23221323 | MN38: =SUM(MB38:MM38) -> 2.7865588e+08
B39: Provision for Bonus, Leave & Other Employment Costs | D39: 199226 | E39: 199226 | F39: 199226 | G39: 199226 | H39: 199226 | I39: 199226 | J39: 199226 | K39: 199226 | L39: 199226 | M39: 199226 | N39: 199226 | O39: 199226 | P39: =+SUBTOTAL(9,D39:O39) -> 2390712 | R39: 16127 | S39: 16127 | T39: 16127 | U39: 16127 | V39: 16127 | W39: 16127 | X39: 16127 | Y39: 16127 | Z39: 16127 | AA39: 16127 | AB39: 16127 | AC39: 16127 | AD39: =+SUBTOTAL(9,R39:AC39) -> 193524 | AF39: 16242 | AG39: 16242 | AH39: 16242 | AI39: 16242 | AJ39: 16242 | AK39: 16242 | AL39: 16242 | AM39: 16242 | AN39: 16242 | AO39: 16242 | AP39: 16242 | AQ39: 16242 | AR39: =+SUBTOTAL(9,AF39:AQ39) -> 194904 | AT39: 50794 | AU39: 50794 | AV39: 50794 | AW39: 50794 | AX39: 50794 | AY39: 50794 | AZ39: 50794 | BA39: 50794 | BB39: 50794 | BC39: 50794 | BD39: 50794 | BE39: 50794 | BF39: =+SUBTOTAL(9,AT39:BE39) -> 609528 | BH39: 291480 | BI39: 291480 | BJ39: 291480 | BK39: 291480 | BL39: 291480 | BM39: 291480 | BN39: 291480 | BO39: 291480 | BP39: 291480 | BQ39: 291480 | BR39: 291480 | BS39: 291480 | BT39: =+SUBTOTAL(9,BH39:BS39) -> 3497760 | BV39: 45451 | BW39: 45451 | BX39: 45451 | BY39: 45451 | BZ39: 45451 | CA39: 45451 | CB39: 45451 | CC39: 45451 | CD39: 45451 | CE39: 45451 | CF39: 45451 | CG39: 45451 | CH39: =+SUBTOTAL(9,BV39:CG39) -> 545412 | CJ39: 117683 | CK39: 117683 | CL39: 117683 | CM39: 117683 | CN39: 117683 | CO39: 117683 | CP39: 117683 | CQ39: 117683 | CR39: 117683 | CS39: 117683 | CT39: 117683 | CU39: 117683 | CV39: =+SUBTOTAL(9,CJ39:CU39) -> 1412196 | CX39: 260820 | CY39: 260820 | CZ39: 260820 | DA39: 260820 | DB39: 260820 | DC39: 260820 | DD39: 260820 | DE39: 260820 | DF39: 260820 | DG39: 260820 | DH39: 260820 | DI39: 260820 | DJ39: =+SUBTOTAL(9,CX39:DI39) -> 3129840 | DL39: 152002 | DM39: 152002 | DN39: 152002 | DO39: 152002 | DP39: 152002 | DQ39: 152002 | DR39: 152002 | DS39: 152002 | DT39: 152002 | DU39: 152002 | DV39: 152002 | DW39: 152002 | DX39: =+SUBTOTAL(9,DL39:DW39) -> 1824024 | DZ39: 24637 | EA39: 24637 | EB39: 24637 | EC39: 24637 | ED39: 24637 | EE39: 24637 | EF39: 24637 | EG39: 24637 | EH39: 24637 | EI39: 24637 | EJ39: 24637 | EK39: 24637 | EL39: =+SUBTOTAL(9,DZ39:EK39) -> 295644 | EN39: 35023 | EO39: 35023 | EP39: 35023 | EQ39: 35023 | ER39: 35023 | ES39: 35023 | ET39: 35023 | EU39: 35023 | EV39: 35023 | EW39: 35023 | EX39: 35023 | EY39: 35023 | EZ39: =+SUBTOTAL(9,EN39:EY39) -> 420276 | FB39: 6007 | FC39: 6007 | FD39: 6007 | FE39: 6007 | FF39: 6007 | FG39: 6007 | FH39: 6007 | FI39: 6007 | FJ39: 6007 | FK39: 6007 | FL39: 6007 | FM39: 6007 | FN39: =+SUBTOTAL(9,FB39:FM39) -> 72084 | FP39: 102815 | FQ39: 102815 | FR39: 102815 | FS39: 102815 | FT39: 102815 | FU39: 102815 | FV39: 102815 | FW39: 102815 | FX39: 102815 | FY39: 102815 | FZ39: 102815 | GA39: 102815 | GB39: =+SUBTOTAL(9,FP39:GA39) -> 1233780 | GD39: 54746 | GE39: 54746 | GF39: 54746 | GG39: 54746 | GH39: 54746 | GI39: 54746 | GJ39: 54746 | GK39: 54746 | GL39: 54746 | GM39: 54746 | GN39: 54746 | GO39: 54746 | GP39: =+SUBTOTAL(9,GD39:GO39) -> 656952 | GR39: -54020.753 | GS39: -54020.753 | GT39: -54020.753 | GU39: -54020.753 | GV39: -54020.753 | GW39: -54020.753 | GX39: -54020.753 | GY39: -54020.753 | GZ39: -54020.753 | HA39: -54020.753 | HB39: -54020.753 | HC39: -54020.753 | HD39: =+SUBTOTAL(9,GR39:HC39)*0 -> 0 | HF39: 44857 | HG39: 44857 | HH39: 44857 | HI39: 44857 | HJ39: 44857 | HK39: 44857 | HL39: 44857 | HM39: 44857 | HN39: 44857 | HO39: 44857 | HP39: 44857 | HQ39: 44857 | HR39: =+SUBTOTAL(9,HF39:HQ39) -> 538284 | HT39: 11700 | HU39: 11700 | HV39: 11700 | HW39: 11700 | HX39: 11700 | HY39: 11700 | HZ39: 11700 | IA39: 11700 | IB39: 11700 | IC39: 11700 | ID39: 11700 | IE39: 11700 | IF39: =+SUBTOTAL(9,HT39:IE39) -> 140400 | IH39: 39168 | II39: 39168 | IJ39: 39168 | IK39: 39168 | IL39: 39168 | IM39: 39168 | IN39: 39168 | IO39: 39168 | IP39: 39168 | IQ39: 39168 | IR39: 39168 | IS39: 39168 | IT39: =+SUBTOTAL(9,IH39:IS39) -> 470016 | IV39: 113373 | IW39: 113373 | IX39: 113373 | IY39: 113373 | IZ39: 113373 | JA39: 113373 | JB39: 113373 | JC39: 113373 | JD39: 113373 | JE39: 113373 | JF39: 113373 | JG39: 113373 | JH39: =+SUBTOTAL(9,IV39:JG39) -> 1360476 | JJ39: 153035 | JK39: 153035 | JL39: 153035 | JM39: 153035 | JN39: 153035 | JO39: 153035 | JP39: 153035 | JQ39: 153035 | JR39: 153035 | JS39: 153035 | JT39: 153035 | JU39: 153035 | JV39: =+SUBTOTAL(9,JJ39:JU39) -> 1836420 | JX39: 82667 | JY39: 82667 | JZ39: 82667 | KA39: 82667 | KB39: 82667 | KC39: 82667 | KD39: 82667 | KE39: 82667 | KF39: 82667 | KG39: 82667 | KH39: 82667 | KI39: 82667 | KJ39: =+SUBTOTAL(9,JX39:KI39) -> 992004 | KL39: 11375 | KM39: 11375 | KN39: 11375 | KO39: 11375 | KP39: 11375 | KQ39: 11375 | KR39: 11375 | KS39: 11375 | KT39: 11375 | KU39: 11375 | KV39: 11375 | KW39: 11375 | KX39: =+SUBTOTAL(9,KL39:KW39) -> 136500 | KZ39: 11833 | LA39: 11833 | LB39: 11833 | LC39: 11833 | LD39: 11833 | LE39: 11833 | LF39: 11833 | LG39: 11833 | LH39: 11833 | LI39: 11833 | LJ39: 11833 | LK39: 11833 | LL39: =+SUBTOTAL(9,KZ39:LK39) -> 141996 | LN39: 0 | LO39: 0 | LP39: 0 | LQ39: 0 | LR39: 0 | LS39: 0 | LT39: 0 | LU39: 0 | LV39: 0 | LW39: 0 | LX39: 0 | LY39: 0 | LZ39: =+SUBTOTAL(9,LN39:LY39) -> 0 | MB39: =SUMIF($D$11:$LY$11,MB$8,$D39:$LY39) -> 1787040.2 | MC39: =SUMIF($D$11:$LY$11,MC$8,$D39:$LY39) -> 1787040.2 | MD39: =SUMIF($D$11:$LY$11,MD$8,$D39:$LY39) -> 1787040.2 | ME39: =SUMIF($D$11:$LY$11,ME$8,$D39:$LY39) -> 1787040.2 | MF39: =SUMIF($D$11:$LY$11,MF$8,$D39:$LY39) -> 1787040.2 | MG39: =SUMIF($D$11:$LY$11,MG$8,$D39:$LY39) -> 1787040.2 | MH39: =SUMIF($D$11:$LY$11,MH$8,$D39:$LY39) -> 1787040.2 | MI39: =SUMIF($D$11:$LY$11,MI$8,$D39:$LY39) -> 1787040.2 | ... MM39: =SUMIF($D$11:$LY$11,MM$8,$D39:$LY39) -> 1787040.2 | MN39: =SUM(MB39:MM39) -> 21444483
B40: Consultants & Contractors | D40: 0 | E40: 0 | F40: 0 | G40: 0 | H40: 0 | I40: 0 | J40: 0 | K40: 0 | L40: 0 | M40: 0 | N40: 0 | O40: 0 | P40: =+SUBTOTAL(9,D40:O40) -> 0 | R40: 0 | S40: 0 | T40: 0 | U40: 0 | V40: 0 | W40: 0 | X40: 0 | Y40: 0 | Z40: 0 | AA40: 0 | AB40: 0 | AC40: 0 | AD40: =+SUBTOTAL(9,R40:AC40) -> 0 | AF40: 0 | AG40: 0 | AH40: 0 | AI40: 0 | AJ40: 0 | AK40: 0 | AL40: 0 | AM40: 0 | AN40: 0 | AO40: 0 | AP40: 0 | AQ40: 0 | AR40: =+SUBTOTAL(9,AF40:AQ40) -> 0 | AT40: 0 | AU40: 0 | AV40: 0 | AW40: 0 | AX40: 0 | AY40: 0 | AZ40: 0 | BA40: 0 | BB40: 0 | BC40: 0 | BD40: 0 | BE40: 0 | BF40: =+SUBTOTAL(9,AT40:BE40) -> 0 | BH40: 0 | BI40: 0 | BJ40: 0 | BK40: 0 | BL40: 0 | BM40: 0 | BN40: 0 | BO40: 0 | BP40: 0 | BQ40: 0 | BR40: 0 | BS40: 0 | BT40: =+SUBTOTAL(9,BH40:BS40) -> 0 | BV40: 0 | BW40: 0 | BX40: 0 | BY40: 0 | BZ40: 0 | CA40: 0 | CB40: 0 | CC40: 0 | CD40: 0 | CE40: 0 | CF40: 0 | CG40: 0 | CH40: =+SUBTOTAL(9,BV40:CG40) -> 0 | CJ40: 0 | CK40: 0 | CL40: 0 | CM40: 0 | CN40: 0 | CO40: 0 | CP40: 0 | CQ40: 0 | CR40: 0 | CS40: 0 | CT40: 0 | CU40: 0 | CV40: =+SUBTOTAL(9,CJ40:CU40) -> 0 | CX40: 190000 | CY40: 190000 | CZ40: 190000 | DA40: 190000 | DB40: 190000 | DC40: 190000 | DD40: 190000 | DE40: 190000 | DF40: 190000 | DG40: 190000 | DH40: 190000 | DI40: 190000 | DJ40: =+SUBTOTAL(9,CX40:DI40) -> 2280000 | DL40: 0 | DM40: 0 | DN40: 0 | DO40: 0 | DP40: 0 | DQ40: 0 | DR40: 0 | DS40: 0 | DT40: 0 | DU40: 0 | DV40: 0 | DW40: 0 | DX40: =+SUBTOTAL(9,DL40:DW40) -> 0 | DZ40: 0 | EA40: 0 | EB40: 0 | EC40: 0 | ED40: 0 | EE40: 0 | EF40: 0 | EG40: 0 | EH40: 0 | EI40: 0 | EJ40: 0 | EK40: 0 | EL40: =+SUBTOTAL(9,DZ40:EK40) -> 0 | EN40: 0 | EO40: 0 | EP40: 0 | EQ40: 0 | ER40: 0 | ES40: 0 | ET40: 0 | EU40: 0 | EV40: 0 | EW40: 0 | EX40: 0 | EY40: 0 | EZ40: =+SUBTOTAL(9,EN40:EY40) -> 0 | FB40: 0 | FC40: 0 | FD40: 0 | FE40: 0 | FF40: 0 | FG40: 0 | FH40: 0 | FI40: 0 | FJ40: 0 | FK40: 0 | FL40: 0 | FM40: 0 | FN40: =+SUBTOTAL(9,FB40:FM40) -> 0 | FP40: 0 | FQ40: 0 | FR40: 0 | FS40: 0 | FT40: 0 | FU40: 0 | FV40: 0 | FW40: 0 | FX40: 0 | FY40: 0 | FZ40: 0 | GA40: 0 | GB40: =+SUBTOTAL(9,FP40:GA40) -> 0 | GD40: 0 | GE40: 0 | GF40: 0 | GG40: 0 | GH40: 0 | GI40: 0 | GJ40: 0 | GK40: 0 | GL40: 0 | GM40: 0 | GN40: 0 | GO40: 0 | GP40: =+SUBTOTAL(9,GD40:GO40) -> 0 | GR40: 0 | GS40: 0 | GT40: 0 | GU40: 0 | GV40: 0 | GW40: 0 | GX40: 0 | GY40: 0 | GZ40: 0 | HA40: 0 | HB40: 0 | HC40: 0 | HD40: =+SUBTOTAL(9,GR40:HC40)*0 -> 0 | HF40: 0 | HG40: 0 | HH40: 0 | HI40: 0 | HJ40: 0 | HK40: 0 | HL40: 0 | HM40: 0 | HN40: 0 | HO40: 0 | HP40: 0 | HQ40: 0 | HR40: =+SUBTOTAL(9,HF40:HQ40) -> 0 | HT40: 0 | HU40: 0 | HV40: 0 | HW40: 0 | HX40: 0 | HY40: 0 | HZ40: 0 | IA40: 0 | IB40: 0 | IC40: 0 | ID40: 0 | IE40: 0 | IF40: =+SUBTOTAL(9,HT40:IE40) -> 0 | IH40: 0 | II40: 0 | IJ40: 0 | IK40: 0 | IL40: 0 | IM40: 0 | IN40: 0 | IO40: 0 | IP40: 0 | IQ40: 0 | IR40: 0 | IS40: 0 | IT40: =+SUBTOTAL(9,IH40:IS40) -> 0 | IV40: 0 | IW40: 0 | IX40: 0 | IY40: 0 | IZ40: 0 | JA40: 0 | JB40: 0 | JC40: 0 | JD40: 0 | JE40: 0 | JF40: 0 | JG40: 0 | JH40: =+SUBTOTAL(9,IV40:JG40) -> 0 | JJ40: 0 | JK40: 0 | JL40: 0 | JM40: 0 | JN40: 0 | JO40: 0 | JP40: 0 | JQ40: 0 | JR40: 0 | JS40: 0 | JT40: 0 | JU40: 0 | JV40: =+SUBTOTAL(9,JJ40:JU40) -> 0 | JX40: 0 | JY40: 0 | JZ40: 0 | KA40: 0 | KB40: 0 | KC40: 0 | KD40: 0 | KE40: 0 | KF40: 0 | KG40: 0 | KH40: 0 | KI40: 0 | KJ40: =+SUBTOTAL(9,JX40:KI40) -> 0 | KL40: 0 | KM40: 0 | KN40: 0 | KO40: 0 | KP40: 0 | KQ40: 0 | KR40: 0 | KS40: 0 | KT40: 0 | KU40: 0 | KV40: 0 | KW40: 0 | KX40: =+SUBTOTAL(9,KL40:KW40) -> 0 | KZ40: 0 | LA40: 0 | LB40: 0 | LC40: 0 | LD40: 0 | LE40: 0 | LF40: 0 | LG40: 0 | LH40: 0 | LI40: 0 | LJ40: 0 | LK40: 0 | LL40: =+SUBTOTAL(9,KZ40:LK40) -> 0 | LN40: 0 | LO40: 0 | LP40: 0 | LQ40: 0 | LR40: 0 | LS40: 0 | LT40: 0 | LU40: 0 | LV40: 0 | LW40: 0 | LX40: 0 | LY40: 0 | LZ40: =+SUBTOTAL(9,LN40:LY40) -> 0 | MB40: =SUMIF($D$11:$LY$11,MB$8,$D40:$LY40) -> 190000 | MC40: =SUMIF($D$11:$LY$11,MC$8,$D40:$LY40) -> 190000 | MD40: =SUMIF($D$11:$LY$11,MD$8,$D40:$LY40) -> 190000 | ME40: =SUMIF($D$11:$LY$11,ME$8,$D40:$LY40) -> 190000 | MF40: =SUMIF($D$11:$LY$11,MF$8,$D40:$LY40) -> 190000 | MG40: =SUMIF($D$11:$LY$11,MG$8,$D40:$LY40) -> 190000 | MH40: =SUMIF($D$11:$LY$11,MH$8,$D40:$LY40) -> 190000 | MI40: =SUMIF($D$11:$LY$11,MI$8,$D40:$LY40) -> 190000 | ... MM40: =SUMIF($D$11:$LY$11,MM$8,$D40:$LY40) -> 190000 | MN40: =SUM(MB40:MM40) -> 2280000
B41: Pension Fund & Social Securities | D41: 197364 | E41: 197364 | F41: 197364 | G41: 197364 | H41: 197364 | I41: 197364 | J41: 197364 | K41: 197364 | L41: 197364 | M41: 197364 | N41: 197364 | O41: 197364 | P41: =+SUBTOTAL(9,D41:O41) -> 2368368 | R41: 15974 | S41: 15974 | T41: 15974 | U41: 15974 | V41: 15974 | W41: 15974 | X41: 15974 | Y41: 15974 | Z41: 15974 | AA41: 15974 | AB41: 15974 | AC41: 15974 | AD41: =+SUBTOTAL(9,R41:AC41) -> 191688 | AF41: 16090 | AG41: 16090 | AH41: 16090 | AI41: 16090 | AJ41: 16090 | AK41: 16090 | AL41: 16090 | AM41: 16090 | AN41: 16090 | AO41: 16090 | AP41: 16090 | AQ41: 16090 | AR41: =+SUBTOTAL(9,AF41:AQ41) -> 193080 | AT41: 50321 | AU41: 50321 | AV41: 50321 | AW41: 50321 | AX41: 50321 | AY41: 50321 | AZ41: 50321 | BA41: 50321 | BB41: 50321 | BC41: 50321 | BD41: 50321 | BE41: 50321 | BF41: =+SUBTOTAL(9,AT41:BE41) -> 603852 | BH41: 288757 | BI41: 288757 | BJ41: 288757 | BK41: 288757 | BL41: 288757 | BM41: 288757 | BN41: 288757 | BO41: 288757 | BP41: 288757 | BQ41: 288757 | BR41: 288757 | BS41: 288757 | BT41: =+SUBTOTAL(9,BH41:BS41) -> 3465084 | BV41: 45026 | BW41: 45026 | BX41: 45026 | BY41: 45026 | BZ41: 45026 | CA41: 45026 | CB41: 45026 | CC41: 45026 | CD41: 45026 | CE41: 45026 | CF41: 45026 | CG41: 45026 | CH41: =+SUBTOTAL(9,BV41:CG41) -> 540312 | CJ41: 116583 | CK41: 116583 | CL41: 116583 | CM41: 116583 | CN41: 116583 | CO41: 116583 | CP41: 116583 | CQ41: 116583 | CR41: 116583 | CS41: 116583 | CT41: 116583 | CU41: 116583 | CV41: =+SUBTOTAL(9,CJ41:CU41) -> 1398996 | CX41: 258385 | CY41: 258385 | CZ41: 258385 | DA41: 258385 | DB41: 258385 | DC41: 258385 | DD41: 258385 | DE41: 258385 | DF41: 258385 | DG41: 258385 | DH41: 258385 | DI41: 258385 | DJ41: =+SUBTOTAL(9,CX41:DI41) -> 3100620 | DL41: 150581 | DM41: 150581 | DN41: 150581 | DO41: 150581 | DP41: 150581 | DQ41: 150581 | DR41: 150581 | DS41: 150581 | DT41: 150581 | DU41: 150581 | DV41: 150581 | DW41: 150581 | DX41: =+SUBTOTAL(9,DL41:DW41) -> 1806972 | DZ41: 24405 | EA41: 24405 | EB41: 24405 | EC41: 24405 | ED41: 24405 | EE41: 24405 | EF41: 24405 | EG41: 24405 | EH41: 24405 | EI41: 24405 | EJ41: 24405 | EK41: 24405 | EL41: =+SUBTOTAL(9,DZ41:EK41) -> 292860 | EN41: 34696 | EO41: 34696 | EP41: 34696 | EQ41: 34696 | ER41: 34696 | ES41: 34696 | ET41: 34696 | EU41: 34696 | EV41: 34696 | EW41: 34696 | EX41: 34696 | EY41: 34696 | EZ41: =+SUBTOTAL(9,EN41:EY41) -> 416352 | FB41: 5952 | FC41: 5952 | FD41: 5952 | FE41: 5952 | FF41: 5952 | FG41: 5952 | FH41: 5952 | FI41: 5952 | FJ41: 5952 | FK41: 5952 | FL41: 5952 | FM41: 5952 | FN41: =+SUBTOTAL(9,FB41:FM41) -> 71424 | FP41: 101854 | FQ41: 101854 | FR41: 101854 | FS41: 101854 | FT41: 101854 | FU41: 101854 | FV41: 101854 | FW41: 101854 | FX41: 101854 | FY41: 101854 | FZ41: 101854 | GA41: 101854 | GB41: =+SUBTOTAL(9,FP41:GA41) -> 1222248 | GD41: 54234 | GE41: 54234 | GF41: 54234 | GG41: 54234 | GH41: 54234 | GI41: 54234 | GJ41: 54234 | GK41: 54234 | GL41: 54234 | GM41: 54234 | GN41: 54234 | GO41: 54234 | GP41: =+SUBTOTAL(9,GD41:GO41) -> 650808 | GR41: -303422.54 | GS41: -303422.54 | GT41: -303422.54 | GU41: -303422.54 | GV41: -303422.54 | GW41: -303422.54 | GX41: -303422.54 | GY41: -303422.54 | GZ41: -303422.54 | HA41: -303422.54 | HB41: -303422.54 | HC41: -303422.54 | HD41: =+SUBTOTAL(9,GR41:HC41)*0 -> 0 | HF41: 44436 | HG41: 44436 | HH41: 44436 | HI41: 44436 | HJ41: 44436 | HK41: 44436 | HL41: 44436 | HM41: 44436 | HN41: 44436 | HO41: 44436 | HP41: 44436 | HQ41: 44436 | HR41: =+SUBTOTAL(9,HF41:HQ41) -> 533232 | HT41: 11591 | HU41: 11591 | HV41: 11591 | HW41: 11591 | HX41: 11591 | HY41: 11591 | HZ41: 11591 | IA41: 11591 | IB41: 11591 | IC41: 11591 | ID41: 11591 | IE41: 11591 | IF41: =+SUBTOTAL(9,HT41:IE41) -> 139092 | IH41: 38803 | II41: 38803 | IJ41: 38803 | IK41: 38803 | IL41: 38803 | IM41: 38803 | IN41: 38803 | IO41: 38803 | IP41: 38803 | IQ41: 38803 | IR41: 38803 | IS41: 38803 | IT41: =+SUBTOTAL(9,IH41:IS41) -> 465636 | IV41: 112315 | IW41: 112315 | IX41: 112315 | IY41: 112315 | IZ41: 112315 | JA41: 112315 | JB41: 112315 | JC41: 112315 | JD41: 112315 | JE41: 112315 | JF41: 112315 | JG41: 112315 | JH41: =+SUBTOTAL(9,IV41:JG41) -> 1347780 | JJ41: 151605 | JK41: 151605 | JL41: 151605 | JM41: 151605 | JN41: 151605 | JO41: 151605 | JP41: 151605 | JQ41: 151605 | JR41: 151605 | JS41: 151605 | JT41: 151605 | JU41: 151605 | JV41: =+SUBTOTAL(9,JJ41:JU41) -> 1819260 | JX41: 81894 | JY41: 81894 | JZ41: 81894 | KA41: 81894 | KB41: 81894 | KC41: 81894 | KD41: 81894 | KE41: 81894 | KF41: 81894 | KG41: 81894 | KH41: 81894 | KI41: 81894 | KJ41: =+SUBTOTAL(9,JX41:KI41) -> 982728 | KL41: 11268 | KM41: 11268 | KN41: 11268 | KO41: 11268 | KP41: 11268 | KQ41: 11268 | KR41: 11268 | KS41: 11268 | KT41: 11268 | KU41: 11268 | KV41: 11268 | KW41: 11268 | KX41: =+SUBTOTAL(9,KL41:KW41) -> 135216 | KZ41: 11723 | LA41: 11723 | LB41: 11723 | LC41: 11723 | LD41: 11723 | LE41: 11723 | LF41: 11723 | LG41: 11723 | LH41: 11723 | LI41: 11723 | LJ41: 11723 | LK41: 11723 | LL41: =+SUBTOTAL(9,KZ41:LK41) -> 140676 | LN41: 0 | LO41: 0 | LP41: 0 | LQ41: 0 | LR41: 0 | LS41: 0 | LT41: 0 | LU41: 0 | LV41: 0 | LW41: 0 | LX41: 0 | LY41: 0 | LZ41: =+SUBTOTAL(9,LN41:LY41) -> 0 | MB41: =SUMIF($D$11:$LY$11,MB$8,$D41:$LY41) -> 1520434.5 | MC41: =SUMIF($D$11:$LY$11,MC$8,$D41:$LY41) -> 1520434.5 | MD41: =SUMIF($D$11:$LY$11,MD$8,$D41:$LY41) -> 1520434.5 | ME41: =SUMIF($D$11:$LY$11,ME$8,$D41:$LY41) -> 1520434.5 | MF41: =SUMIF($D$11:$LY$11,MF$8,$D41:$LY41) -> 1520434.5 | MG41: =SUMIF($D$11:$LY$11,MG$8,$D41:$LY41) -> 1520434.5 | MH41: =SUMIF($D$11:$LY$11,MH$8,$D41:$LY41) -> 1520434.5 | MI41: =SUMIF($D$11:$LY$11,MI$8,$D41:$LY41) -> 1520434.5 | ... MM41: =SUMIF($D$11:$LY$11,MM$8,$D41:$LY41) -> 1520434.5 | MN41: =SUM(MB41:MM41) -> 18245213
B42: Staff Allowances & Benefits | D42: 90040.802 | E42: 94825.802 | F42: 94825.802 | G42: 94825.802 | H42: 94825.802 | I42: 94825.802 | J42: 104950.8 | K42: 104950.8 | L42: 104950.8 | M42: 194950.8 | N42: 104950.8 | O42: 103915.09 | P42: =+SUBTOTAL(9,D42:O42) -> 1282838.9 | R42: 8203.7381 | S42: 8698.7381 | T42: 8698.7381 | U42: 8698.7381 | V42: 8698.7381 | W42: 8698.7381 | X42: 9549.7381 | Y42: 9549.7381 | Z42: 9549.7381 | AA42: 18549.738 | AB42: 9549.7381 | AC42: 9442.5952 | AD42: =+SUBTOTAL(9,R42:AC42) -> 117888.71 | AF42: 8203.7381 | AG42: 8698.7381 | AH42: 8698.7381 | AI42: 8698.7381 | AJ42: 8698.7381 | AK42: 8698.7381 | AL42: 9549.7381 | AM42: 9549.7381 | AN42: 9549.7381 | AO42: 18549.738 | AP42: 9549.7381 | AQ42: 9442.5952 | AR42: =+SUBTOTAL(9,AF42:AQ42) -> 117888.71 | AT42: 8791.1587 | AU42: 9121.1587 | AV42: 9121.1587 | AW42: 9121.1587 | AX42: 9121.1587 | AY42: 9121.1587 | AZ42: 10354.159 | BA42: 10354.159 | BB42: 10354.159 | BC42: 16354.159 | BD42: 10354.159 | BE42: 10282.73 | BF42: =+SUBTOTAL(9,AT42:BE42) -> 122450.48 | BH42: 48117.69 | BI42: 50262.69 | BJ42: 50262.69 | BK42: 50262.69 | BL42: 50262.69 | BM42: 50262.69 | BN42: 56108.69 | BO42: 56108.69 | BP42: 56108.69 | BQ42: 101108.69 | BR42: 56108.69 | BS42: 55572.976 | BT42: =+SUBTOTAL(9,BH42:BS42) -> 680547.57 | BV42: 5873.5794 | BW42: 6038.5794 | BX42: 6038.5794 | BY42: 6038.5794 | BZ42: 6038.5794 | CA42: 6038.5794 | CB42: 6951.5794 | CC42: 6951.5794 | CD42: 6951.5794 | CE42: 9951.5794 | CF42: 6951.5794 | CG42: 6915.8651 | CH42: =+SUBTOTAL(9,BV42:CG42) -> 80740.238 | CJ42: 133771.37 | CK42: 135586.37 | CL42: 135586.37 | CM42: 135586.37 | CN42: 135586.37 | CO42: 135586.37 | CP42: 139442.37 | CQ42: 139442.37 | CR42: 139442.37 | CS42: 172442.37 | CT42: 139442.37 | CU42: 139049.52 | CV42: =+SUBTOTAL(9,CJ42:CU42) -> 1680964.6 | CX42: 92413.222 | CY42: 97033.222 | CZ42: 97033.222 | DA42: 97033.222 | DB42: 97033.222 | DC42: 97033.222 | DD42: 108034.22 | DE42: 108034.22 | DF42: 108034.22 | DG42: 195034.22 | DH42: 108034.22 | DI42: 107034.22 | DJ42: =+SUBTOTAL(9,CX42:DI42) -> 1311784.7 | DL42: 73141.222 | DM42: 77431.222 | DN42: 77431.222 | DO42: 77431.222 | DP42: 77431.222 | DQ42: 77431.222 | DR42: 84930.222 | DS42: 84930.222 | DT42: 84930.222 | DU42: 168930.22 | DV42: 84930.222 | DW42: 83930.222 | DX42: =+SUBTOTAL(9,DL42:DW42) -> 1052878.7 | DZ42: 6167.5794 | EA42: 6332.5794 | EB42: 6332.5794 | EC42: 6332.5794 | ED42: 6332.5794 | EE42: 6332.5794 | EF42: 6951.5794 | EG42: 6951.5794 | EH42: 6951.5794 | EI42: 9951.5794 | EJ42: 6951.5794 | EK42: 6915.8651 | EL42: =+SUBTOTAL(9,DZ42:EK42) -> 82504.238 | EN42: 8791.1587 | EO42: 9121.1587 | EP42: 9121.1587 | EQ42: 9121.1587 | ER42: 9121.1587 | ES42: 9121.1587 | ET42: 10354.159 | EU42: 10354.159 | EV42: 10354.159 | EW42: 16354.159 | EX42: 10354.159 | EY42: 10282.73 | EZ42: =+SUBTOTAL(9,EN42:EY42) -> 122450.48 | FB42: 2917.5794 | FC42: 3082.5794 | FD42: 3082.5794 | FE42: 3082.5794 | FF42: 3082.5794 | FG42: 3082.5794 | FH42: 3402.5794 | FI42: 3402.5794 | FJ42: 3402.5794 | FK42: 6402.5794 | FL42: 3402.5794 | FM42: 3366.8651 | FN42: =+SUBTOTAL(9,FB42:FM42) -> 41710.238 | FP42: 30255.056 | FQ42: 31575.056 | FR42: 31575.056 | FS42: 31575.056 | FT42: 31575.056 | FU42: 31575.056 | FV42: 35521.056 | FW42: 35521.056 | FX42: 35521.056 | FY42: 59521.056 | FZ42: 35521.056 | GA42: 35271.056 | GB42: =+SUBTOTAL(9,FP42:GA42) -> 425006.67 | GD42: 402.57937 | GE42: 402.57937 | GF42: 402.57937 | GG42: 402.57937 | GH42: 402.57937 | GI42: 402.57937 | GJ42: 402.57937 | GK42: 402.57937 | GL42: 402.57937 | GM42: 402.57937 | GN42: 402.57937 | GO42: 366.86508 | GP42: =+SUBTOTAL(9,GD42:GO42) -> 4795.2381 | GR42: 0 | GS42: 0 | GT42: 50225 | GU42: 50225 | GV42: 50225 | GW42: 50225 | GX42: 50225 | GY42: 50225 | GZ42: 50225 | HA42: 50225 | HB42: 50225 | HC42: 50225 | HD42: =+SUBTOTAL(9,GR42:HC42)*0 -> 0 | HF42: 14076.317 | HG42: 14736.317 | HH42: 14736.317 | HI42: 14736.317 | HJ42: 14736.317 | HK42: 14736.317 | HL42: 16500.317 | HM42: 16500.317 | HN42: 16500.317 | HO42: 28500.317 | HP42: 16500.317 | HQ42: 16357.46 | HR42: =+SUBTOTAL(9,HF42:HQ42) -> 198616.95 | HT42: 3086.5794 | HU42: 3251.5794 | HV42: 3251.5794 | HW42: 3251.5794 | HX42: 3251.5794 | HY42: 3251.5794 | HZ42: 3605.5794 | IA42: 3605.5794 | IB42: 3605.5794 | IC42: 6605.5794 | ID42: 3605.5794 | IE42: 3569.8651 | IF42: =+SUBTOTAL(9,HT42:IE42) -> 43942.238 | IH42: 5873.5794 | II42: 6038.5794 | IJ42: 6038.5794 | IK42: 6038.5794 | IL42: 6038.5794 | IM42: 6038.5794 | IN42: 6951.5794 | IO42: 6951.5794 | IP42: 6951.5794 | IQ42: 9951.5794 | IR42: 6951.5794 | IS42: 6915.8651 | IT42: =+SUBTOTAL(9,IH42:IS42) -> 80740.238 | IV42: 26506.056 | IW42: 27661.056 | IX42: 27661.056 | IY42: 27661.056 | IZ42: 27661.056 | JA42: 27661.056 | JB42: 31121.056 | JC42: 31121.056 | JD42: 31121.056 | JE42: 52121.056 | JF42: 31121.056 | JG42: 30871.056 | JH42: =+SUBTOTAL(9,IV42:JG42) -> 372287.67 | JJ42: 33480.373 | JK42: 34965.373 | JL42: 34965.373 | JM42: 34965.373 | JN42: 34965.373 | JO42: 34965.373 | JP42: 39065.373 | JQ42: 39065.373 | JR42: 39065.373 | JS42: 78065.373 | JT42: 39065.373 | JU42: 38672.516 | JV42: =+SUBTOTAL(9,JJ42:JU42) -> 481306.62 | JX42: 16291.897 | JY42: 16951.897 | JZ42: 16951.897 | KA42: 16951.897 | KB42: 16951.897 | KC42: 16951.897 | KD42: 19059.897 | KE42: 19059.897 | KF42: 19059.897 | KG42: 34059.897 | KH42: 19059.897 | KI42: 18881.325 | KJ42: =+SUBTOTAL(9,JX42:KI42) -> 230232.19 | KL42: 27718.159 | KM42: 28213.159 | KN42: 28213.159 | KO42: 28213.159 | KP42: 28213.159 | KQ42: 28213.159 | KR42: 29064.159 | KS42: 29064.159 | KT42: 29064.159 | KU42: 35060.159 | KV42: 29064.159 | KW42: 28992.73 | KX42: =+SUBTOTAL(9,KL42:KW42) -> 349093.48 | KZ42: 10485.579 | LA42: 10485.579 | LB42: 10485.579 | LC42: 10485.579 | LD42: 10485.579 | LE42: 10485.579 | LF42: 10485.579 | LG42: 10485.579 | LH42: 10485.579 | LI42: 13489.579 | LJ42: 10485.579 | LK42: 10449.865 | LL42: =+SUBTOTAL(9,KZ42:LK42) -> 128795.24 | LN42: 0 | LO42: 0 | LP42: 0 | LQ42: 0 | LR42: 0 | LS42: 0 | LT42: 0 | LU42: 0 | LV42: 0 | LW42: 0 | LX42: 0 | LY42: 0 | LZ42: =+SUBTOTAL(9,LN42:LY42) -> 0 | MB42: =SUMIF($D$11:$LY$11,MB$8,$D42:$LY42) -> 654609.02 | MC42: =SUMIF($D$11:$LY$11,MC$8,$D42:$LY42) -> 680514.02 | MD42: =SUMIF($D$11:$LY$11,MD$8,$D42:$LY42) -> 730739.02 | ME42: =SUMIF($D$11:$LY$11,ME$8,$D42:$LY42) -> 730739.02 | MF42: =SUMIF($D$11:$LY$11,MF$8,$D42:$LY42) -> 730739.02 | MG42: =SUMIF($D$11:$LY$11,MG$8,$D42:$LY42) -> 730739.02 | MH42: =SUMIF($D$11:$LY$11,MH$8,$D42:$LY42) -> 792582.02 | MI42: =SUMIF($D$11:$LY$11,MI$8,$D42:$LY42) -> 792582.02 | ... MM42: =SUMIF($D$11:$LY$11,MM$8,$D42:$LY42) -> 786724.87 | MN42: =SUM(MB42:MM42) -> 9511714
B43: Medical Expenses | D43: 0 | E43: 0 | F43: 0 | G43: 0 | H43: 0 | I43: 0 | J43: 0 | K43: 0 | L43: 0 | M43: 0 | N43: 0 | O43: 0 | P43: =+SUBTOTAL(9,D43:O43) -> 0 | R43: 0 | S43: 0 | T43: 0 | U43: 0 | V43: 0 | W43: 0 | X43: 0 | Y43: 0 | Z43: 0 | AA43: 0 | AB43: 0 | AC43: 0 | AD43: =+SUBTOTAL(9,R43:AC43) -> 0 | AF43: 0 | AG43: 0 | AH43: 0 | AI43: 0 | AJ43: 0 | AK43: 0 | AL43: 0 | AM43: 0 | AN43: 0 | AO43: 0 | AP43: 0 | AQ43: 0 | AR43: =+SUBTOTAL(9,AF43:AQ43) -> 0 | AT43: 0 | AU43: 0 | AV43: 0 | AW43: 0 | AX43: 0 | AY43: 0 | AZ43: 0 | BA43: 0 | BB43: 0 | BC43: 0 | BD43: 0 | BE43: 0 | BF43: =+SUBTOTAL(9,AT43:BE43) -> 0 | BH43: 0 | BI43: 0 | BJ43: 0 | BK43: 0 | BL43: 0 | BM43: 0 | BN43: 0 | BO43: 0 | BP43: 0 | BQ43: 0 | BR43: 0 | BS43: 0 | BT43: =+SUBTOTAL(9,BH43:BS43) -> 0 | BV43: 0 | BW43: 0 | BX43: 0 | BY43: 0 | BZ43: 0 | CA43: 0 | CB43: 0 | CC43: 0 | CD43: 0 | CE43: 0 | CF43: 0 | CG43: 0 | CH43: =+SUBTOTAL(9,BV43:CG43) -> 0 | CJ43: 0 | CK43: 0 | CL43: 0 | CM43: 0 | CN43: 0 | CO43: 0 | CP43: 0 | CQ43: 0 | CR43: 0 | CS43: 0 | CT43: 0 | CU43: 0 | CV43: =+SUBTOTAL(9,CJ43:CU43) -> 0 | CX43: 0 | CY43: 0 | CZ43: 0 | DA43: 0 | DB43: 0 | DC43: 0 | DD43: 0 | DE43: 0 | DF43: 0 | DG43: 0 | DH43: 0 | DI43: 0 | DJ43: =+SUBTOTAL(9,CX43:DI43) -> 0 | DL43: 0 | DM43: 0 | DN43: 0 | DO43: 0 | DP43: 0 | DQ43: 0 | DR43: 0 | DS43: 0 | DT43: 0 | DU43: 0 | DV43: 0 | DW43: 0 | DX43: =+SUBTOTAL(9,DL43:DW43) -> 0 | DZ43: 0 | EA43: 0 | EB43: 0 | EC43: 0 | ED43: 0 | EE43: 0 | EF43: 0 | EG43: 0 | EH43: 0 | EI43: 0 | EJ43: 0 | EK43: 0 | EL43: =+SUBTOTAL(9,DZ43:EK43) -> 0 | EN43: 0 | EO43: 0 | EP43: 0 | EQ43: 0 | ER43: 0 | ES43: 0 | ET43: 0 | EU43: 0 | EV43: 0 | EW43: 0 | EX43: 0 | EY43: 0 | EZ43: =+SUBTOTAL(9,EN43:EY43) -> 0 | FB43: 0 | FC43: 0 | FD43: 0 | FE43: 0 | FF43: 0 | FG43: 0 | FH43: 0 | FI43: 0 | FJ43: 0 | FK43: 0 | FL43: 0 | FM43: 0 | FN43: =+SUBTOTAL(9,FB43:FM43) -> 0 | FP43: 0 | FQ43: 0 | FR43: 0 | FS43: 0 | FT43: 0 | FU43: 0 | FV43: 0 | FW43: 0 | FX43: 0 | FY43: 0 | FZ43: 0 | GA43: 0 | GB43: =+SUBTOTAL(9,FP43:GA43) -> 0 | GD43: 0 | GE43: 0 | GF43: 0 | GG43: 0 | GH43: 0 | GI43: 0 | GJ43: 0 | GK43: 0 | GL43: 0 | GM43: 0 | GN43: 0 | GO43: 0 | GP43: =+SUBTOTAL(9,GD43:GO43) -> 0 | GR43: 0 | GS43: 0 | GT43: 0 | GU43: 0 | GV43: 0 | GW43: 0 | GX43: 0 | GY43: 0 | GZ43: 0 | HA43: 0 | HB43: 0 | HC43: 0 | HD43: =+SUBTOTAL(9,GR43:HC43)*0 -> 0 | HF43: 0 | HG43: 0 | HH43: 0 | HI43: 0 | HJ43: 0 | HK43: 0 | HL43: 0 | HM43: 0 | HN43: 0 | HO43: 0 | HP43: 0 | HQ43: 0 | HR43: =+SUBTOTAL(9,HF43:HQ43) -> 0 | HT43: 0 | HU43: 0 | HV43: 0 | HW43: 0 | HX43: 0 | HY43: 0 | HZ43: 0 | IA43: 0 | IB43: 0 | IC43: 0 | ID43: 0 | IE43: 0 | IF43: =+SUBTOTAL(9,HT43:IE43) -> 0 | IH43: 0 | II43: 0 | IJ43: 0 | IK43: 0 | IL43: 0 | IM43: 0 | IN43: 0 | IO43: 0 | IP43: 0 | IQ43: 0 | IR43: 0 | IS43: 0 | IT43: =+SUBTOTAL(9,IH43:IS43) -> 0 | IV43: 0 | IW43: 0 | IX43: 0 | IY43: 0 | IZ43: 0 | JA43: 0 | JB43: 0 | JC43: 0 | JD43: 0 | JE43: 0 | JF43: 0 | JG43: 0 | JH43: =+SUBTOTAL(9,IV43:JG43) -> 0 | JJ43: 0 | JK43: 0 | JL43: 0 | JM43: 0 | JN43: 0 | JO43: 0 | JP43: 0 | JQ43: 0 | JR43: 0 | JS43: 0 | JT43: 0 | JU43: 0 | JV43: =+SUBTOTAL(9,JJ43:JU43) -> 0 | JX43: 0 | JY43: 0 | JZ43: 0 | KA43: 0 | KB43: 0 | KC43: 0 | KD43: 0 | KE43: 0 | KF43: 0 | KG43: 0 | KH43: 0 | KI43: 0 | KJ43: =+SUBTOTAL(9,JX43:KI43) -> 0 | KL43: 0 | KM43: 0 | KN43: 0 | KO43: 0 | KP43: 0 | KQ43: 0 | KR43: 0 | KS43: 0 | KT43: 0 | KU43: 0 | KV43: 0 | KW43: 0 | KX43: =+SUBTOTAL(9,KL43:KW43) -> 0 | KZ43: 0 | LA43: 0 | LB43: 0 | LC43: 0 | LD43: 0 | LE43: 0 | LF43: 0 | LG43: 0 | LH43: 0 | LI43: 0 | LJ43: 0 | LK43: 0 | LL43: =+SUBTOTAL(9,KZ43:LK43) -> 0 | LN43: 0 | LO43: 0 | LP43: 0 | LQ43: 0 | LR43: 0 | LS43: 0 | LT43: 0 | LU43: 0 | LV43: 0 | LW43: 0 | LX43: 0 | LY43: 0 | LZ43: =+SUBTOTAL(9,LN43:LY43) -> 0 | MB43: =SUMIF($D$11:$LY$11,MB$8,$D43:$LY43) -> 0 | MC43: =SUMIF($D$11:$LY$11,MC$8,$D43:$LY43) -> 0 | MD43: =SUMIF($D$11:$LY$11,MD$8,$D43:$LY43) -> 0 | ME43: =SUMIF($D$11:$LY$11,ME$8,$D43:$LY43) -> 0 | MF43: =SUMIF($D$11:$LY$11,MF$8,$D43:$LY43) -> 0 | MG43: =SUMIF($D$11:$LY$11,MG$8,$D43:$LY43) -> 0 | MH43: =SUMIF($D$11:$LY$11,MH$8,$D43:$LY43) -> 0 | MI43: =SUMIF($D$11:$LY$11,MI$8,$D43:$LY43) -> 0 | ... MM43: =SUMIF($D$11:$LY$11,MM$8,$D43:$LY43) -> 0 | MN43: =SUM(MB43:MM43) -> 0
B44: Staff Recruitment / Relocation | D44: 84364.274 | E44: 84364.274 | F44: 84364.274 | G44: 84364.274 | H44: 84364.274 | I44: 84364.274 | J44: 84364.274 | K44: 84364.274 | L44: 84364.274 | M44: 84364.274 | N44: 84364.274 | O44: 84364.274 | P44: =+SUBTOTAL(9,D44:O44) -> 1012371.3 | R44: 8727.3387 | S44: 8727.3387 | T44: 8727.3387 | U44: 8727.3387 | V44: 8727.3387 | W44: 8727.3387 | X44: 8727.3387 | Y44: 8727.3387 | Z44: 8727.3387 | AA44: 8727.3387 | AB44: 8727.3387 | AC44: 8727.3387 | AD44: =+SUBTOTAL(9,R44:AC44) -> 104728.06 | AF44: 8727.3387 | AG44: 8727.3387 | AH44: 8727.3387 | AI44: 8727.3387 | AJ44: 8727.3387 | AK44: 8727.3387 | AL44: 8727.3387 | AM44: 8727.3387 | AN44: 8727.3387 | AO44: 8727.3387 | AP44: 8727.3387 | AQ44: 8727.3387 | AR44: =+SUBTOTAL(9,AF44:AQ44) -> 104728.06 | AT44: 5818.2258 | AU44: 5818.2258 | AV44: 5818.2258 | AW44: 5818.2258 | AX44: 5818.2258 | AY44: 5818.2258 | AZ44: 5818.2258 | BA44: 5818.2258 | BB44: 5818.2258 | BC44: 5818.2258 | BD44: 5818.2258 | BE44: 5818.2258 | BF44: =+SUBTOTAL(9,AT44:BE44) -> 69818.709 | BH44: 43636.693 | BI44: 43636.693 | BJ44: 43636.693 | BK44: 43636.693 | BL44: 43636.693 | BM44: 43636.693 | BN44: 43636.693 | BO44: 43636.693 | BP44: 43636.693 | BQ44: 43636.693 | BR44: 43636.693 | BS44: 43636.693 | BT44: =+SUBTOTAL(9,BH44:BS44) -> 523640.32 | BV44: 2909.1129 | BW44: 2909.1129 | BX44: 2909.1129 | BY44: 2909.1129 | BZ44: 2909.1129 | CA44: 2909.1129 | CB44: 2909.1129 | CC44: 2909.1129 | CD44: 2909.1129 | CE44: 2909.1129 | CF44: 2909.1129 | CG44: 2909.1129 | CH44: =+SUBTOTAL(9,BV44:CG44) -> 34909.355 | CJ44: 32000.242 | CK44: 32000.242 | CL44: 32000.242 | CM44: 32000.242 | CN44: 32000.242 | CO44: 32000.242 | CP44: 32000.242 | CQ44: 32000.242 | CR44: 32000.242 | CS44: 32000.242 | CT44: 32000.242 | CU44: 32000.242 | CV44: =+SUBTOTAL(9,CJ44:CU44) -> 384002.9 | CX44: 81455.161 | CY44: 81455.161 | CZ44: 81455.161 | DA44: 81455.161 | DB44: 81455.161 | DC44: 81455.161 | DD44: 81455.161 | DE44: 81455.161 | DF44: 81455.161 | DG44: 81455.161 | DH44: 81455.161 | DI44: 81455.161 | DJ44: =+SUBTOTAL(9,CX44:DI44) -> 977461.93 | DL44: 81455.161 | DM44: 81455.161 | DN44: 81455.161 | DO44: 81455.161 | DP44: 81455.161 | DQ44: 81455.161 | DR44: 81455.161 | DS44: 81455.161 | DT44: 81455.161 | DU44: 81455.161 | DV44: 81455.161 | DW44: 81455.161 | DX44: =+SUBTOTAL(9,DL44:DW44) -> 977461.93 | DZ44: 2909.1129 | EA44: 2909.1129 | EB44: 2909.1129 | EC44: 2909.1129 | ED44: 2909.1129 | EE44: 2909.1129 | EF44: 2909.1129 | EG44: 2909.1129 | EH44: 2909.1129 | EI44: 2909.1129 | EJ44: 2909.1129 | EK44: 2909.1129 | EL44: =+SUBTOTAL(9,DZ44:EK44) -> 34909.355 | EN44: 5818.2258 | EO44: 5818.2258 | EP44: 5818.2258 | EQ44: 5818.2258 | ER44: 5818.2258 | ES44: 5818.2258 | ET44: 5818.2258 | EU44: 5818.2258 | EV44: 5818.2258 | EW44: 5818.2258 | EX44: 5818.2258 | EY44: 5818.2258 | EZ44: =+SUBTOTAL(9,EN44:EY44) -> 69818.709 | FB44: 2909.1129 | FC44: 2909.1129 | FD44: 2909.1129 | FE44: 2909.1129 | FF44: 2909.1129 | FG44: 2909.1129 | FH44: 2909.1129 | FI44: 2909.1129 | FJ44: 2909.1129 | FK44: 2909.1129 | FL44: 2909.1129 | FM44: 2909.1129 | FN44: =+SUBTOTAL(9,FB44:FM44) -> 34909.355 | FP44: 20363.79 | FQ44: 20363.79 | FR44: 20363.79 | FS44: 20363.79 | FT44: 20363.79 | FU44: 20363.79 | FV44: 20363.79 | FW44: 20363.79 | FX44: 20363.79 | FY44: 20363.79 | FZ44: 20363.79 | GA44: 20363.79 | GB44: =+SUBTOTAL(9,FP44:GA44) -> 244365.48 | GD44: 2909.1129 | GE44: 2909.1129 | GF44: 2909.1129 | GG44: 2909.1129 | GH44: 2909.1129 | GI44: 2909.1129 | GJ44: 2909.1129 | GK44: 2909.1129 | GL44: 2909.1129 | GM44: 2909.1129 | GN44: 2909.1129 | GO44: 2909.1129 | GP44: =+SUBTOTAL(9,GD44:GO44) -> 34909.355 | GR44: -159349.35 | GS44: -159349.35 | GT44: -159349.35 | GU44: -159349.35 | GV44: -159349.35 | GW44: -159349.35 | GX44: -159349.35 | GY44: -159349.35 | GZ44: -159349.35 | HA44: -159349.35 | HB44: -159349.35 | HC44: -159349.35 | HD44: =+SUBTOTAL(9,GR44:HC44)*0 -> 0 | HF44: 11636.452 | HG44: 11636.452 | HH44: 11636.452 | HI44: 11636.452 | HJ44: 11636.452 | HK44: 11636.452 | HL44: 11636.452 | HM44: 11636.452 | HN44: 11636.452 | HO44: 11636.452 | HP44: 11636.452 | HQ44: 11636.452 | HR44: =+SUBTOTAL(9,HF44:HQ44) -> 139637.42 | HT44: 2909.1129 | HU44: 2909.1129 | HV44: 2909.1129 | HW44: 2909.1129 | HX44: 2909.1129 | HY44: 2909.1129 | HZ44: 2909.1129 | IA44: 2909.1129 | IB44: 2909.1129 | IC44: 2909.1129 | ID44: 2909.1129 | IE44: 2909.1129 | IF44: =+SUBTOTAL(9,HT44:IE44) -> 34909.355 | IH44: 2909.1129 | II44: 2909.1129 | IJ44: 2909.1129 | IK44: 2909.1129 | IL44: 2909.1129 | IM44: 2909.1129 | IN44: 2909.1129 | IO44: 2909.1129 | IP44: 2909.1129 | IQ44: 2909.1129 | IR44: 2909.1129 | IS44: 2909.1129 | IT44: =+SUBTOTAL(9,IH44:IS44) -> 34909.355 | IV44: 20363.79 | IW44: 20363.79 | IX44: 20363.79 | IY44: 20363.79 | IZ44: 20363.79 | JA44: 20363.79 | JB44: 20363.79 | JC44: 20363.79 | JD44: 20363.79 | JE44: 20363.79 | JF44: 20363.79 | JG44: 20363.79 | JH44: =+SUBTOTAL(9,IV44:JG44) -> 244365.48 | JJ44: 32000.242 | JK44: 32000.242 | JL44: 32000.242 | JM44: 32000.242 | JN44: 32000.242 | JO44: 32000.242 | JP44: 32000.242 | JQ44: 32000.242 | JR44: 32000.242 | JS44: 32000.242 | JT44: 32000.242 | JU44: 32000.242 | JV44: =+SUBTOTAL(9,JJ44:JU44) -> 384002.9 | JX44: 14545.564 | JY44: 14545.564 | JZ44: 14545.564 | KA44: 14545.564 | KB44: 14545.564 | KC44: 14545.564 | KD44: 14545.564 | KE44: 14545.564 | KF44: 14545.564 | KG44: 14545.564 | KH44: 14545.564 | KI44: 14545.564 | KJ44: =+SUBTOTAL(9,JX44:KI44) -> 174546.77 | KL44: 5818.2258 | KM44: 5818.2258 | KN44: 5818.2258 | KO44: 5818.2258 | KP44: 5818.2258 | KQ44: 5818.2258 | KR44: 5818.2258 | KS44: 5818.2258 | KT44: 5818.2258 | KU44: 5818.2258 | KV44: 5818.2258 | KW44: 5818.2258 | KX44: =+SUBTOTAL(9,KL44:KW44) -> 69818.709 | KZ44: 2909.1129 | LA44: 2909.1129 | LB44: 2909.1129 | LC44: 2909.1129 | LD44: 2909.1129 | LE44: 2909.1129 | LF44: 2909.1129 | LG44: 2909.1129 | LH44: 2909.1129 | LI44: 2909.1129 | LJ44: 2909.1129 | LK44: 2909.1129 | LL44: =+SUBTOTAL(9,KZ44:LK44) -> 34909.355 | LN44: 0 | LO44: 0 | LP44: 0 | LQ44: 0 | LR44: 0 | LS44: 0 | LT44: 0 | LU44: 0 | LV44: 0 | LW44: 0 | LX44: 0 | LY44: 0 | LZ44: =+SUBTOTAL(9,LN44:LY44) -> 0 | MB44: =SUMIF($D$11:$LY$11,MB$8,$D44:$LY44) -> 317745.16 | MC44: =SUMIF($D$11:$LY$11,MC$8,$D44:$LY44) -> 317745.16 | MD44: =SUMIF($D$11:$LY$11,MD$8,$D44:$LY44) -> 317745.16 | ME44: =SUMIF($D$11:$LY$11,ME$8,$D44:$LY44) -> 317745.16 | MF44: =SUMIF($D$11:$LY$11,MF$8,$D44:$LY44) -> 317745.16 | MG44: =SUMIF($D$11:$LY$11,MG$8,$D44:$LY44) -> 317745.16 | MH44: =SUMIF($D$11:$LY$11,MH$8,$D44:$LY44) -> 317745.16 | MI44: =SUMIF($D$11:$LY$11,MI$8,$D44:$LY44) -> 317745.16 | ... MM44: =SUMIF($D$11:$LY$11,MM$8,$D44:$LY44) -> 317745.16 | MN44: =SUM(MB44:MM44) -> 3812942
B45: Staff Functions | D45: 174750 | E45: 12750 | F45: 38250 | G45: 12750 | H45: 12750 | I45: 12750 | J45: 12750 | K45: 117750 | L45: 102750 | M45: 33050 | N45: 38250 | O45: 39750 | P45: =+SUBTOTAL(9,D45:O45) -> 608300 | R45: 17476 | S45: 1276 | T45: 3826 | U45: 1276 | V45: 1276 | W45: 1276 | X45: 1276 | Y45: 11776 | Z45: 10276 | AA45: 3376 | AB45: 3826 | AC45: 3976 | AD45: =+SUBTOTAL(9,R45:AC45) -> 60912 | AF45: 17476 | AG45: 1276 | AH45: 3826 | AI45: 1276 | AJ45: 1276 | AK45: 1276 | AL45: 1276 | AM45: 11776 | AN45: 10276 | AO45: 3376 | AP45: 3826 | AQ45: 3976 | AR45: =+SUBTOTAL(9,AF45:AQ45) -> 60912 | AT45: 11652 | AU45: 852 | AV45: 2552 | AW45: 852 | AX45: 852 | AY45: 852 | AZ45: 852 | BA45: 7852 | BB45: 6852 | BC45: 2252 | BD45: 2552 | BE45: 2652 | BF45: =+SUBTOTAL(9,AT45:BE45) -> 40624 | BH45: 87376 | BI45: 6376 | BJ45: 19126 | BK45: 6376 | BL45: 6376 | BM45: 6376 | BN45: 6376 | BO45: 58876 | BP45: 51376 | BQ45: 15476 | BR45: 19126 | BS45: 19876 | BT45: =+SUBTOTAL(9,BH45:BS45) -> 303112 | BV45: 7326 | BW45: 426 | BX45: 1276 | BY45: 426 | BZ45: 426 | CA45: 426 | CB45: 426 | CC45: 5426 | CD45: 3426 | CE45: 1126 | CF45: 1276 | CG45: 1326 | CH45: =+SUBTOTAL(9,BV45:CG45) -> 23312 | CJ45: 64078 | CK45: 4678 | CL45: 14028 | CM45: 4678 | CN45: 4678 | CO45: 4678 | CP45: 4678 | CQ45: 43178 | CR45: 37678 | CS45: 12378 | CT45: 14028 | CU45: 14578 | CV45: =+SUBTOTAL(9,CJ45:CU45) -> 223336 | CX45: 171178 | CY45: 12328 | CZ45: 36978 | DA45: 12328 | DB45: 12328 | DC45: 12328 | DD45: 12328 | DE45: 116078 | DF45: 99328 | DG45: 32628 | DH45: 36978 | DI45: 38428 | DJ45: =+SUBTOTAL(9,CX45:DI45) -> 593236 | DL45: 163852 | DM45: 11902 | DN45: 35702 | DO45: 11902 | DP45: 11902 | DQ45: 11902 | DR45: 11902 | DS45: 110652 | DT45: 95902 | DU45: 30102 | DV45: 35702 | DW45: 37102 | DX45: =+SUBTOTAL(9,DL45:DW45) -> 568524 | DZ45: 5826 | EA45: 426 | EB45: 1276 | EC45: 426 | ED45: 426 | EE45: 426 | EF45: 426 | EG45: 3926 | EH45: 3426 | EI45: 1126 | EJ45: 1276 | EK45: 1326 | EL45: =+SUBTOTAL(9,DZ45:EK45) -> 20312 | EN45: 11652 | EO45: 852 | EP45: 2552 | EQ45: 852 | ER45: 852 | ES45: 852 | ET45: 852 | EU45: 7852 | EV45: 6852 | EW45: 2252 | EX45: 2552 | EY45: 2652 | EZ45: =+SUBTOTAL(9,EN45:EY45) -> 40624 | FB45: 5826 | FC45: 426 | FD45: 1276 | FE45: 426 | FF45: 426 | FG45: 426 | FH45: 426 | FI45: 3926 | FJ45: 3426 | FK45: 1126 | FL45: 1276 | FM45: 1326 | FN45: =+SUBTOTAL(9,FB45:FM45) -> 20312 | FP45: 46604 | FQ45: 3404 | FR45: 10204 | FS45: 3404 | FT45: 3404 | FU45: 3404 | FV45: 3404 | FW45: 31404 | FX45: 27404 | FY45: 9004 | FZ45: 10204 | GA45: 10604 | GB45: =+SUBTOTAL(9,FP45:GA45) -> 162448 | GD45: 0 | GE45: 0 | GF45: 0 | GG45: 0 | GH45: 0 | GI45: 0 | GJ45: 0 | GK45: 0 | GL45: 0 | GM45: 0 | GN45: 0 | GO45: 0 | GP45: =+SUBTOTAL(9,GD45:GO45) -> 0 | GR45: -120881.11 | GS45: -120881.11 | GT45: -120881.11 | GU45: -120881.11 | GV45: -120881.11 | GW45: -120881.11 | GX45: -120881.11 | GY45: -120881.11 | GZ45: -120881.11 | HA45: -120881.11 | HB45: -120881.11 | HC45: -120881.11 | HD45: =+SUBTOTAL(9,GR45:HC45)*0 -> 0 | HF45: 23304 | HG45: 1704 | HH45: 5104 | HI45: 1704 | HJ45: 1704 | HK45: 1704 | HL45: 1704 | HM45: 15704 | HN45: 13704 | HO45: 4504 | HP45: 5104 | HQ45: 5304 | HR45: =+SUBTOTAL(9,HF45:HQ45) -> 81248 | HT45: 5826 | HU45: 426 | HV45: 1276 | HW45: 426 | HX45: 426 | HY45: 426 | HZ45: 426 | IA45: 3926 | IB45: 3426 | IC45: 1126 | ID45: 1276 | IE45: 1326 | IF45: =+SUBTOTAL(9,HT45:IE45) -> 20312 | IH45: 5826 | II45: 426 | IJ45: 1276 | IK45: 426 | IL45: 426 | IM45: 426 | IN45: 426 | IO45: 3926 | IP45: 3426 | IQ45: 1126 | IR45: 1276 | IS45: 1326 | IT45: =+SUBTOTAL(9,IH45:IS45) -> 20312 | IV45: 40778 | IW45: 2978 | IX45: 8928 | IY45: 2978 | IZ45: 2978 | JA45: 2978 | JB45: 2978 | JC45: 27478 | JD45: 23978 | JE45: 7878 | JF45: 8928 | JG45: 9278 | JH45: =+SUBTOTAL(9,IV45:JG45) -> 142136 | JJ45: 76478 | JK45: 5528 | JL45: 16578 | JM45: 5528 | JN45: 5528 | JO45: 5528 | JP45: 5528 | JQ45: 51778 | JR45: 44528 | JS45: 11828 | JT45: 16578 | JU45: 17228 | JV45: =+SUBTOTAL(9,JJ45:JU45) -> 262636 | JX45: 29126 | JY45: 2126 | JZ45: 6376 | KA45: 2126 | KB45: 2126 | KC45: 2126 | KD45: 2126 | KE45: 19626 | KF45: 17126 | KG45: 4926 | KH45: 6376 | KI45: 6626 | KJ45: =+SUBTOTAL(9,JX45:KI45) -> 100812 | KL45: 11651 | KM45: 851 | KN45: 2551 | KO45: 851 | KP45: 851 | KQ45: 851 | KR45: 851 | KS45: 7851 | KT45: 6851 | KU45: 2251 | KV45: 2551 | KW45: 2651 | KX45: =+SUBTOTAL(9,KL45:KW45) -> 40612 | KZ45: 5825 | LA45: 425 | LB45: 1275 | LC45: 425 | LD45: 425 | LE45: 425 | LF45: 425 | LG45: 3925 | LH45: 3425 | LI45: 1125 | LJ45: 1275 | LK45: 1325 | LL45: =+SUBTOTAL(9,KZ45:LK45) -> 20300 | LN45: 0 | LO45: 0 | LP45: 0 | LQ45: 0 | LR45: 0 | LS45: 0 | LT45: 0 | LU45: 0 | LV45: 0 | LW45: 0 | LX45: 0 | LY45: 0 | LZ45: =+SUBTOTAL(9,LN45:LY45) -> 0 | MB45: =SUMIF($D$11:$LY$11,MB$8,$D45:$LY45) -> 863004.89 | MC45: =SUMIF($D$11:$LY$11,MC$8,$D45:$LY45) -> -49445.113 | MD45: =SUMIF($D$11:$LY$11,MD$8,$D45:$LY45) -> 93354.887 | ME45: =SUMIF($D$11:$LY$11,ME$8,$D45:$LY45) -> -49445.113 | MF45: =SUMIF($D$11:$LY$11,MF$8,$D45:$LY45) -> -49445.113 | MG45: =SUMIF($D$11:$LY$11,MG$8,$D45:$LY45) -> -49445.113 | MH45: =SUMIF($D$11:$LY$11,MH$8,$D45:$LY45) -> -49445.113 | MI45: =SUMIF($D$11:$LY$11,MI$8,$D45:$LY45) -> 543804.89 | ... MM45: =SUMIF($D$11:$LY$11,MM$8,$D45:$LY45) -> 101754.89 | MN45: =SUM(MB45:MM45) -> 1963758.6
B46: Course & Training | D46: 23947 | E46: 23947 | F46: 23947 | G46: 23947 | H46: 23947 | I46: 23947 | J46: 23947 | K46: 23947 | L46: 23947 | M46: 23947 | N46: 23947 | O46: 23947 | P46: =+SUBTOTAL(9,D46:O46) -> 287364 | R46: 1938 | S46: 1938 | T46: 1938 | U46: 1938 | V46: 1938 | W46: 1938 | X46: 1938 | Y46: 1938 | Z46: 1938 | AA46: 1938 | AB46: 1938 | AC46: 1938 | AD46: =+SUBTOTAL(9,R46:AC46) -> 23256 | AF46: 1952 | AG46: 1952 | AH46: 1952 | AI46: 1952 | AJ46: 1952 | AK46: 1952 | AL46: 1952 | AM46: 1952 | AN46: 1952 | AO46: 1952 | AP46: 1952 | AQ46: 1952 | AR46: =+SUBTOTAL(9,AF46:AQ46) -> 23424 | AT46: 6106 | AU46: 6106 | AV46: 6106 | AW46: 6106 | AX46: 6106 | AY46: 6106 | AZ46: 6106 | BA46: 6106 | BB46: 6106 | BC46: 6106 | BD46: 6106 | BE46: 6106 | BF46: =+SUBTOTAL(9,AT46:BE46) -> 73272 | BH46: 35036 | BI46: 35036 | BJ46: 35036 | BK46: 35036 | BL46: 35036 | BM46: 35036 | BN46: 35036 | BO46: 35036 | BP46: 35036 | BQ46: 35036 | BR46: 35036 | BS46: 35036 | BT46: =+SUBTOTAL(9,BH46:BS46) -> 420432 | BV46: 5463 | BW46: 5463 | BX46: 5463 | BY46: 5463 | BZ46: 5463 | CA46: 5463 | CB46: 5463 | CC46: 5463 | CD46: 5463 | CE46: 5463 | CF46: 5463 | CG46: 5463 | CH46: =+SUBTOTAL(9,BV46:CG46) -> 65556 | CJ46: 14146 | CK46: 14146 | CL46: 14146 | CM46: 14146 | CN46: 14146 | CO46: 14146 | CP46: 14146 | CQ46: 14146 | CR46: 14146 | CS46: 14146 | CT46: 14146 | CU46: 14146 | CV46: =+SUBTOTAL(9,CJ46:CU46) -> 169752 | CX46: 31351 | CY46: 31351 | CZ46: 31351 | DA46: 31351 | DB46: 31351 | DC46: 31351 | DD46: 31351 | DE46: 31351 | DF46: 31351 | DG46: 31351 | DH46: 31351 | DI46: 31351 | DJ46: =+SUBTOTAL(9,CX46:DI46) -> 376212 | DL46: 18271 | DM46: 18271 | DN46: 18271 | DO46: 18271 | DP46: 18271 | DQ46: 18271 | DR46: 18271 | DS46: 18271 | DT46: 18271 | DU46: 18271 | DV46: 18271 | DW46: 18271 | DX46: =+SUBTOTAL(9,DL46:DW46) -> 219252 | DZ46: 2961 | EA46: 2961 | EB46: 2961 | EC46: 2961 | ED46: 2961 | EE46: 2961 | EF46: 2961 | EG46: 2961 | EH46: 2961 | EI46: 2961 | EJ46: 2961 | EK46: 2961 | EL46: =+SUBTOTAL(9,DZ46:EK46) -> 35532 | EN46: 4210 | EO46: 4210 | EP46: 4210 | EQ46: 4210 | ER46: 4210 | ES46: 4210 | ET46: 4210 | EU46: 4210 | EV46: 4210 | EW46: 4210 | EX46: 4210 | EY46: 4210 | EZ46: =+SUBTOTAL(9,EN46:EY46) -> 50520 | FB46: 722 | FC46: 722 | FD46: 722 | FE46: 722 | FF46: 722 | FG46: 722 | FH46: 722 | FI46: 722 | FJ46: 722 | FK46: 722 | FL46: 722 | FM46: 722 | FN46: =+SUBTOTAL(9,FB46:FM46) -> 8664 | FP46: 12358 | FQ46: 12358 | FR46: 12358 | FS46: 12358 | FT46: 12358 | FU46: 12358 | FV46: 12358 | FW46: 12358 | FX46: 12358 | FY46: 12358 | FZ46: 12358 | GA46: 12358 | GB46: =+SUBTOTAL(9,FP46:GA46) -> 148296 | GD46: 6580 | GE46: 6580 | GF46: 6580 | GG46: 6580 | GH46: 6580 | GI46: 6580 | GJ46: 6580 | GK46: 6580 | GL46: 6580 | GM46: 6580 | GN46: 6580 | GO46: 6580 | GP46: =+SUBTOTAL(9,GD46:GO46) -> 78960 | GR46: -122636.59 | GS46: -122636.59 | GT46: -122636.59 | GU46: -122636.59 | GV46: -122636.59 | GW46: -122636.59 | GX46: -122636.59 | GY46: -122636.59 | GZ46: -122636.59 | HA46: -122636.59 | HB46: -122636.59 | HC46: -122636.59 | HD46: =+SUBTOTAL(9,GR46:HC46)*0 -> 0 | HF46: 5392 | HG46: 5392 | HH46: 5392 | HI46: 5392 | HJ46: 5392 | HK46: 5392 | HL46: 5392 | HM46: 5392 | HN46: 5392 | HO46: 5392 | HP46: 5392 | HQ46: 5392 | HR46: =+SUBTOTAL(9,HF46:HQ46) -> 64704 | HT46: 1406 | HU46: 1406 | HV46: 1406 | HW46: 1406 | HX46: 1406 | HY46: 1406 | HZ46: 1406 | IA46: 1406 | IB46: 1406 | IC46: 1406 | ID46: 1406 | IE46: 1406 | IF46: =+SUBTOTAL(9,HT46:IE46) -> 16872 | IH46: 4708 | II46: 4708 | IJ46: 4708 | IK46: 4708 | IL46: 4708 | IM46: 4708 | IN46: 4708 | IO46: 4708 | IP46: 4708 | IQ46: 4708 | IR46: 4708 | IS46: 4708 | IT46: =+SUBTOTAL(9,IH46:IS46) -> 56496 | IV46: 13628 | IW46: 13628 | IX46: 13628 | IY46: 13628 | IZ46: 13628 | JA46: 13628 | JB46: 13628 | JC46: 13628 | JD46: 13628 | JE46: 13628 | JF46: 13628 | JG46: 13628 | JH46: =+SUBTOTAL(9,IV46:JG46) -> 163536 | JJ46: 18395 | JK46: 18395 | JL46: 18395 | JM46: 18395 | JN46: 18395 | JO46: 18395 | JP46: 18395 | JQ46: 18395 | JR46: 18395 | JS46: 18395 | JT46: 18395 | JU46: 18395 | JV46: =+SUBTOTAL(9,JJ46:JU46) -> 220740 | JX46: 9936 | JY46: 9936 | JZ46: 9936 | KA46: 9936 | KB46: 9936 | KC46: 9936 | KD46: 9936 | KE46: 9936 | KF46: 9936 | KG46: 9936 | KH46: 9936 | KI46: 9936 | KJ46: =+SUBTOTAL(9,JX46:KI46) -> 119232 | KL46: 1368 | KM46: 1368 | KN46: 1368 | KO46: 1368 | KP46: 1368 | KQ46: 1368 | KR46: 1368 | KS46: 1368 | KT46: 1368 | KU46: 1368 | KV46: 1368 | KW46: 1368 | KX46: =+SUBTOTAL(9,KL46:KW46) -> 16416 | KZ46: 1422 | LA46: 1422 | LB46: 1422 | LC46: 1422 | LD46: 1422 | LE46: 1422 | LF46: 1422 | LG46: 1422 | LH46: 1422 | LI46: 1422 | LJ46: 1422 | LK46: 1422 | LL46: =+SUBTOTAL(9,KZ46:LK46) -> 17064 | LN46: 0 | LO46: 0 | LP46: 0 | LQ46: 0 | LR46: 0 | LS46: 0 | LT46: 0 | LU46: 0 | LV46: 0 | LW46: 0 | LX46: 0 | LY46: 0 | LZ46: =+SUBTOTAL(9,LN46:LY46) -> 0 | MB46: =SUMIF($D$11:$LY$11,MB$8,$D46:$LY46) -> 98659.405 | MC46: =SUMIF($D$11:$LY$11,MC$8,$D46:$LY46) -> 98659.405 | MD46: =SUMIF($D$11:$LY$11,MD$8,$D46:$LY46) -> 98659.405 | ME46: =SUMIF($D$11:$LY$11,ME$8,$D46:$LY46) -> 98659.405 | MF46: =SUMIF($D$11:$LY$11,MF$8,$D46:$LY46) -> 98659.405 | MG46: =SUMIF($D$11:$LY$11,MG$8,$D46:$LY46) -> 98659.405 | MH46: =SUMIF($D$11:$LY$11,MH$8,$D46:$LY46) -> 98659.405 | MI46: =SUMIF($D$11:$LY$11,MI$8,$D46:$LY46) -> 98659.405 | ... MM46: =SUMIF($D$11:$LY$11,MM$8,$D46:$LY46) -> 98659.405 | MN46: =SUM(MB46:MM46) -> 1183912.9
B47: Joint Venture Personnel Cost Recharges | D47: 0 | E47: 0 | F47: 0 | G47: 0 | H47: 0 | I47: 0 | J47: 0 | K47: 0 | L47: 0 | M47: 0 | N47: 0 | O47: 0 | P47: =+SUBTOTAL(9,D47:O47) -> 0 | R47: 0 | S47: 0 | T47: 0 | U47: 0 | V47: 0 | W47: 0 | X47: 0 | Y47: 0 | Z47: 0 | AA47: 0 | AB47: 0 | AC47: 0 | AD47: =+SUBTOTAL(9,R47:AC47) -> 0 | AF47: 0 | AG47: 0 | AH47: 0 | AI47: 0 | AJ47: 0 | AK47: 0 | AL47: 0 | AM47: 0 | AN47: 0 | AO47: 0 | AP47: 0 | AQ47: 0 | AR47: =+SUBTOTAL(9,AF47:AQ47) -> 0 | AT47: 0 | AU47: 0 | AV47: 0 | AW47: 0 | AX47: 0 | AY47: 0 | AZ47: 0 | BA47: 0 | BB47: 0 | BC47: 0 | BD47: 0 | BE47: 0 | BF47: =+SUBTOTAL(9,AT47:BE47) -> 0 | BH47: 0 | BI47: 0 | BJ47: 0 | BK47: 0 | BL47: 0 | BM47: 0 | BN47: 0 | BO47: 0 | BP47: 0 | BQ47: 0 | BR47: 0 | BS47: 0 | BT47: =+SUBTOTAL(9,BH47:BS47) -> 0 | BV47: 0 | BW47: 0 | BX47: 0 | BY47: 0 | BZ47: 0 | CA47: 0 | CB47: 0 | CC47: 0 | CD47: 0 | CE47: 0 | CF47: 0 | CG47: 0 | CH47: =+SUBTOTAL(9,BV47:CG47) -> 0 | CJ47: 0 | CK47: 0 | CL47: 0 | CM47: 0 | CN47: 0 | CO47: 0 | CP47: 0 | CQ47: 0 | CR47: 0 | CS47: 0 | CT47: 0 | CU47: 0 | CV47: =+SUBTOTAL(9,CJ47:CU47) -> 0 | CX47: 0 | CY47: 0 | CZ47: 0 | DA47: 0 | DB47: 0 | DC47: 0 | DD47: 0 | DE47: 0 | DF47: 0 | DG47: 0 | DH47: 0 | DI47: 0 | DJ47: =+SUBTOTAL(9,CX47:DI47) -> 0 | DL47: 0 | DM47: 0 | DN47: 0 | DO47: 0 | DP47: 0 | DQ47: 0 | DR47: 0 | DS47: 0 | DT47: 0 | DU47: 0 | DV47: 0 | DW47: 0 | DX47: =+SUBTOTAL(9,DL47:DW47) -> 0 | DZ47: 0 | EA47: 0 | EB47: 0 | EC47: 0 | ED47: 0 | EE47: 0 | EF47: 0 | EG47: 0 | EH47: 0 | EI47: 0 | EJ47: 0 | EK47: 0 | EL47: =+SUBTOTAL(9,DZ47:EK47) -> 0 | EN47: 0 | EO47: 0 | EP47: 0 | EQ47: 0 | ER47: 0 | ES47: 0 | ET47: 0 | EU47: 0 | EV47: 0 | EW47: 0 | EX47: 0 | EY47: 0 | EZ47: =+SUBTOTAL(9,EN47:EY47) -> 0 | FB47: 0 | FC47: 0 | FD47: 0 | FE47: 0 | FF47: 0 | FG47: 0 | FH47: 0 | FI47: 0 | FJ47: 0 | FK47: 0 | FL47: 0 | FM47: 0 | FN47: =+SUBTOTAL(9,FB47:FM47) -> 0 | FP47: 0 | FQ47: 0 | FR47: 0 | FS47: 0 | FT47: 0 | FU47: 0 | FV47: 0 | FW47: 0 | FX47: 0 | FY47: 0 | FZ47: 0 | GA47: 0 | GB47: =+SUBTOTAL(9,FP47:GA47) -> 0 | GD47: 0 | GE47: 0 | GF47: 0 | GG47: 0 | GH47: 0 | GI47: 0 | GJ47: 0 | GK47: 0 | GL47: 0 | GM47: 0 | GN47: 0 | GO47: 0 | GP47: =+SUBTOTAL(9,GD47:GO47) -> 0 | GR47: 0 | GS47: 0 | GT47: 0 | GU47: 0 | GV47: 0 | GW47: 0 | GX47: 0 | GY47: 0 | GZ47: 0 | HA47: 0 | HB47: 0 | HC47: 0 | HD47: =+SUBTOTAL(9,GR47:HC47)*0 -> 0 | HF47: 0 | HG47: 0 | HH47: 0 | HI47: 0 | HJ47: 0 | HK47: 0 | HL47: 0 | HM47: 0 | HN47: 0 | HO47: 0 | HP47: 0 | HQ47: 0 | HR47: =+SUBTOTAL(9,HF47:HQ47) -> 0 | HT47: 0 | HU47: 0 | HV47: 0 | HW47: 0 | HX47: 0 | HY47: 0 | HZ47: 0 | IA47: 0 | IB47: 0 | IC47: 0 | ID47: 0 | IE47: 0 | IF47: =+SUBTOTAL(9,HT47:IE47) -> 0 | IH47: 0 | II47: 0 | IJ47: 0 | IK47: 0 | IL47: 0 | IM47: 0 | IN47: 0 | IO47: 0 | IP47: 0 | IQ47: 0 | IR47: 0 | IS47: 0 | IT47: =+SUBTOTAL(9,IH47:IS47) -> 0 | IV47: 0 | IW47: 0 | IX47: 0 | IY47: 0 | IZ47: 0 | JA47: 0 | JB47: 0 | JC47: 0 | JD47: 0 | JE47: 0 | JF47: 0 | JG47: 0 | JH47: =+SUBTOTAL(9,IV47:JG47) -> 0 | JJ47: 0 | JK47: 0 | JL47: 0 | JM47: 0 | JN47: 0 | JO47: 0 | JP47: 0 | JQ47: 0 | JR47: 0 | JS47: 0 | JT47: 0 | JU47: 0 | JV47: =+SUBTOTAL(9,JJ47:JU47) -> 0 | JX47: 0 | JY47: 0 | JZ47: 0 | KA47: 0 | KB47: 0 | KC47: 0 | KD47: 0 | KE47: 0 | KF47: 0 | KG47: 0 | KH47: 0 | KI47: 0 | KJ47: =+SUBTOTAL(9,JX47:KI47) -> 0 | KL47: 0 | KM47: 0 | KN47: 0 | KO47: 0 | KP47: 0 | KQ47: 0 | KR47: 0 | KS47: 0 | KT47: 0 | KU47: 0 | KV47: 0 | KW47: 0 | KX47: =+SUBTOTAL(9,KL47:KW47) -> 0 | KZ47: 0 | LA47: 0 | LB47: 0 | LC47: 0 | LD47: 0 | LE47: 0 | LF47: 0 | LG47: 0 | LH47: 0 | LI47: 0 | LJ47: 0 | LK47: 0 | LL47: =+SUBTOTAL(9,KZ47:LK47) -> 0 | LN47: 0 | LO47: 0 | LP47: 0 | LQ47: 0 | LR47: 0 | LS47: 0 | LT47: 0 | LU47: 0 | LV47: 0 | LW47: 0 | LX47: 0 | LY47: 0 | LZ47: =+SUBTOTAL(9,LN47:LY47) -> 0 | MB47: =SUMIF($D$11:$LY$11,MB$8,$D47:$LY47) -> 0 | MC47: =SUMIF($D$11:$LY$11,MC$8,$D47:$LY47) -> 0 | MD47: =SUMIF($D$11:$LY$11,MD$8,$D47:$LY47) -> 0 | ME47: =SUMIF($D$11:$LY$11,ME$8,$D47:$LY47) -> 0 | MF47: =SUMIF($D$11:$LY$11,MF$8,$D47:$LY47) -> 0 | MG47: =SUMIF($D$11:$LY$11,MG$8,$D47:$LY47) -> 0 | MH47: =SUMIF($D$11:$LY$11,MH$8,$D47:$LY47) -> 0 | MI47: =SUMIF($D$11:$LY$11,MI$8,$D47:$LY47) -> 0 | ... MM47: =SUMIF($D$11:$LY$11,MM$8,$D47:$LY47) -> 0 | MN47: =SUM(MB47:MM47) -> 0
B48: Intra-group Personnel Cost Recharges | D48: 0 | E48: 0 | F48: 0 | G48: 0 | H48: 0 | I48: 0 | J48: 0 | K48: 0 | L48: 0 | M48: 0 | N48: 0 | O48: 0 | P48: =+SUBTOTAL(9,D48:O48) -> 0 | R48: 0 | S48: 0 | T48: 0 | U48: 0 | V48: 0 | W48: 0 | X48: 0 | Y48: 0 | Z48: 0 | AA48: 0 | AB48: 0 | AC48: 0 | AD48: =+SUBTOTAL(9,R48:AC48) -> 0 | AF48: 0 | AG48: 0 | AH48: 0 | AI48: 0 | AJ48: 0 | AK48: 0 | AL48: 0 | AM48: 0 | AN48: 0 | AO48: 0 | AP48: 0 | AQ48: 0 | AR48: =+SUBTOTAL(9,AF48:AQ48) -> 0 | AT48: 0 | AU48: 0 | AV48: 0 | AW48: 0 | AX48: 0 | AY48: 0 | AZ48: 0 | BA48: 0 | BB48: 0 | BC48: 0 | BD48: 0 | BE48: 0 | BF48: =+SUBTOTAL(9,AT48:BE48) -> 0 | BH48: 0 | BI48: 0 | BJ48: 0 | BK48: 0 | BL48: 0 | BM48: 0 | BN48: 0 | BO48: 0 | BP48: 0 | BQ48: 0 | BR48: 0 | BS48: 0 | BT48: =+SUBTOTAL(9,BH48:BS48) -> 0 | BV48: 0 | BW48: 0 | BX48: 0 | BY48: 0 | BZ48: 0 | CA48: 0 | CB48: 0 | CC48: 0 | CD48: 0 | CE48: 0 | CF48: 0 | CG48: 0 | CH48: =+SUBTOTAL(9,BV48:CG48) -> 0 | CJ48: 0 | CK48: 0 | CL48: 0 | CM48: 0 | CN48: 0 | CO48: 0 | CP48: 0 | CQ48: 0 | CR48: 0 | CS48: 0 | CT48: 0 | CU48: 0 | CV48: =+SUBTOTAL(9,CJ48:CU48) -> 0 | CX48: 0 | CY48: 0 | CZ48: 0 | DA48: 0 | DB48: 0 | DC48: 0 | DD48: 0 | DE48: 0 | DF48: 0 | DG48: 0 | DH48: 0 | DI48: 0 | DJ48: =+SUBTOTAL(9,CX48:DI48) -> 0 | DL48: 0 | DM48: 0 | DN48: 0 | DO48: 0 | DP48: 0 | DQ48: 0 | DR48: 0 | DS48: 0 | DT48: 0 | DU48: 0 | DV48: 0 | DW48: 0 | DX48: =+SUBTOTAL(9,DL48:DW48) -> 0 | DZ48: 0 | EA48: 0 | EB48: 0 | EC48: 0 | ED48: 0 | EE48: 0 | EF48: 0 | EG48: 0 | EH48: 0 | EI48: 0 | EJ48: 0 | EK48: 0 | EL48: =+SUBTOTAL(9,DZ48:EK48) -> 0 | EN48: 0 | EO48: 0 | EP48: 0 | EQ48: 0 | ER48: 0 | ES48: 0 | ET48: 0 | EU48: 0 | EV48: 0 | EW48: 0 | EX48: 0 | EY48: 0 | EZ48: =+SUBTOTAL(9,EN48:EY48) -> 0 | FB48: 0 | FC48: 0 | FD48: 0 | FE48: 0 | FF48: 0 | FG48: 0 | FH48: 0 | FI48: 0 | FJ48: 0 | FK48: 0 | FL48: 0 | FM48: 0 | FN48: =+SUBTOTAL(9,FB48:FM48) -> 0 | FP48: 0 | FQ48: 0 | FR48: 0 | FS48: 0 | FT48: 0 | FU48: 0 | FV48: 0 | FW48: 0 | FX48: 0 | FY48: 0 | FZ48: 0 | GA48: 0 | GB48: =+SUBTOTAL(9,FP48:GA48) -> 0 | GD48: 0 | GE48: 0 | GF48: 0 | GG48: 0 | GH48: 0 | GI48: 0 | GJ48: 0 | GK48: 0 | GL48: 0 | GM48: 0 | GN48: 0 | GO48: 0 | GP48: =+SUBTOTAL(9,GD48:GO48) -> 0 | GR48: 0 | GS48: 0 | GT48: 0 | GU48: 0 | GV48: 0 | GW48: 0 | GX48: 0 | GY48: 0 | GZ48: 0 | HA48: 0 | HB48: 0 | HC48: 0 | HD48: =+SUBTOTAL(9,GR48:HC48)*0 -> 0 | HF48: 0 | HG48: 0 | HH48: 0 | HI48: 0 | HJ48: 0 | HK48: 0 | HL48: 0 | HM48: 0 | HN48: 0 | HO48: 0 | HP48: 0 | HQ48: 0 | HR48: =+SUBTOTAL(9,HF48:HQ48) -> 0 | HT48: 0 | HU48: 0 | HV48: 0 | HW48: 0 | HX48: 0 | HY48: 0 | HZ48: 0 | IA48: 0 | IB48: 0 | IC48: 0 | ID48: 0 | IE48: 0 | IF48: =+SUBTOTAL(9,HT48:IE48) -> 0 | IH48: 0 | II48: 0 | IJ48: 0 | IK48: 0 | IL48: 0 | IM48: 0 | IN48: 0 | IO48: 0 | IP48: 0 | IQ48: 0 | IR48: 0 | IS48: 0 | IT48: =+SUBTOTAL(9,IH48:IS48) -> 0 | IV48: 0 | IW48: 0 | IX48: 0 | IY48: 0 | IZ48: 0 | JA48: 0 | JB48: 0 | JC48: 0 | JD48: 0 | JE48: 0 | JF48: 0 | JG48: 0 | JH48: =+SUBTOTAL(9,IV48:JG48) -> 0 | JJ48: 0 | JK48: 0 | JL48: 0 | JM48: 0 | JN48: 0 | JO48: 0 | JP48: 0 | JQ48: 0 | JR48: 0 | JS48: 0 | JT48: 0 | JU48: 0 | JV48: =+SUBTOTAL(9,JJ48:JU48) -> 0 | JX48: 0 | JY48: 0 | JZ48: 0 | KA48: 0 | KB48: 0 | KC48: 0 | KD48: 0 | KE48: 0 | KF48: 0 | KG48: 0 | KH48: 0 | KI48: 0 | KJ48: =+SUBTOTAL(9,JX48:KI48) -> 0 | KL48: 0 | KM48: 0 | KN48: 0 | KO48: 0 | KP48: 0 | KQ48: 0 | KR48: 0 | KS48: 0 | KT48: 0 | KU48: 0 | KV48: 0 | KW48: 0 | KX48: =+SUBTOTAL(9,KL48:KW48) -> 0 | KZ48: 0 | LA48: 0 | LB48: 0 | LC48: 0 | LD48: 0 | LE48: 0 | LF48: 0 | LG48: 0 | LH48: 0 | LI48: 0 | LJ48: 0 | LK48: 0 | LL48: =+SUBTOTAL(9,KZ48:LK48) -> 0 | LN48: 0 | LO48: 0 | LP48: 0 | LQ48: 0 | LR48: 0 | LS48: 0 | LT48: 0 | LU48: 0 | LV48: 0 | LW48: 0 | LX48: 0 | LY48: 0 | LZ48: =+SUBTOTAL(9,LN48:LY48) -> 0 | MB48: =SUMIF($D$11:$LY$11,MB$8,$D48:$LY48) -> 0 | MC48: =SUMIF($D$11:$LY$11,MC$8,$D48:$LY48) -> 0 | MD48: =SUMIF($D$11:$LY$11,MD$8,$D48:$LY48) -> 0 | ME48: =SUMIF($D$11:$LY$11,ME$8,$D48:$LY48) -> 0 | MF48: =SUMIF($D$11:$LY$11,MF$8,$D48:$LY48) -> 0 | MG48: =SUMIF($D$11:$LY$11,MG$8,$D48:$LY48) -> 0 | MH48: =SUMIF($D$11:$LY$11,MH$8,$D48:$LY48) -> 0 | MI48: =SUMIF($D$11:$LY$11,MI$8,$D48:$LY48) -> 0 | ... MM48: =SUMIF($D$11:$LY$11,MM$8,$D48:$LY48) -> 0 | MN48: =SUM(MB48:MM48) -> 0
