Workbook

Sheet SSC Recharge Summary
A1: India Shared Services
A2: 45658 | B2: January, 2025 | D2: 1 | E2: =3+1+7 -> 11 | F2: 1 | G2: 30 | H2: 3 | I2: 3 | J2: =1+1 -> 2 | K2: 15 | L2: 17 | M2: 1 | N2: =18+9 -> 27 | O2: =13+13+1 -> 27 | P2: 1 | Q2: 4 | R2: =1+1 -> 2 | S2: =4+3 -> 7 | T2: 1 | U2: =1+1+2 -> 4 | V2: 1 | W2: =1+1 -> 2 | X2: =2+2+3 -> 7 | Y2: =4+2+7 -> 13 | Z2: 4
D3: CMI | E3: CMI | F3: CMI | N3: GCC +Jibe | R3: Germany | T3: 13th Floor
B4: Business Unit Name | C4: Expense Type | D4: Crew Management | E4: Cruise Management | F4: Accounts | G4: Accounts | H4: Admin | I4: Agency Services | J4: Commercial | K4: Consultancy Services | L4: Environmental Compliance | M4: Environmental Compliance | N4: IT | O4: Procurement | P4: Procurement | Q4: Ship Management | R4: Ship Management | S4: Ship Management | T4: Ship Management | U4: Ship Management | V4: Ship Management | W4: Ship Management | X4: Ship Management | Y4: Ship Management | Z4: Ship Management | AA4: Technical Services | AB4: Ship Management | AC4: Ship Management | AD4: Actual
B5: Division Name | D5: Group Marine HR | E5: Miami Ship Management | F5: CMI Accounts Payables | G5: Fleet Accounts | H5: Administration | I5: Agency Hub | J5: Commercial | K5: Fleet Performance | L5: Carbon Emission Services | M5: Other Environmental Compliance | N5: Group IT | O5: Galleymasters | P5: Sourcing | Q5: Antwerp Dry | R5: Goes Dry | S5: Group Operations | T5: Group Shared Service Center | U5: Hamburg Dry | V5: Hong Kong Dry 1 | W5: JV Ardmore | X5: Singapore Dry | Y5: Singapore Tanker 1 | Z5: Singapore Tanker 2 | AA5: AE Technical Services | AB5: Hong Kong Dry 2 | AC5: Hong Kong Dry 3 | AD5: Total
A7: A | B7: PERSONNEL EXPENSES
B8: Salaries & Wages | C8: Fixed | D8: 6313.72 | E8: 16347.8 | F8: 1643.79 | G8: 29043.29 | H8: 2239.97 | I8: 2256.14 | J8: 7056.17 | K8: 39208.36 | L8: 17844.41 | M8: 4645.25 | N8: 36370.33 | O8: 20535.24 | P8: 3422.24 | Q8: 6549.82 | R8: 1316.03 | S8: 14282.4 | T8: 7330.55 | U8: 3505.1 | V8: 1625.39 | W8: 6195.08 | X8: 15528.55 | Y8: 24979.43 | Z8: 4581.77 | AA8: 826.95 | AB8: 0 | AC8: 0 | AD8: =SUM(D8:AA8) -> 273647.78
B9: Provision for Bonus, Leave & Other Employment Costs | C9: Fixed | D9: 483.74 | E9: 1252.5 | F9: 125.94 | G9: 2233.66 | H9: 171.64 | I9: 172.87 | J9: 540.61 | K9: 3055.21 | L9: 653.74 | M9: 170.33 | N9: 2780.99 | O9: 1596.5 | P9: 262.21 | Q9: 434.51 | R9: 81.59 | S9: 1094.27 | T9: 86.89 | U9: 377.45 | V9: 124.52 | W9: 444.51 | X9: 1198.53 | Y9: 1765.18 | Z9: 626.76 | AA9: 30.32 | AB9: 0 | AC9: 0 | AD9: =SUM(D9:AA9) -> 19764.47
B10: Consultants & Contractors | C10: Fixed | D10: 0 | E10: 0 | F10: 0 | G10: 0 | H10: 0 | I10: 0 | J10: 0 | K10: 0 | L10: 0 | M10: -608.36 | N10: 3344.15 | O10: 0 | P10: 0 | Q10: 0 | R10: 0 | S10: 655.35 | T10: 0 | U10: 0 | V10: 0 | W10: 0 | X10: 0 | Y10: 0 | Z10: 0 | AA10: 0 | AB10: 0 | AC10: 0 | AD10: =SUM(D10:AA10) -> 3391.14
B11: Pension Fund & Social Securities | C11: Fixed | D11: 434.26 | E11: 1017.43 | F11: 94.83 | G11: 1814.75 | H11: 130.79 | I11: 131.66 | J11: 474.57 | K11: 2634.98 | L11: 1247.53 | M11: 349.29 | N11: 2369.94 | O11: 1272.76 | P11: 235.76 | Q11: 431.96 | R11: 79.6 | S11: 945.66 | T11: 522.85 | U11: 195.02 | V11: 93.81 | W11: 422.37 | X11: 1027.41 | Y11: 1671.28 | Z11: 235.91 | AA11: 52.55 | AB11: 0 | AC11: 0 | AD11: =SUM(D11:AA11) -> 17886.97
B12: Staff Allowances & Benefits | C12: Fixed | D12: 36.52 | E12: 1445.56 | F12: 43.99 | G12: 1319.61 | H12: 109.52 | I12: 109.52 | J12: 73.03 | K12: 547.64 | L12: 620.65 | M12: 36.52 | N12: 985.74 | O12: 985.76 | P12: 36.52 | Q12: 146.04 | R12: 73.03 | S12: 255.56 | T12: 36.52 | U12: 146.04 | V12: 36.52 | W12: 73.03 | X12: 255.54 | Y12: 474.61 | Z12: 146.04 | AA12: 36.52 | AB12: 0 | AC12: 0 | AD12: =SUM(D12:AA12) -> 8030.03
B13: Medical Expenses | C13: Variable | D13: 0 | E13: 0 | F13: 0 | G13: 0 | H13: 0 | I13: 0 | J13: 0 | K13: 0 | L13: 0 | M13: 0 | N13: 0 | O13: 0 | P13: 0 | Q13: 0 | R13: 0 | S13: 0 | T13: 0 | U13: 0 | V13: 0 | W13: 0 | X13: 0 | Y13: 0 | Z13: 0 | AA13: 0 | AB13: 0 | AC13: 0 | AD13: =SUM(D13:AA13) -> 0
B14: Staff Recruitment / Relocation | C14: Variable | D14: -0.45 | E14: -5.01 | F14: -0.46 | G14: -13.66 | H14: -1.37 | I14: -1.37 | J14: -0.9 | K14: 24.79 | L14: -7.74 | M14: -0.45 | N14: -1.84 | O14: -12.28 | P14: -0.45 | Q14: -1.82 | R14: 9.53 | S14: -3.19 | T14: 348.58 | U14: 8.63 | V14: -0.45 | W14: -0.9 | X14: -3.18 | Y14: 14.96 | Z14: -1.82 | AA14: -0.45 | AB14: 0 | AC14: 0 | AD14: =SUM(D14:AA14) -> 348.7
B15: Staff Functions | C15: Variable | D15: 37.57 | E15: 413.36 | F15: 37.58 | G15: 1127.39 | H15: 112.74 | I15: 112.74 | J15: 75.14 | K15: 563.68 | L15: 638.84 | M15: 37.57 | N15: 1014.7 | O15: 1014.63 | P15: 37.57 | Q15: 150.32 | R15: 75.14 | S15: 263.06 | T15: 37.57 | U15: 150.3 | V15: 37.57 | W15: 75.14 | X15: 263.04 | Y15: 488.53 | Z15: 150.32 | AA15: 37.57 | AB15: 0 | AC15: 0 | AD15: =SUM(D15:AA15) -> 6952.07
B16: Course & Training | C16: Variable | D16: 0 | E16: 0 | F16: 0 | G16: 0 | H16: 0 | I16: 0 | J16: 0 | K16: 0 | L16: 0 | M16: 0 | N16: 1876.8 | O16: 0 | P16: 0 | Q16: 0 | R16: 0 | S16: 0 | T16: 0 | U16: 0 | V16: 0 | W16: 0 | X16: 0 | Y16: 0 | Z16: 0 | AA16: 0 | AB16: 0 | AC16: 0 | AD16: =SUM(D16:AA16) -> 1876.8
B17: Joint Venture Personnel Cost Recharges | C17: Fixed | D17: 0 | E17: 0 | F17: 0 | G17: 0 | H17: 0 | I17: 0 | J17: 0 | K17: 0 | L17: 0 | M17: 0 | N17: 0 | O17: 0 | P17: 0 | Q17: 0 | R17: 0 | S17: 0 | T17: 0 | U17: 0 | V17: 0 | W17: 0 | X17: 0 | Y17: 0 | Z17: 0 | AA17: 0 | AB17: 0 | AC17: 0 | AD17: =SUM(D17:AA17) -> 0
B18: Intra-group Personnel Cost Recharges | C18: Fixed | D18: 0 | E18: 0 | F18: 0 | G18: 0 | H18: 0 | I18: 0 | J18: 0 | K18: 0 | L18: 0 | M18: 0 | N18: 0 | O18: 0 | P18: 0 | Q18: 0 | R18: 0 | S18: 0 | T18: 0 | U18: 0 | V18: 0 | W18: 0 | X18: 0 | Y18: 0 | Z18: 0 | AA18: 0 | AB18: 0 | AC18: 0 | AD18: =SUM(D18:AA18) -> 0
AD19: =SUM(AD8:AD18) -> 331897.96
A20: B | B20: OFFICE EXPENSES
B21: Rent - Depreciation | C21: Fixed | D21: 131.16383 | E21: 1442.8021 | F21: 131.16383 | G21: 3934.9148 | H21: 393.49148 | I21: 393.49148 | J21: 262.32765 | K21: 1967.4574 | L21: 2229.785 | M21: 131.16383 | N21: 3541.4233 | O21: 3541.4233 | P21: 0 | Q21: 524.6553 | R21: 262.32765 | S21: 918.14678 | T21: 131.16383 | U21: 524.6553 | V21: 131.16383 | W21: 262.32765 | X21: 918.14678 | Y21: 1705.1297 | Z21: 524.6553 | AA21: 124.36981 | AB21: 0 | AC21: 0 | AD21: =SUM(D21:AA21) -> 24127.35
B22: Rent - Lease Interest | C22: Fixed | D22: 0 | E22: 0 | F22: 0 | G22: 0 | H22: 0 | I22: 0 | J22: 0 | K22: 0 | L22: 0 | M22: 0 | N22: 0 | O22: 0 | P22: 0 | Q22: 0 | R22: 0 | S22: 0 | T22: 0 | U22: 0 | V22: 0 | W22: 0 | X22: 0 | Y22: 0 | Z22: 0 | AA22: 0 | AB22: 0 | AC22: 0 | AD22: =SUM(D22:AA22) -> 0
B23: Rates & Management Fees | C23: Fixed | D23: 15.58 | E23: 171.38 | F23: 15.58 | G23: 467.47 | H23: 46.73 | I23: 46.73 | J23: 31.16 | K23: 384.51 | L23: 264.88 | M23: 15.58 | N23: 420.6 | O23: 420.71 | P23: 0 | Q23: 62.3 | R23: 31.16 | S23: 109.04 | T23: 4098.63 | U23: 62.31 | V23: 15.58 | W23: 31.16 | X23: 109.05 | Y23: 202.53 | Z23: 62.3 | AA23: 15.58 | AB23: 0 | AC23: 0 | AD23: =SUM(D23:AA23) -> 7100.55
B24: Light & Power | C24: Fixed | D24: 5.88 | E24: 64.75 | F24: 5.88 | G24: 176.49 | H24: 17.67 | I24: 17.67 | J24: 11.76 | K24: 88.3 | L24: 100.1 | M24: 5.88 | N24: 158.93 | O24: 158.93 | P24: 0 | Q24: 23.54 | R24: 11.76 | S24: 41.2 | T24: 342.85 | U24: 23.54 | V24: 5.88 | W24: 11.76 | X24: 41.21 | Y24: 76.51 | Z24: 23.54 | AA24: 5.88 | AB24: 0 | AC24: 0 | AD24: =SUM(D24:AA24) -> 1419.91
B25: Office Supplies & Cleaning | C25: Variable | D25: 8.04 | E25: 88.46 | F25: 8.05 | G25: 241.37 | H25: 24.13 | I25: 24.13 | J25: 16.08 | K25: 120.65 | L25: 136.72 | M25: 8.04 | N25: 217.14 | O25: 217.13 | P25: 0 | Q25: 32.17 | R25: 16.08 | S25: 56.29 | T25: 8.04 | U25: 32.15 | V25: 8.04 | W25: 16.08 | X25: 56.28 | Y25: 104.54 | Z25: 32.17 | AA25: 8.04 | AB25: 0 | AC25: 0 | AD25: =SUM(D25:AA25) -> 1479.82
B26: Archive Storage / Warehouse | C26: Fixed | D26: 0.56 | E26: 6.14 | F26: 0.56 | G26: 16.83 | H26: 1.67 | I26: 1.67 | J26: 1.11 | K26: 8.39 | L26: 9.5 | M26: 0.56 | N26: 15.08 | O26: 15.08 | P26: 0 | Q26: 2.23 | R26: 1.11 | S26: 3.9 | T26: 0.56 | U26: 2.23 | V26: 0.56 | W26: 1.11 | X26: 3.9 | Y26: 7.25 | Z26: 2.23 | AA26: 0.56 | AB26: 0 | AC26: 0 | AD26: =SUM(D26:AA26) -> 102.79
B27: Office Repairs & Maintenance | C27: Fixed | D27: 2.76 | E27: 30.36 | F27: 2.76 | G27: 82.73 | H27: 8.28 | I27: 8.28 | J27: 5.52 | K27: 37.92 | L27: 46.87 | M27: 2.76 | N27: 74.49 | O27: 74.49 | P27: 0 | Q27: 11.04 | R27: 5.52 | S27: 19.32 | T27: 2.76 | U27: 11.03 | V27: 2.53 | W27: 5.52 | X27: 19.3 | Y27: 35.87 | Z27: 11.04 | AA27: 2.76 | AB27: 0 | AC27: 0 | AD27: =SUM(D27:AA27) -> 503.91
B28: Intra-group rental cost recharges | C28: Fixed | D28: 61.71 | E28: 678.76 | F28: 61.7 | G28: 1851.08 | H28: 185.12 | I28: 185.12 | J28: 123.42 | K28: 925.58 | L28: 1048.99 | M28: 61.71 | N28: 1666.04 | O28: 1666.05 | P28: 0 | Q28: 246.82 | R28: 123.42 | S28: 431.93 | T28: 61.71 | U28: 246.83 | V28: 61.71 | W28: 123.42 | X28: 431.93 | Y28: 802.16 | Z28: 246.82 | AA28: 61.71 | AB28: 0 | AC28: 0 | AD28: =SUM(D28:AA28) -> 11353.74
AD29: =SUM(AD21:AD28) -> 46088.07
A30: C | B30: ADMINISTRATIVE EXPENSES
B31: IT - Software & Applications | C31: Variable | D31: 42.96 | E31: 472.54 | F31: 42.95 | G31: 1288.59 | H31: 128.87 | I31: 128.87 | J31: 85.93 | K31: 644.36 | L31: 730.26 | M31: 42.96 | N31: 1159.84 | O31: 1159.87 | P31: 42.96 | Q31: 171.84 | R31: 85.93 | S31: 300.71 | T31: 42.96 | U31: 171.84 | V31: 42.96 | W31: 85.93 | X31: 300.68 | Y31: 558.45 | Z31: 171.84 | AA31: 42.96 | AB31: 0 | AC31: 0 | AD31: =SUM(D31:AA31) -> 7947.06
B32: IT - Communications | C32: Variable | D32: 22.55 | E32: 248.14 | F32: 23.57 | G32: 707.2 | H32: 76.75 | I32: 67.66 | J32: 45.1 | K32: 175.33 | L32: 392.97 | M32: 22.55 | N32: 690.99 | O32: 641.24 | P32: -6.96 | Q32: 90.22 | R32: 45.1 | S32: 157.88 | T32: 22.55 | U32: 90.2 | V32: 11.68 | W32: 45.1 | X32: 157.86 | Y32: 293.25 | Z32: 90.22 | AA32: 22.55 | AB32: 0 | AC32: 0 | AD32: =SUM(D32:AA32) -> 4133.7
B33: IT - IT Services | C33: Variable | D33: 3.33 | E33: 36.61 | F33: 3.32 | G33: 99.73 | H33: 9.99 | I33: 9.99 | J33: 6.66 | K33: 9.56 | L33: 56.57 | M33: 3.33 | N33: 459.3 | O33: 89.86 | P33: 0.64 | Q33: 13.32 | R33: 6.66 | S33: 23.3 | T33: 3.33 | U33: 13.32 | V33: 0.64 | W33: 6.66 | X33: 23.3 | Y33: 43.27 | Z33: 13.32 | AA33: 3.33 | AB33: 0 | AC33: 0 | AD33: =SUM(D33:AA33) -> 939.34
B34: IT - Network & Infrastructure Services | C34: Variable | D34: 0 | E34: 0 | F34: 0 | G34: 0 | H34: 0 | I34: 0 | J34: 0 | K34: 0 | L34: 0 | M34: 0 | N34: 0 | O34: 0 | P34: 0 | Q34: 0 | R34: 0 | S34: 0 | T34: 0 | U34: 0 | V34: 0 | W34: 0 | X34: 0 | Y34: 0 | Z34: 0 | AA34: 0 | AB34: 0 | AC34: 0 | AD34: =SUM(D34:AA34) -> 0
B35: Insurance | C35: Fixed | D35: 0.26 | E35: 2.77 | F35: 0.25 | G35: 7.51 | H35: 0.75 | I35: 0.75 | J35: 0.51 | K35: 3.78 | L35: 4.29 | M35: 0.26 | N35: 6.82 | O35: 6.82 | P35: 0 | Q35: 1.01 | R35: 0.51 | S35: 1.76 | T35: 114.91 | U35: 1.02 | V35: 0.26 | W35: 0.51 | X35: 1.77 | Y35: 3.28 | Z35: 1.01 | AA35: 0.26 | AB35: 0 | AC35: 0 | AD35: =SUM(D35:AA35) -> 161.07
B36: Marketing, Branding & Communications | C36: Variable | D36: 0 | E36: 0 | F36: 0 | G36: 0 | H36: 0 | I36: 0 | J36: 0 | K36: 0 | L36: 0 | M36: 0 | N36: 0 | O36: 0 | P36: 0 | Q36: 0 | R36: 0 | S36: 0 | T36: 0 | U36: 0 | V36: 0 | W36: 0 | X36: 0 | Y36: 0 | Z36: 0 | AA36: 0 | AB36: 0 | AC36: 0 | AD36: =SUM(D36:AA36) -> 0
B37: Overseas Travelling | C37: Variable | D37: 2757.23 | E37: 0 | F37: 0 | G37: 0 | H37: 0 | I37: 0 | J37: 0 | K37: 673.8 | L37: 0 | M37: 0 | N37: 0 | O37: 0 | P37: 0 | Q37: 0 | R37: 0 | S37: 0 | T37: 2970.37 | U37: 0 | V37: 384.24 | W37: 0 | X37: 0 | Y37: 62.15 | Z37: 0 | AA37: 0 | AB37: 0 | AC37: 0 | AD37: =SUM(D37:AA37) -> 6847.79
B38: Local Travelling | C38: Variable | D38: 21.39 | E38: 594.86 | F38: 18.25 | G38: 547.57 | H38: 100.96 | I38: 64.17 | J38: 179.19 | K38: 4.94 | L38: 318.94 | M38: 21.39 | N38: 549.07 | O38: 549.08 | P38: 0.01 | Q38: 85.56 | R38: 42.78 | S38: 157.08 | T38: 336.26 | U38: 85.57 | V38: -7.78 | W38: 42.78 | X38: 149.75 | Y38: 278.07 | Z38: 85.56 | AA38: 21.39 | AB38: 0 | AC38: 0 | AD38: =SUM(D38:AA38) -> 4246.84
B39: ISSC Team | C39: Variable | D39: 0 | E39: 0 | F39: 0 | G39: 0 | H39: 0 | I39: 0 | J39: 0 | K39: 0 | L39: 0 | M39: 0 | N39: 0 | O39: 0 | P39: 0 | Q39: 0 | R39: 0 | S39: 0 | T39: 0 | U39: 0 | V39: 0 | W39: 0 | X39: 0 | Y39: 0 | Z39: 0 | AD39: =SUM(D39:AA39) -> 0
B40: Motor Car Expenses | C40: Variable | D40: 198.46 | E40: -138.76 | F40: 2.5 | G40: 74.97 | H40: 0 | I40: 0 | J40: 0 | K40: 0 | L40: 0 | M40: 0 | N40: 0 | O40: 0 | P40: 0 | Q40: 0 | R40: 0 | S40: 0 | T40: 543.23 | U40: 0 | V40: 0 | W40: 0 | X40: 0 | Y40: 0 | Z40: 0 | AA40: 0 | AB40: 0 | AC40: 0 | AD40: =SUM(D40:AA40) -> 680.4
B41: Entertainment | C41: Variable | D41: 0 | E41: 0 | F41: 0 | G41: 0 | H41: 0 | I41: 0 | J41: 0 | K41: 0 | L41: 0 | M41: 0 | N41: 0 | O41: 0 | P41: 0 | Q41: 0 | R41: 0 | S41: 40.53 | T41: 56.99 | U41: 0 | V41: 0 | W41: 0 | X41: 0 | Y41: 0 | Z41: 0 | AA41: 0 | AB41: 0 | AC41: 0 | AD41: =SUM(D41:AA41) -> 97.52
B42: Printing & Stationery | C42: Variable | D42: 13.62 | E42: 121.09 | F42: 12.01 | G42: 360.33 | H42: 33.67 | I42: 40.88 | J42: 27.24 | K42: 204.44 | L42: 197.47 | M42: 13.62 | N42: 319.38 | O42: 321.18 | P42: 5.94 | Q42: 49.12 | R42: 25.44 | S42: 84.6 | T42: 13.62 | U42: 43.68 | V42: 11.82 | W42: 25.44 | X42: 82.79 | Y42: 160.98 | Z42: 43.72 | AA42: 13.62 | AB42: 0 | AC42: 0 | AD42: =SUM(D42:AA42) -> 2225.7
B43: Postage & Courier | C43: Variable | D43: 0.79 | E43: 8.72 | F43: 0.8 | G43: 23.86 | H43: 2.38 | I43: 2.38 | J43: 1.58 | K43: 11.89 | L43: 13.49 | M43: 0.79 | N43: 21.41 | O43: 21.41 | P43: 0.79 | Q43: 3.18 | R43: 1.58 | S43: 5.56 | T43: 0.79 | U43: 3.16 | V43: 0.79 | W43: 1.58 | X43: 5.53 | Y43: 10.31 | Z43: 3.18 | AA43: 0.79 | AB43: 0 | AC43: 0 | AD43: =SUM(D43:AA43) -> 146.74
B44: Corporate Membership & Subscriptions | C44: Variable | D44: 0 | E44: 0 | F44: 0 | G44: 0 | H44: 0 | I44: 0 | J44: 0 | K44: 0 | L44: 0 | M44: 0 | N44: 0 | O44: 0 | P44: 0 | Q44: 0 | R44: 0 | S44: 0 | T44: 0 | U44: 0 | V44: 0 | W44: 0 | X44: 0 | Y44: 0 | Z44: 0 | AA44: 0 | AB44: 0 | AC44: 0 | AD44: =SUM(D44:AA44) -> 0
B45: Audit Fee | C45: Fixed | D45: =(146902/31)/86.21 -> 54.967802 | E45: =(146902/31)/86.21 -> 54.967802 | F45: =(146902/31)/86.21 -> 54.967802 | G45: =(146902/31)/86.21 -> 54.967802 | H45: =(146902/31)/86.21 -> 54.967802 | I45: =(146902/31)/86.21 -> 54.967802 | J45: =(146902/31)/86.21 -> 54.967802 | K45: =(146902/31)/86.21 -> 54.967802 | ... Z45: =(146902/31)/86.21 -> 54.967802 | AA45: 54.967802 | AB45: 0 | AC45: 0 | AD45: =SUM(D45:AA45) -> 1319.2272
B46: Taxation Service Fees | C46: Fixed | D46: 0.96 | E46: 10.52 | F46: 0.95 | G46: 28.52 | H46: 2.85 | I46: 2.87 | J46: 1.93 | K46: 14.33 | L46: 16.24 | M46: 0.96 | N46: 25.8 | O46: 25.81 | P46: 0.96 | Q46: 3.82 | R46: 1.93 | S46: 6.68 | T46: 0.96 | U46: 3.84 | V46: 0.96 | W46: 1.93 | X46: 6.69 | Y46: 12.42 | Z46: 3.82 | AA46: 0.96 | AB46: 0 | AC46: 0 | AD46: =SUM(D46:AA46) -> 176.71
B47: Legal Fees | C47: Variable | D47: 0 | E47: 0 | F47: 0 | G47: 0 | H47: 0 | I47: 0 | J47: 0 | K47: 0 | L47: 0 | M47: 0 | N47: 0 | O47: 0 | P47: 0 | Q47: 0 | R47: 0 | S47: 0 | T47: 0 | U47: 0 | V47: 0 | W47: 0 | X47: 0 | Y47: 0 | Z47: 0 | AA47: 0 | AB47: 0 | AC47: 0 | AD47: =SUM(D47:AA47) -> 0
B48: Professional Fees | C48: Variable | D48: 4.47 | E48: 49.04 | F48: 4.45 | G48: 133.63 | H48: 13.37 | I48: 13.37 | J48: 8.93 | K48: 66.86 | L48: 75.78 | M48: 4.47 | N48: 120.36 | O48: 120.37 | P48: 4.47 | Q48: 17.83 | R48: 8.93 | S48: 31.2 | T48: 4.47 | U48: 17.85 | V48: 4.47 | W48: 8.93 | X48: 31.21 | Y48: 57.95 | Z48: 17.83 | AA48: 4.47 | AB48: 0 | AC48: 0 | AD48: =SUM(D48:AA48) -> 824.71
B49: Compliance Costs, Licence Fees & Certification | C49: Variable | D49: 0 | E49: 0 | F49: 0 | G49: 0 | H49: 0 | I49: 0 | J49: 0 | K49: 0 | L49: 0 | M49: 0 | N49: 0 | O49: 0 | P49: 0 | Q49: 0 | R49: 0 | S49: 0 | T49: 0 | U49: 0 | V49: 0 | W49: 0 | X49: 0 | Y49: 0 | Z49: 0 | AA49: 0 | AB49: 0 | AC49: 0 | AD49: =SUM(D49:AA49) -> 0
B50: Sundry Expenses | C50: Variable | D50: 0 | E50: 0 | F50: 0 | G50: 0 | H50: 0 | I50: 0 | J50: 0 | K50: 0 | L50: 0 | M50: 0 | N50: 0 | O50: 0 | P50: 0 | Q50: 0 | R50: 0 | S50: 0 | T50: 0 | U50: 0 | V50: 0 | W50: 0 | X50: 0 | Y50: 0 | Z50: 0 | AA50: 0 | AB50: 0 | AC50: 0 | AD50: =SUM(D50:AA50) -> 0
B51: Intra-group IT Cost Recharges | C51: Variable | D51: 0 | E51: 0 | F51: 0 | G51: 0 | H51: 0 | I51: 0 | J51: 0 | K51: 0 | L51: 0 | M51: 0 | N51: 0 | O51: 0 | P51: 0 | Q51: 0 | R51: 0 | S51: 0 | T51: 0 | U51: 0 | V51: 0 | W51: 0 | X51: 0 | Y51: 0 | Z51: 0 | AA51: 0 | AB51: 0 | AC51: 0 | AD51: =SUM(D51:AA51) -> 0
B52: Intra-group Administrative Cost Recharges | C52: Variable | D52: 0 | E52: 0 | F52: 0 | G52: 0 | H52: 0 | I52: 0 | J52: 0 | K52: 0 | L52: 0 | M52: 0 | N52: 0 | O52: 0 | P52: 0 | Q52: 0 | R52: 0 | S52: 0 | T52: 0 | U52: 0 | V52: 0 | W52: 0 | X52: 0 | Y52: 0 | Z52: 0 | AA52: 0 | AB52: 0 | AC52: 0 | AD52: =SUM(D52:AA52) -> 0
AD53: =SUM(AD31:AD52) -> 29746.807
A54: D | B54: FINANCIAL EXPENSES
B55: Loan Expenses | C55: Fixed | D55: 0 | E55: 0 | F55: 0 | G55: 0 | H55: 0 | I55: 0 | J55: 0 | K55: 0 | L55: 0 | M55: 0 | N55: 0 | O55: 0 | P55: 0 | Q55: 0 | R55: 0 | S55: 0 | T55: 0 | U55: 0 | V55: 0 | W55: 0 | X55: 0 | Y55: 0 | Z55: 0 | AA55: 0 | AB55: 0 | AC55: 0 | AD55: =SUM(D55:AA55) -> 0
B56: Other Interest Expenses | C56: Fixed | D56: 0 | E56: 0 | F56: 0 | G56: 0 | H56: 0 | I56: 0 | J56: 0 | K56: 0 | L56: 0 | M56: 0 | N56: 0 | O56: 0 | P56: 0 | Q56: 0 | R56: 0 | S56: 0 | T56: 0 | U56: 0 | V56: 0 | W56: 0 | X56: 0 | Y56: 0 | Z56: 0 | AA56: 0 | AB56: 0 | AC56: 0 | AD56: =SUM(D56:AA56) -> 0
B57: Bank Charges | C57: Variable | D57: 0 | E57: 0 | F57: 0 | G57: 0 | H57: 0 | I57: 0 | J57: 0 | K57: 0 | L57: 0 | M57: 0 | N57: 0 | O57: 5.01 | P57: 0 | Q57: 0 | R57: 0 | S57: 0 | T57: 0 | U57: 0 | V57: 0 | W57: 0 | X57: 0 | Y57: -0.01 | Z57: 0 | AA57: 0 | AB57: 0 | AC57: 0 | AD57: =SUM(D57:AA57) -> 5
B58: Exchange Difference | C58: Variable | D58: 0 | E58: 0 | F58: 0 | G58: 0 | H58: 0 | I58: 0 | J58: 0 | K58: 0 | L58: 0 | M58: 0 | N58: 0 | O58: 0 | P58: 0 | Q58: 0 | R58: 0 | S58: 0 | T58: 0 | U58: 0 | V58: 0 | W58: 0 | X58: 0 | Y58: 0 | Z58: 0 | AA58: 0 | AB58: 0 | AC58: 0 | AD58: =SUM(D58:AA58) -> 0
B59: Fair value loss/(gain) on financial instrument/ CCB | C59: Variable | D59: 0 | E59: 0 | F59: 0 | G59: 0 | H59: 0 | I59: 0 | J59: 0 | K59: 0 | L59: 0 | M59: 0 | N59: 0 | O59: 0 | P59: 0 | Q59: 0 | R59: 0 | S59: 0 | T59: 0 | U59: 0 | V59: 0 | W59: 0 | X59: 0 | Y59: 0 | Z59: 0 | AA59: 0 | AB59: 0 | AC59: 0 | AD59: =SUM(D59:AA59) -> 0
AD60: =SUM(AD55:AD59) -> 5
A61: E | B61: OTHER OPERATING EXPENSES
B62: ESG / Donation (e.g. Humanitarian Funds) | C62: Variable | D62: 0 | E62: 0 | F62: 0 | G62: 0 | H62: 0 | I62: 0 | J62: 0 | K62: 0 | L62: 0 | M62: 0 | N62: 0 | O62: 0 | P62: 0 | Q62: 0 | R62: 0 | S62: 0 | T62: 0 | U62: 0 | V62: 0 | W62: 0 | X62: 0 | Y62: 0 | Z62: 0 | AA62: 0 | AB62: 0 | AC62: 0 | AD62: =SUM(D62:AA62) -> 0
B63: Loss/(Gain) on Disposal of Fixed Assets | C63: Variable | D63: 0 | E63: 0 | F63: 0 | G63: 0 | H63: 0 | I63: 0 | J63: 0 | K63: 0 | L63: 0 | M63: 0 | N63: 0 | O63: 0 | P63: 0 | Q63: 0 | R63: 0 | S63: 0 | T63: 0 | U63: 0 | V63: 0 | W63: 0 | X63: 0 | Y63: 0 | Z63: 0 | AA63: 0 | AB63: 0 | AC63: 0 | AD63: =SUM(D63:AA63) -> 0
B64: Depreciation | C64: Fixed | D64: 175 | E64: 1928 | F64: 175 | G64: 5258 | H64: 526 | I64: 526 | J64: 351 | K64: 2629 | L64: 2979 | M64: 175 | N64: 4732 | O64: 4732 | P64: 175 | Q64: 701 | R64: 351 | S64: 1227 | T64: 175 | U64: 701 | V64: 175 | W64: 351 | X64: 1227 | Y64: 2278 | Z64: 701 | AA64: 175.26108 | AB64: 0 | AC64: 0 | AD64: =SUM(D64:AA64) -> 32423.261
B65: Amortisation | C65: Fixed | D65: 0 | E65: 0 | F65: 0 | G65: 0 | H65: 0 | I65: 0 | J65: 0 | K65: 0 | L65: 0 | M65: 0 | N65: 0 | O65: 0 | P65: 0 | Q65: 0 | R65: 0 | S65: 0 | T65: 0 | U65: 0 | V65: 0 | W65: 0 | X65: 0 | Y65: 0 | Z65: 0 | AA65: 0 | AB65: 0 | AC65: 0 | AD65: =SUM(D65:AA65) -> 0
B66: Provision for impairment in value | C66: Variable | D66: 0 | E66: 0 | F66: 0 | G66: 0 | H66: 0 | I66: 0 | J66: 0 | K66: 0 | L66: 0 | M66: 0 | N66: 0 | O66: 0 | P66: 0 | Q66: 0 | R66: 0 | S66: 0 | T66: 0 | U66: 0 | V66: 0 | W66: 0 | X66: 0 | Y66: 0 | Z66: 0 | AA66: 0 | AB66: 0 | AC66: 0 | AD66: =SUM(D66:AA66) -> 0
B67: Provision for Accounts Receivable | C67: Variable | D67: 0 | E67: 0 | F67: 0 | G67: 0 | H67: 0 | I67: 0 | J67: 0 | K67: 0 | L67: 0 | M67: 0 | N67: 0 | O67: 0 | P67: 0 | Q67: 0 | R67: 0 | S67: 0 | T67: 0 | U67: 0 | V67: 0 | W67: 0 | X67: 0 | Y67: 0 | Z67: 0 | AA67: 0 | AB67: 0 | AC67: 0 | AD67: =SUM(D67:AA67) -> 0
B68: Other tax - VAT & GST | C68: Variable | D68: 0 | E68: 0 | F68: 0 | G68: 0 | H68: 0 | I68: 0 | J68: 0 | K68: 0 | L68: 0 | M68: 0 | N68: 0 | O68: 0 | P68: 0 | Q68: 0 | R68: 0 | S68: 0 | T68: 0 | U68: 0 | V68: 0 | W68: 0 | X68: 0 | Y68: 0 | Z68: 0 | AA68: 0 | AB68: 0 | AC68: 0 | AD68: =SUM(D68:AA68) -> 0
B69: Other tax - WHT | C69: Variable | D69: 0 | E69: 0 | F69: 0 | G69: 0 | H69: 0 | I69: 0 | J69: 0 | K69: 0 | L69: 0 | M69: 0 | N69: 0 | O69: 0 | P69: 0 | Q69: 0 | R69: 0 | S69: 0 | T69: 0 | U69: 0 | V69: 0 | W69: 0 | X69: 0 | Y69: 0 | Z69: 0 | AA69: 0 | AB69: 0 | AC69: 0 | AD69: =SUM(D69:AA69) -> 0
AD70: =SUM(AD62:AD69) -> 32423.261
B72: Total Cost (USD) | D72: =SUM(D6:D71) -> 10827.042 | E72: =SUM(E6:E71) -> 26342.79 | F72: =SUM(F6:F71) -> 2510.3816 | G72: =SUM(G6:G71) -> 50880.803 | H72: =SUM(H6:H71) -> 4390.9393 | I72: =SUM(I6:I71) -> 4370.5593 | J72: =SUM(J6:J71) -> 9433.0355 | K72: =SUM(K6:K71) -> 54060.725 | ... AC72: =SUM(AC6:AC71) -> 0 | AD72: =+AD19+AD29+AD53+AD70+AD60 -> 440161.1
C73: Fixed | D73: =ROUND(SUMIF($C$8:$C$69,$C$73,D8:D69)/D72,2) -> 0.71 | E73: =ROUND(SUMIF($C$8:$C$69,$C$73,E8:E69)/E72,2) -> 0.93 | F73: =ROUND(SUMIF($C$8:$C$69,$C$73,F8:F69)/F72,2) -> 0.94 | G73: =ROUND(SUMIF($C$8:$C$69,$C$73,G8:G69)/G72,2) -> 0.91 | H73: =ROUND(SUMIF($C$8:$C$69,$C$73,H8:H69)/H72,2) -> 0.89 | I73: =ROUND(SUMIF($C$8:$C$69,$C$73,I8:I69)/I72,2) -> 0.89 | J73: =ROUND(SUMIF($C$8:$C$69,$C$73,J8:J69)/J72,2) -> 0.95 | K73: =ROUND(SUMIF($C$8:$C$69,$C$73,K8:K69)/K72,2) -> 0.95 | ... AA73: =ROUND(SUMIF($C$8:$C$69,$C$73,AA8:AA69)/AA72,2) -> 0.9 | AD73: =ROUND(SUMIF($C$8:$C$69,$C$73,AD8:AD69)/AD72,2) -> 0.91
C74: Variable | D74: =ROUND(SUMIF($C$8:$C$69,$C$74,D8:D69)/D72,2) -> 0.29 | E74: =ROUND(SUMIF($C$8:$C$69,$C$74,E8:E69)/E72,2) -> 0.07 | F74: =ROUND(SUMIF($C$8:$C$69,$C$74,F8:F69)/F72,2) -> 0.06 | G74: =ROUND(SUMIF($C$8:$C$69,$C$74,G8:G69)/G72,2) -> 0.09 | H74: =ROUND(SUMIF($C$8:$C$69,$C$74,H8:H69)/H72,2) -> 0.11 | I74: =ROUND(SUMIF($C$8:$C$69,$C$74,I8:I69)/I72,2) -> 0.11 | J74: =ROUND(SUMIF($C$8:$C$69,$C$74,J8:J69)/J72,2) -> 0.05 | K74: =ROUND(SUMIF($C$8:$C$69,$C$74,K8:K69)/K72,2) -> 0.05 | ... AA74: =ROUND(SUMIF($C$8:$C$69,$C$74,AA8:AA69)/AA72,2) -> 0.1 | AD74: =ROUND(SUMIF($C$8:$C$69,$C$74,AD8:AD69)/AD72,2) -> 0.09
B77: Headcount | D77: 1 | E77: 11 | F77: 1 | G77: 30 | H77: 3 | I77: 3 | J77: 2 | K77: 15 | L77: 17 | M77: 1 | N77: 27 | O77: 27 | P77: 1 | Q77: 4 | R77: 2 | S77: 7 | T77: 1 | U77: 4 | V77: 1 | W77: 2 | X77: 7 | Y77: 13 | Z77: 4 | AA77: 1 | AD77: =SUM(D77:AA77) -> 185
B78: Average Salaries and Wages per employee | D78: =(+D8+D9+D10+D11)/D77 -> 7231.72 | E78: =(+E8+E9+E10+E11)/E77 -> 1692.5209 | F78: =(+F8+F9+F10+F11)/F77 -> 1864.56 | G78: =(+G8+G9+G10+G11)/G77 -> 1103.0567 | H78: =(+H8+H9+H10+H11)/H77 -> 847.46667 | I78: =(+I8+I9+I10+I11)/I77 -> 853.55667 | J78: =(+J8+J9+J10+J11)/J77 -> 4035.675 | K78: =(+K8+K9+K10+K11)/K77 -> 2993.2367 | ... Z78: =(+Z8+Z9+Z10+Z11)/Z77 -> 1361.11 | AA78: 909.82 | AD78: =(+AD8+AD9+AD10+AD11)/AD77 -> 1701.029
B79: Average Personnel expenses per employee | D79: =SUM(D12:D18)/D77 -> 73.64 | E79: =SUM(E12:E18)/E77 -> 168.53727 | F79: =SUM(F12:F18)/F77 -> 81.11 | G79: =SUM(G12:G18)/G77 -> 81.111333 | H79: =SUM(H12:H18)/H77 -> 73.63 | I79: =SUM(I12:I18)/I77 -> 73.63 | J79: =SUM(J12:J18)/J77 -> 73.635 | K79: =SUM(K12:K18)/K77 -> 75.740667 | ... Z79: =SUM(Z12:Z18)/Z77 -> 73.635 | AA79: 73.64 | AD79: =SUM(AD12:AD18)/AD77 -> 93.014054
B80: Average Office expenses per employee | D80: =SUM(D21:D28)/D77 -> 225.69383 | E80: =SUM(E21:E28)/E77 -> 225.69564 | F80: =SUM(F21:F28)/F77 -> 225.69383 | G80: =SUM(G21:G28)/G77 -> 225.69616 | H80: =SUM(H21:H28)/H77 -> 225.69716 | I80: =SUM(I21:I28)/I77 -> 225.69716 | J80: =SUM(J21:J28)/J77 -> 225.68883 | K80: =SUM(K21:K28)/K77 -> 235.52049 | ... Z80: =SUM(Z21:Z28)/Z77 -> 225.68883 | AA80: 218.89981 | AD80: =SUM(AD21:AD28)/AD77 -> 249.1247
B81: Average IT expenses per employee | D81: =SUM(D31:D34)/D77 -> 68.84 | E81: =SUM(E31:E34)/E77 -> 68.844545 | F81: =SUM(F31:F34)/F77 -> 69.84 | G81: =SUM(G31:G34)/G77 -> 69.850667 | H81: =SUM(H31:H34)/H77 -> 71.87 | I81: =SUM(I31:I34)/I77 -> 68.84 | J81: =SUM(J31:J34)/J77 -> 68.845 | K81: =SUM(K31:K34)/K77 -> 55.283333 | ... Z81: =SUM(Z31:Z34)/Z77 -> 68.845 | AA81: 68.84 | AD81: =SUM(AD31:AD34)/AD77 -> 70.378919
B82: Average Administrative expenses per employee | D82: =SUM(D35:D52)/D77 -> 3052.1478 | E82: =SUM(E35:E52)/E77 -> 63.927982 | F82: =SUM(F35:F52)/F77 -> 94.177802 | G82: =SUM(G35:G52)/G77 -> 41.04526 | H82: =SUM(H35:H52)/H77 -> 69.649267 | I82: =SUM(I35:I52)/I77 -> 59.795934 | J82: =SUM(J35:J52)/J77 -> 137.1739 | K82: =SUM(K35:K52)/K77 -> 69.00052 | ... Z82: =SUM(Z35:Z52)/Z77 -> 52.52195 | AA82: 96.457802 | AD82: =SUM(AD35:AD52)/AD77 -> 90.414634
B83: Average financial and other operative expenses per employee | D83: =(SUM(D62:D69)+SUM(D55:D59))/D77 -> 175 | E83: =(SUM(E62:E69)+SUM(E55:E59))/E77 -> 175.27273 | F83: =(SUM(F62:F69)+SUM(F55:F59))/F77 -> 175 | G83: =(SUM(G62:G69)+SUM(G55:G59))/G77 -> 175.26667 | H83: =(SUM(H62:H69)+SUM(H55:H59))/H77 -> 175.33333 | I83: =(SUM(I62:I69)+SUM(I55:I59))/I77 -> 175.33333 | J83: =(SUM(J62:J69)+SUM(J55:J59))/J77 -> 175.5 | K83: =(SUM(K62:K69)+SUM(K55:K59))/K77 -> 175.26667 | ... Z83: =(SUM(Z62:Z69)+SUM(Z55:Z59))/Z77 -> 175.25 | AA83: 175.26108 | AD83: =(SUM(AD62:AD69)+SUM(AD55:AD59))/AD77 -> 175.2879
B84: Average TOTAL expenses per employee | D84: =+D72/D77 -> 10827.042 | E84: =+E72/E77 -> 2394.7991 | F84: =+F72/F77 -> 2510.3816 | G84: =+G72/G77 -> 1696.0268 | H84: =+H72/H77 -> 1463.6464 | I84: =+I72/I77 -> 1456.8531 | J84: =+J72/J77 -> 4716.5177 | K84: =+K72/K77 -> 3604.0483 | ... Z84: =+Z72/Z77 -> 1957.0508 | AA84: 1542.9187 | AD84: =+AD72/AD77 -> 2379.2492
B86: Personnal Expenses % of overall ISSC cost | D86: =SUM(D8:D16)/D72 -> 0.67473279 | E86: =SUM(E8:E16)/E72 -> 0.77712498 | F86: =SUM(F8:F16)/F72 -> 0.77504949 | G86: =SUM(G8:G16)/G72 -> 0.69820125 | H86: =SUM(H8:H16)/H72 -> 0.62931638 | I86: =SUM(I8:I16)/I72 -> 0.63643113 | J86: =SUM(J8:J16)/J72 -> 0.87125931 | K86: =SUM(K8:K16)/K72 -> 0.85153612 | ... Z86: =SUM(Z8:Z16)/Z72 -> 0.73311588 | AA86: 0.63740235 | AD86: =SUM(AD8:AD16)/AD72 -> 0.75403747
B87: Other Personnel expenses as % Salaries and Wages | D87: =+D79/D78 -> 0.010182916 | E87: =+E79/E78 -> 0.099577661 | F87: =+F79/F78 -> 0.04350088 | G87: =+G79/G78 -> 0.073533242 | H87: =+H79/H78 -> 0.086882473 | I87: =+I79/I78 -> 0.08626258 | J87: =+J79/J78 -> 0.018246018 | K87: =+K79/K78 -> 0.025303935 | ... Z87: =+Z79/Z78 -> 0.054099228 | AA87: 0.080939087 | AD87: =+AD79/AD78 -> 0.054681052
B88: Office expenses as % Salaries and Wages | D88: =+D80/D78 -> 0.031208872 | E88: =+E80/E78 -> 0.13334881 | F88: =+F80/F78 -> 0.12104401 | G88: =+G80/G78 -> 0.20460976 | H88: =+H80/H78 -> 0.26631981 | I88: =+I80/I78 -> 0.26441965 | J88: =+J80/J78 -> 0.055923439 | K88: =+K80/K78 -> 0.07868422 | ... Z88: =+Z80/Z78 -> 0.16581233 | AA88: 0.24059684 | AD88: =+AD80/AD78 -> 0.1464553
B89: IT as % Salaries and Wages | D89: =+D81/D78 -> 0.0095191739 | E89: =+E81/E78 -> 0.040675743 | F89: =+F81/F78 -> 0.037456558 | G89: =+G81/G78 -> 0.06332464 | H89: =+H81/H78 -> 0.084805695 | I89: =+I81/I78 -> 0.080650767 | J89: =+J81/J78 -> 0.017059104 | K89: =+K81/K78 -> 0.018469416 | ... Z89: =+Z81/Z78 -> 0.050580041 | AA89: 0.075663318 | AD89: =+AD81/AD78 -> 0.041374321
B90: Administrative expenses as % of Salaries and Wages | D90: =+D82/D78 -> 0.42205005 | E90: =+E82/E78 -> 0.037770867 | F90: =+F82/F78 -> 0.050509397 | G90: =+G82/G78 -> 0.037210473 | H90: =+H82/H78 -> 0.082185259 | I90: =+I82/I78 -> 0.070055025 | J90: =+J82/J78 -> 0.033990324 | K90: =+K82/K78 -> 0.023052143 | ... Z90: =+Z82/Z78 -> 0.038587587 | AA90: 0.10601856 | AD90: =+AD82/AD78 -> 0.053152906
B91: Financial and other operative as % of Salaries and Wages | D91: =+D83/D78 -> 0.024198946 | E91: =+E83/E78 -> 0.1035572 | F91: =+F83/F78 -> 0.093855923 | G91: =+G83/G78 -> 0.15889181 | H91: =+H83/H78 -> 0.20689113 | I91: =+I83/I78 -> 0.20541499 | J91: =+J83/J78 -> 0.043487149 | K91: =+K83/K78 -> 0.058554229 | ... Z91: =+Z83/Z78 -> 0.12875521 | AA91: 0.1926327 | AD91: =+AD83/AD78 -> 0.10304816
B92: TOTAL expenses except Salaries and Wages as % Salaries and Wages | D92: =SUM(D79:D83)/D78 -> 0.49715996 | E92: =SUM(E79:E83)/E78 -> 0.41493028 | F92: =SUM(F79:F83)/F78 -> 0.34636677 | G92: =SUM(G79:G83)/G78 -> 0.53756992 | H92: =SUM(H79:H83)/H78 -> 0.72708436 | I92: =SUM(I79:I83)/I78 -> 0.70680302 | J92: =SUM(J79:J83)/J78 -> 0.16870603 | K92: =SUM(K79:K83)/K78 -> 0.20406394 | ... Z92: =SUM(Z79:Z83)/Z78 -> 0.4378344 | AA92: 0.69585049 | AD92: =SUM(AD79:AD83)/AD78 -> 0.39871173
A95: 45689 | B95: February, 2025
B97: Business Unit Name | D97: Crew Management | E97: Cruise Management | F97: Accounts | G97: Accounts | H97: Admin | I97: Agency Services | J97: Commercial | K97: Consultancy Services | L97: Environmental Compliance | M97: Environmental Compliance | N97: IT | O97: Procurement | P97: Procurement | Q97: Ship Management | R97: Ship Management | S97: Ship Management | T97: Ship Management | U97: Ship Management | V97: Ship Management | W97: Ship Management | X97: Ship Management | Y97: Ship Management | Z97: Ship Management | AA97: Technical Services | AB97: Ship Management | AC97: Ship Management | AD97: Actual
B98: Division Name | D98: Group Marine HR | E98: Miami Ship Management | F98: CMI Accounts Payables | G98: Fleet Accounts | H98: Administration | I98: Agency Hub | J98: Commercial | K98: Fleet Performance | L98: Carbon Emission Services | M98: Other Environmental Compliance | N98: Group IT | O98: Galleymasters | P98: Sourcing | Q98: Antwerp Dry | R98: Goes Dry | S98: Group Operations | T98: Group Shared Service Center | U98: Hamburg Dry | V98: Hong Kong Dry 1 | W98: JV Ardmore | X98: Singapore Dry | Y98: Singapore Tanker 1 | Z98: Singapore Tanker 2 | AA98: AE Technical Services | AB98: Hong Kong Dry 2 | AC98: Hong Kong Dry 3 | AD98: Total
A100: A | B100: PERSONNEL EXPENSES
B101: Salaries & Wages | C101: =VLOOKUP(B101,$B$8:$C$69,2,0) -> Fixed | D101: 6696.27 | E101: 17506.92 | F101: 1755.28 | G101: 29960.69 | H101: 2368.32 | I101: 2804.64 | J101: 7490.98 | K101: 42352.58 | L101: 19178.81 | M101: 4884.42 | N101: 38754.56 | O101: 21720.47 | P101: 3654.35 | Q101: 12043.42 | R101: 1386.01 | S101: 14964.12 | T101: 7519.45 | U101: 3699.95 | V101: 1735.64 | W101: 6581.46 | X101: 17549 | Y101: 26893.36 | Z101: 4800.33 | AA101: 974.37 | AB101: 526.08 | AC101: 505.62 | AD101: =SUM(D101:AC101) -> 298307.1
B102: Provision for Bonus, Leave & Other Employment Costs | C102: =VLOOKUP(B102,$B$8:$C$69,2,0) -> Fixed | D102: 494.8 | E102: 1287.32 | F102: 129.26 | G102: 2253.55 | H102: 175.29 | I102: 191.92 | J102: 553.23 | K102: 3152.13 | L102: 703.22 | M102: 179.1 | N102: 2851.38 | O102: 1630.03 | P102: 269.11 | Q102: 633.66 | R102: 83.76 | S102: 1112.55 | T102: 95.96 | U102: 381.68 | V102: 127.8 | W102: 456.13 | X102: 1265.22 | Y102: 1825.37 | Z102: 629.38 | AA102: 35.73 | AB102: 19.29 | AC102: 18.54 | AD102: =SUM(D102:AC102) -> 20555.41
B103: Consultants & Contractors | C103: =VLOOKUP(B103,$B$8:$C$69,2,0) -> Fixed | D103: 0 | E103: 0 | F103: 0 | G103: 0 | H103: 0 | I103: 0 | J103: 0 | K103: 0 | L103: 0 | M103: 0 | N103: 4522.04 | O103: 0 | P103: 0 | Q103: 0 | R103: 0 | S103: 341.71 | T103: 0 | U103: 0 | V103: 0 | W103: 0 | X103: 0 | Y103: 0 | Z103: 0 | AA103: 4367.46 | AB103: 0 | AC103: 0 | AD103: =SUM(D103:AC103) -> 9231.21
B104: Pension Fund & Social Securities | C104: =VLOOKUP(B104,$B$8:$C$69,2,0) -> Fixed | D104: 463.4 | E104: 1085.27 | F104: 102.02 | G104: 1874.8 | H104: 138.7 | I104: 166.86 | J104: 506.81 | K104: 2857.81 | L104: 1340.33 | M104: 367.25 | N104: 2535.94 | O104: 1354.02 | P104: 253.48 | Q104: 833.57 | R104: 83.97 | S104: 994.57 | T104: 537.34 | U104: 205.62 | V104: 100.88 | W104: 451.08 | X104: 1164.1 | Y104: 1800.15 | Z104: 244.45 | AA104: 61.76 | AB104: 34.07 | AC104: 32.46 | AD104: =SUM(D104:AC104) -> 19590.71
B105: Staff Allowances & Benefits | C105: =VLOOKUP(B105,$B$8:$C$69,2,0) -> Fixed | D105: 30.45 | E105: 1481.27 | F105: 26.63 | G105: 772.23 | H105: 91.35 | I105: 121.81 | J105: 60.89 | K105: 456.74 | L105: 456.74 | M105: 30.45 | N105: 822.1 | O105: 822.14 | P105: 30.45 | Q105: 182.7 | R105: 60.89 | S105: 213.16 | T105: 30.45 | U105: 121.8 | V105: 30.45 | W105: 60.89 | X105: 243.62 | Y105: 453.18 | Z105: 121.81 | AA105: 30.45 | AB105: 60.89 | AC105: 30.45 | AD105: =SUM(D105:AC105) -> 6843.99
B106: Staff Recruitment / Relocation | C106: =VLOOKUP(B106,$B$8:$C$69,2,0) -> Variable | D106: 0 | E106: 0 | F106: 0 | G106: 0 | H106: 0 | I106: 0 | J106: 0 | K106: 49.29 | L106: 0 | M106: 0 | N106: 0 | O106: 0 | P106: 0 | Q106: 90.85 | R106: 0 | S106: 0 | T106: 0 | U106: 0 | V106: 0 | W106: 0 | X106: 10.32 | Y106: 74.51 | Z106: 10.32 | AA106: 0 | AB106: 20.63 | AC106: 0 | AD106: =SUM(D106:AC106) -> 255.92
B107: Staff Functions | C107: =VLOOKUP(B107,$B$8:$C$69,2,0) -> Variable | D107: 0 | E107: 0.71 | F107: -0.95 | G107: -27.53 | H107: 0.19 | I107: 30.65 | J107: 0.14 | K107: 0.96 | L107: -59.83 | M107: 1261.02 | N107: 1.63 | O107: 1.72 | P107: 0.07 | Q107: 61.17 | R107: 0.14 | S107: 0.45 | T107: 0.07 | U107: 0.26 | V107: 0.07 | W107: 0.14 | X107: 30.9 | Y107: 0.83 | Z107: 0.25 | AA107: 0.07 | AB107: 60.92 | AC107: 30.46 | AD107: =SUM(D107:AC107) -> 1394.51
B108: Course & Training | C108: Variable | D108: 0 | E108: 0 | F108: 0 | G108: 0 | H108: 0 | I108: 0 | J108: 0 | K108: 0 | L108: 0 | M108: 0 | N108: 0 | O108: 0 | P108: 0 | Q108: 0 | R108: 0 | S108: 0 | T108: 0 | U108: 0 | V108: 0 | W108: 0 | X108: 0 | Y108: 0 | Z108: 0 | AA108: 0 | AB108: 0 | AC108: 0 | AD108: =SUM(D108:AC108) -> 0
AD109: =SUM(AD101:AD108) -> 356178.85
...

Sheet ISSC spend kpi
A1: Months | B1: Category 1 | C1: Head counts | D1: 1. Total ISSC Spend | E1: 2. Spend vs. Budget Variance | F1: 3. Fixed vs. Variable Cost Ratio | G1: 4. Cost Per FTE (Desk Cost) | H1: Category 2 | I1: 1. Employee Cost as % of Total ISSC Spend | J1: 2. Training Cost per Employee | K1: Category 3 | L1: 1. IT Spend as % of Total ISSC Spend | M1: Category 4 | N1: 1. Total Facility Spend | O1: 2. Facility Spend as % of Total Spend | P1: 3. Average Cost per Employee | Q1: 4. Space Utilization | R1: 5. Admin Cost per FTE | S1: Category 5 | T1: 1. Travel Spend per Employee | U1: 2. Overall Travel Cost | V1: 3.Travel Cost as % of Total ISSC Spend
A3: 45658 | B3: Overall Cost Insights | C3: =+'SSC Recharge Summary'!AD77 -> 185 | D3: =+'SSC Recharge Summary'!AD72 -> 440161.1 | E3: =+D3-'P& L budget 2025'!MB259 -> 1805.5196 | F3: ='SSC Recharge Summary'!AD73&" "&":"&" "&'SSC Recharge Summary'!AD74 -> 0.91 : 0.09 | G3: =D3/C3 -> 2379.2492 | H3: Employee-Related Costs | I3: =SUM('SSC Recharge Summary'!AD8:AD18)/D3 -> 0.75403747 | J3: - | K3: IT & Technology Costs | L3: {=SUM('SSC Recharge Summary'!AD31:AD34/'ISSC spend kpi'!D3)} -> 0.029580306 | M3: Facility & Office Costs | N3: =SUM('SSC Recharge Summary'!AD21:AD28) -> 46088.07 | O3: =N3/D3 -> 0.10470728 | P3: =N3/C3 -> 249.1247 | Q3: - | R3: =SUM('SSC Recharge Summary'!AD35:AD52)/C3 -> 90.414634 | S3: Travel and Transportation Costs | T3: =SUM('SSC Recharge Summary'!AD37:AD38)/C3 -> 59.970973 | U3: =SUM('SSC Recharge Summary'!AD37:AD38) -> 11094.63 | V3: ='[1]ISSC Spend_KPI''s'!$F$27 -> 0.02520584
A4: 45689 | B4: Overall Cost Insights | C4: =+'SSC Recharge Summary'!AD154 -> 189 | D4: =+'SSC Recharge Summary'!AD149 -> 448023.2 | H4: Employee-Related Costs | K4: IT & Technology Costs | L4: {=SUM('SSC Recharge Summary'!AD121:AD123/D4)} -> 0.026190496 | M4: Facility & Office Costs | S4: Travel and Transportation Costs
A5: 45717 | B5: Overall Cost Insights | H5: Employee-Related Costs | K5: IT & Technology Costs | M5: Facility & Office Costs | S5: Travel and Transportation Costs
A6: 45748 | B6: Overall Cost Insights | H6: Employee-Related Costs | K6: IT & Technology Costs | M6: Facility & Office Costs | S6: Travel and Transportation Costs
A7: 45778 | B7: Overall Cost Insights | H7: Employee-Related Costs | K7: IT & Technology Costs | M7: Facility & Office Costs | S7: Travel and Transportation Costs
A8: 45809 | B8: Overall Cost Insights | H8: Employee-Related Costs | K8: IT & Technology Costs | M8: Facility & Office Costs | S8: Travel and Transportation Costs
A9: 45839 | B9: Overall Cost Insights | H9: Employee-Related Costs | K9: IT & Technology Costs | M9: Facility & Office Costs | S9: Travel and Transportation Costs
A10: 45870 | B10: Overall Cost Insights | H10: Employee-Related Costs | K10: IT & Technology Costs | M10: Facility & Office Costs | S10: Travel and Transportation Costs
A11: 45901 | B11: Overall Cost Insights | H11: Employee-Related Costs | K11: IT & Technology Costs | M11: Facility & Office Costs | S11: Travel and Transportation Costs
A12: 45931 | B12: Overall Cost Insights | H12: Employee-Related Costs | K12: IT & Technology Costs | M12: Facility & Office Costs | S12: Travel and Transportation Costs
A13: 45962 | B13: Overall Cost Insights | H13: Employee-Related Costs | K13: IT & Technology Costs | M13: Facility & Office Costs | S13: Travel and Transportation Costs
A14: 45992 | B14: Overall Cost Insights | H14: Employee-Related Costs | K14: IT & Technology Costs | M14: Facility & Office Costs | S14: Travel and Transportation Costs

Sheet P& L budget 2025
B1: ANGLO-EASTERN MARITIME SERVICES PRIVATE LIMITED | P1: =+P6 -> Budget-2025 | AD1: =+AD6 -> Budget-2025 | AR1: =+AR6 -> Budget-2025 | BF1: =+BF6 -> Budget-2025 | BT1: =+BT6 -> #REF! | CH1: =+CH6 -> #REF! | CV1: =+CV6 -> #REF! | DJ1: =+DJ6 -> #REF! | DX1: =+DX6 -> #REF! | EL1: =+EL6 -> #REF! | EZ1: =+EZ6 -> #REF! | FN1: =+FN6 -> #REF! | GB1: =+GB6 -> #REF! | GP1: =+GP6 -> #REF! | HD1: =+HD6 -> Total | HR1: =+HR6 -> #REF! | IF1: =+IF6 -> #REF! | IT1: =+IT6 -> #REF! | JH1: =+JH6 -> #REF! | JV1: =+JV6 -> #REF! | KJ1: =+KJ6 -> #REF! | KX1: =+KX6 -> Total | LL1: =+LL6 -> Total | LZ1: =+LZ6 -> Total | MB1: =+LZ1 -> Total | MC1: =+MB1 -> Total | MD1: =+MC1 -> Total | ME1: =+MD1 -> Total | MF1: =+ME1 -> Total | MG1: =+MF1 -> Total | MH1: =+MG1 -> Total | MI1: =+MH1 -> Total | MJ1: =+MI1 -> Total | ... MN1: =+MM1 -> Total
B2: Budget 2025 | P2: 1 | AD2: 2 | AR2: 3 | BF2: 4 | BT2: 6 | CH2: 8 | CV2: 11 | DJ2: 12 | DX2: 13 | EL2: 14 | EZ2: 15 | FN2: 16 | GB2: 17 | GP2: 19 | HD2: 30 | HR2: 20 | IF2: 21 | IT2: 22 | JH2: 23 | JV2: 24 | KJ2: 25 | KX2: 28 | LL2: 29 | LZ2: 31
B3: BU | D3: Accounts | P3: =+D3 -> Accounts | R3: Admin | AD3: =+R3 -> Admin | AF3: Agency Services | AR3: =AF3 -> Agency Services | AT3: Commercial | BF3: =AT3 -> Commercial | BH3: Consultancy Services | BT3: =+BH3 -> Consultancy Services | BV3: Crew Management | CH3: =+BV3 -> Crew Management | CJ3: Cruise Management | CV3: =+CJ3 -> Cruise Management | CX3: IT | DJ3: =+CX3 -> IT | DL3: Procurement | DX3: =+DL3 -> Procurement | DZ3: Procurement | EL3: =+DZ3 -> Procurement | EN3: Ship Management | EZ3: =+EN3 -> Ship Management | FB3: Ship Management | FN3: =+FB3 -> Ship Management | FP3: Ship Management | GB3: =+FP3 -> Ship Management | GD3: Ship Management | GP3: =+GD3 -> Ship Management | GR3: Vacant Seats | HD3: =+GR3 -> Vacant Seats | HF3: Ship Management | HR3: =+HF3 -> Ship Management | HT3: Ship Management | IF3: =+HT3 -> Ship Management | IH3: Ship Management | IT3: =+IH3 -> Ship Management | IV3: Ship Management | JH3: =+IV3 -> Ship Management | JJ3: Ship Management | JV3: =+JJ3 -> Ship Management | JX3: Ship Management | KJ3: =+JX3 -> Ship Management | KL3: Accounts | KX3: =+KL3 -> Accounts | KZ3: Accounts | LL3: =+KZ3 -> Accounts | LZ3: =+LN3 -> 0 | MB3: =LN6 -> 45688 | MC3: =LO6 -> 45716 | MD3: =LP6 -> 45747 | ME3: =LQ6 -> 45777 | MF3: =LR6 -> 45808 | MG3: =LS6 -> 45838 | MH3: =LT6 -> 45869 | MI3: =LU6 -> 45900 | ... MN3: =LZ6 -> Total
B4: Division | D4: Fleet Accounts | P4: =+D4 -> Fleet Accounts | R4: Administration | AD4: =+R4 -> Administration | AF4: Agency Hub | AR4: =AF4 -> Agency Hub | AT4: Commercial | BF4: =AT4 -> Commercial | BH4: Fleet Performance | BT4: =+BH4 -> Fleet Performance | BV4: Group Marine HR | CH4: =+BV4 -> Group Marine HR | CJ4: Miami Ship Management | CV4: =+CJ4 -> Miami Ship Management | CX4: Group IT | DJ4: =+CX4 -> Group IT | DL4: Galleymasters | DX4: =+DL4 -> Galleymasters | DZ4: Sourcing | EL4: =+DZ4 -> Sourcing | EN4: Antwerp Dry | EZ4: =+EN4 -> Antwerp Dry | FB4: Goes Dry | FN4: =+FB4 -> Goes Dry | FP4: Group Operations | GB4: =+FP4 -> Group Operations | GD4: Group Shared Service Center | GP4: =+GD4 -> Group Shared Service Center | GR4: Vacant Seats | HD4: =+GR4 -> Vacant Seats | HF4: Hamburg Dry | HR4: =+HF4 -> Hamburg Dry | HT4: Hong Kong Dry 1 | IF4: =+HT4 -> Hong Kong Dry 1 | IH4: JV Ardmore | IT4: =+IH4 -> JV Ardmore | IV4: Singapore Dry | JH4: =+IV4 -> Singapore Dry | JJ4: Singapore Tanker 1 | JV4: =+JJ4 -> Singapore Tanker 1 | JX4: Singapore Tanker 2 | KJ4: =+JX4 -> Singapore Tanker 2 | KL4: Accounts Payables | KX4: =+KL4 -> Accounts Payables | KZ4: CMI Accounts Payables | LL4: =+KZ4 -> CMI Accounts Payables | LZ4: =+LN4 -> 0 | MB4: All Divisions | MC4: =MB4 -> All Divisions | MD4: =MC4 -> All Divisions | ME4: =MD4 -> All Divisions | MF4: =ME4 -> All Divisions | MG4: =MF4 -> All Divisions | MH4: =MG4 -> All Divisions | MI4: =MH4 -> All Divisions | MJ4: =MI4 -> All Divisions | ... MN4: =MM4 -> All Divisions
B5: Amount (INR) | D5: INR | E5: INR | F5: INR | G5: INR | H5: INR | I5: INR | J5: INR | K5: INR | L5: INR | M5: INR | N5: INR | O5: INR | P5: INR | R5: INR | S5: INR | T5: INR | U5: INR | V5: INR | W5: INR | X5: INR | Y5: INR | Z5: INR | AA5: INR | AB5: INR | AC5: INR | AD5: INR | AF5: INR | AG5: INR | AH5: INR | AI5: INR | AJ5: INR | AK5: INR | AL5: INR | AM5: INR | AN5: INR | AO5: INR | AP5: INR | AQ5: INR | AR5: INR | AT5: INR | AU5: INR | AV5: INR | AW5: INR | AX5: INR | AY5: INR | AZ5: INR | BA5: INR | BB5: INR | BC5: INR | BD5: INR | BE5: INR | BF5: INR | BH5: INR | BI5: INR | BJ5: INR | BK5: INR | BL5: INR | BM5: INR | BN5: INR | BO5: INR | BP5: INR | BQ5: INR | BR5: INR | BS5: INR | BT5: INR | BV5: INR | BW5: INR | BX5: INR | BY5: INR | BZ5: INR | CA5: INR | CB5: INR | CC5: INR | CD5: INR | CE5: INR | CF5: INR | CG5: INR | CH5: INR | CJ5: INR | CK5: INR | CL5: INR | CM5: INR | CN5: INR | CO5: INR | CP5: INR | CQ5: INR | CR5: INR | CS5: INR | CT5: INR | CU5: INR | CV5: INR | CX5: INR | CY5: INR | CZ5: INR | DA5: INR | DB5: INR | DC5: INR | DD5: INR | DE5: INR | DF5: INR | DG5: INR | DH5: INR | DI5: INR | DJ5: INR | DL5: INR | DM5: INR | DN5: INR | DO5: INR | DP5: INR | DQ5: INR | DR5: INR | DS5: INR | DT5: INR | DU5: INR | DV5: INR | DW5: INR | DX5: INR | DZ5: INR | EA5: INR | EB5: INR | EC5: INR | ED5: INR | EE5: INR | EF5: INR | EG5: INR | EH5: INR | EI5: INR | EJ5: INR | EK5: INR | EL5: INR | EN5: INR | EO5: INR | EP5: INR | EQ5: INR | ER5: INR | ES5: INR | ET5: INR | EU5: INR | EV5: INR | EW5: INR | EX5: INR | EY5: INR | EZ5: INR | FB5: INR | FC5: INR | FD5: INR | FE5: INR | FF5: INR | FG5: INR | FH5: INR | FI5: INR | FJ5: INR | FK5: INR | FL5: INR | FM5: INR | FN5: INR | FP5: INR | FQ5: INR | FR5: INR | FS5: INR | FT5: INR | FU5: INR | FV5: INR | FW5: INR | FX5: INR | FY5: INR | FZ5: INR | GA5: INR | GB5: INR | GD5: INR | GE5: INR | GF5: INR | GG5: INR | GH5: INR | GI5: INR | GJ5: INR | GK5: INR | GL5: INR | GM5: INR | GN5: INR | GO5: INR | GP5: INR | GR5: INR | GS5: INR | GT5: INR | GU5: INR | GV5: INR | GW5: INR | GX5: INR | GY5: INR | GZ5: INR | HA5: INR | HB5: INR | HC5: INR | HD5: INR | HF5: INR | HG5: INR | HH5: INR | HI5: INR | HJ5: INR | HK5: INR | HL5: INR | HM5: INR | HN5: INR | HO5: INR | HP5: INR | HQ5: INR | HR5: INR | HT5: INR | HU5: INR | HV5: INR | HW5: INR | HX5: INR | HY5: INR | HZ5: INR | IA5: INR | IB5: INR | IC5: INR | ID5: INR | IE5: INR | IF5: INR | IH5: INR | II5: INR | IJ5: INR | IK5: INR | IL5: INR | IM5: INR | IN5: INR | IO5: INR | IP5: INR | IQ5: INR | IR5: INR | IS5: INR | IT5: INR | IV5: INR | IW5: INR | IX5: INR | IY5: INR | IZ5: INR | JA5: INR | JB5: INR | JC5: INR | JD5: INR | JE5: INR | JF5: INR | JG5: INR | JH5: INR | JJ5: INR | JK5: INR | JL5: INR | JM5: INR | JN5: INR | JO5: INR | JP5: INR | JQ5: INR | JR5: INR | JS5: INR | JT5: INR | JU5: INR | JV5: INR | JX5: INR | JY5: INR | JZ5: INR | KA5: INR | KB5: INR | KC5: INR | KD5: INR | KE5: INR | KF5: INR | KG5: INR | KH5: INR | KI5: INR | KJ5: INR | KL5: INR | KM5: INR | KN5: INR | KO5: INR | KP5: INR | KQ5: INR | KR5: INR | KS5: INR | KT5: INR | KU5: INR | KV5: INR | KW5: INR | KX5: INR | KZ5: INR | LA5: INR | LB5: INR | LC5: INR | LD5: INR | LE5: INR | LF5: INR | LG5: INR | LH5: INR | LI5: INR | LJ5: INR | LK5: INR | LL5: INR | LN5: INR | LO5: INR | LP5: INR | LQ5: INR | LR5: INR | LS5: INR | LT5: INR | LU5: INR | LV5: INR | LW5: INR | LX5: INR | LY5: INR | LZ5: INR | MB5: INR | MC5: =MB5 -> INR | MD5: =MC5 -> INR | ME5: =MD5 -> INR | MF5: =ME5 -> INR | MG5: =MF5 -> INR | MH5: =MG5 -> INR | MI5: =MH5 -> INR | MJ5: =MI5 -> INR | ... MN5: =MM5 -> INR
B6: Month (2025) | D6: 45688 | E6: 45716 | F6: 45747 | G6: 45777 | H6: 45808 | I6: 45838 | J6: 45869 | K6: 45900 | L6: 45930 | M6: 45961 | N6: 45991 | O6: 46022 | P6: Budget-2025 | R6: 45688 | S6: 45716 | T6: 45747 | U6: 45777 | V6: 45808 | W6: 45838 | X6: 45869 | Y6: 45900 | Z6: 45930 | AA6: 45961 | AB6: 45991 | AC6: 46022 | AD6: =+P6 -> Budget-2025 | AF6: 45688 | AG6: 45716 | AH6: 45747 | AI6: 45777 | AJ6: 45808 | AK6: 45838 | AL6: 45869 | AM6: 45900 | AN6: 45930 | AO6: 45961 | AP6: 45991 | AQ6: 46022 | AR6: =AD6 -> Budget-2025 | AT6: 45688 | AU6: 45716 | AV6: 45747 | AW6: 45777 | AX6: 45808 | AY6: 45838 | AZ6: 45869 | BA6: 45900 | BB6: 45930 | BC6: 45961 | BD6: 45991 | BE6: 46022 | BF6: =AR6 -> Budget-2025 | BH6: 45688 | BI6: 45716 | BJ6: 45747 | BK6: 45777 | BL6: 45808 | BM6: 45838 | BN6: 45869 | BO6: 45900 | BP6: 45930 | BQ6: 45961 | BR6: 45991 | BS6: 46022 | BT6: =+#REF! -> #REF! | BV6: 45688 | BW6: 45716 | BX6: 45747 | BY6: 45777 | BZ6: 45808 | CA6: 45838 | CB6: 45869 | CC6: 45900 | CD6: 45930 | CE6: 45961 | CF6: 45991 | CG6: 46022 | CH6: =+#REF! -> #REF! | CJ6: 45688 | CK6: 45716 | CL6: 45747 | CM6: 45777 | CN6: 45808 | CO6: 45838 | CP6: 45869 | CQ6: 45900 | CR6: 45930 | CS6: 45961 | CT6: 45991 | CU6: 46022 | CV6: =+#REF! -> #REF! | CX6: 45688 | CY6: 45716 | CZ6: 45747 | DA6: 45777 | DB6: 45808 | DC6: 45838 | DD6: 45869 | DE6: 45900 | DF6: 45930 | DG6: 45961 | DH6: 45991 | DI6: 46022 | DJ6: =+CV6 -> #REF! | DL6: 45688 | DM6: 45716 | DN6: 45747 | DO6: 45777 | DP6: 45808 | DQ6: 45838 | DR6: 45869 | DS6: 45900 | DT6: 45930 | DU6: 45961 | DV6: 45991 | DW6: 46022 | DX6: =+DJ6 -> #REF! | DZ6: 45688 | EA6: 45716 | EB6: 45747 | EC6: 45777 | ED6: 45808 | EE6: 45838 | EF6: 45869 | EG6: 45900 | EH6: 45930 | EI6: 45961 | EJ6: 45991 | EK6: 46022 | EL6: =+DX6 -> #REF! | EN6: 45688 | EO6: 45716 | EP6: 45747 | EQ6: 45777 | ER6: 45808 | ES6: 45838 | ET6: 45869 | EU6: 45900 | EV6: 45930 | EW6: 45961 | EX6: 45991 | EY6: 46022 | EZ6: =+EL6 -> #REF! | FB6: 45688 | FC6: 45716 | FD6: 45747 | FE6: 45777 | FF6: 45808 | FG6: 45838 | FH6: 45869 | FI6: 45900 | FJ6: 45930 | FK6: 45961 | FL6: 45991 | FM6: 46022 | FN6: =+EZ6 -> #REF! | FP6: 45688 | FQ6: 45716 | FR6: 45747 | FS6: 45777 | FT6: 45808 | FU6: 45838 | FV6: 45869 | FW6: 45900 | FX6: 45930 | FY6: 45961 | FZ6: 45991 | GA6: 46022 | GB6: =+FN6 -> #REF! | GD6: 45688 | GE6: 45716 | GF6: 45747 | GG6: 45777 | GH6: 45808 | GI6: 45838 | GJ6: 45869 | GK6: 45900 | GL6: 45930 | GM6: 45961 | GN6: 45991 | GO6: 46022 | GP6: =+#REF! -> #REF! | GR6: 45688 | GS6: 45716 | GT6: 45747 | GU6: 45777 | GV6: 45808 | GW6: 45838 | GX6: 45869 | GY6: 45900 | GZ6: 45930 | HA6: 45961 | HB6: 45991 | HC6: 46022 | HD6: =+LL6 -> Total | HF6: 45688 | HG6: 45716 | HH6: 45747 | HI6: 45777 | HJ6: 45808 | HK6: 45838 | HL6: 45869 | HM6: 45900 | HN6: 45930 | HO6: 45961 | HP6: 45991 | HQ6: 46022 | HR6: =+GP6 -> #REF! | HT6: 45688 | HU6: 45716 | HV6: 45747 | HW6: 45777 | HX6: 45808 | HY6: 45838 | HZ6: 45869 | IA6: 45900 | IB6: 45930 | IC6: 45961 | ID6: 45991 | IE6: 46022 | IF6: =+HR6 -> #REF! | IH6: 45688 | II6: 45716 | IJ6: 45747 | IK6: 45777 | IL6: 45808 | IM6: 45838 | IN6: 45869 | IO6: 45900 | IP6: 45930 | IQ6: 45961 | IR6: 45991 | IS6: 46022 | IT6: =+IF6 -> #REF! | IV6: 45688 | IW6: 45716 | IX6: 45747 | IY6: 45777 | IZ6: 45808 | JA6: 45838 | JB6: 45869 | JC6: 45900 | JD6: 45930 | JE6: 45961 | JF6: 45991 | JG6: 46022 | JH6: =+IT6 -> #REF! | JJ6: 45688 | JK6: 45716 | JL6: 45747 | JM6: 45777 | JN6: 45808 | JO6: 45838 | JP6: 45869 | JQ6: 45900 | JR6: 45930 | JS6: 45961 | JT6: 45991 | JU6: 46022 | JV6: =+JH6 -> #REF! | JX6: 45688 | JY6: 45716 | JZ6: 45747 | KA6: 45777 | KB6: 45808 | KC6: 45838 | KD6: 45869 | KE6: 45900 | KF6: 45930 | KG6: 45961 | KH6: 45991 | KI6: 46022 | KJ6: =+JV6 -> #REF! | KL6: 45688 | KM6: 45716 | KN6: 45747 | KO6: 45777 | KP6: 45808 | KQ6: 45838 | KR6: 45869 | KS6: 45900 | KT6: 45930 | KU6: 45961 | KV6: 45991 | KW6: 46022 | KX6: Total | KZ6: 45688 | LA6: 45716 | LB6: 45747 | LC6: 45777 | LD6: 45808 | LE6: 45838 | LF6: 45869 | LG6: 45900 | LH6: 45930 | LI6: 45961 | LJ6: 45991 | LK6: 46022 | LL6: =+KX6 -> Total | LN6: 45688 | LO6: 45716 | LP6: 45747 | LQ6: 45777 | LR6: 45808 | LS6: 45838 | LT6: 45869 | LU6: 45900 | LV6: 45930 | LW6: 45961 | LX6: 45991 | LY6: 46022 | LZ6: =+HD6 -> Total | MB6: Total | MC6: =MB6 -> Total | MD6: =MC6 -> Total | ME6: =MD6 -> Total | MF6: =ME6 -> Total | MG6: =MF6 -> Total | MH6: =MG6 -> Total | MI6: =MH6 -> Total | MJ6: =MI6 -> Total | ... MN6: =MM6 -> Total
B7: Unique BU-Division Name | D7: Accounts-Fleet Accounts | E7: Accounts-Fleet Accounts | F7: Accounts-Fleet Accounts | G7: Accounts-Fleet Accounts | H7: Accounts-Fleet Accounts | I7: Accounts-Fleet Accounts | J7: Accounts-Fleet Accounts | K7: Accounts-Fleet Accounts | L7: Accounts-Fleet Accounts | M7: Accounts-Fleet Accounts | N7: Accounts-Fleet Accounts | O7: Accounts-Fleet Accounts | P7: Accounts-Fleet Accounts | R7: Admin-Administration | S7: Admin-Administration | T7: Admin-Administration | U7: Admin-Administration | V7: Admin-Administration | W7: Admin-Administration | X7: Admin-Administration | Y7: Admin-Administration | Z7: Admin-Administration | AA7: Admin-Administration | AB7: Admin-Administration | AC7: Admin-Administration | AD7: Admin-Administration | AF7: Agency Services-Agency Hub | AG7: Agency Services-Agency Hub | AH7: Agency Services-Agency Hub | AI7: Agency Services-Agency Hub | AJ7: Agency Services-Agency Hub | AK7: Agency Services-Agency Hub | AL7: Agency Services-Agency Hub | AM7: Agency Services-Agency Hub | AN7: Agency Services-Agency Hub | AO7: Agency Services-Agency Hub | AP7: Agency Services-Agency Hub | AQ7: Agency Services-Agency Hub | AR7: Agency Services-Agency Hub | AT7: Commercial-Commercial | AU7: Commercial-Commercial | AV7: Commercial-Commercial | AW7: Commercial-Commercial | AX7: Commercial-Commercial | AY7: Commercial-Commercial | AZ7: Commercial-Commercial | BA7: Commercial-Commercial | BB7: Commercial-Commercial | BC7: Commercial-Commercial | BD7: Commercial-Commercial | BE7: Commercial-Commercial | BF7: Commercial-Commercial | BH7: Consultancy Services-Fleet Performance | BI7: Consultancy Services-Fleet Performance | BJ7: Consultancy Services-Fleet Performance | BK7: Consultancy Services-Fleet Performance | BL7: Consultancy Services-Fleet Performance | BM7: Consultancy Services-Fleet Performance | BN7: Consultancy Services-Fleet Performance | BO7: Consultancy Services-Fleet Performance | BP7: Consultancy Services-Fleet Performance | BQ7: Consultancy Services-Fleet Performance | BR7: Consultancy Services-Fleet Performance | BS7: Consultancy Services-Fleet Performance | BT7: Consultancy Services-Fleet Performance | BV7: Crew Management-Group Marine HR | BW7: Crew Management-Group Marine HR | BX7: Crew Management-Group Marine HR | BY7: Crew Management-Group Marine HR | BZ7: Crew Management-Group Marine HR | CA7: Crew Management-Group Marine HR | CB7: Crew Management-Group Marine HR | CC7: Crew Management-Group Marine HR | CD7: Crew Management-Group Marine HR | CE7: Crew Management-Group Marine HR | CF7: Crew Management-Group Marine HR | CG7: Crew Management-Group Marine HR | CH7: Crew Management-Group Marine HR | CJ7: Cruise Management-Miami Ship Management | CK7: Cruise Management-Miami Ship Management | CL7: Cruise Management-Miami Ship Management | CM7: Cruise Management-Miami Ship Management | CN7: Cruise Management-Miami Ship Management | CO7: Cruise Management-Miami Ship Management | CP7: Cruise Management-Miami Ship Management | CQ7: Cruise Management-Miami Ship Management | CR7: Cruise Management-Miami Ship Management | CS7: Cruise Management-Miami Ship Management | CT7: Cruise Management-Miami Ship Management | CU7: Cruise Management-Miami Ship Management | CV7: Cruise Management-Miami Ship Management | CX7: IT-Group IT | CY7: IT-Group IT | CZ7: IT-Group IT | DA7: IT-Group IT | DB7: IT-Group IT | DC7: IT-Group IT | DD7: IT-Group IT | DE7: IT-Group IT | DF7: IT-Group IT | DG7: IT-Group IT | DH7: IT-Group IT | DI7: IT-Group IT | DJ7: IT-Group IT | DL7: Procurement-Galleymasters | DM7: Procurement-Galleymasters | DN7: Procurement-Galleymasters | DO7: Procurement-Galleymasters | DP7: Procurement-Galleymasters | DQ7: Procurement-Galleymasters | DR7: Procurement-Galleymasters | DS7: Procurement-Galleymasters | DT7: Procurement-Galleymasters | DU7: Procurement-Galleymasters | DV7: Procurement-Galleymasters | DW7: Procurement-Galleymasters | DX7: Procurement-Galleymasters | DZ7: Procurement-Sourcing | EA7: Procurement-Sourcing | EB7: Procurement-Sourcing | EC7: Procurement-Sourcing | ED7: Procurement-Sourcing | EE7: Procurement-Sourcing | EF7: Procurement-Sourcing | EG7: Procurement-Sourcing | EH7: Procurement-Sourcing | EI7: Procurement-Sourcing | EJ7: Procurement-Sourcing | EK7: Procurement-Sourcing | EL7: Procurement-Sourcing | EN7: Ship Management-Antwerp Dry | EO7: Ship Management-Antwerp Dry | EP7: Ship Management-Antwerp Dry | EQ7: Ship Management-Antwerp Dry | ER7: Ship Management-Antwerp Dry | ES7: Ship Management-Antwerp Dry | ET7: Ship Management-Antwerp Dry | EU7: Ship Management-Antwerp Dry | EV7: Ship Management-Antwerp Dry | EW7: Ship Management-Antwerp Dry | EX7: Ship Management-Antwerp Dry | EY7: Ship Management-Antwerp Dry | EZ7: Ship Management-Antwerp Dry | FB7: Ship Management-Goes Dry | FC7: Ship Management-Goes Dry | FD7: Ship Management-Goes Dry | FE7: Ship Management-Goes Dry | FF7: Ship Management-Goes Dry | FG7: Ship Management-Goes Dry | FH7: Ship Management-Goes Dry | FI7: Ship Management-Goes Dry | FJ7: Ship Management-Goes Dry | FK7: Ship Management-Goes Dry | FL7: Ship Management-Goes Dry | FM7: Ship Management-Goes Dry | FN7: Ship Management-Goes Dry | FP7: Ship Management-Group Operations | FQ7: Ship Management-Group Operations | FR7: Ship Management-Group Operations | FS7: Ship Management-Group Operations | FT7: Ship Management-Group Operations | FU7: Ship Management-Group Operations | FV7: Ship Management-Group Operations | FW7: Ship Management-Group Operations | FX7: Ship Management-Group Operations | FY7: Ship Management-Group Operations | FZ7: Ship Management-Group Operations | GA7: Ship Management-Group Operations | GB7: Ship Management-Group Operations | GD7: Ship Management-Group Shared Service Center | GE7: Ship Management-Group Shared Service Center | GF7: Ship Management-Group Shared Service Center | GG7: Ship Management-Group Shared Service Center | GH7: Ship Management-Group Shared Service Center | GI7: Ship Management-Group Shared Service Center | GJ7: Ship Management-Group Shared Service Center | GK7: Ship Management-Group Shared Service Center | GL7: Ship Management-Group Shared Service Center | GM7: Ship Management-Group Shared Service Center | GN7: Ship Management-Group Shared Service Center | GO7: Ship Management-Group Shared Service Center | GP7: Ship Management-Group Shared Service Center | GR7: Vacant Seats | GS7: Vacant Seats | GT7: Vacant Seats | GU7: Vacant Seats | GV7: Vacant Seats | GW7: Vacant Seats | GX7: Vacant Seats | GY7: Vacant Seats | GZ7: Vacant Seats | HA7: Vacant Seats | HB7: Vacant Seats | HC7: Vacant Seats | HD7: Vacant Seats | HF7: Ship Management-Hamburg Dry | HG7: Ship Management-Hamburg Dry | HH7: Ship Management-Hamburg Dry | HI7: Ship Management-Hamburg Dry | HJ7: Ship Management-Hamburg Dry | HK7: Ship Management-Hamburg Dry | HL7: Ship Management-Hamburg Dry | HM7: Ship Management-Hamburg Dry | HN7: Ship Management-Hamburg Dry | HO7: Ship Management-Hamburg Dry | HP7: Ship Management-Hamburg Dry | HQ7: Ship Management-Hamburg Dry | HR7: Ship Management-Hamburg Dry | HT7: Ship Management-Hong Kong Dry 1 | HU7: Ship Management-Hong Kong Dry 1 | HV7: Ship Management-Hong Kong Dry 1 | HW7: Ship Management-Hong Kong Dry 1 | HX7: Ship Management-Hong Kong Dry 1 | HY7: Ship Management-Hong Kong Dry 1 | HZ7: Ship Management-Hong Kong Dry 1 | IA7: Ship Management-Hong Kong Dry 1 | IB7: Ship Management-Hong Kong Dry 1 | IC7: Ship Management-Hong Kong Dry 1 | ID7: Ship Management-Hong Kong Dry 1 | IE7: Ship Management-Hong Kong Dry 1 | IF7: Ship Management-Hong Kong Dry 1 | IH7: Ship Management-JV Ardmore | II7: Ship Management-JV Ardmore | IJ7: Ship Management-JV Ardmore | IK7: Ship Management-JV Ardmore | IL7: Ship Management-JV Ardmore | IM7: Ship Management-JV Ardmore | IN7: Ship Management-JV Ardmore | IO7: Ship Management-JV Ardmore | IP7: Ship Management-JV Ardmore | IQ7: Ship Management-JV Ardmore | IR7: Ship Management-JV Ardmore | IS7: Ship Management-JV Ardmore | IT7: Ship Management-JV Ardmore | IV7: Ship Management-Singapore Dry | IW7: Ship Management-Singapore Dry | IX7: Ship Management-Singapore Dry | IY7: Ship Management-Singapore Dry | IZ7: Ship Management-Singapore Dry | JA7: Ship Management-Singapore Dry | JB7: Ship Management-Singapore Dry | JC7: Ship Management-Singapore Dry | JD7: Ship Management-Singapore Dry | JE7: Ship Management-Singapore Dry | JF7: Ship Management-Singapore Dry | JG7: Ship Management-Singapore Dry | JH7: Ship Management-Singapore Dry | JJ7: Ship Management-Singapore Tanker 1 | JK7: Ship Management-Singapore Tanker 1 | JL7: Ship Management-Singapore Tanker 1 | JM7: Ship Management-Singapore Tanker 1 | JN7: Ship Management-Singapore Tanker 1 | JO7: Ship Management-Singapore Tanker 1 | JP7: Ship Management-Singapore Tanker 1 | JQ7: Ship Management-Singapore Tanker 1 | JR7: Ship Management-Singapore Tanker 1 | JS7: Ship Management-Singapore Tanker 1 | JT7: Ship Management-Singapore Tanker 1 | JU7: Ship Management-Singapore Tanker 1 | JV7: Ship Management-Singapore Tanker 1 | JX7: Ship Management-Singapore Tanker 2 | JY7: Ship Management-Singapore Tanker 2 | JZ7: Ship Management-Singapore Tanker 2 | KA7: Ship Management-Singapore Tanker 2 | KB7: Ship Management-Singapore Tanker 2 | KC7: Ship Management-Singapore Tanker 2 | KD7: Ship Management-Singapore Tanker 2 | KE7: Ship Management-Singapore Tanker 2 | KF7: Ship Management-Singapore Tanker 2 | KG7: Ship Management-Singapore Tanker 2 | KH7: Ship Management-Singapore Tanker 2 | KI7: Ship Management-Singapore Tanker 2 | KJ7: Ship Management-Singapore Tanker 2 | KL7: Accounts-Accounts Payables | KM7: Accounts-Accounts Payables | KN7: Accounts-Accounts Payables | KO7: Accounts-Accounts Payables | KP7: Accounts-Accounts Payables | KQ7: Accounts-Accounts Payables | KR7: Accounts-Accounts Payables | KS7: Accounts-Accounts Payables | KT7: Accounts-Accounts Payables | KU7: Accounts-Accounts Payables | KV7: Accounts-Accounts Payables | KW7: Accounts-Accounts Payables | KX7: Accounts-Accounts Payables | KZ7: Accounts-CMI Accounts Payables | LA7: Accounts-CMI Accounts Payables | LB7: Accounts-CMI Accounts Payables | LC7: Accounts-CMI Accounts Payables | LD7: Accounts-CMI Accounts Payables | LE7: Accounts-CMI Accounts Payables | LF7: Accounts-CMI Accounts Payables | LG7: Accounts-CMI Accounts Payables | LH7: Accounts-CMI Accounts Payables | LI7: Accounts-CMI Accounts Payables | LJ7: Accounts-CMI Accounts Payables | LK7: Accounts-CMI Accounts Payables | LL7: Accounts-CMI Accounts Payables | MB7: 30 Divisions | MC7: =MB7 -> 30 Divisions | MD7: =MC7 -> 30 Divisions | ME7: =MD7 -> 30 Divisions | MF7: =ME7 -> 30 Divisions | MG7: =MF7 -> 30 Divisions | MH7: =MG7 -> 30 Divisions | MI7: =MH7 -> 30 Divisions | MJ7: =MI7 -> 30 Divisions | ... MN7: =MM7 -> 30 Divisions
B8: INCOME
B9: Ship Management - Other Income | D9: 0 | E9: 0 | F9: 0 | G9: 0 | H9: 0 | I9: 0 | J9: 0 | K9: 0 | L9: 0 | M9: 0 | N9: 0 | O9: 0 | P9: =+SUBTOTAL(9,D9:O9) -> 0 | R9: 0 | S9: 0 | T9: 0 | U9: 0 | V9: 0 | W9: 0 | X9: 0 | Y9: 0 | Z9: 0 | AA9: 0 | AB9: 0 | AC9: 0 | AD9: =+SUBTOTAL(9,R9:AC9) -> 0 | AF9: 0 | AG9: 0 | AH9: 0 | AI9: 0 | AJ9: 0 | AK9: 0 | AL9: 0 | AM9: 0 | AN9: 0 | AO9: 0 | AP9: 0 | AQ9: 0 | AR9: =+SUBTOTAL(9,AF9:AQ9) -> 0 | AT9: 0 | AU9: 0 | AV9: 0 | AW9: 0 | AX9: 0 | AY9: 0 | AZ9: 0 | BA9: 0 | BB9: 0 | BC9: 0 | BD9: 0 | BE9: 0 | BF9: =+SUBTOTAL(9,AT9:BE9) -> 0 | BH9: 0 | BI9: 0 | BJ9: 0 | BK9: 0 | BL9: 0 | BM9: 0 | BN9: 0 | BO9: 0 | BP9: 0 | BQ9: 0 | BR9: 0 | BS9: 0 | BT9: =+SUBTOTAL(9,BH9:BS9) -> 0 | BV9: 0 | BW9: 0 | BX9: 0 | BY9: 0 | BZ9: 0 | CA9: 0 | CB9: 0 | CC9: 0 | CD9: 0 | CE9: 0 | CF9: 0 | CG9: 0 | CH9: =+SUBTOTAL(9,BV9:CG9) -> 0 | CJ9: 0 | CK9: 0 | CL9: 0 | CM9: 0 | CN9: 0 | CO9: 0 | CP9: 0 | CQ9: 0 | CR9: 0 | CS9: 0 | CT9: 0 | CU9: 0 | CV9: =+SUBTOTAL(9,CJ9:CU9) -> 0 | CX9: 0 | CY9: 0 | CZ9: 0 | DA9: 0 | DB9: 0 | DC9: 0 | DD9: 0 | DE9: 0 | DF9: 0 | DG9: 0 | DH9: 0 | DI9: 0 | DJ9: =+SUBTOTAL(9,CX9:DI9) -> 0 | DL9: 0 | DM9: 0 | DN9: 0 | DO9: 0 | DP9: 0 | DQ9: 0 | DR9: 0 | DS9: 0 | DT9: 0 | DU9: 0 | DV9: 0 | DW9: 0 | DX9: =+SUBTOTAL(9,DL9:DW9) -> 0 | DZ9: 0 | EA9: 0 | EB9: 0 | EC9: 0 | ED9: 0 | EE9: 0 | EF9: 0 | EG9: 0 | EH9: 0 | EI9: 0 | EJ9: 0 | EK9: 0 | EL9: =+SUBTOTAL(9,DZ9:EK9) -> 0 | EN9: 0 | EO9: 0 | EP9: 0 | EQ9: 0 | ER9: 0 | ES9: 0 | ET9: 0 | EU9: 0 | EV9: 0 | EW9: 0 | EX9: 0 | EY9: 0 | EZ9: =+SUBTOTAL(9,EN9:EY9) -> 0 | FB9: 0 | FC9: 0 | FD9: 0 | FE9: 0 | FF9: 0 | FG9: 0 | FH9: 0 | FI9: 0 | FJ9: 0 | FK9: 0 | FL9: 0 | FM9: 0 | FN9: =+SUBTOTAL(9,FB9:FM9) -> 0 | FP9: 0 | FQ9: 0 | FR9: 0 | FS9: 0 | FT9: 0 | FU9: 0 | FV9: 0 | FW9: 0 | FX9: 0 | FY9: 0 | FZ9: 0 | GA9: 0 | GB9: =+SUBTOTAL(9,FP9:GA9) -> 0 | GD9: 0 | GE9: 0 | GF9: 0 | GG9: 0 | GH9: 0 | GI9: 0 | GJ9: 0 | GK9: 0 | GL9: 0 | GM9: 0 | GN9: 0 | GO9: 0 | GP9: =+SUBTOTAL(9,GD9:GO9) -> 0 | GR9: 0 | GS9: 0 | GT9: 0 | GU9: 0 | GV9: 0 | GW9: 0 | GX9: 0 | GY9: 0 | GZ9: 0 | HA9: 0 | HB9: 0 | HC9: 0 | HD9: =+SUBTOTAL(9,GR9:HC9) -> 0 | HF9: 0 | HG9: 0 | HH9: 0 | HI9: 0 | HJ9: 0 | HK9: 0 | HL9: 0 | HM9: 0 | HN9: 0 | HO9: 0 | HP9: 0 | HQ9: 0 | HR9: =+SUBTOTAL(9,HF9:HQ9) -> 0 | HT9: 0 | HU9: 0 | HV9: 0 | HW9: 0 | HX9: 0 | HY9: 0 | HZ9: 0 | IA9: 0 | IB9: 0 | IC9: 0 | ID9: 0 | IE9: 0 | IF9: =+SUBTOTAL(9,HT9:IE9) -> 0 | IH9: 0 | II9: 0 | IJ9: 0 | IK9: 0 | IL9: 0 | IM9: 0 | IN9: 0 | IO9: 0 | IP9: 0 | IQ9: 0 | IR9: 0 | IS9: 0 | IT9: =+SUBTOTAL(9,IH9:IS9) -> 0 | IV9: 0 | IW9: 0 | IX9: 0 | IY9: 0 | IZ9: 0 | JA9: 0 | JB9: 0 | JC9: 0 | JD9: 0 | JE9: 0 | JF9: 0 | JG9: 0 | JH9: =+SUBTOTAL(9,IV9:JG9) -> 0 | JJ9: 0 | JK9: 0 | JL9: 0 | JM9: 0 | JN9: 0 | JO9: 0 | JP9: 0 | JQ9: 0 | JR9: 0 | JS9: 0 | JT9: 0 | JU9: 0 | JV9: =+SUBTOTAL(9,JJ9:JU9) -> 0 | JX9: 0 | JY9: 0 | JZ9: 0 | KA9: 0 | KB9: 0 | KC9: 0 | KD9: 0 | KE9: 0 | KF9: 0 | KG9: 0 | KH9: 0 | KI9: 0 | KJ9: =+SUBTOTAL(9,JX9:KI9) -> 0 | KL9: 0 | KM9: 0 | KN9: 0 | KO9: 0 | KP9: 0 | KQ9: 0 | KR9: 0 | KS9: 0 | KT9: 0 | KU9: 0 | KV9: 0 | KW9: 0 | KX9: =+SUBTOTAL(9,KL9:KW9) -> 0 | KZ9: 0 | LA9: 0 | LB9: 0 | LC9: 0 | LD9: 0 | LE9: 0 | LF9: 0 | LG9: 0 | LH9: 0 | LI9: 0 | LJ9: 0 | LK9: 0 | LL9: =+SUBTOTAL(9,KZ9:LK9) -> 0 | LN9: 0 | LO9: 0 | LP9: 0 | LQ9: 0 | LR9: 0 | LS9: 0 | LT9: 0 | LU9: 0 | LV9: 0 | LW9: 0 | LX9: 0 | LY9: 0 | LZ9: =+SUBTOTAL(9,LN9:LY9) -> 0 | MB9: =SUMIF($D$6:$LY$6,MB$3,$D9:$LY9) -> 0 | MC9: =SUMIF($D$6:$LY$6,MC$3,$D9:$LY9) -> 0 | MD9: =SUMIF($D$6:$LY$6,MD$3,$D9:$LY9) -> 0 | ME9: =SUMIF($D$6:$LY$6,ME$3,$D9:$LY9) -> 0 | MF9: =SUMIF($D$6:$LY$6,MF$3,$D9:$LY9) -> 0 | MG9: =SUMIF($D$6:$LY$6,MG$3,$D9:$LY9) -> 0 | MH9: =SUMIF($D$6:$LY$6,MH$3,$D9:$LY9) -> 0 | MI9: =SUMIF($D$6:$LY$6,MI$3,$D9:$LY9) -> 0 | ... MM9: =SUMIF($D$6:$LY$6,MM$3,$D9:$LY9) -> 0 | MN9: =SUM(MB9:MM9) -> 0
B10: Intercompany Sales | D10: 0 | E10: 0 | F10: 0 | G10: 0 | H10: 0 | I10: 0 | J10: 0 | K10: 0 | L10: 0 | M10: 0 | N10: 0 | O10: 0 | P10: =+SUBTOTAL(9,D10:O10) -> 0 | R10: 0 | S10: 0 | T10: 0 | U10: 0 | V10: 0 | W10: 0 | X10: 0 | Y10: 0 | Z10: 0 | AA10: 0 | AB10: 0 | AC10: 0 | AD10: =+SUBTOTAL(9,R10:AC10) -> 0 | AF10: 0 | AG10: 0 | AH10: 0 | AI10: 0 | AJ10: 0 | AK10: 0 | AL10: 0 | AM10: 0 | AN10: 0 | AO10: 0 | AP10: 0 | AQ10: 0 | AR10: =+SUBTOTAL(9,AF10:AQ10) -> 0 | AT10: 0 | AU10: 0 | AV10: 0 | AW10: 0 | AX10: 0 | AY10: 0 | AZ10: 0 | BA10: 0 | BB10: 0 | BC10: 0 | BD10: 0 | BE10: 0 | BF10: =+SUBTOTAL(9,AT10:BE10) -> 0 | BH10: 0 | BI10: 0 | BJ10: 0 | BK10: 0 | BL10: 0 | BM10: 0 | BN10: 0 | BO10: 0 | BP10: 0 | BQ10: 0 | BR10: 0 | BS10: 0 | BT10: =+SUBTOTAL(9,BH10:BS10) -> 0 | BV10: 0 | BW10: 0 | BX10: 0 | BY10: 0 | BZ10: 0 | CA10: 0 | CB10: 0 | CC10: 0 | CD10: 0 | CE10: 0 | CF10: 0 | CG10: 0 | CH10: =+SUBTOTAL(9,BV10:CG10) -> 0 | CJ10: 0 | CK10: 0 | CL10: 0 | CM10: 0 | CN10: 0 | CO10: 0 | CP10: 0 | CQ10: 0 | CR10: 0 | CS10: 0 | CT10: 0 | CU10: 0 | CV10: =+SUBTOTAL(9,CJ10:CU10) -> 0 | CX10: 0 | CY10: 0 | CZ10: 0 | DA10: 0 | DB10: 0 | DC10: 0 | DD10: 0 | DE10: 0 | DF10: 0 | DG10: 0 | DH10: 0 | DI10: 0 | DJ10: =+SUBTOTAL(9,CX10:DI10) -> 0 | DL10: 0 | DM10: 0 | DN10: 0 | DO10: 0 | DP10: 0 | DQ10: 0 | DR10: 0 | DS10: 0 | DT10: 0 | DU10: 0 | DV10: 0 | DW10: 0 | DX10: =+SUBTOTAL(9,DL10:DW10) -> 0 | DZ10: 0 | EA10: 0 | EB10: 0 | EC10: 0 | ED10: 0 | EE10: 0 | EF10: 0 | EG10: 0 | EH10: 0 | EI10: 0 | EJ10: 0 | EK10: 0 | EL10: =+SUBTOTAL(9,DZ10:EK10) -> 0 | EN10: 0 | EO10: 0 | EP10: 0 | EQ10: 0 | ER10: 0 | ES10: 0 | ET10: 0 | EU10: 0 | EV10: 0 | EW10: 0 | EX10: 0 | EY10: 0 | EZ10: =+SUBTOTAL(9,EN10:EY10) -> 0 | FB10: 0 | FC10: 0 | FD10: 0 | FE10: 0 | FF10: 0 | FG10: 0 | FH10: 0 | FI10: 0 | FJ10: 0 | FK10: 0 | FL10: 0 | FM10: 0 | FN10: =+SUBTOTAL(9,FB10:FM10) -> 0 | FP10: 0 | FQ10: 0 | FR10: 0 | FS10: 0 | FT10: 0 | FU10: 0 | FV10: 0 | FW10: 0 | FX10: 0 | FY10: 0 | FZ10: 0 | GA10: 0 | GB10: =+SUBTOTAL(9,FP10:GA10) -> 0 | GD10: 0 | GE10: 0 | GF10: 0 | GG10: 0 | GH10: 0 | GI10: 0 | GJ10: 0 | GK10: 0 | GL10: 0 | GM10: 0 | GN10: 0 | GO10: 0 | GP10: =+SUBTOTAL(9,GD10:GO10) -> 0 | GR10: 0 | GS10: 0 | GT10: 0 | GU10: 0 | GV10: 0 | GW10: 0 | GX10: 0 | GY10: 0 | GZ10: 0 | HA10: 0 | HB10: 0 | HC10: 0 | HD10: =+SUBTOTAL(9,GR10:HC10) -> 0 | HF10: 0 | HG10: 0 | HH10: 0 | HI10: 0 | HJ10: 0 | HK10: 0 | HL10: 0 | HM10: 0 | HN10: 0 | HO10: 0 | HP10: 0 | HQ10: 0 | HR10: =+SUBTOTAL(9,HF10:HQ10) -> 0 | HT10: 0 | HU10: 0 | HV10: 0 | HW10: 0 | HX10: 0 | HY10: 0 | HZ10: 0 | IA10: 0 | IB10: 0 | IC10: 0 | ID10: 0 | IE10: 0 | IF10: =+SUBTOTAL(9,HT10:IE10) -> 0 | IH10: 0 | II10: 0 | IJ10: 0 | IK10: 0 | IL10: 0 | IM10: 0 | IN10: 0 | IO10: 0 | IP10: 0 | IQ10: 0 | IR10: 0 | IS10: 0 | IT10: =+SUBTOTAL(9,IH10:IS10) -> 0 | IV10: 0 | IW10: 0 | IX10: 0 | IY10: 0 | IZ10: 0 | JA10: 0 | JB10: 0 | JC10: 0 | JD10: 0 | JE10: 0 | JF10: 0 | JG10: 0 | JH10: =+SUBTOTAL(9,IV10:JG10) -> 0 | JJ10: 0 | JK10: 0 | JL10: 0 | JM10: 0 | JN10: 0 | JO10: 0 | JP10: 0 | JQ10: 0 | JR10: 0 | JS10: 0 | JT10: 0 | JU10: 0 | JV10: =+SUBTOTAL(9,JJ10:JU10) -> 0 | JX10: 0 | JY10: 0 | JZ10: 0 | KA10: 0 | KB10: 0 | KC10: 0 | KD10: 0 | KE10: 0 | KF10: 0 | KG10: 0 | KH10: 0 | KI10: 0 | KJ10: =+SUBTOTAL(9,JX10:KI10) -> 0 | KL10: 0 | KM10: 0 | KN10: 0 | KO10: 0 | KP10: 0 | KQ10: 0 | KR10: 0 | KS10: 0 | KT10: 0 | KU10: 0 | KV10: 0 | KW10: 0 | KX10: =+SUBTOTAL(9,KL10:KW10) -> 0 | KZ10: 0 | LA10: 0 | LB10: 0 | LC10: 0 | LD10: 0 | LE10: 0 | LF10: 0 | LG10: 0 | LH10: 0 | LI10: 0 | LJ10: 0 | LK10: 0 | LL10: =+SUBTOTAL(9,KZ10:LK10) -> 0 | LN10: 0 | LO10: 0 | LP10: 0 | LQ10: 0 | LR10: 0 | LS10: 0 | LT10: 0 | LU10: 0 | LV10: 0 | LW10: 0 | LX10: 0 | LY10: 0 | LZ10: =+SUBTOTAL(9,LN10:LY10) -> 0 | MB10: =SUMIF($D$6:$LY$6,MB$3,$D10:$LY10) -> 0 | MC10: =SUMIF($D$6:$LY$6,MC$3,$D10:$LY10) -> 0 | MD10: =SUMIF($D$6:$LY$6,MD$3,$D10:$LY10) -> 0 | ME10: =SUMIF($D$6:$LY$6,ME$3,$D10:$LY10) -> 0 | MF10: =SUMIF($D$6:$LY$6,MF$3,$D10:$LY10) -> 0 | MG10: =SUMIF($D$6:$LY$6,MG$3,$D10:$LY10) -> 0 | MH10: =SUMIF($D$6:$LY$6,MH$3,$D10:$LY10) -> 0 | MI10: =SUMIF($D$6:$LY$6,MI$3,$D10:$LY10) -> 0 | ... MM10: =SUMIF($D$6:$LY$6,MM$3,$D10:$LY10) -> 0 | MN10: =SUM(MB10:MM10) -> 0
B12: TOTAL INCOME | D12: =SUM(D9:D11) -> 0 | E12: =SUM(E9:E11) -> 0 | F12: =SUM(F9:F11) -> 0 | G12: =SUM(G9:G11) -> 0 | H12: =SUM(H9:H11) -> 0 | I12: =SUM(I9:I11) -> 0 | J12: =SUM(J9:J11) -> 0 | K12: =SUM(K9:K11) -> 0 | ... O12: =SUM(O9:O11) -> 0 | P12: =+SUBTOTAL(9,D12:O12) -> 0 | R12: =SUM(R9:R11) -> 0 | S12: =SUM(S9:S11) -> 0 | T12: =SUM(T9:T11) -> 0 | U12: =SUM(U9:U11) -> 0 | V12: =SUM(V9:V11) -> 0 | W12: =SUM(W9:W11) -> 0 | X12: =SUM(X9:X11) -> 0 | Y12: =SUM(Y9:Y11) -> 0 | ... AC12: =SUM(AC9:AC11) -> 0 | AD12: =+SUBTOTAL(9,R12:AC12) -> 0 | AF12: =SUM(AF9:AF11) -> 0 | AG12: =SUM(AG9:AG11) -> 0 | AH12: =SUM(AH9:AH11) -> 0 | AI12: =SUM(AI9:AI11) -> 0 | AJ12: =SUM(AJ9:AJ11) -> 0 | AK12: =SUM(AK9:AK11) -> 0 | AL12: =SUM(AL9:AL11) -> 0 | AM12: =SUM(AM9:AM11) -> 0 | ... AQ12: =SUM(AQ9:AQ11) -> 0 | AR12: =+SUBTOTAL(9,AF12:AQ12) -> 0 | AT12: =SUM(AT9:AT11) -> 0 | AU12: =SUM(AU9:AU11) -> 0 | AV12: =SUM(AV9:AV11) -> 0 | AW12: =SUM(AW9:AW11) -> 0 | AX12: =SUM(AX9:AX11) -> 0 | AY12: =SUM(AY9:AY11) -> 0 | AZ12: =SUM(AZ9:AZ11) -> 0 | BA12: =SUM(BA9:BA11) -> 0 | ... BE12: =SUM(BE9:BE11) -> 0 | BF12: =+SUBTOTAL(9,AT12:BE12) -> 0 | BH12: =SUM(BH9:BH11) -> 0 | BI12: =SUM(BI9:BI11) -> 0 | BJ12: =SUM(BJ9:BJ11) -> 0 | BK12: =SUM(BK9:BK11) -> 0 | BL12: =SUM(BL9:BL11) -> 0 | BM12: =SUM(BM9:BM11) -> 0 | BN12: =SUM(BN9:BN11) -> 0 | BO12: =SUM(BO9:BO11) -> 0 | ... BS12: =SUM(BS9:BS11) -> 0 | BT12: =+SUBTOTAL(9,BH12:BS12) -> 0 | BV12: =SUM(BV9:BV11) -> 0 | BW12: =SUM(BW9:BW11) -> 0 | BX12: =SUM(BX9:BX11) -> 0 | BY12: =SUM(BY9:BY11) -> 0 | BZ12: =SUM(BZ9:BZ11) -> 0 | CA12: =SUM(CA9:CA11) -> 0 | CB12: =SUM(CB9:CB11) -> 0 | CC12: =SUM(CC9:CC11) -> 0 | ... CG12: =SUM(CG9:CG11) -> 0 | CH12: =+SUBTOTAL(9,BV12:CG12) -> 0 | CJ12: =SUM(CJ9:CJ11) -> 0 | CK12: =SUM(CK9:CK11) -> 0 | CL12: =SUM(CL9:CL11) -> 0 | CM12: =SUM(CM9:CM11) -> 0 | CN12: =SUM(CN9:CN11) -> 0 | CO12: =SUM(CO9:CO11) -> 0 | CP12: =SUM(CP9:CP11) -> 0 | CQ12: =SUM(CQ9:CQ11) -> 0 | ... CU12: =SUM(CU9:CU11) -> 0 | CV12: =+SUBTOTAL(9,CJ12:CU12) -> 0 | CX12: =SUM(CX9:CX11) -> 0 | CY12: =SUM(CY9:CY11) -> 0 | CZ12: =SUM(CZ9:CZ11) -> 0 | DA12: =SUM(DA9:DA11) -> 0 | DB12: =SUM(DB9:DB11) -> 0 | DC12: =SUM(DC9:DC11) -> 0 | DD12: =SUM(DD9:DD11) -> 0 | DE12: =SUM(DE9:DE11) -> 0 | ... DI12: =SUM(DI9:DI11) -> 0 | DJ12: =+SUBTOTAL(9,CX12:DI12) -> 0 | DL12: =SUM(DL9:DL11) -> 0 | DM12: =SUM(DM9:DM11) -> 0 | DN12: =SUM(DN9:DN11) -> 0 | DO12: =SUM(DO9:DO11) -> 0 | DP12: =SUM(DP9:DP11) -> 0 | DQ12: =SUM(DQ9:DQ11) -> 0 | DR12: =SUM(DR9:DR11) -> 0 | DS12: =SUM(DS9:DS11) -> 0 | ... DW12: =SUM(DW9:DW11) -> 0 | DX12: =+SUBTOTAL(9,DL12:DW12) -> 0 | DZ12: =SUM(DZ9:DZ11) -> 0 | EA12: =SUM(EA9:EA11) -> 0 | EB12: =SUM(EB9:EB11) -> 0 | EC12: =SUM(EC9:EC11) -> 0 | ED12: =SUM(ED9:ED11) -> 0 | EE12: =SUM(EE9:EE11) -> 0 | EF12: =SUM(EF9:EF11) -> 0 | EG12: =SUM(EG9:EG11) -> 0 | ... EK12: =SUM(EK9:EK11) -> 0 | EL12: =+SUBTOTAL(9,DZ12:EK12) -> 0 | EN12: =SUM(EN9:EN11) -> 0 | EO12: =SUM(EO9:EO11) -> 0 | EP12: =SUM(EP9:EP11) -> 0 | EQ12: =SUM(EQ9:EQ11) -> 0 | ER12: =SUM(ER9:ER11) -> 0 | ES12: =SUM(ES9:ES11) -> 0 | ET12: =SUM(ET9:ET11) -> 0 | EU12: =SUM(EU9:EU11) -> 0 | ... EY12: =SUM(EY9:EY11) -> 0 | EZ12: =+SUBTOTAL(9,EN12:EY12) -> 0 | FB12: =SUM(FB9:FB11) -> 0 | FC12: =SUM(FC9:FC11) -> 0 | FD12: =SUM(FD9:FD11) -> 0 | FE12: =SUM(FE9:FE11) -> 0 | FF12: =SUM(FF9:FF11) -> 0 | FG12: =SUM(FG9:FG11) -> 0 | FH12: =SUM(FH9:FH11) -> 0 | FI12: =SUM(FI9:FI11) -> 0 | ... FM12: =SUM(FM9:FM11) -> 0 | FN12: =+SUBTOTAL(9,FB12:FM12) -> 0 | FP12: =SUM(FP9:FP11) -> 0 | FQ12: =SUM(FQ9:FQ11) -> 0 | FR12: =SUM(FR9:FR11) -> 0 | FS12: =SUM(FS9:FS11) -> 0 | FT12: =SUM(FT9:FT11) -> 0 | FU12: =SUM(FU9:FU11) -> 0 | FV12: =SUM(FV9:FV11) -> 0 | FW12: =SUM(FW9:FW11) -> 0 | ... GA12: =SUM(GA9:GA11) -> 0 | GB12: =+SUBTOTAL(9,FP12:GA12) -> 0 | GD12: =SUM(GD9:GD11) -> 0 | GE12: =SUM(GE9:GE11) -> 0 | GF12: =SUM(GF9:GF11) -> 0 | GG12: =SUM(GG9:GG11) -> 0 | GH12: =SUM(GH9:GH11) -> 0 | GI12: =SUM(GI9:GI11) -> 0 | GJ12: =SUM(GJ9:GJ11) -> 0 | GK12: =SUM(GK9:GK11) -> 0 | ... GO12: =SUM(GO9:GO11) -> 0 | GP12: =+SUBTOTAL(9,GD12:GO12) -> 0 | GR12: =SUM(GR9:GR11) -> 0 | GS12: =SUM(GS9:GS11) -> 0 | GT12: =SUM(GT9:GT11) -> 0 | GU12: =SUM(GU9:GU11) -> 0 | GV12: =SUM(GV9:GV11) -> 0 | GW12: =SUM(GW9:GW11) -> 0 | GX12: =SUM(GX9:GX11) -> 0 | GY12: =SUM(GY9:GY11) -> 0 | ... HC12: =SUM(HC9:HC11) -> 0 | HD12: =+SUBTOTAL(9,GR12:HC12) -> 0 | HF12: =SUM(HF9:HF11) -> 0 | HG12: =SUM(HG9:HG11) -> 0 | HH12: =SUM(HH9:HH11) -> 0 | HI12: =SUM(HI9:HI11) -> 0 | HJ12: =SUM(HJ9:HJ11) -> 0 | HK12: =SUM(HK9:HK11) -> 0 | HL12: =SUM(HL9:HL11) -> 0 | HM12: =SUM(HM9:HM11) -> 0 | ... HQ12: =SUM(HQ9:HQ11) -> 0 | HR12: =+SUBTOTAL(9,HF12:HQ12) -> 0 | HT12: =SUM(HT9:HT11) -> 0 | HU12: =SUM(HU9:HU11) -> 0 | HV12: =SUM(HV9:HV11) -> 0 | HW12: =SUM(HW9:HW11) -> 0 | HX12: =SUM(HX9:HX11) -> 0 | HY12: =SUM(HY9:HY11) -> 0 | HZ12: =SUM(HZ9:HZ11) -> 0 | IA12: =SUM(IA9:IA11) -> 0 | ... IE12: =SUM(IE9:IE11) -> 0 | IF12: =+SUBTOTAL(9,HT12:IE12) -> 0 | IH12: =SUM(IH9:IH11) -> 0 | II12: =SUM(II9:II11) -> 0 | IJ12: =SUM(IJ9:IJ11) -> 0 | IK12: =SUM(IK9:IK11) -> 0 | IL12: =SUM(IL9:IL11) -> 0 | IM12: =SUM(IM9:IM11) -> 0 | IN12: =SUM(IN9:IN11) -> 0 | IO12: =SUM(IO9:IO11) -> 0 | ... IS12: =SUM(IS9:IS11) -> 0 | IT12: =+SUBTOTAL(9,IH12:IS12) -> 0 | IV12: =SUM(IV9:IV11) -> 0 | IW12: =SUM(IW9:IW11) -> 0 | IX12: =SUM(IX9:IX11) -> 0 | IY12: =SUM(IY9:IY11) -> 0 | IZ12: =SUM(IZ9:IZ11) -> 0 | JA12: =SUM(JA9:JA11) -> 0 | JB12: =SUM(JB9:JB11) -> 0 | JC12: =SUM(JC9:JC11) -> 0 | ... JG12: =SUM(JG9:JG11) -> 0 | JH12: =+SUBTOTAL(9,IV12:JG12) -> 0 | JJ12: =SUM(JJ9:JJ11) -> 0 | JK12: =SUM(JK9:JK11) -> 0 | JL12: =SUM(JL9:JL11) -> 0 | JM12: =SUM(JM9:JM11) -> 0 | JN12: =SUM(JN9:JN11) -> 0 | JO12: =SUM(JO9:JO11) -> 0 | JP12: =SUM(JP9:JP11) -> 0 | JQ12: =SUM(JQ9:JQ11) -> 0 | ... JU12: =SUM(JU9:JU11) -> 0 | JV12: =+SUBTOTAL(9,JJ12:JU12) -> 0 | JX12: =SUM(JX9:JX11) -> 0 | JY12: =SUM(JY9:JY11) -> 0 | JZ12: =SUM(JZ9:JZ11) -> 0 | KA12: =SUM(KA9:KA11) -> 0 | KB12: =SUM(KB9:KB11) -> 0 | KC12: =SUM(KC9:KC11) -> 0 | KD12: =SUM(KD9:KD11) -> 0 | KE12: =SUM(KE9:KE11) -> 0 | ... KI12: =SUM(KI9:KI11) -> 0 | KJ12: =+SUBTOTAL(9,JX12:KI12) -> 0 | KL12: =SUM(KL9:KL11) -> 0 | KM12: =SUM(KM9:KM11) -> 0 | KN12: =SUM(KN9:KN11) -> 0 | KO12: =SUM(KO9:KO11) -> 0 | KP12: =SUM(KP9:KP11) -> 0 | KQ12: =SUM(KQ9:KQ11) -> 0 | KR12: =SUM(KR9:KR11) -> 0 | KS12: =SUM(KS9:KS11) -> 0 | ... KW12: =SUM(KW9:KW11) -> 0 | KX12: =+SUBTOTAL(9,KL12:KW12) -> 0 | KZ12: =SUM(KZ9:KZ11) -> 0 | LA12: =SUM(LA9:LA11) -> 0 | LB12: =SUM(LB9:LB11) -> 0 | LC12: =SUM(LC9:LC11) -> 0 | LD12: =SUM(LD9:LD11) -> 0 | LE12: =SUM(LE9:LE11) -> 0 | LF12: =SUM(LF9:LF11) -> 0 | LG12: =SUM(LG9:LG11) -> 0 | ... LK12: =SUM(LK9:LK11) -> 0 | LL12: =+SUBTOTAL(9,KZ12:LK12) -> 0 | LN12: =SUM(LN9:LN11) -> 0 | LO12: =SUM(LO9:LO11) -> 0 | LP12: =SUM(LP9:LP11) -> 0 | LQ12: =SUM(LQ9:LQ11) -> 0 | LR12: =SUM(LR9:LR11) -> 0 | LS12: =SUM(LS9:LS11) -> 0 | LT12: =SUM(LT9:LT11) -> 0 | LU12: =SUM(LU9:LU11) -> 0 | ... LY12: =SUM(LY9:LY11) -> 0 | LZ12: =+SUBTOTAL(9,LN12:LY12) -> 0 | MB12: =SUM(MB9:MB11) -> 0 | MC12: =SUM(MC9:MC11) -> 0 | MD12: =SUM(MD9:MD11) -> 0 | ME12: =SUM(ME9:ME11) -> 0 | MF12: =SUM(MF9:MF11) -> 0 | MG12: =SUM(MG9:MG11) -> 0 | MH12: =SUM(MH9:MH11) -> 0 | MI12: =SUM(MI9:MI11) -> 0 | ... MN12: =SUM(MN9:MN11) -> 0
B14: DIRECT COSTS
B15: Crew Management | D15: 0 | E15: 0 | F15: 0 | G15: 0 | H15: 0 | I15: 0 | J15: 0 | K15: 0 | L15: 0 | M15: 0 | N15: 0 | O15: 0 | P15: =+SUBTOTAL(9,D15:O15) -> 0 | R15: 0 | S15: 0 | T15: 0 | U15: 0 | V15: 0 | W15: 0 | X15: 0 | Y15: 0 | Z15: 0 | AA15: 0 | AB15: 0 | AC15: 0 | AD15: =+SUBTOTAL(9,R15:AC15) -> 0 | AF15: 0 | AG15: 0 | AH15: 0 | AI15: 0 | AJ15: 0 | AK15: 0 | AL15: 0 | AM15: 0 | AN15: 0 | AO15: 0 | AP15: 0 | AQ15: 0 | AR15: =+SUBTOTAL(9,AF15:AQ15) -> 0 | AT15: 0 | AU15: 0 | AV15: 0 | AW15: 0 | AX15: 0 | AY15: 0 | AZ15: 0 | BA15: 0 | BB15: 0 | BC15: 0 | BD15: 0 | BE15: 0 | BF15: =+SUBTOTAL(9,AT15:BE15) -> 0 | BH15: 0 | BI15: 0 | BJ15: 0 | BK15: 0 | BL15: 0 | BM15: 0 | BN15: 0 | BO15: 0 | BP15: 0 | BQ15: 0 | BR15: 0 | BS15: 0 | BT15: =+SUBTOTAL(9,BH15:BS15) -> 0 | BV15: 0 | BW15: 0 | BX15: 0 | BY15: 0 | BZ15: 0 | CA15: 0 | CB15: 0 | CC15: 0 | CD15: 0 | CE15: 0 | CF15: 0 | CG15: 0 | CH15: =+SUBTOTAL(9,BV15:CG15) -> 0 | CJ15: 0 | CK15: 0 | CL15: 0 | CM15: 0 | CN15: 0 | CO15: 0 | CP15: 0 | CQ15: 0 | CR15: 0 | CS15: 0 | CT15: 0 | CU15: 0 | CV15: =+SUBTOTAL(9,CJ15:CU15) -> 0 | CX15: 0 | CY15: 0 | CZ15: 0 | DA15: 0 | DB15: 0 | DC15: 0 | DD15: 0 | DE15: 0 | DF15: 0 | DG15: 0 | DH15: 0 | DI15: 0 | DJ15: =+SUBTOTAL(9,CX15:DI15) -> 0 | DL15: 0 | DM15: 0 | DN15: 0 | DO15: 0 | DP15: 0 | DQ15: 0 | DR15: 0 | DS15: 0 | DT15: 0 | DU15: 0 | DV15: 0 | DW15: 0 | DX15: =+SUBTOTAL(9,DL15:DW15) -> 0 | DZ15: 0 | EA15: 0 | EB15: 0 | EC15: 0 | ED15: 0 | EE15: 0 | EF15: 0 | EG15: 0 | EH15: 0 | EI15: 0 | EJ15: 0 | EK15: 0 | EL15: =+SUBTOTAL(9,DZ15:EK15) -> 0 | EN15: 0 | EO15: 0 | EP15: 0 | EQ15: 0 | ER15: 0 | ES15: 0 | ET15: 0 | EU15: 0 | EV15: 0 | EW15: 0 | EX15: 0 | EY15: 0 | EZ15: =+SUBTOTAL(9,EN15:EY15) -> 0 | FB15: 0 | FC15: 0 | FD15: 0 | FE15: 0 | FF15: 0 | FG15: 0 | FH15: 0 | FI15: 0 | FJ15: 0 | FK15: 0 | FL15: 0 | FM15: 0 | FN15: =+SUBTOTAL(9,FB15:FM15) -> 0 | FP15: 0 | FQ15: 0 | FR15: 0 | FS15: 0 | FT15: 0 | FU15: 0 | FV15: 0 | FW15: 0 | FX15: 0 | FY15: 0 | FZ15: 0 | GA15: 0 | GB15: =+SUBTOTAL(9,FP15:GA15) -> 0 | GD15: 0 | GE15: 0 | GF15: 0 | GG15: 0 | GH15: 0 | GI15: 0 | GJ15: 0 | GK15: 0 | GL15: 0 | GM15: 0 | GN15: 0 | GO15: 0 | GP15: =+SUBTOTAL(9,GD15:GO15) -> 0 | GR15: 0 | GS15: 0 | GT15: 0 | GU15: 0 | GV15: 0 | GW15: 0 | GX15: 0 | GY15: 0 | GZ15: 0 | HA15: 0 | HB15: 0 | HC15: 0 | HD15: =+SUBTOTAL(9,GR15:HC15) -> 0 | HF15: 0 | HG15: 0 | HH15: 0 | HI15: 0 | HJ15: 0 | HK15: 0 | HL15: 0 | HM15: 0 | HN15: 0 | HO15: 0 | HP15: 0 | HQ15: 0 | HR15: =+SUBTOTAL(9,HF15:HQ15) -> 0 | HT15: 0 | HU15: 0 | HV15: 0 | HW15: 0 | HX15: 0 | HY15: 0 | HZ15: 0 | IA15: 0 | IB15: 0 | IC15: 0 | ID15: 0 | IE15: 0 | IF15: =+SUBTOTAL(9,HT15:IE15) -> 0 | IH15: 0 | II15: 0 | IJ15: 0 | IK15: 0 | IL15: 0 | IM15: 0 | IN15: 0 | IO15: 0 | IP15: 0 | IQ15: 0 | IR15: 0 | IS15: 0 | IT15: =+SUBTOTAL(9,IH15:IS15) -> 0 | IV15: 0 | IW15: 0 | IX15: 0 | IY15: 0 | IZ15: 0 | JA15: 0 | JB15: 0 | JC15: 0 | JD15: 0 | JE15: 0 | JF15: 0 | JG15: 0 | JH15: =+SUBTOTAL(9,IV15:JG15) -> 0 | JJ15: 0 | JK15: 0 | JL15: 0 | JM15: 0 | JN15: 0 | JO15: 0 | JP15: 0 | JQ15: 0 | JR15: 0 | JS15: 0 | JT15: 0 | JU15: 0 | JV15: =+SUBTOTAL(9,JJ15:JU15) -> 0 | JX15: 0 | JY15: 0 | JZ15: 0 | KA15: 0 | KB15: 0 | KC15: 0 | KD15: 0 | KE15: 0 | KF15: 0 | KG15: 0 | KH15: 0 | KI15: 0 | KJ15: =+SUBTOTAL(9,JX15:KI15) -> 0 | KL15: 0 | KM15: 0 | KN15: 0 | KO15: 0 | KP15: 0 | KQ15: 0 | KR15: 0 | KS15: 0 | KT15: 0 | KU15: 0 | KV15: 0 | KW15: 0 | KX15: =+SUBTOTAL(9,KL15:KW15) -> 0 | KZ15: 0 | LA15: 0 | LB15: 0 | LC15: 0 | LD15: 0 | LE15: 0 | LF15: 0 | LG15: 0 | LH15: 0 | LI15: 0 | LJ15: 0 | LK15: 0 | LL15: =+SUBTOTAL(9,KZ15:LK15) -> 0 | LN15: 0 | LO15: 0 | LP15: 0 | LQ15: 0 | LR15: 0 | LS15: 0 | LT15: 0 | LU15: 0 | LV15: 0 | LW15: 0 | LX15: 0 | LY15: 0 | LZ15: =+SUBTOTAL(9,LN15:LY15) -> 0 | MB15: =SUMIF($D$6:$LY$6,MB$3,$D15:$LY15) -> 0 | MC15: =SUMIF($D$6:$LY$6,MC$3,$D15:$LY15) -> 0 | MD15: =SUMIF($D$6:$LY$6,MD$3,$D15:$LY15) -> 0 | ME15: =SUMIF($D$6:$LY$6,ME$3,$D15:$LY15) -> 0 | MF15: =SUMIF($D$6:$LY$6,MF$3,$D15:$LY15) -> 0 | MG15: =SUMIF($D$6:$LY$6,MG$3,$D15:$LY15) -> 0 | MH15: =SUMIF($D$6:$LY$6,MH$3,$D15:$LY15) -> 0 | MI15: =SUMIF($D$6:$LY$6,MI$3,$D15:$LY15) -> 0 | ... MM15: =SUMIF($D$6:$LY$6,MM$3,$D15:$LY15) -> 0 | MN15: =SUM(MB15:MM15) -> 0
B16: Cruise Management | D16: 0 | E16: 0 | F16: 0 | G16: 0 | H16: 0 | I16: 0 | J16: 0 | K16: 0 | L16: 0 | M16: 0 | N16: 0 | O16: 0 | P16: =+SUBTOTAL(9,D16:O16) -> 0 | R16: 0 | S16: 0 | T16: 0 | U16: 0 | V16: 0 | W16: 0 | X16: 0 | Y16: 0 | Z16: 0 | AA16: 0 | AB16: 0 | AC16: 0 | AD16: =+SUBTOTAL(9,R16:AC16) -> 0 | AF16: 0 | AG16: 0 | AH16: 0 | AI16: 0 | AJ16: 0 | AK16: 0 | AL16: 0 | AM16: 0 | AN16: 0 | AO16: 0 | AP16: 0 | AQ16: 0 | AR16: =+SUBTOTAL(9,AF16:AQ16) -> 0 | AT16: 0 | AU16: 0 | AV16: 0 | AW16: 0 | AX16: 0 | AY16: 0 | AZ16: 0 | BA16: 0 | BB16: 0 | BC16: 0 | BD16: 0 | BE16: 0 | BF16: =+SUBTOTAL(9,AT16:BE16) -> 0 | BH16: 0 | BI16: 0 | BJ16: 0 | BK16: 0 | BL16: 0 | BM16: 0 | BN16: 0 | BO16: 0 | BP16: 0 | BQ16: 0 | BR16: 0 | BS16: 0 | BT16: =+SUBTOTAL(9,BH16:BS16) -> 0 | BV16: 0 | BW16: 0 | BX16: 0 | BY16: 0 | BZ16: 0 | CA16: 0 | CB16: 0 | CC16: 0 | CD16: 0 | CE16: 0 | CF16: 0 | CG16: 0 | CH16: =+SUBTOTAL(9,BV16:CG16) -> 0 | CJ16: 0 | CK16: 0 | CL16: 0 | CM16: 0 | CN16: 0 | CO16: 0 | CP16: 0 | CQ16: 0 | CR16: 0 | CS16: 0 | CT16: 0 | CU16: 0 | CV16: =+SUBTOTAL(9,CJ16:CU16) -> 0 | CX16: 0 | CY16: 0 | CZ16: 0 | DA16: 0 | DB16: 0 | DC16: 0 | DD16: 0 | DE16: 0 | DF16: 0 | DG16: 0 | DH16: 0 | DI16: 0 | DJ16: =+SUBTOTAL(9,CX16:DI16) -> 0 | DL16: 0 | DM16: 0 | DN16: 0 | DO16: 0 | DP16: 0 | DQ16: 0 | DR16: 0 | DS16: 0 | DT16: 0 | DU16: 0 | DV16: 0 | DW16: 0 | DX16: =+SUBTOTAL(9,DL16:DW16) -> 0 | DZ16: 0 | EA16: 0 | EB16: 0 | EC16: 0 | ED16: 0 | EE16: 0 | EF16: 0 | EG16: 0 | EH16: 0 | EI16: 0 | EJ16: 0 | EK16: 0 | EL16: =+SUBTOTAL(9,DZ16:EK16) -> 0 | EN16: 0 | EO16: 0 | EP16: 0 | EQ16: 0 | ER16: 0 | ES16: 0 | ET16: 0 | EU16: 0 | EV16: 0 | EW16: 0 | EX16: 0 | EY16: 0 | EZ16: =+SUBTOTAL(9,EN16:EY16) -> 0 | FB16: 0 | FC16: 0 | FD16: 0 | FE16: 0 | FF16: 0 | FG16: 0 | FH16: 0 | FI16: 0 | FJ16: 0 | FK16: 0 | FL16: 0 | FM16: 0 | FN16: =+SUBTOTAL(9,FB16:FM16) -> 0 | FP16: 0 | FQ16: 0 | FR16: 0 | FS16: 0 | FT16: 0 | FU16: 0 | FV16: 0 | FW16: 0 | FX16: 0 | FY16: 0 | FZ16: 0 | GA16: 0 | GB16: =+SUBTOTAL(9,FP16:GA16) -> 0 | GD16: 0 | GE16: 0 | GF16: 0 | GG16: 0 | GH16: 0 | GI16: 0 | GJ16: 0 | GK16: 0 | GL16: 0 | GM16: 0 | GN16: 0 | GO16: 0 | GP16: =+SUBTOTAL(9,GD16:GO16) -> 0 | GR16: 0 | GS16: 0 | GT16: 0 | GU16: 0 | GV16: 0 | GW16: 0 | GX16: 0 | GY16: 0 | GZ16: 0 | HA16: 0 | HB16: 0 | HC16: 0 | HD16: =+SUBTOTAL(9,GR16:HC16) -> 0 | HF16: 0 | HG16: 0 | HH16: 0 | HI16: 0 | HJ16: 0 | HK16: 0 | HL16: 0 | HM16: 0 | HN16: 0 | HO16: 0 | HP16: 0 | HQ16: 0 | HR16: =+SUBTOTAL(9,HF16:HQ16) -> 0 | HT16: 0 | HU16: 0 | HV16: 0 | HW16: 0 | HX16: 0 | HY16: 0 | HZ16: 0 | IA16: 0 | IB16: 0 | IC16: 0 | ID16: 0 | IE16: 0 | IF16: =+SUBTOTAL(9,HT16:IE16) -> 0 | IH16: 0 | II16: 0 | IJ16: 0 | IK16: 0 | IL16: 0 | IM16: 0 | IN16: 0 | IO16: 0 | IP16: 0 | IQ16: 0 | IR16: 0 | IS16: 0 | IT16: =+SUBTOTAL(9,IH16:IS16) -> 0 | IV16: 0 | IW16: 0 | IX16: 0 | IY16: 0 | IZ16: 0 | JA16: 0 | JB16: 0 | JC16: 0 | JD16: 0 | JE16: 0 | JF16: 0 | JG16: 0 | JH16: =+SUBTOTAL(9,IV16:JG16) -> 0 | JJ16: 0 | JK16: 0 | JL16: 0 | JM16: 0 | JN16: 0 | JO16: 0 | JP16: 0 | JQ16: 0 | JR16: 0 | JS16: 0 | JT16: 0 | JU16: 0 | JV16: =+SUBTOTAL(9,JJ16:JU16) -> 0 | JX16: 0 | JY16: 0 | JZ16: 0 | KA16: 0 | KB16: 0 | KC16: 0 | KD16: 0 | KE16: 0 | KF16: 0 | KG16: 0 | KH16: 0 | KI16: 0 | KJ16: =+SUBTOTAL(9,JX16:KI16) -> 0 | KL16: 0 | KM16: 0 | KN16: 0 | KO16: 0 | KP16: 0 | KQ16: 0 | KR16: 0 | KS16: 0 | KT16: 0 | KU16: 0 | KV16: 0 | KW16: 0 | KX16: =+SUBTOTAL(9,KL16:KW16) -> 0 | KZ16: 0 | LA16: 0 | LB16: 0 | LC16: 0 | LD16: 0 | LE16: 0 | LF16: 0 | LG16: 0 | LH16: 0 | LI16: 0 | LJ16: 0 | LK16: 0 | LL16: =+SUBTOTAL(9,KZ16:LK16) -> 0 | LN16: 0 | LO16: 0 | LP16: 0 | LQ16: 0 | LR16: 0 | LS16: 0 | LT16: 0 | LU16: 0 | LV16: 0 | LW16: 0 | LX16: 0 | LY16: 0 | LZ16: =+SUBTOTAL(9,LN16:LY16) -> 0 | MB16: =SUMIF($D$6:$LY$6,MB$3,$D16:$LY16) -> 0 | MC16: =SUMIF($D$6:$LY$6,MC$3,$D16:$LY16) -> 0 | MD16: =SUMIF($D$6:$LY$6,MD$3,$D16:$LY16) -> 0 | ME16: =SUMIF($D$6:$LY$6,ME$3,$D16:$LY16) -> 0 | MF16: =SUMIF($D$6:$LY$6,MF$3,$D16:$LY16) -> 0 | MG16: =SUMIF($D$6:$LY$6,MG$3,$D16:$LY16) -> 0 | MH16: =SUMIF($D$6:$LY$6,MH$3,$D16:$LY16) -> 0 | MI16: =SUMIF($D$6:$LY$6,MI$3,$D16:$LY16) -> 0 | ... MM16: =SUMIF($D$6:$LY$6,MM$3,$D16:$LY16) -> 0 | MN16: =SUM(MB16:MM16) -> 0
B17: Travel | D17: 0 | E17: 0 | F17: 0 | G17: 0 | H17: 0 | I17: 0 | J17: 0 | K17: 0 | L17: 0 | M17: 0 | N17: 0 | O17: 0 | P17: =+SUBTOTAL(9,D17:O17) -> 0 | R17: 0 | S17: 0 | T17: 0 | U17: 0 | V17: 0 | W17: 0 | X17: 0 | Y17: 0 | Z17: 0 | AA17: 0 | AB17: 0 | AC17: 0 | AD17: =+SUBTOTAL(9,R17:AC17) -> 0 | AF17: 0 | AG17: 0 | AH17: 0 | AI17: 0 | AJ17: 0 | AK17: 0 | AL17: 0 | AM17: 0 | AN17: 0 | AO17: 0 | AP17: 0 | AQ17: 0 | AR17: =+SUBTOTAL(9,AF17:AQ17) -> 0 | AT17: 0 | AU17: 0 | AV17: 0 | AW17: 0 | AX17: 0 | AY17: 0 | AZ17: 0 | BA17: 0 | BB17: 0 | BC17: 0 | BD17: 0 | BE17: 0 | BF17: =+SUBTOTAL(9,AT17:BE17) -> 0 | BH17: 0 | BI17: 0 | BJ17: 0 | BK17: 0 | BL17: 0 | BM17: 0 | BN17: 0 | BO17: 0 | BP17: 0 | BQ17: 0 | BR17: 0 | BS17: 0 | BT17: =+SUBTOTAL(9,BH17:BS17) -> 0 | BV17: 0 | BW17: 0 | BX17: 0 | BY17: 0 | BZ17: 0 | CA17: 0 | CB17: 0 | CC17: 0 | CD17: 0 | CE17: 0 | CF17: 0 | CG17: 0 | CH17: =+SUBTOTAL(9,BV17:CG17) -> 0 | CJ17: 0 | CK17: 0 | CL17: 0 | CM17: 0 | CN17: 0 | CO17: 0 | CP17: 0 | CQ17: 0 | CR17: 0 | CS17: 0 | CT17: 0 | CU17: 0 | CV17: =+SUBTOTAL(9,CJ17:CU17) -> 0 | CX17: 0 | CY17: 0 | CZ17: 0 | DA17: 0 | DB17: 0 | DC17: 0 | DD17: 0 | DE17: 0 | DF17: 0 | DG17: 0 | DH17: 0 | DI17: 0 | DJ17: =+SUBTOTAL(9,CX17:DI17) -> 0 | DL17: 0 | DM17: 0 | DN17: 0 | DO17: 0 | DP17: 0 | DQ17: 0 | DR17: 0 | DS17: 0 | DT17: 0 | DU17: 0 | DV17: 0 | DW17: 0 | DX17: =+SUBTOTAL(9,DL17:DW17) -> 0 | DZ17: 0 | EA17: 0 | EB17: 0 | EC17: 0 | ED17: 0 | EE17: 0 | EF17: 0 | EG17: 0 | EH17: 0 | EI17: 0 | EJ17: 0 | EK17: 0 | EL17: =+SUBTOTAL(9,DZ17:EK17) -> 0 | EN17: 0 | EO17: 0 | EP17: 0 | EQ17: 0 | ER17: 0 | ES17: 0 | ET17: 0 | EU17: 0 | EV17: 0 | EW17: 0 | EX17: 0 | EY17: 0 | EZ17: =+SUBTOTAL(9,EN17:EY17) -> 0 | FB17: 0 | FC17: 0 | FD17: 0 | FE17: 0 | FF17: 0 | FG17: 0 | FH17: 0 | FI17: 0 | FJ17: 0 | FK17: 0 | FL17: 0 | FM17: 0 | FN17: =+SUBTOTAL(9,FB17:FM17) -> 0 | FP17: 0 | FQ17: 0 | FR17: 0 | FS17: 0 | FT17: 0 | FU17: 0 | FV17: 0 | FW17: 0 | FX17: 0 | FY17: 0 | FZ17: 0 | GA17: 0 | GB17: =+SUBTOTAL(9,FP17:GA17) -> 0 | GD17: 0 | GE17: 0 | GF17: 0 | GG17: 0 | GH17: 0 | GI17: 0 | GJ17: 0 | GK17: 0 | GL17: 0 | GM17: 0 | GN17: 0 | GO17: 0 | GP17: =+SUBTOTAL(9,GD17:GO17) -> 0 | GR17: 0 | GS17: 0 | GT17: 0 | GU17: 0 | GV17: 0 | GW17: 0 | GX17: 0 | GY17: 0 | GZ17: 0 | HA17: 0 | HB17: 0 | HC17: 0 | HD17: =+SUBTOTAL(9,GR17:HC17) -> 0 | HF17: 0 | HG17: 0 | HH17: 0 | HI17: 0 | HJ17: 0 | HK17: 0 | HL17: 0 | HM17: 0 | HN17: 0 | HO17: 0 | HP17: 0 | HQ17: 0 | HR17: =+SUBTOTAL(9,HF17:HQ17) -> 0 | HT17: 0 | HU17: 0 | HV17: 0 | HW17: 0 | HX17: 0 | HY17: 0 | HZ17: 0 | IA17: 0 | IB17: 0 | IC17: 0 | ID17: 0 | IE17: 0 | IF17: =+SUBTOTAL(9,HT17:IE17) -> 0 | IH17: 0 | II17: 0 | IJ17: 0 | IK17: 0 | IL17: 0 | IM17: 0 | IN17: 0 | IO17: 0 | IP17: 0 | IQ17: 0 | IR17: 0 | IS17: 0 | IT17: =+SUBTOTAL(9,IH17:IS17) -> 0 | IV17: 0 | IW17: 0 | IX17: 0 | IY17: 0 | IZ17: 0 | JA17: 0 | JB17: 0 | JC17: 0 | JD17: 0 | JE17: 0 | JF17: 0 | JG17: 0 | JH17: =+SUBTOTAL(9,IV17:JG17) -> 0 | JJ17: 0 | JK17: 0 | JL17: 0 | JM17: 0 | JN17: 0 | JO17: 0 | JP17: 0 | JQ17: 0 | JR17: 0 | JS17: 0 | JT17: 0 | JU17: 0 | JV17: =+SUBTOTAL(9,JJ17:JU17) -> 0 | JX17: 0 | JY17: 0 | JZ17: 0 | KA17: 0 | KB17: 0 | KC17: 0 | KD17: 0 | KE17: 0 | KF17: 0 | KG17: 0 | KH17: 0 | KI17: 0 | KJ17: =+SUBTOTAL(9,JX17:KI17) -> 0 | KL17: 0 | KM17: 0 | KN17: 0 | KO17: 0 | KP17: 0 | KQ17: 0 | KR17: 0 | KS17: 0 | KT17: 0 | KU17: 0 | KV17: 0 | KW17: 0 | KX17: =+SUBTOTAL(9,KL17:KW17) -> 0 | KZ17: 0 | LA17: 0 | LB17: 0 | LC17: 0 | LD17: 0 | LE17: 0 | LF17: 0 | LG17: 0 | LH17: 0 | LI17: 0 | LJ17: 0 | LK17: 0 | LL17: =+SUBTOTAL(9,KZ17:LK17) -> 0 | LN17: 0 | LO17: 0 | LP17: 0 | LQ17: 0 | LR17: 0 | LS17: 0 | LT17: 0 | LU17: 0 | LV17: 0 | LW17: 0 | LX17: 0 | LY17: 0 | LZ17: =+SUBTOTAL(9,LN17:LY17) -> 0 | MB17: =SUMIF($D$6:$LY$6,MB$3,$D17:$LY17) -> 0 | MC17: =SUMIF($D$6:$LY$6,MC$3,$D17:$LY17) -> 0 | MD17: =SUMIF($D$6:$LY$6,MD$3,$D17:$LY17) -> 0 | ME17: =SUMIF($D$6:$LY$6,ME$3,$D17:$LY17) -> 0 | MF17: =SUMIF($D$6:$LY$6,MF$3,$D17:$LY17) -> 0 | MG17: =SUMIF($D$6:$LY$6,MG$3,$D17:$LY17) -> 0 | MH17: =SUMIF($D$6:$LY$6,MH$3,$D17:$LY17) -> 0 | MI17: =SUMIF($D$6:$LY$6,MI$3,$D17:$LY17) -> 0 | ... MM17: =SUMIF($D$6:$LY$6,MM$3,$D17:$LY17) -> 0 | MN17: =SUM(MB17:MM17) -> 0
B18: Training | D18: 0 | E18: 0 | F18: 0 | G18: 0 | H18: 0 | I18: 0 | J18: 0 | K18: 0 | L18: 0 | M18: 0 | N18: 0 | O18: 0 | P18: =+SUBTOTAL(9,D18:O18) -> 0 | R18: 0 | S18: 0 | T18: 0 | U18: 0 | V18: 0 | W18: 0 | X18: 0 | Y18: 0 | Z18: 0 | AA18: 0 | AB18: 0 | AC18: 0 | AD18: =+SUBTOTAL(9,R18:AC18) -> 0 | AF18: 0 | AG18: 0 | AH18: 0 | AI18: 0 | AJ18: 0 | AK18: 0 | AL18: 0 | AM18: 0 | AN18: 0 | AO18: 0 | AP18: 0 | AQ18: 0 | AR18: =+SUBTOTAL(9,AF18:AQ18) -> 0 | AT18: 0 | AU18: 0 | AV18: 0 | AW18: 0 | AX18: 0 | AY18: 0 | AZ18: 0 | BA18: 0 | BB18: 0 | BC18: 0 | BD18: 0 | BE18: 0 | BF18: =+SUBTOTAL(9,AT18:BE18) -> 0 | BH18: 0 | BI18: 0 | BJ18: 0 | BK18: 0 | BL18: 0 | BM18: 0 | BN18: 0 | BO18: 0 | BP18: 0 | BQ18: 0 | BR18: 0 | BS18: 0 | BT18: =+SUBTOTAL(9,BH18:BS18) -> 0 | BV18: 0 | BW18: 0 | BX18: 0 | BY18: 0 | BZ18: 0 | CA18: 0 | CB18: 0 | CC18: 0 | CD18: 0 | CE18: 0 | CF18: 0 | CG18: 0 | CH18: =+SUBTOTAL(9,BV18:CG18) -> 0 | CJ18: 0 | CK18: 0 | CL18: 0 | CM18: 0 | CN18: 0 | CO18: 0 | CP18: 0 | CQ18: 0 | CR18: 0 | CS18: 0 | CT18: 0 | CU18: 0 | CV18: =+SUBTOTAL(9,CJ18:CU18) -> 0 | CX18: 0 | CY18: 0 | CZ18: 0 | DA18: 0 | DB18: 0 | DC18: 0 | DD18: 0 | DE18: 0 | DF18: 0 | DG18: 0 | DH18: 0 | DI18: 0 | DJ18: =+SUBTOTAL(9,CX18:DI18) -> 0 | DL18: 0 | DM18: 0 | DN18: 0 | DO18: 0 | DP18: 0 | DQ18: 0 | DR18: 0 | DS18: 0 | DT18: 0 | DU18: 0 | DV18: 0 | DW18: 0 | DX18: =+SUBTOTAL(9,DL18:DW18) -> 0 | DZ18: 0 | EA18: 0 | EB18: 0 | EC18: 0 | ED18: 0 | EE18: 0 | EF18: 0 | EG18: 0 | EH18: 0 | EI18: 0 | EJ18: 0 | EK18: 0 | EL18: =+SUBTOTAL(9,DZ18:EK18) -> 0 | EN18: 0 | EO18: 0 | EP18: 0 | EQ18: 0 | ER18: 0 | ES18: 0 | ET18: 0 | EU18: 0 | EV18: 0 | EW18: 0 | EX18: 0 | EY18: 0 | EZ18: =+SUBTOTAL(9,EN18:EY18) -> 0 | FB18: 0 | FC18: 0 | FD18: 0 | FE18: 0 | FF18: 0 | FG18: 0 | FH18: 0 | FI18: 0 | FJ18: 0 | FK18: 0 | FL18: 0 | FM18: 0 | FN18: =+SUBTOTAL(9,FB18:FM18) -> 0 | FP18: 0 | FQ18: 0 | FR18: 0 | FS18: 0 | FT18: 0 | FU18: 0 | FV18: 0 | FW18: 0 | FX18: 0 | FY18: 0 | FZ18: 0 | GA18: 0 | GB18: =+SUBTOTAL(9,FP18:GA18) -> 0 | GD18: 0 | GE18: 0 | GF18: 0 | GG18: 0 | GH18: 0 | GI18: 0 | GJ18: 0 | GK18: 0 | GL18: 0 | GM18: 0 | GN18: 0 | GO18: 0 | GP18: =+SUBTOTAL(9,GD18:GO18) -> 0 | GR18: 0 | GS18: 0 | GT18: 0 | GU18: 0 | GV18: 0 | GW18: 0 | GX18: 0 | GY18: 0 | GZ18: 0 | HA18: 0 | HB18: 0 | HC18: 0 | HD18: =+SUBTOTAL(9,GR18:HC18) -> 0 | HF18: 0 | HG18: 0 | HH18: 0 | HI18: 0 | HJ18: 0 | HK18: 0 | HL18: 0 | HM18: 0 | HN18: 0 | HO18: 0 | HP18: 0 | HQ18: 0 | HR18: =+SUBTOTAL(9,HF18:HQ18) -> 0 | HT18: 0 | HU18: 0 | HV18: 0 | HW18: 0 | HX18: 0 | HY18: 0 | HZ18: 0 | IA18: 0 | IB18: 0 | IC18: 0 | ID18: 0 | IE18: 0 | IF18: =+SUBTOTAL(9,HT18:IE18) -> 0 | IH18: 0 | II18: 0 | IJ18: 0 | IK18: 0 | IL18: 0 | IM18: 0 | IN18: 0 | IO18: 0 | IP18: 0 | IQ18: 0 | IR18: 0 | IS18: 0 | IT18: =+SUBTOTAL(9,IH18:IS18) -> 0 | IV18: 0 | IW18: 0 | IX18: 0 | IY18: 0 | IZ18: 0 | JA18: 0 | JB18: 0 | JC18: 0 | JD18: 0 | JE18: 0 | JF18: 0 | JG18: 0 | JH18: =+SUBTOTAL(9,IV18:JG18) -> 0 | JJ18: 0 | JK18: 0 | JL18: 0 | JM18: 0 | JN18: 0 | JO18: 0 | JP18: 0 | JQ18: 0 | JR18: 0 | JS18: 0 | JT18: 0 | JU18: 0 | JV18: =+SUBTOTAL(9,JJ18:JU18) -> 0 | JX18: 0 | JY18: 0 | JZ18: 0 | KA18: 0 | KB18: 0 | KC18: 0 | KD18: 0 | KE18: 0 | KF18: 0 | KG18: 0 | KH18: 0 | KI18: 0 | KJ18: =+SUBTOTAL(9,JX18:KI18) -> 0 | KL18: 0 | KM18: 0 | KN18: 0 | KO18: 0 | KP18: 0 | KQ18: 0 | KR18: 0 | KS18: 0 | KT18: 0 | KU18: 0 | KV18: 0 | KW18: 0 | KX18: =+SUBTOTAL(9,KL18:KW18) -> 0 | KZ18: 0 | LA18: 0 | LB18: 0 | LC18: 0 | LD18: 0 | LE18: 0 | LF18: 0 | LG18: 0 | LH18: 0 | LI18: 0 | LJ18: 0 | LK18: 0 | LL18: =+SUBTOTAL(9,KZ18:LK18) -> 0 | LN18: 0 | LO18: 0 | LP18: 0 | LQ18: 0 | LR18: 0 | LS18: 0 | LT18: 0 | LU18: 0 | LV18: 0 | LW18: 0 | LX18: 0 | LY18: 0 | LZ18: =+SUBTOTAL(9,LN18:LY18) -> 0 | MB18: =SUMIF($D$6:$LY$6,MB$3,$D18:$LY18) -> 0 | MC18: =SUMIF($D$6:$LY$6,MC$3,$D18:$LY18) -> 0 | MD18: =SUMIF($D$6:$LY$6,MD$3,$D18:$LY18) -> 0 | ME18: =SUMIF($D$6:$LY$6,ME$3,$D18:$LY18) -> 0 | MF18: =SUMIF($D$6:$LY$6,MF$3,$D18:$LY18) -> 0 | MG18: =SUMIF($D$6:$LY$6,MG$3,$D18:$LY18) -> 0 | MH18: =SUMIF($D$6:$LY$6,MH$3,$D18:$LY18) -> 0 | MI18: =SUMIF($D$6:$LY$6,MI$3,$D18:$LY18) -> 0 | ... MM18: =SUMIF($D$6:$LY$6,MM$3,$D18:$LY18) -> 0 | MN18: =SUM(MB18:MM18) -> 0
B19: School Expenses | D19: 0 | E19: 0 | F19: 0 | G19: 0 | H19: 0 | I19: 0 | J19: 0 | K19: 0 | L19: 0 | M19: 0 | N19: 0 | O19: 0 | P19: =+SUBTOTAL(9,D19:O19) -> 0 | R19: 0 | S19: 0 | T19: 0 | U19: 0 | V19: 0 | W19: 0 | X19: 0 | Y19: 0 | Z19: 0 | AA19: 0 | AB19: 0 | AC19: 0 | AD19: =+SUBTOTAL(9,R19:AC19) -> 0 | AF19: 0 | AG19: 0 | AH19: 0 | AI19: 0 | AJ19: 0 | AK19: 0 | AL19: 0 | AM19: 0 | AN19: 0 | AO19: 0 | AP19: 0 | AQ19: 0 | AR19: =+SUBTOTAL(9,AF19:AQ19) -> 0 | AT19: 0 | AU19: 0 | AV19: 0 | AW19: 0 | AX19: 0 | AY19: 0 | AZ19: 0 | BA19: 0 | BB19: 0 | BC19: 0 | BD19: 0 | BE19: 0 | BF19: =+SUBTOTAL(9,AT19:BE19) -> 0 | BH19: 0 | BI19: 0 | BJ19: 0 | BK19: 0 | BL19: 0 | BM19: 0 | BN19: 0 | BO19: 0 | BP19: 0 | BQ19: 0 | BR19: 0 | BS19: 0 | BT19: =+SUBTOTAL(9,BH19:BS19) -> 0 | BV19: 0 | BW19: 0 | BX19: 0 | BY19: 0 | BZ19: 0 | CA19: 0 | CB19: 0 | CC19: 0 | CD19: 0 | CE19: 0 | CF19: 0 | CG19: 0 | CH19: =+SUBTOTAL(9,BV19:CG19) -> 0 | CJ19: 0 | CK19: 0 | CL19: 0 | CM19: 0 | CN19: 0 | CO19: 0 | CP19: 0 | CQ19: 0 | CR19: 0 | CS19: 0 | CT19: 0 | CU19: 0 | CV19: =+SUBTOTAL(9,CJ19:CU19) -> 0 | CX19: 0 | CY19: 0 | CZ19: 0 | DA19: 0 | DB19: 0 | DC19: 0 | DD19: 0 | DE19: 0 | DF19: 0 | DG19: 0 | DH19: 0 | DI19: 0 | DJ19: =+SUBTOTAL(9,CX19:DI19) -> 0 | DL19: 0 | DM19: 0 | DN19: 0 | DO19: 0 | DP19: 0 | DQ19: 0 | DR19: 0 | DS19: 0 | DT19: 0 | DU19: 0 | DV19: 0 | DW19: 0 | DX19: =+SUBTOTAL(9,DL19:DW19) -> 0 | DZ19: 0 | EA19: 0 | EB19: 0 | EC19: 0 | ED19: 0 | EE19: 0 | EF19: 0 | EG19: 0 | EH19: 0 | EI19: 0 | EJ19: 0 | EK19: 0 | EL19: =+SUBTOTAL(9,DZ19:EK19) -> 0 | EN19: 0 | EO19: 0 | EP19: 0 | EQ19: 0 | ER19: 0 | ES19: 0 | ET19: 0 | EU19: 0 | EV19: 0 | EW19: 0 | EX19: 0 | EY19: 0 | EZ19: =+SUBTOTAL(9,EN19:EY19) -> 0 | FB19: 0 | FC19: 0 | FD19: 0 | FE19: 0 | FF19: 0 | FG19: 0 | FH19: 0 | FI19: 0 | FJ19: 0 | FK19: 0 | FL19: 0 | FM19: 0 | FN19: =+SUBTOTAL(9,FB19:FM19) -> 0 | FP19: 0 | FQ19: 0 | FR19: 0 | FS19: 0 | FT19: 0 | FU19: 0 | FV19: 0 | FW19: 0 | FX19: 0 | FY19: 0 | FZ19: 0 | GA19: 0 | GB19: =+SUBTOTAL(9,FP19:GA19) -> 0 | GD19: 0 | GE19: 0 | GF19: 0 | GG19: 0 | GH19: 0 | GI19: 0 | GJ19: 0 | GK19: 0 | GL19: 0 | GM19: 0 | GN19: 0 | GO19: 0 | GP19: =+SUBTOTAL(9,GD19:GO19) -> 0 | GR19: 0 | GS19: 0 | GT19: 0 | GU19: 0 | GV19: 0 | GW19: 0 | GX19: 0 | GY19: 0 | GZ19: 0 | HA19: 0 | HB19: 0 | HC19: 0 | HD19: =+SUBTOTAL(9,GR19:HC19) -> 0 | HF19: 0 | HG19: 0 | HH19: 0 | HI19: 0 | HJ19: 0 | HK19: 0 | HL19: 0 | HM19: 0 | HN19: 0 | HO19: 0 | HP19: 0 | HQ19: 0 | HR19: =+SUBTOTAL(9,HF19:HQ19) -> 0 | HT19: 0 | HU19: 0 | HV19: 0 | HW19: 0 | HX19: 0 | HY19: 0 | HZ19: 0 | IA19: 0 | IB19: 0 | IC19: 0 | ID19: 0 | IE19: 0 | IF19: =+SUBTOTAL(9,HT19:IE19) -> 0 | IH19: 0 | II19: 0 | IJ19: 0 | IK19: 0 | IL19: 0 | IM19: 0 | IN19: 0 | IO19: 0 | IP19: 0 | IQ19: 0 | IR19: 0 | IS19: 0 | IT19: =+SUBTOTAL(9,IH19:IS19) -> 0 | IV19: 0 | IW19: 0 | IX19: 0 | IY19: 0 | IZ19: 0 | JA19: 0 | JB19: 0 | JC19: 0 | JD19: 0 | JE19: 0 | JF19: 0 | JG19: 0 | JH19: =+SUBTOTAL(9,IV19:JG19) -> 0 | JJ19: 0 | JK19: 0 | JL19: 0 | JM19: 0 | JN19: 0 | JO19: 0 | JP19: 0 | JQ19: 0 | JR19: 0 | JS19: 0 | JT19: 0 | JU19: 0 | JV19: =+SUBTOTAL(9,JJ19:JU19) -> 0 | JX19: 0 | JY19: 0 | JZ19: 0 | KA19: 0 | KB19: 0 | KC19: 0 | KD19: 0 | KE19: 0 | KF19: 0 | KG19: 0 | KH19: 0 | KI19: 0 | KJ19: =+SUBTOTAL(9,JX19:KI19) -> 0 | KL19: 0 | KM19: 0 | KN19: 0 | KO19: 0 | KP19: 0 | KQ19: 0 | KR19: 0 | KS19: 0 | KT19: 0 | KU19: 0 | KV19: 0 | KW19: 0 | KX19: =+SUBTOTAL(9,KL19:KW19) -> 0 | KZ19: 0 | LA19: 0 | LB19: 0 | LC19: 0 | LD19: 0 | LE19: 0 | LF19: 0 | LG19: 0 | LH19: 0 | LI19: 0 | LJ19: 0 | LK19: 0 | LL19: =+SUBTOTAL(9,KZ19:LK19) -> 0 | LN19: 0 | LO19: 0 | LP19: 0 | LQ19: 0 | LR19: 0 | LS19: 0 | LT19: 0 | LU19: 0 | LV19: 0 | LW19: 0 | LX19: 0 | LY19: 0 | LZ19: =+SUBTOTAL(9,LN19:LY19) -> 0 | MB19: =SUMIF($D$6:$LY$6,MB$3,$D19:$LY19) -> 0 | MC19: =SUMIF($D$6:$LY$6,MC$3,$D19:$LY19) -> 0 | MD19: =SUMIF($D$6:$LY$6,MD$3,$D19:$LY19) -> 0 | ME19: =SUMIF($D$6:$LY$6,ME$3,$D19:$LY19) -> 0 | MF19: =SUMIF($D$6:$LY$6,MF$3,$D19:$LY19) -> 0 | MG19: =SUMIF($D$6:$LY$6,MG$3,$D19:$LY19) -> 0 | MH19: =SUMIF($D$6:$LY$6,MH$3,$D19:$LY19) -> 0 | MI19: =SUMIF($D$6:$LY$6,MI$3,$D19:$LY19) -> 0 | ... MM19: =SUMIF($D$6:$LY$6,MM$3,$D19:$LY19) -> 0 | MN19: =SUM(MB19:MM19) -> 0
B20: Care Training Centre Expenses | D20: 0 | E20: 0 | F20: 0 | G20: 0 | H20: 0 | I20: 0 | J20: 0 | K20: 0 | L20: 0 | M20: 0 | N20: 0 | O20: 0 | P20: =+SUBTOTAL(9,D20:O20) -> 0 | R20: 0 | S20: 0 | T20: 0 | U20: 0 | V20: 0 | W20: 0 | X20: 0 | Y20: 0 | Z20: 0 | AA20: 0 | AB20: 0 | AC20: 0 | AD20: =+SUBTOTAL(9,R20:AC20) -> 0 | AF20: 0 | AG20: 0 | AH20: 0 | AI20: 0 | AJ20: 0 | AK20: 0 | AL20: 0 | AM20: 0 | AN20: 0 | AO20: 0 | AP20: 0 | AQ20: 0 | AR20: =+SUBTOTAL(9,AF20:AQ20) -> 0 | AT20: 0 | AU20: 0 | AV20: 0 | AW20: 0 | AX20: 0 | AY20: 0 | AZ20: 0 | BA20: 0 | BB20: 0 | BC20: 0 | BD20: 0 | BE20: 0 | BF20: =+SUBTOTAL(9,AT20:BE20) -> 0 | BH20: 0 | BI20: 0 | BJ20: 0 | BK20: 0 | BL20: 0 | BM20: 0 | BN20: 0 | BO20: 0 | BP20: 0 | BQ20: 0 | BR20: 0 | BS20: 0 | BT20: =+SUBTOTAL(9,BH20:BS20) -> 0 | BV20: 0 | BW20: 0 | BX20: 0 | BY20: 0 | BZ20: 0 | CA20: 0 | CB20: 0 | CC20: 0 | CD20: 0 | CE20: 0 | CF20: 0 | CG20: 0 | CH20: =+SUBTOTAL(9,BV20:CG20) -> 0 | CJ20: 0 | CK20: 0 | CL20: 0 | CM20: 0 | CN20: 0 | CO20: 0 | CP20: 0 | CQ20: 0 | CR20: 0 | CS20: 0 | CT20: 0 | CU20: 0 | CV20: =+SUBTOTAL(9,CJ20:CU20) -> 0 | CX20: 0 | CY20: 0 | CZ20: 0 | DA20: 0 | DB20: 0 | DC20: 0 | DD20: 0 | DE20: 0 | DF20: 0 | DG20: 0 | DH20: 0 | DI20: 0 | DJ20: =+SUBTOTAL(9,CX20:DI20) -> 0 | DL20: 0 | DM20: 0 | DN20: 0 | DO20: 0 | DP20: 0 | DQ20: 0 | DR20: 0 | DS20: 0 | DT20: 0 | DU20: 0 | DV20: 0 | DW20: 0 | DX20: =+SUBTOTAL(9,DL20:DW20) -> 0 | DZ20: 0 | EA20: 0 | EB20: 0 | EC20: 0 | ED20: 0 | EE20: 0 | EF20: 0 | EG20: 0 | EH20: 0 | EI20: 0 | EJ20: 0 | EK20: 0 | EL20: =+SUBTOTAL(9,DZ20:EK20) -> 0 | EN20: 0 | EO20: 0 | EP20: 0 | EQ20: 0 | ER20: 0 | ES20: 0 | ET20: 0 | EU20: 0 | EV20: 0 | EW20: 0 | EX20: 0 | EY20: 0 | EZ20: =+SUBTOTAL(9,EN20:EY20) -> 0 | FB20: 0 | FC20: 0 | FD20: 0 | FE20: 0 | FF20: 0 | FG20: 0 | FH20: 0 | FI20: 0 | FJ20: 0 | FK20: 0 | FL20: 0 | FM20: 0 | FN20: =+SUBTOTAL(9,FB20:FM20) -> 0 | FP20: 0 | FQ20: 0 | FR20: 0 | FS20: 0 | FT20: 0 | FU20: 0 | FV20: 0 | FW20: 0 | FX20: 0 | FY20: 0 | FZ20: 0 | GA20: 0 | GB20: =+SUBTOTAL(9,FP20:GA20) -> 0 | GD20: 0 | GE20: 0 | GF20: 0 | GG20: 0 | GH20: 0 | GI20: 0 | GJ20: 0 | GK20: 0 | GL20: 0 | GM20: 0 | GN20: 0 | GO20: 0 | GP20: =+SUBTOTAL(9,GD20:GO20) -> 0 | GR20: 0 | GS20: 0 | GT20: 0 | GU20: 0 | GV20: 0 | GW20: 0 | GX20: 0 | GY20: 0 | GZ20: 0 | HA20: 0 | HB20: 0 | HC20: 0 | HD20: =+SUBTOTAL(9,GR20:HC20) -> 0 | HF20: 0 | HG20: 0 | HH20: 0 | HI20: 0 | HJ20: 0 | HK20: 0 | HL20: 0 | HM20: 0 | HN20: 0 | HO20: 0 | HP20: 0 | HQ20: 0 | HR20: =+SUBTOTAL(9,HF20:HQ20) -> 0 | HT20: 0 | HU20: 0 | HV20: 0 | HW20: 0 | HX20: 0 | HY20: 0 | HZ20: 0 | IA20: 0 | IB20: 0 | IC20: 0 | ID20: 0 | IE20: 0 | IF20: =+SUBTOTAL(9,HT20:IE20) -> 0 | IH20: 0 | II20: 0 | IJ20: 0 | IK20: 0 | IL20: 0 | IM20: 0 | IN20: 0 | IO20: 0 | IP20: 0 | IQ20: 0 | IR20: 0 | IS20: 0 | IT20: =+SUBTOTAL(9,IH20:IS20) -> 0 | IV20: 0 | IW20: 0 | IX20: 0 | IY20: 0 | IZ20: 0 | JA20: 0 | JB20: 0 | JC20: 0 | JD20: 0 | JE20: 0 | JF20: 0 | JG20: 0 | JH20: =+SUBTOTAL(9,IV20:JG20) -> 0 | JJ20: 0 | JK20: 0 | JL20: 0 | JM20: 0 | JN20: 0 | JO20: 0 | JP20: 0 | JQ20: 0 | JR20: 0 | JS20: 0 | JT20: 0 | JU20: 0 | JV20: =+SUBTOTAL(9,JJ20:JU20) -> 0 | JX20: 0 | JY20: 0 | JZ20: 0 | KA20: 0 | KB20: 0 | KC20: 0 | KD20: 0 | KE20: 0 | KF20: 0 | KG20: 0 | KH20: 0 | KI20: 0 | KJ20: =+SUBTOTAL(9,JX20:KI20) -> 0 | KL20: 0 | KM20: 0 | KN20: 0 | KO20: 0 | KP20: 0 | KQ20: 0 | KR20: 0 | KS20: 0 | KT20: 0 | KU20: 0 | KV20: 0 | KW20: 0 | KX20: =+SUBTOTAL(9,KL20:KW20) -> 0 | KZ20: 0 | LA20: 0 | LB20: 0 | LC20: 0 | LD20: 0 | LE20: 0 | LF20: 0 | LG20: 0 | LH20: 0 | LI20: 0 | LJ20: 0 | LK20: 0 | LL20: =+SUBTOTAL(9,KZ20:LK20) -> 0 | LN20: 0 | LO20: 0 | LP20: 0 | LQ20: 0 | LR20: 0 | LS20: 0 | LT20: 0 | LU20: 0 | LV20: 0 | LW20: 0 | LX20: 0 | LY20: 0 | LZ20: =+SUBTOTAL(9,LN20:LY20) -> 0 | MB20: =SUMIF($D$6:$LY$6,MB$3,$D20:$LY20) -> 0 | MC20: =SUMIF($D$6:$LY$6,MC$3,$D20:$LY20) -> 0 | MD20: =SUMIF($D$6:$LY$6,MD$3,$D20:$LY20) -> 0 | ME20: =SUMIF($D$6:$LY$6,ME$3,$D20:$LY20) -> 0 | MF20: =SUMIF($D$6:$LY$6,MF$3,$D20:$LY20) -> 0 | MG20: =SUMIF($D$6:$LY$6,MG$3,$D20:$LY20) -> 0 | MH20: =SUMIF($D$6:$LY$6,MH$3,$D20:$LY20) -> 0 | MI20: =SUMIF($D$6:$LY$6,MI$3,$D20:$LY20) -> 0 | ... MM20: =SUMIF($D$6:$LY$6,MM$3,$D20:$LY20) -> 0 | MN20: =SUM(MB20:MM20) -> 0
B21: Intercompany Cost of Sales | D21: 0 | E21: 0 | F21: 0 | G21: 0 | H21: 0 | I21: 0 | J21: 0 | K21: 0 | L21: 0 | M21: 0 | N21: 0 | O21: 0 | P21: =+SUBTOTAL(9,D21:O21) -> 0 | R21: 0 | S21: 0 | T21: 0 | U21: 0 | V21: 0 | W21: 0 | X21: 0 | Y21: 0 | Z21: 0 | AA21: 0 | AB21: 0 | AC21: 0 | AD21: =+SUBTOTAL(9,R21:AC21) -> 0 | AF21: 0 | AG21: 0 | AH21: 0 | AI21: 0 | AJ21: 0 | AK21: 0 | AL21: 0 | AM21: 0 | AN21: 0 | AO21: 0 | AP21: 0 | AQ21: 0 | AR21: =+SUBTOTAL(9,AF21:AQ21) -> 0 | AT21: 0 | AU21: 0 | AV21: 0 | AW21: 0 | AX21: 0 | AY21: 0 | AZ21: 0 | BA21: 0 | BB21: 0 | BC21: 0 | BD21: 0 | BE21: 0 | BF21: =+SUBTOTAL(9,AT21:BE21) -> 0 | BH21: 0 | BI21: 0 | BJ21: 0 | BK21: 0 | BL21: 0 | BM21: 0 | BN21: 0 | BO21: 0 | BP21: 0 | BQ21: 0 | BR21: 0 | BS21: 0 | BT21: =+SUBTOTAL(9,BH21:BS21) -> 0 | BV21: 0 | BW21: 0 | BX21: 0 | BY21: 0 | BZ21: 0 | CA21: 0 | CB21: 0 | CC21: 0 | CD21: 0 | CE21: 0 | CF21: 0 | CG21: 0 | CH21: =+SUBTOTAL(9,BV21:CG21) -> 0 | CJ21: 0 | CK21: 0 | CL21: 0 | CM21: 0 | CN21: 0 | CO21: 0 | CP21: 0 | CQ21: 0 | CR21: 0 | CS21: 0 | CT21: 0 | CU21: 0 | CV21: =+SUBTOTAL(9,CJ21:CU21) -> 0 | CX21: 0 | CY21: 0 | CZ21: 0 | DA21: 0 | DB21: 0 | DC21: 0 | DD21: 0 | DE21: 0 | DF21: 0 | DG21: 0 | DH21: 0 | DI21: 0 | DJ21: =+SUBTOTAL(9,CX21:DI21) -> 0 | DL21: 0 | DM21: 0 | DN21: 0 | DO21: 0 | DP21: 0 | DQ21: 0 | DR21: 0 | DS21: 0 | DT21: 0 | DU21: 0 | DV21: 0 | DW21: 0 | DX21: =+SUBTOTAL(9,DL21:DW21) -> 0 | DZ21: 0 | EA21: 0 | EB21: 0 | EC21: 0 | ED21: 0 | EE21: 0 | EF21: 0 | EG21: 0 | EH21: 0 | EI21: 0 | EJ21: 0 | EK21: 0 | EL21: =+SUBTOTAL(9,DZ21:EK21) -> 0 | EN21: 0 | EO21: 0 | EP21: 0 | EQ21: 0 | ER21: 0 | ES21: 0 | ET21: 0 | EU21: 0 | EV21: 0 | EW21: 0 | EX21: 0 | EY21: 0 | EZ21: =+SUBTOTAL(9,EN21:EY21) -> 0 | FB21: 0 | FC21: 0 | FD21: 0 | FE21: 0 | FF21: 0 | FG21: 0 | FH21: 0 | FI21: 0 | FJ21: 0 | FK21: 0 | FL21: 0 | FM21: 0 | FN21: =+SUBTOTAL(9,FB21:FM21) -> 0 | FP21: 0 | FQ21: 0 | FR21: 0 | FS21: 0 | FT21: 0 | FU21: 0 | FV21: 0 | FW21: 0 | FX21: 0 | FY21: 0 | FZ21: 0 | GA21: 0 | GB21: =+SUBTOTAL(9,FP21:GA21) -> 0 | GD21: 0 | GE21: 0 | GF21: 0 | GG21: 0 | GH21: 0 | GI21: 0 | GJ21: 0 | GK21: 0 | GL21: 0 | GM21: 0 | GN21: 0 | GO21: 0 | GP21: =+SUBTOTAL(9,GD21:GO21) -> 0 | GR21: 0 | GS21: 0 | GT21: 0 | GU21: 0 | GV21: 0 | GW21: 0 | GX21: 0 | GY21: 0 | GZ21: 0 | HA21: 0 | HB21: 0 | HC21: 0 | HD21: =+SUBTOTAL(9,GR21:HC21) -> 0 | HF21: 0 | HG21: 0 | HH21: 0 | HI21: 0 | HJ21: 0 | HK21: 0 | HL21: 0 | HM21: 0 | HN21: 0 | HO21: 0 | HP21: 0 | HQ21: 0 | HR21: =+SUBTOTAL(9,HF21:HQ21) -> 0 | HT21: 0 | HU21: 0 | HV21: 0 | HW21: 0 | HX21: 0 | HY21: 0 | HZ21: 0 | IA21: 0 | IB21: 0 | IC21: 0 | ID21: 0 | IE21: 0 | IF21: =+SUBTOTAL(9,HT21:IE21) -> 0 | IH21: 0 | II21: 0 | IJ21: 0 | IK21: 0 | IL21: 0 | IM21: 0 | IN21: 0 | IO21: 0 | IP21: 0 | IQ21: 0 | IR21: 0 | IS21: 0 | IT21: =+SUBTOTAL(9,IH21:IS21) -> 0 | IV21: 0 | IW21: 0 | IX21: 0 | IY21: 0 | IZ21: 0 | JA21: 0 | JB21: 0 | JC21: 0 | JD21: 0 | JE21: 0 | JF21: 0 | JG21: 0 | JH21: =+SUBTOTAL(9,IV21:JG21) -> 0 | JJ21: 0 | JK21: 0 | JL21: 0 | JM21: 0 | JN21: 0 | JO21: 0 | JP21: 0 | JQ21: 0 | JR21: 0 | JS21: 0 | JT21: 0 | JU21: 0 | JV21: =+SUBTOTAL(9,JJ21:JU21) -> 0 | JX21: 0 | JY21: 0 | JZ21: 0 | KA21: 0 | KB21: 0 | KC21: 0 | KD21: 0 | KE21: 0 | KF21: 0 | KG21: 0 | KH21: 0 | KI21: 0 | KJ21: =+SUBTOTAL(9,JX21:KI21) -> 0 | KL21: 0 | KM21: 0 | KN21: 0 | KO21: 0 | KP21: 0 | KQ21: 0 | KR21: 0 | KS21: 0 | KT21: 0 | KU21: 0 | KV21: 0 | KW21: 0 | KX21: =+SUBTOTAL(9,KL21:KW21) -> 0 | KZ21: 0 | LA21: 0 | LB21: 0 | LC21: 0 | LD21: 0 | LE21: 0 | LF21: 0 | LG21: 0 | LH21: 0 | LI21: 0 | LJ21: 0 | LK21: 0 | LL21: =+SUBTOTAL(9,KZ21:LK21) -> 0 | LN21: 0 | LO21: 0 | LP21: 0 | LQ21: 0 | LR21: 0 | LS21: 0 | LT21: 0 | LU21: 0 | LV21: 0 | LW21: 0 | LX21: 0 | LY21: 0 | LZ21: =+SUBTOTAL(9,LN21:LY21) -> 0 | MB21: =SUMIF($D$6:$LY$6,MB$3,$D21:$LY21) -> 0 | MC21: =SUMIF($D$6:$LY$6,MC$3,$D21:$LY21) -> 0 | MD21: =SUMIF($D$6:$LY$6,MD$3,$D21:$LY21) -> 0 | ME21: =SUMIF($D$6:$LY$6,ME$3,$D21:$LY21) -> 0 | MF21: =SUMIF($D$6:$LY$6,MF$3,$D21:$LY21) -> 0 | MG21: =SUMIF($D$6:$LY$6,MG$3,$D21:$LY21) -> 0 | MH21: =SUMIF($D$6:$LY$6,MH$3,$D21:$LY21) -> 0 | MI21: =SUMIF($D$6:$LY$6,MI$3,$D21:$LY21) -> 0 | ... MM21: =SUMIF($D$6:$LY$6,MM$3,$D21:$LY21) -> 0 | MN21: =SUM(MB21:MM21) -> 0
P22: =+SUBTOTAL(9,D22:O22) -> 0 | AD22: =+SUBTOTAL(9,R22:AC22) -> 0 | AR22: =+SUBTOTAL(9,AF22:AQ22) -> 0 | BF22: =+SUBTOTAL(9,AT22:BE22) -> 0 | BT22: =+SUBTOTAL(9,BH22:BS22) -> 0 | CH22: =+SUBTOTAL(9,BV22:CG22) -> 0 | CV22: =+SUBTOTAL(9,CJ22:CU22) -> 0 | DJ22: =+SUBTOTAL(9,CX22:DI22) -> 0 | DX22: =+SUBTOTAL(9,DL22:DW22) -> 0 | EL22: =+SUBTOTAL(9,DZ22:EK22) -> 0 | EZ22: =+SUBTOTAL(9,EN22:EY22) -> 0 | FN22: =+SUBTOTAL(9,FB22:FM22) -> 0 | GB22: =+SUBTOTAL(9,FP22:GA22) -> 0 | GP22: =+SUBTOTAL(9,GD22:GO22) -> 0 | HD22: =+SUBTOTAL(9,GR22:HC22) -> 0 | HR22: =+SUBTOTAL(9,HF22:HQ22) -> 0 | IF22: =+SUBTOTAL(9,HT22:IE22) -> 0 | IT22: =+SUBTOTAL(9,IH22:IS22) -> 0 | JH22: =+SUBTOTAL(9,IV22:JG22) -> 0 | JV22: =+SUBTOTAL(9,JJ22:JU22) -> 0 | KJ22: =+SUBTOTAL(9,JX22:KI22) -> 0 | KX22: =+SUBTOTAL(9,KL22:KW22) -> 0 | LL22: =+SUBTOTAL(9,KZ22:LK22) -> 0 | LZ22: =+SUBTOTAL(9,LN22:LY22) -> 0
B23: TOTAL DIRECT COSTS | D23: =SUM(D15:D22) -> 0 | E23: =SUM(E15:E22) -> 0 | F23: =SUM(F15:F22) -> 0 | G23: =SUM(G15:G22) -> 0 | H23: =SUM(H15:H22) -> 0 | I23: =SUM(I15:I22) -> 0 | J23: =SUM(J15:J22) -> 0 | K23: =SUM(K15:K22) -> 0 | ... O23: =SUM(O15:O22) -> 0 | P23: =+SUBTOTAL(9,D23:O23) -> 0 | R23: =SUM(R15:R22) -> 0 | S23: =SUM(S15:S22) -> 0 | T23: =SUM(T15:T22) -> 0 | U23: =SUM(U15:U22) -> 0 | V23: =SUM(V15:V22) -> 0 | W23: =SUM(W15:W22) -> 0 | X23: =SUM(X15:X22) -> 0 | Y23: =SUM(Y15:Y22) -> 0 | ... AC23: =SUM(AC15:AC22) -> 0 | AD23: =+SUBTOTAL(9,R23:AC23) -> 0 | AF23: =SUM(AF15:AF22) -> 0 | AG23: =SUM(AG15:AG22) -> 0 | AH23: =SUM(AH15:AH22) -> 0 | AI23: =SUM(AI15:AI22) -> 0 | AJ23: =SUM(AJ15:AJ22) -> 0 | AK23: =SUM(AK15:AK22) -> 0 | AL23: =SUM(AL15:AL22) -> 0 | AM23: =SUM(AM15:AM22) -> 0 | ... AQ23: =SUM(AQ15:AQ22) -> 0 | AR23: =+SUBTOTAL(9,AF23:AQ23) -> 0 | AT23: =SUM(AT15:AT22) -> 0 | AU23: =SUM(AU15:AU22) -> 0 | AV23: =SUM(AV15:AV22) -> 0 | AW23: =SUM(AW15:AW22) -> 0 | AX23: =SUM(AX15:AX22) -> 0 | AY23: =SUM(AY15:AY22) -> 0 | AZ23: =SUM(AZ15:AZ22) -> 0 | BA23: =SUM(BA15:BA22) -> 0 | ... BE23: =SUM(BE15:BE22) -> 0 | BF23: =+SUBTOTAL(9,AT23:BE23) -> 0 | BH23: =SUM(BH15:BH22) -> 0 | BI23: =SUM(BI15:BI22) -> 0 | BJ23: =SUM(BJ15:BJ22) -> 0 | BK23: =SUM(BK15:BK22) -> 0 | BL23: =SUM(BL15:BL22) -> 0 | BM23: =SUM(BM15:BM22) -> 0 | BN23: =SUM(BN15:BN22) -> 0 | BO23: =SUM(BO15:BO22) -> 0 | ... BS23: =SUM(BS15:BS22) -> 0 | BT23: =+SUBTOTAL(9,BH23:BS23) -> 0 | BV23: =SUM(BV15:BV22) -> 0 | BW23: =SUM(BW15:BW22) -> 0 | BX23: =SUM(BX15:BX22) -> 0 | BY23: =SUM(BY15:BY22) -> 0 | BZ23: =SUM(BZ15:BZ22) -> 0 | CA23: =SUM(CA15:CA22) -> 0 | CB23: =SUM(CB15:CB22) -> 0 | CC23: =SUM(CC15:CC22) -> 0 | ... CG23: =SUM(CG15:CG22) -> 0 | CH23: =+SUBTOTAL(9,BV23:CG23) -> 0 | CJ23: =SUM(CJ15:CJ22) -> 0 | CK23: =SUM(CK15:CK22) -> 0 | CL23: =SUM(CL15:CL22) -> 0 | CM23: =SUM(CM15:CM22) -> 0 | CN23: =SUM(CN15:CN22) -> 0 | CO23: =SUM(CO15:CO22) -> 0 | CP23: =SUM(CP15:CP22) -> 0 | CQ23: =SUM(CQ15:CQ22) -> 0 | ... CU23: =SUM(CU15:CU22) -> 0 | CV23: =+SUBTOTAL(9,CJ23:CU23) -> 0 | CX23: =SUM(CX15:CX22) -> 0 | CY23: =SUM(CY15:CY22) -> 0 | CZ23: =SUM(CZ15:CZ22) -> 0 | DA23: =SUM(DA15:DA22) -> 0 | DB23: =SUM(DB15:DB22) -> 0 | DC23: =SUM(DC15:DC22) -> 0 | DD23: =SUM(DD15:DD22) -> 0 | DE23: =SUM(DE15:DE22) -> 0 | ... DI23: =SUM(DI15:DI22) -> 0 | DJ23: =+SUBTOTAL(9,CX23:DI23) -> 0 | DL23: =SUM(DL15:DL22) -> 0 | DM23: =SUM(DM15:DM22) -> 0 | DN23: =SUM(DN15:DN22) -> 0 | DO23: =SUM(DO15:DO22) -> 0 | DP23: =SUM(DP15:DP22) -> 0 | DQ23: =SUM(DQ15:DQ22) -> 0 | DR23: =SUM(DR15:DR22) -> 0 | DS23: =SUM(DS15:DS22) -> 0 | ... DW23: =SUM(DW15:DW22) -> 0 | DX23: =+SUBTOTAL(9,DL23:DW23) -> 0 | DZ23: =SUM(DZ15:DZ22) -> 0 | EA23: =SUM(EA15:EA22) -> 0 | EB23: =SUM(EB15:EB22) -> 0 | EC23: =SUM(EC15:EC22) -> 0 | ED23: =SUM(ED15:ED22) -> 0 | EE23: =SUM(EE15:EE22) -> 0 | EF23: =SUM(EF15:EF22) -> 0 | EG23: =SUM(EG15:EG22) -> 0 | ... EK23: =SUM(EK15:EK22) -> 0 | EL23: =+SUBTOTAL(9,DZ23:EK23) -> 0 | EN23: =SUM(EN15:EN22) -> 0 | EO23: =SUM(EO15:EO22) -> 0 | EP23: =SUM(EP15:EP22) -> 0 | EQ23: =SUM(EQ15:EQ22) -> 0 | ER23: =SUM(ER15:ER22) -> 0 | ES23: =SUM(ES15:ES22) -> 0 | ET23: =SUM(ET15:ET22) -> 0 | EU23: =SUM(EU15:EU22) -> 0 | ... EY23: =SUM(EY15:EY22) -> 0 | EZ23: =+SUBTOTAL(9,EN23:EY23) -> 0 | FB23: =SUM(FB15:FB22) -> 0 | FC23: =SUM(FC15:FC22) -> 0 | FD23: =SUM(FD15:FD22) -> 0 | FE23: =SUM(FE15:FE22) -> 0 | FF23: =SUM(FF15:FF22) -> 0 | FG23: =SUM(FG15:FG22) -> 0 | FH23: =SUM(FH15:FH22) -> 0 | FI23: =SUM(FI15:FI22) -> 0 | ... FM23: =SUM(FM15:FM22) -> 0 | FN23: =+SUBTOTAL(9,FB23:FM23) -> 0 | FP23: =SUM(FP15:FP22) -> 0 | FQ23: =SUM(FQ15:FQ22) -> 0 | FR23: =SUM(FR15:FR22) -> 0 | FS23: =SUM(FS15:FS22) -> 0 | FT23: =SUM(FT15:FT22) -> 0 | FU23: =SUM(FU15:FU22) -> 0 | FV23: =SUM(FV15:FV22) -> 0 | FW23: =SUM(FW15:FW22) -> 0 | ... GA23: =SUM(GA15:GA22) -> 0 | GB23: =+SUBTOTAL(9,FP23:GA23) -> 0 | GD23: =SUM(GD15:GD22) -> 0 | GE23: =SUM(GE15:GE22) -> 0 | GF23: =SUM(GF15:GF22) -> 0 | GG23: =SUM(GG15:GG22) -> 0 | GH23: =SUM(GH15:GH22) -> 0 | GI23: =SUM(GI15:GI22) -> 0 | GJ23: =SUM(GJ15:GJ22) -> 0 | GK23: =SUM(GK15:GK22) -> 0 | ... GO23: =SUM(GO15:GO22) -> 0 | GP23: =+SUBTOTAL(9,GD23:GO23) -> 0 | GR23: =SUM(GR15:GR22) -> 0 | GS23: =SUM(GS15:GS22) -> 0 | GT23: =SUM(GT15:GT22) -> 0 | GU23: =SUM(GU15:GU22) -> 0 | GV23: =SUM(GV15:GV22) -> 0 | GW23: =SUM(GW15:GW22) -> 0 | GX23: =SUM(GX15:GX22) -> 0 | GY23: =SUM(GY15:GY22) -> 0 | ... HC23: =SUM(HC15:HC22) -> 0 | HD23: =+SUBTOTAL(9,GR23:HC23) -> 0 | HF23: =SUM(HF15:HF22) -> 0 | HG23: =SUM(HG15:HG22) -> 0 | HH23: =SUM(HH15:HH22) -> 0 | HI23: =SUM(HI15:HI22) -> 0 | HJ23: =SUM(HJ15:HJ22) -> 0 | HK23: =SUM(HK15:HK22) -> 0 | HL23: =SUM(HL15:HL22) -> 0 | HM23: =SUM(HM15:HM22) -> 0 | ... HQ23: =SUM(HQ15:HQ22) -> 0 | HR23: =+SUBTOTAL(9,HF23:HQ23) -> 0 | HT23: =SUM(HT15:HT22) -> 0 | HU23: =SUM(HU15:HU22) -> 0 | HV23: =SUM(HV15:HV22) -> 0 | HW23: =SUM(HW15:HW22) -> 0 | HX23: =SUM(HX15:HX22) -> 0 | HY23: =SUM(HY15:HY22) -> 0 | HZ23: =SUM(HZ15:HZ22) -> 0 | IA23: =SUM(IA15:IA22) -> 0 | ... IE23: =SUM(IE15:IE22) -> 0 | IF23: =+SUBTOTAL(9,HT23:IE23) -> 0 | IH23: =SUM(IH15:IH22) -> 0 | II23: =SUM(II15:II22) -> 0 | IJ23: =SUM(IJ15:IJ22) -> 0 | IK23: =SUM(IK15:IK22) -> 0 | IL23: =SUM(IL15:IL22) -> 0 | IM23: =SUM(IM15:IM22) -> 0 | IN23: =SUM(IN15:IN22) -> 0 | IO23: =SUM(IO15:IO22) -> 0 | ... IS23: =SUM(IS15:IS22) -> 0 | IT23: =+SUBTOTAL(9,IH23:IS23) -> 0 | IV23: =SUM(IV15:IV22) -> 0 | IW23: =SUM(IW15:IW22) -> 0 | IX23: =SUM(IX15:IX22) -> 0 | IY23: =SUM(IY15:IY22) -> 0 | IZ23: =SUM(IZ15:IZ22) -> 0 | JA23: =SUM(JA15:JA22) -> 0 | JB23: =SUM(JB15:JB22) -> 0 | JC23: =SUM(JC15:JC22) -> 0 | ... JG23: =SUM(JG15:JG22) -> 0 | JH23: =+SUBTOTAL(9,IV23:JG23) -> 0 | JJ23: =SUM(JJ15:JJ22) -> 0 | JK23: =SUM(JK15:JK22) -> 0 | JL23: =SUM(JL15:JL22) -> 0 | JM23: =SUM(JM15:JM22) -> 0 | JN23: =SUM(JN15:JN22) -> 0 | JO23: =SUM(JO15:JO22) -> 0 | JP23: =SUM(JP15:JP22) -> 0 | JQ23: =SUM(JQ15:JQ22) -> 0 | ... JU23: =SUM(JU15:JU22) -> 0 | JV23: =+SUBTOTAL(9,JJ23:JU23) -> 0 | JX23: =SUM(JX15:JX22) -> 0 | JY23: =SUM(JY15:JY22) -> 0 | JZ23: =SUM(JZ15:JZ22) -> 0 | KA23: =SUM(KA15:KA22) -> 0 | KB23: =SUM(KB15:KB22) -> 0 | KC23: =SUM(KC15:KC22) -> 0 | KD23: =SUM(KD15:KD22) -> 0 | KE23: =SUM(KE15:KE22) -> 0 | ... KI23: =SUM(KI15:KI22) -> 0 | KJ23: =+SUBTOTAL(9,JX23:KI23) -> 0 | KL23: =SUM(KL15:KL22) -> 0 | KM23: =SUM(KM15:KM22) -> 0 | KN23: =SUM(KN15:KN22) -> 0 | KO23: =SUM(KO15:KO22) -> 0 | KP23: =SUM(KP15:KP22) -> 0 | KQ23: =SUM(KQ15:KQ22) -> 0 | KR23: =SUM(KR15:KR22) -> 0 | KS23: =SUM(KS15:KS22) -> 0 | ... KW23: =SUM(KW15:KW22) -> 0 | KX23: =+SUBTOTAL(9,KL23:KW23) -> 0 | KZ23: =SUM(KZ15:KZ22) -> 0 | LA23: =SUM(LA15:LA22) -> 0 | LB23: =SUM(LB15:LB22) -> 0 | LC23: =SUM(LC15:LC22) -> 0 | LD23: =SUM(LD15:LD22) -> 0 | LE23: =SUM(LE15:LE22) -> 0 | LF23: =SUM(LF15:LF22) -> 0 | LG23: =SUM(LG15:LG22) -> 0 | ... LK23: =SUM(LK15:LK22) -> 0 | LL23: =+SUBTOTAL(9,KZ23:LK23) -> 0 | LN23: =SUM(LN15:LN22) -> 0 | LO23: =SUM(LO15:LO22) -> 0 | LP23: =SUM(LP15:LP22) -> 0 | LQ23: =SUM(LQ15:LQ22) -> 0 | LR23: =SUM(LR15:LR22) -> 0 | LS23: =SUM(LS15:LS22) -> 0 | LT23: =SUM(LT15:LT22) -> 0 | LU23: =SUM(LU15:LU22) -> 0 | ... LY23: =SUM(LY15:LY22) -> 0 | LZ23: =+SUBTOTAL(9,LN23:LY23) -> 0 | MB23: =SUM(MB15:MB22) -> 0 | MC23: =SUM(MC15:MC22) -> 0 | MD23: =SUM(MD15:MD22) -> 0 | ME23: =SUM(ME15:ME22) -> 0 | MF23: =SUM(MF15:MF22) -> 0 | MG23: =SUM(MG15:MG22) -> 0 | MH23: =SUM(MH15:MH22) -> 0 | MI23: =SUM(MI15:MI22) -> 0 | ... MN23: =SUM(MN15:MN22) -> 0
B25: OTHER INCOME
B26: Miscellaneous Income (Others [e.g. Govt subsidy]) | D26: 0 | E26: 0 | F26: 0 | G26: 0 | H26: 0 | I26: 0 | J26: 0 | K26: 0 | L26: 0 | M26: 0 | N26: 0 | O26: 0 | P26: =+SUBTOTAL(9,D26:O26) -> 0 | R26: 0 | S26: 0 | T26: 0 | U26: 0 | V26: 0 | W26: 0 | X26: 0 | Y26: 0 | Z26: 0 | AA26: 0 | AB26: 0 | AC26: 0 | AD26: =+SUBTOTAL(9,R26:AC26) -> 0 | AF26: 0 | AG26: 0 | AH26: 0 | AI26: 0 | AJ26: 0 | AK26: 0 | AL26: 0 | AM26: 0 | AN26: 0 | AO26: 0 | AP26: 0 | AQ26: 0 | AR26: =+SUBTOTAL(9,AF26:AQ26) -> 0 | AT26: 0 | AU26: 0 | AV26: 0 | AW26: 0 | AX26: 0 | AY26: 0 | AZ26: 0 | BA26: 0 | BB26: 0 | BC26: 0 | BD26: 0 | BE26: 0 | BF26: =+SUBTOTAL(9,AT26:BE26) -> 0 | BH26: 0 | BI26: 0 | BJ26: 0 | BK26: 0 | BL26: 0 | BM26: 0 | BN26: 0 | BO26: 0 | BP26: 0 | BQ26: 0 | BR26: 0 | BS26: 0 | BT26: =+SUBTOTAL(9,BH26:BS26) -> 0 | BV26: 0 | BW26: 0 | BX26: 0 | BY26: 0 | BZ26: 0 | CA26: 0 | CB26: 0 | CC26: 0 | CD26: 0 | CE26: 0 | CF26: 0 | CG26: 0 | CH26: =+SUBTOTAL(9,BV26:CG26) -> 0 | CJ26: 0 | CK26: 0 | CL26: 0 | CM26: 0 | CN26: 0 | CO26: 0 | CP26: 0 | CQ26: 0 | CR26: 0 | CS26: 0 | CT26: 0 | CU26: 0 | CV26: =+SUBTOTAL(9,CJ26:CU26) -> 0 | CX26: 0 | CY26: 0 | CZ26: 0 | DA26: 0 | DB26: 0 | DC26: 0 | DD26: 0 | DE26: 0 | DF26: 0 | DG26: 0 | DH26: 0 | DI26: 0 | DJ26: =+SUBTOTAL(9,CX26:DI26) -> 0 | DL26: 0 | DM26: 0 | DN26: 0 | DO26: 0 | DP26: 0 | DQ26: 0 | DR26: 0 | DS26: 0 | DT26: 0 | DU26: 0 | DV26: 0 | DW26: 0 | DX26: =+SUBTOTAL(9,DL26:DW26) -> 0 | DZ26: 0 | EA26: 0 | EB26: 0 | EC26: 0 | ED26: 0 | EE26: 0 | EF26: 0 | EG26: 0 | EH26: 0 | EI26: 0 | EJ26: 0 | EK26: 0 | EL26: =+SUBTOTAL(9,DZ26:EK26) -> 0 | EN26: 0 | EO26: 0 | EP26: 0 | EQ26: 0 | ER26: 0 | ES26: 0 | ET26: 0 | EU26: 0 | EV26: 0 | EW26: 0 | EX26: 0 | EY26: 0 | EZ26: =+SUBTOTAL(9,EN26:EY26) -> 0 | FB26: 0 | FC26: 0 | FD26: 0 | FE26: 0 | FF26: 0 | FG26: 0 | FH26: 0 | FI26: 0 | FJ26: 0 | FK26: 0 | FL26: 0 | FM26: 0 | FN26: =+SUBTOTAL(9,FB26:FM26) -> 0 | FP26: 0 | FQ26: 0 | FR26: 0 | FS26: 0 | FT26: 0 | FU26: 0 | FV26: 0 | FW26: 0 | FX26: 0 | FY26: 0 | FZ26: 0 | GA26: 0 | GB26: =+SUBTOTAL(9,FP26:GA26) -> 0 | GD26: 0 | GE26: 0 | GF26: 0 | GG26: 0 | GH26: 0 | GI26: 0 | GJ26: 0 | GK26: 0 | GL26: 0 | GM26: 0 | GN26: 0 | GO26: 0 | GP26: =+SUBTOTAL(9,GD26:GO26) -> 0 | GR26: 0 | GS26: 0 | GT26: 0 | GU26: 0 | GV26: 0 | GW26: 0 | GX26: 0 | GY26: 0 | GZ26: 0 | HA26: 0 | HB26: 0 | HC26: 0 | HD26: =+SUBTOTAL(9,GR26:HC26) -> 0 | HF26: 0 | HG26: 0 | HH26: 0 | HI26: 0 | HJ26: 0 | HK26: 0 | HL26: 0 | HM26: 0 | HN26: 0 | HO26: 0 | HP26: 0 | HQ26: 0 | HR26: =+SUBTOTAL(9,HF26:HQ26) -> 0 | HT26: 0 | HU26: 0 | HV26: 0 | HW26: 0 | HX26: 0 | HY26: 0 | HZ26: 0 | IA26: 0 | IB26: 0 | IC26: 0 | ID26: 0 | IE26: 0 | IF26: =+SUBTOTAL(9,HT26:IE26) -> 0 | IH26: 0 | II26: 0 | IJ26: 0 | IK26: 0 | IL26: 0 | IM26: 0 | IN26: 0 | IO26: 0 | IP26: 0 | IQ26: 0 | IR26: 0 | IS26: 0 | IT26: =+SUBTOTAL(9,IH26:IS26) -> 0 | IV26: 0 | IW26: 0 | IX26: 0 | IY26: 0 | IZ26: 0 | JA26: 0 | JB26: 0 | JC26: 0 | JD26: 0 | JE26: 0 | JF26: 0 | JG26: 0 | JH26: =+SUBTOTAL(9,IV26:JG26) -> 0 | JJ26: 0 | JK26: 0 | JL26: 0 | JM26: 0 | JN26: 0 | JO26: 0 | JP26: 0 | JQ26: 0 | JR26: 0 | JS26: 0 | JT26: 0 | JU26: 0 | JV26: =+SUBTOTAL(9,JJ26:JU26) -> 0 | JX26: 0 | JY26: 0 | JZ26: 0 | KA26: 0 | KB26: 0 | KC26: 0 | KD26: 0 | KE26: 0 | KF26: 0 | KG26: 0 | KH26: 0 | KI26: 0 | KJ26: =+SUBTOTAL(9,JX26:KI26) -> 0 | KL26: 0 | KM26: 0 | KN26: 0 | KO26: 0 | KP26: 0 | KQ26: 0 | KR26: 0 | KS26: 0 | KT26: 0 | KU26: 0 | KV26: 0 | KW26: 0 | KX26: =+SUBTOTAL(9,KL26:KW26) -> 0 | KZ26: 0 | LA26: 0 | LB26: 0 | LC26: 0 | LD26: 0 | LE26: 0 | LF26: 0 | LG26: 0 | LH26: 0 | LI26: 0 | LJ26: 0 | LK26: 0 | LL26: =+SUBTOTAL(9,KZ26:LK26) -> 0 | LN26: 0 | LO26: 0 | LP26: 0 | LQ26: 0 | LR26: 0 | LS26: 0 | LT26: 0 | LU26: 0 | LV26: 0 | LW26: 0 | LX26: 0 | LY26: 0 | LZ26: =+SUBTOTAL(9,LN26:LY26) -> 0 | MB26: =SUMIF($D$6:$LY$6,MB$3,$D26:$LY26) -> 0 | MC26: =SUMIF($D$6:$LY$6,MC$3,$D26:$LY26) -> 0 | MD26: =SUMIF($D$6:$LY$6,MD$3,$D26:$LY26) -> 0 | ME26: =SUMIF($D$6:$LY$6,ME$3,$D26:$LY26) -> 0 | MF26: =SUMIF($D$6:$LY$6,MF$3,$D26:$LY26) -> 0 | MG26: =SUMIF($D$6:$LY$6,MG$3,$D26:$LY26) -> 0 | MH26: =SUMIF($D$6:$LY$6,MH$3,$D26:$LY26) -> 0 | MI26: =SUMIF($D$6:$LY$6,MI$3,$D26:$LY26) -> 0 | ... MM26: =SUMIF($D$6:$LY$6,MM$3,$D26:$LY26) -> 0 | MN26: =SUM(MB26:MM26) -> 0
B27: Vessel System Income | D27: 0 | E27: 0 | F27: 0 | G27: 0 | H27: 0 | I27: 0 | J27: 0 | K27: 0 | L27: 0 | M27: 0 | N27: 0 | O27: 0 | P27: =+SUBTOTAL(9,D27:O27) -> 0 | R27: 0 | S27: 0 | T27: 0 | U27: 0 | V27: 0 | W27: 0 | X27: 0 | Y27: 0 | Z27: 0 | AA27: 0 | AB27: 0 | AC27: 0 | AD27: =+SUBTOTAL(9,R27:AC27) -> 0 | AF27: 0 | AG27: 0 | AH27: 0 | AI27: 0 | AJ27: 0 | AK27: 0 | AL27: 0 | AM27: 0 | AN27: 0 | AO27: 0 | AP27: 0 | AQ27: 0 | AR27: =+SUBTOTAL(9,AF27:AQ27) -> 0 | AT27: 0 | AU27: 0 | AV27: 0 | AW27: 0 | AX27: 0 | AY27: 0 | AZ27: 0 | BA27: 0 | BB27: 0 | BC27: 0 | BD27: 0 | BE27: 0 | BF27: =+SUBTOTAL(9,AT27:BE27) -> 0 | BH27: 0 | BI27: 0 | BJ27: 0 | BK27: 0 | BL27: 0 | BM27: 0 | BN27: 0 | BO27: 0 | BP27: 0 | BQ27: 0 | BR27: 0 | BS27: 0 | BT27: =+SUBTOTAL(9,BH27:BS27) -> 0 | BV27: 0 | BW27: 0 | BX27: 0 | BY27: 0 | BZ27: 0 | CA27: 0 | CB27: 0 | CC27: 0 | CD27: 0 | CE27: 0 | CF27: 0 | CG27: 0 | CH27: =+SUBTOTAL(9,BV27:CG27) -> 0 | CJ27: 0 | CK27: 0 | CL27: 0 | CM27: 0 | CN27: 0 | CO27: 0 | CP27: 0 | CQ27: 0 | CR27: 0 | CS27: 0 | CT27: 0 | CU27: 0 | CV27: =+SUBTOTAL(9,CJ27:CU27) -> 0 | CX27: 0 | CY27: 0 | CZ27: 0 | DA27: 0 | DB27: 0 | DC27: 0 | DD27: 0 | DE27: 0 | DF27: 0 | DG27: 0 | DH27: 0 | DI27: 0 | DJ27: =+SUBTOTAL(9,CX27:DI27) -> 0 | DL27: 0 | DM27: 0 | DN27: 0 | DO27: 0 | DP27: 0 | DQ27: 0 | DR27: 0 | DS27: 0 | DT27: 0 | DU27: 0 | DV27: 0 | DW27: 0 | DX27: =+SUBTOTAL(9,DL27:DW27) -> 0 | DZ27: 0 | EA27: 0 | EB27: 0 | EC27: 0 | ED27: 0 | EE27: 0 | EF27: 0 | EG27: 0 | EH27: 0 | EI27: 0 | EJ27: 0 | EK27: 0 | EL27: =+SUBTOTAL(9,DZ27:EK27) -> 0 | EN27: 0 | EO27: 0 | EP27: 0 | EQ27: 0 | ER27: 0 | ES27: 0 | ET27: 0 | EU27: 0 | EV27: 0 | EW27: 0 | EX27: 0 | EY27: 0 | EZ27: =+SUBTOTAL(9,EN27:EY27) -> 0 | FB27: 0 | FC27: 0 | FD27: 0 | FE27: 0 | FF27: 0 | FG27: 0 | FH27: 0 | FI27: 0 | FJ27: 0 | FK27: 0 | FL27: 0 | FM27: 0 | FN27: =+SUBTOTAL(9,FB27:FM27) -> 0 | FP27: 0 | FQ27: 0 | FR27: 0 | FS27: 0 | FT27: 0 | FU27: 0 | FV27: 0 | FW27: 0 | FX27: 0 | FY27: 0 | FZ27: 0 | GA27: 0 | GB27: =+SUBTOTAL(9,FP27:GA27) -> 0 | GD27: 0 | GE27: 0 | GF27: 0 | GG27: 0 | GH27: 0 | GI27: 0 | GJ27: 0 | GK27: 0 | GL27: 0 | GM27: 0 | GN27: 0 | GO27: 0 | GP27: =+SUBTOTAL(9,GD27:GO27) -> 0 | GR27: 0 | GS27: 0 | GT27: 0 | GU27: 0 | GV27: 0 | GW27: 0 | GX27: 0 | GY27: 0 | GZ27: 0 | HA27: 0 | HB27: 0 | HC27: 0 | HD27: =+SUBTOTAL(9,GR27:HC27) -> 0 | HF27: 0 | HG27: 0 | HH27: 0 | HI27: 0 | HJ27: 0 | HK27: 0 | HL27: 0 | HM27: 0 | HN27: 0 | HO27: 0 | HP27: 0 | HQ27: 0 | HR27: =+SUBTOTAL(9,HF27:HQ27) -> 0 | HT27: 0 | HU27: 0 | HV27: 0 | HW27: 0 | HX27: 0 | HY27: 0 | HZ27: 0 | IA27: 0 | IB27: 0 | IC27: 0 | ID27: 0 | IE27: 0 | IF27: =+SUBTOTAL(9,HT27:IE27) -> 0 | IH27: 0 | II27: 0 | IJ27: 0 | IK27: 0 | IL27: 0 | IM27: 0 | IN27: 0 | IO27: 0 | IP27: 0 | IQ27: 0 | IR27: 0 | IS27: 0 | IT27: =+SUBTOTAL(9,IH27:IS27) -> 0 | IV27: 0 | IW27: 0 | IX27: 0 | IY27: 0 | IZ27: 0 | JA27: 0 | JB27: 0 | JC27: 0 | JD27: 0 | JE27: 0 | JF27: 0 | JG27: 0 | JH27: =+SUBTOTAL(9,IV27:JG27) -> 0 | JJ27: 0 | JK27: 0 | JL27: 0 | JM27: 0 | JN27: 0 | JO27: 0 | JP27: 0 | JQ27: 0 | JR27: 0 | JS27: 0 | JT27: 0 | JU27: 0 | JV27: =+SUBTOTAL(9,JJ27:JU27) -> 0 | JX27: 0 | JY27: 0 | JZ27: 0 | KA27: 0 | KB27: 0 | KC27: 0 | KD27: 0 | KE27: 0 | KF27: 0 | KG27: 0 | KH27: 0 | KI27: 0 | KJ27: =+SUBTOTAL(9,JX27:KI27) -> 0 | KL27: 0 | KM27: 0 | KN27: 0 | KO27: 0 | KP27: 0 | KQ27: 0 | KR27: 0 | KS27: 0 | KT27: 0 | KU27: 0 | KV27: 0 | KW27: 0 | KX27: =+SUBTOTAL(9,KL27:KW27) -> 0 | KZ27: 0 | LA27: 0 | LB27: 0 | LC27: 0 | LD27: 0 | LE27: 0 | LF27: 0 | LG27: 0 | LH27: 0 | LI27: 0 | LJ27: 0 | LK27: 0 | LL27: =+SUBTOTAL(9,KZ27:LK27) -> 0 | LN27: 0 | LO27: 0 | LP27: 0 | LQ27: 0 | LR27: 0 | LS27: 0 | LT27: 0 | LU27: 0 | LV27: 0 | LW27: 0 | LX27: 0 | LY27: 0 | LZ27: =+SUBTOTAL(9,LN27:LY27) -> 0 | MB27: =SUMIF($D$6:$LY$6,MB$3,$D27:$LY27) -> 0 | MC27: =SUMIF($D$6:$LY$6,MC$3,$D27:$LY27) -> 0 | MD27: =SUMIF($D$6:$LY$6,MD$3,$D27:$LY27) -> 0 | ME27: =SUMIF($D$6:$LY$6,ME$3,$D27:$LY27) -> 0 | MF27: =SUMIF($D$6:$LY$6,MF$3,$D27:$LY27) -> 0 | MG27: =SUMIF($D$6:$LY$6,MG$3,$D27:$LY27) -> 0 | MH27: =SUMIF($D$6:$LY$6,MH$3,$D27:$LY27) -> 0 | MI27: =SUMIF($D$6:$LY$6,MI$3,$D27:$LY27) -> 0 | ... MM27: =SUMIF($D$6:$LY$6,MM$3,$D27:$LY27) -> 0 | MN27: =SUM(MB27:MM27) -> 0
B29: TOTAL OTHER INCOME | D29: =SUM(D26:D28) -> 0 | E29: =SUM(E26:E28) -> 0 | F29: =SUM(F26:F28) -> 0 | G29: =SUM(G26:G28) -> 0 | H29: =SUM(H26:H28) -> 0 | I29: =SUM(I26:I28) -> 0 | J29: =SUM(J26:J28) -> 0 | K29: =SUM(K26:K28) -> 0 | ... O29: =SUM(O26:O28) -> 0 | P29: =+SUBTOTAL(9,D29:O29) -> 0 | R29: =SUM(R26:R28) -> 0 | S29: =SUM(S26:S28) -> 0 | T29: =SUM(T26:T28) -> 0 | U29: =SUM(U26:U28) -> 0 | V29: =SUM(V26:V28) -> 0 | W29: =SUM(W26:W28) -> 0 | X29: =SUM(X26:X28) -> 0 | Y29: =SUM(Y26:Y28) -> 0 | ... AC29: =SUM(AC26:AC28) -> 0 | AD29: =+SUBTOTAL(9,R29:AC29) -> 0 | AF29: =SUM(AF26:AF28) -> 0 | AG29: =SUM(AG26:AG28) -> 0 | AH29: =SUM(AH26:AH28) -> 0 | AI29: =SUM(AI26:AI28) -> 0 | AJ29: =SUM(AJ26:AJ28) -> 0 | AK29: =SUM(AK26:AK28) -> 0 | AL29: =SUM(AL26:AL28) -> 0 | AM29: =SUM(AM26:AM28) -> 0 | ... AQ29: =SUM(AQ26:AQ28) -> 0 | AR29: =+SUBTOTAL(9,AF29:AQ29) -> 0 | AT29: =SUM(AT26:AT28) -> 0 | AU29: =SUM(AU26:AU28) -> 0 | AV29: =SUM(AV26:AV28) -> 0 | AW29: =SUM(AW26:AW28) -> 0 | AX29: =SUM(AX26:AX28) -> 0 | AY29: =SUM(AY26:AY28) -> 0 | AZ29: =SUM(AZ26:AZ28) -> 0 | BA29: =SUM(BA26:BA28) -> 0 | ... BE29: =SUM(BE26:BE28) -> 0 | BF29: =+SUBTOTAL(9,AT29:BE29) -> 0 | BH29: =SUM(BH26:BH28) -> 0 | BI29: =SUM(BI26:BI28) -> 0 | BJ29: =SUM(BJ26:BJ28) -> 0 | BK29: =SUM(BK26:BK28) -> 0 | BL29: =SUM(BL26:BL28) -> 0 | BM29: =SUM(BM26:BM28) -> 0 | BN29: =SUM(BN26:BN28) -> 0 | BO29: =SUM(BO26:BO28) -> 0 | ... BS29: =SUM(BS26:BS28) -> 0 | BT29: =+SUBTOTAL(9,BH29:BS29) -> 0 | BV29: =SUM(BV26:BV28) -> 0 | BW29: =SUM(BW26:BW28) -> 0 | BX29: =SUM(BX26:BX28) -> 0 | BY29: =SUM(BY26:BY28) -> 0 | BZ29: =SUM(BZ26:BZ28) -> 0 | CA29: =SUM(CA26:CA28) -> 0 | CB29: =SUM(CB26:CB28) -> 0 | CC29: =SUM(CC26:CC28) -> 0 | ... CG29: =SUM(CG26:CG28) -> 0 | CH29: =+SUBTOTAL(9,BV29:CG29) -> 0 | CJ29: =SUM(CJ26:CJ28) -> 0 | CK29: =SUM(CK26:CK28) -> 0 | CL29: =SUM(CL26:CL28) -> 0 | CM29: =SUM(CM26:CM28) -> 0 | CN29: =SUM(CN26:CN28) -> 0 | CO29: =SUM(CO26:CO28) -> 0 | CP29: =SUM(CP26:CP28) -> 0 | CQ29: =SUM(CQ26:CQ28) -> 0 | ... CU29: =SUM(CU26:CU28) -> 0 | CV29: =+SUBTOTAL(9,CJ29:CU29) -> 0 | CX29: =SUM(CX26:CX28) -> 0 | CY29: =SUM(CY26:CY28) -> 0 | CZ29: =SUM(CZ26:CZ28) -> 0 | DA29: =SUM(DA26:DA28) -> 0 | DB29: =SUM(DB26:DB28) -> 0 | DC29: =SUM(DC26:DC28) -> 0 | DD29: =SUM(DD26:DD28) -> 0 | DE29: =SUM(DE26:DE28) -> 0 | ... DI29: =SUM(DI26:DI28) -> 0 | DJ29: =+SUBTOTAL(9,CX29:DI29) -> 0 | DL29: =SUM(DL26:DL28) -> 0 | DM29: =SUM(DM26:DM28) -> 0 | DN29: =SUM(DN26:DN28) -> 0 | DO29: =SUM(DO26:DO28) -> 0 | DP29: =SUM(DP26:DP28) -> 0 | DQ29: =SUM(DQ26:DQ28) -> 0 | DR29: =SUM(DR26:DR28) -> 0 | DS29: =SUM(DS26:DS28) -> 0 | ... DW29: =SUM(DW26:DW28) -> 0 | DX29: =+SUBTOTAL(9,DL29:DW29) -> 0 | DZ29: =SUM(DZ26:DZ28) -> 0 | EA29: =SUM(EA26:EA28) -> 0 | EB29: =SUM(EB26:EB28) -> 0 | EC29: =SUM(EC26:EC28) -> 0 | ED29: =SUM(ED26:ED28) -> 0 | EE29: =SUM(EE26:EE28) -> 0 | EF29: =SUM(EF26:EF28) -> 0 | EG29: =SUM(EG26:EG28) -> 0 | ... EK29: =SUM(EK26:EK28) -> 0 | EL29: =+SUBTOTAL(9,DZ29:EK29) -> 0 | EN29: =SUM(EN26:EN28) -> 0 | EO29: =SUM(EO26:EO28) -> 0 | EP29: =SUM(EP26:EP28) -> 0 | EQ29: =SUM(EQ26:EQ28) -> 0 | ER29: =SUM(ER26:ER28) -> 0 | ES29: =SUM(ES26:ES28) -> 0 | ET29: =SUM(ET26:ET28) -> 0 | EU29: =SUM(EU26:EU28) -> 0 | ... EY29: =SUM(EY26:EY28) -> 0 | EZ29: =+SUBTOTAL(9,EN29:EY29) -> 0 | FB29: =SUM(FB26:FB28) -> 0 | FC29: =SUM(FC26:FC28) -> 0 | FD29: =SUM(FD26:FD28) -> 0 | FE29: =SUM(FE26:FE28) -> 0 | FF29: =SUM(FF26:FF28) -> 0 | FG29: =SUM(FG26:FG28) -> 0 | FH29: =SUM(FH26:FH28) -> 0 | FI29: =SUM(FI26:FI28) -> 0 | ... FM29: =SUM(FM26:FM28) -> 0 | FN29: =+SUBTOTAL(9,FB29:FM29) -> 0 | FP29: =SUM(FP26:FP28) -> 0 | FQ29: =SUM(FQ26:FQ28) -> 0 | FR29: =SUM(FR26:FR28) -> 0 | FS29: =SUM(FS26:FS28) -> 0 | FT29: =SUM(FT26:FT28) -> 0 | FU29: =SUM(FU26:FU28) -> 0 | FV29: =SUM(FV26:FV28) -> 0 | FW29: =SUM(FW26:FW28) -> 0 | ... GA29: =SUM(GA26:GA28) -> 0 | GB29: =+SUBTOTAL(9,FP29:GA29) -> 0 | GD29: =SUM(GD26:GD28) -> 0 | GE29: =SUM(GE26:GE28) -> 0 | GF29: =SUM(GF26:GF28) -> 0 | GG29: =SUM(GG26:GG28) -> 0 | GH29: =SUM(GH26:GH28) -> 0 | GI29: =SUM(GI26:GI28) -> 0 | GJ29: =SUM(GJ26:GJ28) -> 0 | GK29: =SUM(GK26:GK28) -> 0 | ... GO29: =SUM(GO26:GO28) -> 0 | GP29: =+SUBTOTAL(9,GD29:GO29) -> 0 | GR29: =SUM(GR26:GR28) -> 0 | GS29: =SUM(GS26:GS28) -> 0 | GT29: =SUM(GT26:GT28) -> 0 | GU29: =SUM(GU26:GU28) -> 0 | GV29: =SUM(GV26:GV28) -> 0 | GW29: =SUM(GW26:GW28) -> 0 | GX29: =SUM(GX26:GX28) -> 0 | GY29: =SUM(GY26:GY28) -> 0 | ... HC29: =SUM(HC26:HC28) -> 0 | HD29: =+SUBTOTAL(9,GR29:HC29) -> 0 | HF29: =SUM(HF26:HF28) -> 0 | HG29: =SUM(HG26:HG28) -> 0 | HH29: =SUM(HH26:HH28) -> 0 | HI29: =SUM(HI26:HI28) -> 0 | HJ29: =SUM(HJ26:HJ28) -> 0 | HK29: =SUM(HK26:HK28) -> 0 | HL29: =SUM(HL26:HL28) -> 0 | HM29: =SUM(HM26:HM28) -> 0 | ... HQ29: =SUM(HQ26:HQ28) -> 0 | HR29: =+SUBTOTAL(9,HF29:HQ29) -> 0 | HT29: =SUM(HT26:HT28) -> 0 | HU29: =SUM(HU26:HU28) -> 0 | HV29: =SUM(HV26:HV28) -> 0 | HW29: =SUM(HW26:HW28) -> 0 | HX29: =SUM(HX26:HX28) -> 0 | HY29: =SUM(HY26:HY28) -> 0 | HZ29: =SUM(HZ26:HZ28) -> 0 | IA29: =SUM(IA26:IA28) -> 0 | ... IE29: =SUM(IE26:IE28) -> 0 | IF29: =+SUBTOTAL(9,HT29:IE29) -> 0 | IH29: =SUM(IH26:IH28) -> 0 | II29: =SUM(II26:II28) -> 0 | IJ29: =SUM(IJ26:IJ28) -> 0 | IK29: =SUM(IK26:IK28) -> 0 | IL29: =SUM(IL26:IL28) -> 0 | IM29: =SUM(IM26:IM28) -> 0 | IN29: =SUM(IN26:IN28) -> 0 | IO29: =SUM(IO26:IO28) -> 0 | ... IS29: =SUM(IS26:IS28) -> 0 | IT29: =+SUBTOTAL(9,IH29:IS29) -> 0 | IV29: =SUM(IV26:IV28) -> 0 | IW29: =SUM(IW26:IW28) -> 0 | IX29: =SUM(IX26:IX28) -> 0 | IY29: =SUM(IY26:IY28) -> 0 | IZ29: =SUM(IZ26:IZ28) -> 0 | JA29: =SUM(JA26:JA28) -> 0 | JB29: =SUM(JB26:JB28) -> 0 | JC29: =SUM(JC26:JC28) -> 0 | ... JG29: =SUM(JG26:JG28) -> 0 | JH29: =+SUBTOTAL(9,IV29:JG29) -> 0 | JJ29: =SUM(JJ26:JJ28) -> 0 | JK29: =SUM(JK26:JK28) -> 0 | JL29: =SUM(JL26:JL28) -> 0 | JM29: =SUM(JM26:JM28) -> 0 | JN29: =SUM(JN26:JN28) -> 0 | JO29: =SUM(JO26:JO28) -> 0 | JP29: =SUM(JP26:JP28) -> 0 | JQ29: =SUM(JQ26:JQ28) -> 0 | ... JU29: =SUM(JU26:JU28) -> 0 | JV29: =+SUBTOTAL(9,JJ29:JU29) -> 0 | JX29: =SUM(JX26:JX28) -> 0 | JY29: =SUM(JY26:JY28) -> 0 | JZ29: =SUM(JZ26:JZ28) -> 0 | KA29: =SUM(KA26:KA28) -> 0 | KB29: =SUM(KB26:KB28) -> 0 | KC29: =SUM(KC26:KC28) -> 0 | KD29: =SUM(KD26:KD28) -> 0 | KE29: =SUM(KE26:KE28) -> 0 | ... KI29: =SUM(KI26:KI28) -> 0 | KJ29: =+SUBTOTAL(9,JX29:KI29) -> 0 | KL29: =SUM(KL26:KL28) -> 0 | KM29: =SUM(KM26:KM28) -> 0 | KN29: =SUM(KN26:KN28) -> 0 | KO29: =SUM(KO26:KO28) -> 0 | KP29: =SUM(KP26:KP28) -> 0 | KQ29: =SUM(KQ26:KQ28) -> 0 | KR29: =SUM(KR26:KR28) -> 0 | KS29: =SUM(KS26:KS28) -> 0 | ... KW29: =SUM(KW26:KW28) -> 0 | KX29: =+SUBTOTAL(9,KL29:KW29) -> 0 | KZ29: =SUM(KZ26:KZ28) -> 0 | LA29: =SUM(LA26:LA28) -> 0 | LB29: =SUM(LB26:LB28) -> 0 | LC29: =SUM(LC26:LC28) -> 0 | LD29: =SUM(LD26:LD28) -> 0 | LE29: =SUM(LE26:LE28) -> 0 | LF29: =SUM(LF26:LF28) -> 0 | LG29: =SUM(LG26:LG28) -> 0 | ... LK29: =SUM(LK26:LK28) -> 0 | LL29: =+SUBTOTAL(9,KZ29:LK29) -> 0 | LN29: =SUM(LN26:LN28) -> 0 | LO29: =SUM(LO26:LO28) -> 0 | LP29: =SUM(LP26:LP28) -> 0 | LQ29: =SUM(LQ26:LQ28) -> 0 | LR29: =SUM(LR26:LR28) -> 0 | LS29: =SUM(LS26:LS28) -> 0 | LT29: =SUM(LT26:LT28) -> 0 | LU29: =SUM(LU26:LU28) -> 0 | ... LY29: =SUM(LY26:LY28) -> 0 | LZ29: =+SUBTOTAL(9,LN29:LY29) -> 0 | MB29: =SUM(MB26:MB28) -> 0 | MC29: =SUM(MC26:MC28) -> 0 | MD29: =SUM(MD26:MD28) -> 0 | ME29: =SUM(ME26:ME28) -> 0 | MF29: =SUM(MF26:MF28) -> 0 | MG29: =SUM(MG26:MG28) -> 0 | MH29: =SUM(MH26:MH28) -> 0 | MI29: =SUM(MI26:MI28) -> 0 | ... MN29: =SUM(MN26:MN28) -> 0
B31: OPERATING EXPENSES
B32: PERSONNEL EXPENSES
B33: Salaries & Wages | D33: 2631519 | E33: 2631519 | F33: 2631519 | G33: 2631519 | H33: 2631519 | I33: 2631519 | J33: 2631519 | K33: 2631519 | L33: 2631519 | M33: 2631519 | N33: 2631519 | O33: 2631519 | P33: =+SUBTOTAL(9,D33:O33) -> 31578228 | R33: 212989 | S33: 212989 | T33: 212989 | U33: 212989 | V33: 212989 | W33: 212989 | X33: 212989 | Y33: 212989 | Z33: 212989 | AA33: 212989 | AB33: 212989 | AC33: 212989 | AD33: =+SUBTOTAL(9,R33:AC33) -> 2555868 | AF33: 214527 | AG33: 214527 | AH33: 214527 | AI33: 214527 | AJ33: 214527 | AK33: 214527 | AL33: 214527 | AM33: 214527 | AN33: 214527 | AO33: 214527 | AP33: 214527 | AQ33: 214527 | AR33: =+SUBTOTAL(9,AF33:AQ33) -> 2574324 | AT33: 670941 | AU33: 670941 | AV33: 670941 | AW33: 670941 | AX33: 670941 | AY33: 670941 | AZ33: 670941 | BA33: 670941 | BB33: 670941 | BC33: 670941 | BD33: 670941 | BE33: 670941 | BF33: =+SUBTOTAL(9,AT33:BE33) -> 8051292 | BH33: 3850090 | BI33: 3850090 | BJ33: 3850090 | BK33: 3850090 | BL33: 3850090 | BM33: 3850090 | BN33: 3850090 | BO33: 3850090 | BP33: 3850090 | BQ33: 3850090 | BR33: 3850090 | BS33: 3850090 | BT33: =+SUBTOTAL(9,BH33:BS33) -> 46201080 | BV33: 600345 | BW33: 600345 | BX33: 600345 | BY33: 600345 | BZ33: 600345 | CA33: 600345 | CB33: 600345 | CC33: 600345 | CD33: 600345 | CE33: 600345 | CF33: 600345 | CG33: 600345 | CH33: =+SUBTOTAL(9,BV33:CG33) -> 7204140 | CJ33: 1554444 | CK33: 1554444 | CL33: 1554444 | CM33: 1554444 | CN33: 1554444 | CO33: 1554444 | CP33: 1554444 | CQ33: 1554444 | CR33: 1554444 | CS33: 1554444 | CT33: 1554444 | CU33: 1554444 | CV33: =+SUBTOTAL(9,CJ33:CU33) -> 18653328 | CX33: 3445127 | CY33: 3445127 | CZ33: 3445127 | DA33: 3445127 | DB33: 3445127 | DC33: 3445127 | DD33: 3445127 | DE33: 3445127 | DF33: 3445127 | DG33: 3445127 | DH33: 3445127 | DI33: 3445127 | DJ33: =+SUBTOTAL(9,CX33:DI33) -> 41341524 | DL33: 2007756 | DM33: 2007756 | DN33: 2007756 | DO33: 2007756 | DP33: 2007756 | DQ33: 2007756 | DR33: 2007756 | DS33: 2007756 | DT33: 2007756 | DU33: 2007756 | DV33: 2007756 | DW33: 2007756 | DX33: =+SUBTOTAL(9,DL33:DW33) -> 24093072 | DZ33: 325406 | EA33: 325406 | EB33: 325406 | EC33: 325406 | ED33: 325406 | EE33: 325406 | EF33: 325406 | EG33: 325406 | EH33: 325406 | EI33: 325406 | EJ33: 325406 | EK33: 325406 | EL33: =+SUBTOTAL(9,DZ33:EK33) -> 3904872 | EN33: 462618 | EO33: 462618 | EP33: 462618 | EQ33: 462618 | ER33: 462618 | ES33: 462618 | ET33: 462618 | EU33: 462618 | EV33: 462618 | EW33: 462618 | EX33: 462618 | EY33: 462618 | EZ33: =+SUBTOTAL(9,EN33:EY33) -> 5551416 | FB33: 79363 | FC33: 79363 | FD33: 79363 | FE33: 79363 | FF33: 79363 | FG33: 79363 | FH33: 79363 | FI33: 79363 | FJ33: 79363 | FK33: 79363 | FL33: 79363 | FM33: 79363 | FN33: =+SUBTOTAL(9,FB33:FM33) -> 952356 | FP33: 1358053 | FQ33: 1358053 | FR33: 1358053 | FS33: 1358053 | FT33: 1358053 | FU33: 1358053 | FV33: 1358053 | FW33: 1358053 | FX33: 1358053 | FY33: 1358053 | FZ33: 1358053 | GA33: 1358053 | GB33: =+SUBTOTAL(9,FP33:GA33) -> 16296636 | GD33: 723125 | GE33: 723125 | GF33: 723125 | GG33: 723125 | GH33: 723125 | GI33: 723125 | GJ33: 723125 | GK33: 723125 | GL33: 723125 | GM33: 723125 | GN33: 723125 | GO33: 723125 | GP33: =+SUBTOTAL(9,GD33:GO33) -> 8677500 | GR33: -1096797.9 | GS33: -1096797.9 | GT33: -1096797.9 | GU33: -1096797.9 | GV33: -1096797.9 | GW33: -1096797.9 | GX33: -1096797.9 | GY33: -1096797.9 | GZ33: -1096797.9 | HA33: -1096797.9 | HB33: -1096797.9 | HC33: -1096797.9 | HD33: =+SUBTOTAL(9,GR33:HC33)*0 -> 0 | HF33: 592480 | HG33: 592480 | HH33: 592480 | HI33: 592480 | HJ33: 592480 | HK33: 592480 | HL33: 592480 | HM33: 592480 | HN33: 592480 | HO33: 592480 | HP33: 592480 | HQ33: 592480 | HR33: =+SUBTOTAL(9,HF33:HQ33) -> 7109760 | HT33: 154552 | HU33: 154552 | HV33: 154552 | HW33: 154552 | HX33: 154552 | HY33: 154552 | HZ33: 154552 | IA33: 154552 | IB33: 154552 | IC33: 154552 | ID33: 154552 | IE33: 154552 | IF33: =+SUBTOTAL(9,HT33:IE33) -> 1854624 | IH33: 517372 | II33: 517372 | IJ33: 517372 | IK33: 517372 | IL33: 517372 | IM33: 517372 | IN33: 517372 | IO33: 517372 | IP33: 517372 | IQ33: 517372 | IR33: 517372 | IS33: 517372 | IT33: =+SUBTOTAL(9,IH33:IS33) -> 6208464 | IV33: 1497536 | IW33: 1497536 | IX33: 1497536 | IY33: 1497536 | IZ33: 1497536 | JA33: 1497536 | JB33: 1497536 | JC33: 1497536 | JD33: 1497536 | JE33: 1497536 | JF33: 1497536 | JG33: 1497536 | JH33: =+SUBTOTAL(9,IV33:JG33) -> 17970432 | JJ33: 2021408 | JK33: 2021408 | JL33: 2021408 | JM33: 2021408 | JN33: 2021408 | JO33: 2021408 | JP33: 2021408 | JQ33: 2021408 | JR33: 2021408 | JS33: 2021408 | JT33: 2021408 | JU33: 2021408 | JV33: =+SUBTOTAL(9,JJ33:JU33) -> 24256896 | JX33: 1091919 | JY33: 1091919 | JZ33: 1091919 | KA33: 1091919 | KB33: 1091919 | KC33: 1091919 | KD33: 1091919 | KE33: 1091919 | KF33: 1091919 | KG33: 1091919 | KH33: 1091919 | KI33: 1091919 | KJ33: =+SUBTOTAL(9,JX33:KI33) -> 13103028 | KL33: 150250 | KM33: 150250 | KN33: 150250 | KO33: 150250 | KP33: 150250 | KQ33: 150250 | KR33: 150250 | KS33: 150250 | KT33: 150250 | KU33: 150250 | KV33: 150250 | KW33: 150250 | KX33: =+SUBTOTAL(9,KL33:KW33) -> 1803000 | KZ33: 156301 | LA33: 156301 | LB33: 156301 | LC33: 156301 | LD33: 156301 | LE33: 156301 | LF33: 156301 | LG33: 156301 | LH33: 156301 | LI33: 156301 | LJ33: 156301 | LK33: 156301 | LL33: =+SUBTOTAL(9,KZ33:LK33) -> 1875612 | LN33: 0 | LO33: 0 | LP33: 0 | LQ33: 0 | LR33: 0 | LS33: 0 | LT33: 0 | LU33: 0 | LV33: 0 | LW33: 0 | LX33: 0 | LY33: 0 | LZ33: =+SUBTOTAL(9,LN33:LY33) -> 0 | MB33: =SUMIF($D$6:$LY$6,MB$3,$D33:$LY33) -> 23221323 | MC33: =SUMIF($D$6:$LY$6,MC$3,$D33:$LY33) -> 23221323 | MD33: =SUMIF($D$6:$LY$6,MD$3,$D33:$LY33) -> 23221323 | ME33: =SUMIF($D$6:$LY$6,ME$3,$D33:$LY33) -> 23221323 | MF33: =SUMIF($D$6:$LY$6,MF$3,$D33:$LY33) -> 23221323 | MG33: =SUMIF($D$6:$LY$6,MG$3,$D33:$LY33) -> 23221323 | MH33: =SUMIF($D$6:$LY$6,MH$3,$D33:$LY33) -> 23221323 | MI33: =SUMIF($D$6:$LY$6,MI$3,$D33:$LY33) -> 23221323 | ... MM33: =SUMIF($D$6:$LY$6,MM$3,$D33:$LY33) -> 23221323 | MN33: =SUM(MB33:MM33) -> 2.7865588e+08
B34: Provision for Bonus, Leave & Other Employment Costs | D34: 199226 | E34: 199226 | F34: 199226 | G34: 199226 | H34: 199226 | I34: 199226 | J34: 199226 | K34: 199226 | L34: 199226 | M34: 199226 | N34: 199226 | O34: 199226 | P34: =+SUBTOTAL(9,D34:O34) -> 2390712 | R34: 16127 | S34: 16127 | T34: 16127 | U34: 16127 | V34: 16127 | W34: 16127 | X34: 16127 | Y34: 16127 | Z34: 16127 | AA34: 16127 | AB34: 16127 | AC34: 16127 | AD34: =+SUBTOTAL(9,R34:AC34) -> 193524 | AF34: 16242 | AG34: 16242 | AH34: 16242 | AI34: 16242 | AJ34: 16242 | AK34: 16242 | AL34: 16242 | AM34: 16242 | AN34: 16242 | AO34: 16242 | AP34: 16242 | AQ34: 16242 | AR34: =+SUBTOTAL(9,AF34:AQ34) -> 194904 | AT34: 50794 | AU34: 50794 | AV34: 50794 | AW34: 50794 | AX34: 50794 | AY34: 50794 | AZ34: 50794 | BA34: 50794 | BB34: 50794 | BC34: 50794 | BD34: 50794 | BE34: 50794 | BF34: =+SUBTOTAL(9,AT34:BE34) -> 609528 | BH34: 291480 | BI34: 291480 | BJ34: 291480 | BK34: 291480 | BL34: 291480 | BM34: 291480 | BN34: 291480 | BO34: 291480 | BP34: 291480 | BQ34: 291480 | BR34: 291480 | BS34: 291480 | BT34: =+SUBTOTAL(9,BH34:BS34) -> 3497760 | BV34: 45451 | BW34: 45451 | BX34: 45451 | BY34: 45451 | BZ34: 45451 | CA34: 45451 | CB34: 45451 | CC34: 45451 | CD34: 45451 | CE34: 45451 | CF34: 45451 | CG34: 45451 | CH34: =+SUBTOTAL(9,BV34:CG34) -> 545412 | CJ34: 117683 | CK34: 117683 | CL34: 117683 | CM34: 117683 | CN34: 117683 | CO34: 117683 | CP34: 117683 | CQ34: 117683 | CR34: 117683 | CS34: 117683 | CT34: 117683 | CU34: 117683 | CV34: =+SUBTOTAL(9,CJ34:CU34) -> 1412196 | CX34: 260820 | CY34: 260820 | CZ34: 260820 | DA34: 260820 | DB34: 260820 | DC34: 260820 | DD34: 260820 | DE34: 260820 | DF34: 260820 | DG34: 260820 | DH34: 260820 | DI34: 260820 | DJ34: =+SUBTOTAL(9,CX34:DI34) -> 3129840 | DL34: 152002 | DM34: 152002 | DN34: 152002 | DO34: 152002 | DP34: 152002 | DQ34: 152002 | DR34: 152002 | DS34: 152002 | DT34: 152002 | DU34: 152002 | DV34: 152002 | DW34: 152002 | DX34: =+SUBTOTAL(9,DL34:DW34) -> 1824024 | DZ34: 24637 | EA34: 24637 | EB34: 24637 | EC34: 24637 | ED34: 24637 | EE34: 24637 | EF34: 24637 | EG34: 24637 | EH34: 24637 | EI34: 24637 | EJ34: 24637 | EK34: 24637 | EL34: =+SUBTOTAL(9,DZ34:EK34) -> 295644 | EN34: 35023 | EO34: 35023 | EP34: 35023 | EQ34: 35023 | ER34: 35023 | ES34: 35023 | ET34: 35023 | EU34: 35023 | EV34: 35023 | EW34: 35023 | EX34: 35023 | EY34: 35023 | EZ34: =+SUBTOTAL(9,EN34:EY34) -> 420276 | FB34: 6007 | FC34: 6007 | FD34: 6007 | FE34: 6007 | FF34: 6007 | FG34: 6007 | FH34: 6007 | FI34: 6007 | FJ34: 6007 | FK34: 6007 | FL34: 6007 | FM34: 6007 | FN34: =+SUBTOTAL(9,FB34:FM34) -> 72084 | FP34: 102815 | FQ34: 102815 | FR34: 102815 | FS34: 102815 | FT34: 102815 | FU34: 102815 | FV34: 102815 | FW34: 102815 | FX34: 102815 | FY34: 102815 | FZ34: 102815 | GA34: 102815 | GB34: =+SUBTOTAL(9,FP34:GA34) -> 1233780 | GD34: 54746 | GE34: 54746 | GF34: 54746 | GG34: 54746 | GH34: 54746 | GI34: 54746 | GJ34: 54746 | GK34: 54746 | GL34: 54746 | GM34: 54746 | GN34: 54746 | GO34: 54746 | GP34: =+SUBTOTAL(9,GD34:GO34) -> 656952 | GR34: -54020.753 | GS34: -54020.753 | GT34: -54020.753 | GU34: -54020.753 | GV34: -54020.753 | GW34: -54020.753 | GX34: -54020.753 | GY34: -54020.753 | GZ34: -54020.753 | HA34: -54020.753 | HB34: -54020.753 | HC34: -54020.753 | HD34: =+SUBTOTAL(9,GR34:HC34)*0 -> 0 | HF34: 44857 | HG34: 44857 | HH34: 44857 | HI34: 44857 | HJ34: 44857 | HK34: 44857 | HL34: 44857 | HM34: 44857 | HN34: 44857 | HO34: 44857 | HP34: 44857 | HQ34: 44857 | HR34: =+SUBTOTAL(9,HF34:HQ34) -> 538284 | HT34: 11700 | HU34: 11700 | HV34: 11700 | HW34: 11700 | HX34: 11700 | HY34: 11700 | HZ34: 11700 | IA34: 11700 | IB34: 11700 | IC34: 11700 | ID34: 11700 | IE34: 11700 | IF34: =+SUBTOTAL(9,HT34:IE34) -> 140400 | IH34: 39168 | II34: 39168 | IJ34: 39168 | IK34: 39168 | IL34: 39168 | IM34: 39168 | IN34: 39168 | IO34: 39168 | IP34: 39168 | IQ34: 39168 | IR34: 39168 | IS34: 39168 | IT34: =+SUBTOTAL(9,IH34:IS34) -> 470016 | IV34: 113373 | IW34: 113373 | IX34: 113373 | IY34: 113373 | IZ34: 113373 | JA34: 113373 | JB34: 113373 | JC34: 113373 | JD34: 113373 | JE34: 113373 | JF34: 113373 | JG34: 113373 | JH34: =+SUBTOTAL(9,IV34:JG34) -> 1360476 | JJ34: 153035 | JK34: 153035 | JL34: 153035 | JM34: 153035 | JN34: 153035 | JO34: 153035 | JP34: 153035 | JQ34: 153035 | JR34: 153035 | JS34: 153035 | JT34: 153035 | JU34: 153035 | JV34: =+SUBTOTAL(9,JJ34:JU34) -> 1836420 | JX34: 82667 | JY34: 82667 | JZ34: 82667 | KA34: 82667 | KB34: 82667 | KC34: 82667 | KD34: 82667 | KE34: 82667 | KF34: 82667 | KG34: 82667 | KH34: 82667 | KI34: 82667 | KJ34: =+SUBTOTAL(9,JX34:KI34) -> 992004 | KL34: 11375 | KM34: 11375 | KN34: 11375 | KO34: 11375 | KP34: 11375 | KQ34: 11375 | KR34: 11375 | KS34: 11375 | KT34: 11375 | KU34: 11375 | KV34: 11375 | KW34: 11375 | KX34: =+SUBTOTAL(9,KL34:KW34) -> 136500 | KZ34: 11833 | LA34: 11833 | LB34: 11833 | LC34: 11833 | LD34: 11833 | LE34: 11833 | LF34: 11833 | LG34: 11833 | LH34: 11833 | LI34: 11833 | LJ34: 11833 | LK34: 11833 | LL34: =+SUBTOTAL(9,KZ34:LK34) -> 141996 | LN34: 0 | LO34: 0 | LP34: 0 | LQ34: 0 | LR34: 0 | LS34: 0 | LT34: 0 | LU34: 0 | LV34: 0 | LW34: 0 | LX34: 0 | LY34: 0 | LZ34: =+SUBTOTAL(9,LN34:LY34) -> 0 | MB34: =SUMIF($D$6:$LY$6,MB$3,$D34:$LY34) -> 1787040.2 | MC34: =SUMIF($D$6:$LY$6,MC$3,$D34:$LY34) -> 1787040.2 | MD34: =SUMIF($D$6:$LY$6,MD$3,$D34:$LY34) -> 1787040.2 | ME34: =SUMIF($D$6:$LY$6,ME$3,$D34:$LY34) -> 1787040.2 | MF34: =SUMIF($D$6:$LY$6,MF$3,$D34:$LY34) -> 1787040.2 | MG34: =SUMIF($D$6:$LY$6,MG$3,$D34:$LY34) -> 1787040.2 | MH34: =SUMIF($D$6:$LY$6,MH$3,$D34:$LY34) -> 1787040.2 | MI34: =SUMIF($D$6:$LY$6,MI$3,$D34:$LY34) -> 1787040.2 | ... MM34: =SUMIF($D$6:$LY$6,MM$3,$D34:$LY34) -> 1787040.2 | MN34: =SUM(MB34:MM34) -> 21444483
B35: Consultants & Contractors | D35: 0 | E35: 0 | F35: 0 | G35: 0 | H35: 0 | I35: 0 | J35: 0 | K35: 0 | L35: 0 | M35: 0 | N35: 0 | O35: 0 | P35: =+SUBTOTAL(9,D35:O35) -> 0 | R35: 0 | S35: 0 | T35: 0 | U35: 0 | V35: 0 | W35: 0 | X35: 0 | Y35: 0 | Z35: 0 | AA35: 0 | AB35: 0 | AC35: 0 | AD35: =+SUBTOTAL(9,R35:AC35) -> 0 | AF35: 0 | AG35: 0 | AH35: 0 | AI35: 0 | AJ35: 0 | AK35: 0 | AL35: 0 | AM35: 0 | AN35: 0 | AO35: 0 | AP35: 0 | AQ35: 0 | AR35: =+SUBTOTAL(9,AF35:AQ35) -> 0 | AT35: 0 | AU35: 0 | AV35: 0 | AW35: 0 | AX35: 0 | AY35: 0 | AZ35: 0 | BA35: 0 | BB35: 0 | BC35: 0 | BD35: 0 | BE35: 0 | BF35: =+SUBTOTAL(9,AT35:BE35) -> 0 | BH35: 0 | BI35: 0 | BJ35: 0 | BK35: 0 | BL35: 0 | BM35: 0 | BN35: 0 | BO35: 0 | BP35: 0 | BQ35: 0 | BR35: 0 | BS35: 0 | BT35: =+SUBTOTAL(9,BH35:BS35) -> 0 | BV35: 0 | BW35: 0 | BX35: 0 | BY35: 0 | BZ35: 0 | CA35: 0 | CB35: 0 | CC35: 0 | CD35: 0 | CE35: 0 | CF35: 0 | CG35: 0 | CH35: =+SUBTOTAL(9,BV35:CG35) -> 0 | CJ35: 0 | CK35: 0 | CL35: 0 | CM35: 0 | CN35: 0 | CO35: 0 | CP35: 0 | CQ35: 0 | CR35: 0 | CS35: 0 | CT35: 0 | CU35: 0 | CV35: =+SUBTOTAL(9,CJ35:CU35) -> 0 | CX35: 190000 | CY35: 190000 | CZ35: 190000 | DA35: 190000 | DB35: 190000 | DC35: 190000 | DD35: 190000 | DE35: 190000 | DF35: 190000 | DG35: 190000 | DH35: 190000 | DI35: 190000 | DJ35: =+SUBTOTAL(9,CX35:DI35) -> 2280000 | DL35: 0 | DM35: 0 | DN35: 0 | DO35: 0 | DP35: 0 | DQ35: 0 | DR35: 0 | DS35: 0 | DT35: 0 | DU35: 0 | DV35: 0 | DW35: 0 | DX35: =+SUBTOTAL(9,DL35:DW35) -> 0 | DZ35: 0 | EA35: 0 | EB35: 0 | EC35: 0 | ED35: 0 | EE35: 0 | EF35: 0 | EG35: 0 | EH35: 0 | EI35: 0 | EJ35: 0 | EK35: 0 | EL35: =+SUBTOTAL(9,DZ35:EK35) -> 0 | EN35: 0 | EO35: 0 | EP35: 0 | EQ35: 0 | ER35: 0 | ES35: 0 | ET35: 0 | EU35: 0 | EV35: 0 | EW35: 0 | EX35: 0 | EY35: 0 | EZ35: =+SUBTOTAL(9,EN35:EY35) -> 0 | FB35: 0 | FC35: 0 | FD35: 0 | FE35: 0 | FF35: 0 | FG35: 0 | FH35: 0 | FI35: 0 | FJ35: 0 | FK35: 0 | FL35: 0 | FM35: 0 | FN35: =+SUBTOTAL(9,FB35:FM35) -> 0 | FP35: 0 | FQ35: 0 | FR35: 0 | FS35: 0 | FT35: 0 | FU35: 0 | FV35: 0 | FW35: 0 | FX35: 0 | FY35: 0 | FZ35: 0 | GA35: 0 | GB35: =+SUBTOTAL(9,FP35:GA35) -> 0 | GD35: 0 | GE35: 0 | GF35: 0 | GG35: 0 | GH35: 0 | GI35: 0 | GJ35: 0 | GK35: 0 | GL35: 0 | GM35: 0 | GN35: 0 | GO35: 0 | GP35: =+SUBTOTAL(9,GD35:GO35) -> 0 | GR35: 0 | GS35: 0 | GT35: 0 | GU35: 0 | GV35: 0 | GW35: 0 | GX35: 0 | GY35: 0 | GZ35: 0 | HA35: 0 | HB35: 0 | HC35: 0 | HD35: =+SUBTOTAL(9,GR35:HC35)*0 -> 0 | HF35: 0 | HG35: 0 | HH35: 0 | HI35: 0 | HJ35: 0 | HK35: 0 | HL35: 0 | HM35: 0 | HN35: 0 | HO35: 0 | HP35: 0 | HQ35: 0 | HR35: =+SUBTOTAL(9,HF35:HQ35) -> 0 | HT35: 0 | HU35: 0 | HV35: 0 | HW35: 0 | HX35: 0 | HY35: 0 | HZ35: 0 | IA35: 0 | IB35: 0 | IC35: 0 | ID35: 0 | IE35: 0 | IF35: =+SUBTOTAL(9,HT35:IE35) -> 0 | IH35: 0 | II35: 0 | IJ35: 0 | IK35: 0 | IL35: 0 | IM35: 0 | IN35: 0 | IO35: 0 | IP35: 0 | IQ35: 0 | IR35: 0 | IS35: 0 | IT35: =+SUBTOTAL(9,IH35:IS35) -> 0 | IV35: 0 | IW35: 0 | IX35: 0 | IY35: 0 | IZ35: 0 | JA35: 0 | JB35: 0 | JC35: 0 | JD35: 0 | JE35: 0 | JF35: 0 | JG35: 0 | JH35: =+SUBTOTAL(9,IV35:JG35) -> 0 | JJ35: 0 | JK35: 0 | JL35: 0 | JM35: 0 | JN35: 0 | JO35: 0 | JP35: 0 | JQ35: 0 | JR35: 0 | JS35: 0 | JT35: 0 | JU35: 0 | JV35: =+SUBTOTAL(9,JJ35:JU35) -> 0 | JX35: 0 | JY35: 0 | JZ35: 0 | KA35: 0 | KB35: 0 | KC35: 0 | KD35: 0 | KE35: 0 | KF35: 0 | KG35: 0 | KH35: 0 | KI35: 0 | KJ35: =+SUBTOTAL(9,JX35:KI35) -> 0 | KL35: 0 | KM35: 0 | KN35: 0 | KO35: 0 | KP35: 0 | KQ35: 0 | KR35: 0 | KS35: 0 | KT35: 0 | KU35: 0 | KV35: 0 | KW35: 0 | KX35: =+SUBTOTAL(9,KL35:KW35) -> 0 | KZ35: 0 | LA35: 0 | LB35: 0 | LC35: 0 | LD35: 0 | LE35: 0 | LF35: 0 | LG35: 0 | LH35: 0 | LI35: 0 | LJ35: 0 | LK35: 0 | LL35: =+SUBTOTAL(9,KZ35:LK35) -> 0 | LN35: 0 | LO35: 0 | LP35: 0 | LQ35: 0 | LR35: 0 | LS35: 0 | LT35: 0 | LU35: 0 | LV35: 0 | LW35: 0 | LX35: 0 | LY35: 0 | LZ35: =+SUBTOTAL(9,LN35:LY35) -> 0 | MB35: =SUMIF($D$6:$LY$6,MB$3,$D35:$LY35) -> 190000 | MC35: =SUMIF($D$6:$LY$6,MC$3,$D35:$LY35) -> 190000 | MD35: =SUMIF($D$6:$LY$6,MD$3,$D35:$LY35) -> 190000 | ME35: =SUMIF($D$6:$LY$6,ME$3,$D35:$LY35) -> 190000 | MF35: =SUMIF($D$6:$LY$6,MF$3,$D35:$LY35) -> 190000 | MG35: =SUMIF($D$6:$LY$6,MG$3,$D35:$LY35) -> 190000 | MH35: =SUMIF($D$6:$LY$6,MH$3,$D35:$LY35) -> 190000 | MI35: =SUMIF($D$6:$LY$6,MI$3,$D35:$LY35) -> 190000 | ... MM35: =SUMIF($D$6:$LY$6,MM$3,$D35:$LY35) -> 190000 | MN35: =SUM(MB35:MM35) -> 2280000
B36: Pension Fund & Social Securities | D36: 197364 | E36: 197364 | F36: 197364 | G36: 197364 | H36: 197364 | I36: 197364 | J36: 197364 | K36: 197364 | L36: 197364 | M36: 197364 | N36: 197364 | O36: 197364 | P36: =+SUBTOTAL(9,D36:O36) -> 2368368 | R36: 15974 | S36: 15974 | T36: 15974 | U36: 15974 | V36: 15974 | W36: 15974 | X36: 15974 | Y36: 15974 | Z36: 15974 | AA36: 15974 | AB36: 15974 | AC36: 15974 | AD36: =+SUBTOTAL(9,R36:AC36) -> 191688 | AF36: 16090 | AG36: 16090 | AH36: 16090 | AI36: 16090 | AJ36: 16090 | AK36: 16090 | AL36: 16090 | AM36: 16090 | AN36: 16090 | AO36: 16090 | AP36: 16090 | AQ36: 16090 | AR36: =+SUBTOTAL(9,AF36:AQ36) -> 193080 | AT36: 50321 | AU36: 50321 | AV36: 50321 | AW36: 50321 | AX36: 50321 | AY36: 50321 | AZ36: 50321 | BA36: 50321 | BB36: 50321 | BC36: 50321 | BD36: 50321 | BE36: 50321 | BF36: =+SUBTOTAL(9,AT36:BE36) -> 603852 | BH36: 288757 | BI36: 288757 | BJ36: 288757 | BK36: 288757 | BL36: 288757 | BM36: 288757 | BN36: 288757 | BO36: 288757 | BP36: 288757 | BQ36: 288757 | BR36: 288757 | BS36: 288757 | BT36: =+SUBTOTAL(9,BH36:BS36) -> 3465084 | BV36: 45026 | BW36: 45026 | BX36: 45026 | BY36: 45026 | BZ36: 45026 | CA36: 45026 | CB36: 45026 | CC36: 45026 | CD36: 45026 | CE36: 45026 | CF36: 45026 | CG36: 45026 | CH36: =+SUBTOTAL(9,BV36:CG36) -> 540312 | CJ36: 116583 | CK36: 116583 | CL36: 116583 | CM36: 116583 | CN36: 116583 | CO36: 116583 | CP36: 116583 | CQ36: 116583 | CR36: 116583 | CS36: 116583 | CT36: 116583 | CU36: 116583 | CV36: =+SUBTOTAL(9,CJ36:CU36) -> 1398996 | CX36: 258385 | CY36: 258385 | CZ36: 258385 | DA36: 258385 | DB36: 258385 | DC36: 258385 | DD36: 258385 | DE36: 258385 | DF36: 258385 | DG36: 258385 | DH36: 258385 | DI36: 258385 | DJ36: =+SUBTOTAL(9,CX36:DI36) -> 3100620 | DL36: 150581 | DM36: 150581 | DN36: 150581 | DO36: 150581 | DP36: 150581 | DQ36: 150581 | DR36: 150581 | DS36: 150581 | DT36: 150581 | DU36: 150581 | DV36: 150581 | DW36: 150581 | DX36: =+SUBTOTAL(9,DL36:DW36) -> 1806972 | DZ36: 24405 | EA36: 24405 | EB36: 24405 | EC36: 24405 | ED36: 24405 | EE36: 24405 | EF36: 24405 | EG36: 24405 | EH36: 24405 | EI36: 24405 | EJ36: 24405 | EK36: 24405 | EL36: =+SUBTOTAL(9,DZ36:EK36) -> 292860 | EN36: 34696 | EO36: 34696 | EP36: 34696 | EQ36: 34696 | ER36: 34696 | ES36: 34696 | ET36: 34696 | EU36: 34696 | EV36: 34696 | EW36: 34696 | EX36: 34696 | EY36: 34696 | EZ36: =+SUBTOTAL(9,EN36:EY36) -> 416352 | FB36: 5952 | FC36: 5952 | FD36: 5952 | FE36: 5952 | FF36: 5952 | FG36: 5952 | FH36: 5952 | FI36: 5952 | FJ36: 5952 | FK36: 5952 | FL36: 5952 | FM36: 5952 | FN36: =+SUBTOTAL(9,FB36:FM36) -> 71424 | FP36: 101854 | FQ36: 101854 | FR36: 101854 | FS36: 101854 | FT36: 101854 | FU36: 101854 | FV36: 101854 | FW36: 101854 | FX36: 101854 | FY36: 101854 | FZ36: 101854 | GA36: 101854 | GB36: =+SUBTOTAL(9,FP36:GA36) -> 1222248 | GD36: 54234 | GE36: 54234 | GF36: 54234 | GG36: 54234 | GH36: 54234 | GI36: 54234 | GJ36: 54234 | GK36: 54234 | GL36: 54234 | GM36: 54234 | GN36: 54234 | GO36: 54234 | GP36: =+SUBTOTAL(9,GD36:GO36) -> 650808 | GR36: -303422.54 | GS36: -303422.54 | GT36: -303422.54 | GU36: -303422.54 | GV36: -303422.54 | GW36: -303422.54 | GX36: -303422.54 | GY36: -303422.54 | GZ36: -303422.54 | HA36: -303422.54 | HB36: -303422.54 | HC36: -303422.54 | HD36: =+SUBTOTAL(9,GR36:HC36)*0 -> 0 | HF36: 44436 | HG36: 44436 | HH36: 44436 | HI36: 44436 | HJ36: 44436 | HK36: 44436 | HL36: 44436 | HM36: 44436 | HN36: 44436 | HO36: 44436 | HP36: 44436 | HQ36: 44436 | HR36: =+SUBTOTAL(9,HF36:HQ36) -> 533232 | HT36: 11591 | HU36: 11591 | HV36: 11591 | HW36: 11591 | HX36: 11591 | HY36: 11591 | HZ36: 11591 | IA36: 11591 | IB36: 11591 | IC36: 11591 | ID36: 11591 | IE36: 11591 | IF36: =+SUBTOTAL(9,HT36:IE36) -> 139092 | IH36: 38803 | II36: 38803 | IJ36: 38803 | IK36: 38803 | IL36: 38803 | IM36: 38803 | IN36: 38803 | IO36: 38803 | IP36: 38803 | IQ36: 38803 | IR36: 38803 | IS36: 38803 | IT36: =+SUBTOTAL(9,IH36:IS36) -> 465636 | IV36: 112315 | IW36: 112315 | IX36: 112315 | IY36: 112315 | IZ36: 112315 | JA36: 112315 | JB36: 112315 | JC36: 112315 | JD36: 112315 | JE36: 112315 | JF36: 112315 | JG36: 112315 | JH36: =+SUBTOTAL(9,IV36:JG36) -> 1347780 | JJ36: 151605 | JK36: 151605 | JL36: 151605 | JM36: 151605 | JN36: 151605 | JO36: 151605 | JP36: 151605 | JQ36: 151605 | JR36: 151605 | JS36: 151605 | JT36: 151605 | JU36: 151605 | JV36: =+SUBTOTAL(9,JJ36:JU36) -> 1819260 | JX36: 81894 | JY36: 81894 | JZ36: 81894 | KA36: 81894 | KB36: 81894 | KC36: 81894 | KD36: 81894 | KE36: 81894 | KF36: 81894 | KG36: 81894 | KH36: 81894 | KI36: 81894 | KJ36: =+SUBTOTAL(9,JX36:KI36) -> 982728 | KL36: 11268 | KM36: 11268 | KN36: 11268 | KO36: 11268 | KP36: 11268 | KQ36: 11268 | KR36: 11268 | KS36: 11268 | KT36: 11268 | KU36: 11268 | KV36: 11268 | KW36: 11268 | KX36: =+SUBTOTAL(9,KL36:KW36) -> 135216 | KZ36: 11723 | LA36: 11723 | LB36: 11723 | LC36: 11723 | LD36: 11723 | LE36: 11723 | LF36: 11723 | LG36: 11723 | LH36: 11723 | LI36: 11723 | LJ36: 11723 | LK36: 11723 | LL36: =+SUBTOTAL(9,KZ36:LK36) -> 140676 | LN36: 0 | LO36: 0 | LP36: 0 | LQ36: 0 | LR36: 0 | LS36: 0 | LT36: 0 | LU36: 0 | LV36: 0 | LW36: 0 | LX36: 0 | LY36: 0 | LZ36: =+SUBTOTAL(9,LN36:LY36) -> 0 | MB36: =SUMIF($D$6:$LY$6,MB$3,$D36:$LY36) -> 1520434.5 | MC36: =SUMIF($D$6:$LY$6,MC$3,$D36:$LY36) -> 1520434.5 | MD36: =SUMIF($D$6:$LY$6,MD$3,$D36:$LY36) -> 1520434.5 | ME36: =SUMIF($D$6:$LY$6,ME$3,$D36:$LY36) -> 1520434.5 | MF36: =SUMIF($D$6:$LY$6,MF$3,$D36:$LY36) -> 1520434.5 | MG36: =SUMIF($D$6:$LY$6,MG$3,$D36:$LY36) -> 1520434.5 | MH36: =SUMIF($D$6:$LY$6,MH$3,$D36:$LY36) -> 1520434.5 | MI36: =SUMIF($D$6:$LY$6,MI$3,$D36:$LY36) -> 1520434.5 | ... MM36: =SUMIF($D$6:$LY$6,MM$3,$D36:$LY36) -> 1520434.5 | MN36: =SUM(MB36:MM36) -> 18245213
B37: Staff Allowances & Benefits | D37: 90040.802 | E37: 94825.802 | F37: 94825.802 | G37: 94825.802 | H37: 94825.802 | I37: 94825.802 | J37: 104950.8 | K37: 104950.8 | L37: 104950.8 | M37: 194950.8 | N37: 104950.8 | O37: 103915.09 | P37: =+SUBTOTAL(9,D37:O37) -> 1282838.9 | R37: 8203.7381 | S37: 8698.7381 | T37: 8698.7381 | U37: 8698.7381 | V37: 8698.7381 | W37: 8698.7381 | X37: 9549.7381 | Y37: 9549.7381 | Z37: 9549.7381 | AA37: 18549.738 | AB37: 9549.7381 | AC37: 9442.5952 | AD37: =+SUBTOTAL(9,R37:AC37) -> 117888.71 | AF37: 8203.7381 | AG37: 8698.7381 | AH37: 8698.7381 | AI37: 8698.7381 | AJ37: 8698.7381 | AK37: 8698.7381 | AL37: 9549.7381 | AM37: 9549.7381 | AN37: 9549.7381 | AO37: 18549.738 | AP37: 9549.7381 | AQ37: 9442.5952 | AR37: =+SUBTOTAL(9,AF37:AQ37) -> 117888.71 | AT37: 8791.1587 | AU37: 9121.1587 | AV37: 9121.1587 | AW37: 9121.1587 | AX37: 9121.1587 | AY37: 9121.1587 | AZ37: 10354.159 | BA37: 10354.159 | BB37: 10354.159 | BC37: 16354.159 | BD37: 10354.159 | BE37: 10282.73 | BF37: =+SUBTOTAL(9,AT37:BE37) -> 122450.48 | BH37: 48117.69 | BI37: 50262.69 | BJ37: 50262.69 | BK37: 50262.69 | BL37: 50262.69 | BM37: 50262.69 | BN37: 56108.69 | BO37: 56108.69 | BP37: 56108.69 | BQ37: 101108.69 | BR37: 56108.69 | BS37: 55572.976 | BT37: =+SUBTOTAL(9,BH37:BS37) -> 680547.57 | BV37: 5873.5794 | BW37: 6038.5794 | BX37: 6038.5794 | BY37: 6038.5794 | BZ37: 6038.5794 | CA37: 6038.5794 | CB37: 6951.5794 | CC37: 6951.5794 | CD37: 6951.5794 | CE37: 9951.5794 | CF37: 6951.5794 | CG37: 6915.8651 | CH37: =+SUBTOTAL(9,BV37:CG37) -> 80740.238 | CJ37: 133771.37 | CK37: 135586.37 | CL37: 135586.37 | CM37: 135586.37 | CN37: 135586.37 | CO37: 135586.37 | CP37: 139442.37 | CQ37: 139442.37 | CR37: 139442.37 | CS37: 172442.37 | CT37: 139442.37 | CU37: 139049.52 | CV37: =+SUBTOTAL(9,CJ37:CU37) -> 1680964.6 | CX37: 92413.222 | CY37: 97033.222 | CZ37: 97033.222 | DA37: 97033.222 | DB37: 97033.222 | DC37: 97033.222 | DD37: 108034.22 | DE37: 108034.22 | DF37: 108034.22 | DG37: 195034.22 | DH37: 108034.22 | DI37: 107034.22 | DJ37: =+SUBTOTAL(9,CX37:DI37) -> 1311784.7 | DL37: 73141.222 | DM37: 77431.222 | DN37: 77431.222 | DO37: 77431.222 | DP37: 77431.222 | DQ37: 77431.222 | DR37: 84930.222 | DS37: 84930.222 | DT37: 84930.222 | DU37: 168930.22 | DV37: 84930.222 | DW37: 83930.222 | DX37: =+SUBTOTAL(9,DL37:DW37) -> 1052878.7 | DZ37: 6167.5794 | EA37: 6332.5794 | EB37: 6332.5794 | EC37: 6332.5794 | ED37: 6332.5794 | EE37: 6332.5794 | EF37: 6951.5794 | EG37: 6951.5794 | EH37: 6951.5794 | EI37: 9951.5794 | EJ37: 6951.5794 | EK37: 6915.8651 | EL37: =+SUBTOTAL(9,DZ37:EK37) -> 82504.238 | EN37: 8791.1587 | EO37: 9121.1587 | EP37: 9121.1587 | EQ37: 9121.1587 | ER37: 9121.1587 | ES37: 9121.1587 | ET37: 10354.159 | EU37: 10354.159 | EV37: 10354.159 | EW37: 16354.159 | EX37: 10354.159 | EY37: 10282.73 | EZ37: =+SUBTOTAL(9,EN37:EY37) -> 122450.48 | FB37: 2917.5794 | FC37: 3082.5794 | FD37: 3082.5794 | FE37: 3082.5794 | FF37: 3082.5794 | FG37: 3082.5794 | FH37: 3402.5794 | FI37: 3402.5794 | FJ37: 3402.5794 | FK37: 6402.5794 | FL37: 3402.5794 | FM37: 3366.8651 | FN37: =+SUBTOTAL(9,FB37:FM37) -> 41710.238 | FP37: 30255.056 | FQ37: 31575.056 | FR37: 31575.056 | FS37: 31575.056 | FT37: 31575.056 | FU37: 31575.056 | FV37: 35521.056 | FW37: 35521.056 | FX37: 35521.056 | FY37: 59521.056 | FZ37: 35521.056 | GA37: 35271.056 | GB37: =+SUBTOTAL(9,FP37:GA37) -> 425006.67 | GD37: 402.57937 | GE37: 402.57937 | GF37: 402.57937 | GG37: 402.57937 | GH37: 402.57937 | GI37: 402.57937 | GJ37: 402.57937 | GK37: 402.57937 | GL37: 402.57937 | GM37: 402.57937 | GN37: 402.57937 | GO37: 366.86508 | GP37: =+SUBTOTAL(9,GD37:GO37) -> 4795.2381 | GR37: 0 | GS37: 0 | GT37: 50225 | GU37: 50225 | GV37: 50225 | GW37: 50225 | GX37: 50225 | GY37: 50225 | GZ37: 50225 | HA37: 50225 | HB37: 50225 | HC37: 50225 | HD37: =+SUBTOTAL(9,GR37:HC37)*0 -> 0 | HF37: 14076.317 | HG37: 14736.317 | HH37: 14736.317 | HI37: 14736.317 | HJ37: 14736.317 | HK37: 14736.317 | HL37: 16500.317 | HM37: 16500.317 | HN37: 16500.317 | HO37: 28500.317 | HP37: 16500.317 | HQ37: 16357.46 | HR37: =+SUBTOTAL(9,HF37:HQ37) -> 198616.95 | HT37: 3086.5794 | HU37: 3251.5794 | HV37: 3251.5794 | HW37: 3251.5794 | HX37: 3251.5794 | HY37: 3251.5794 | HZ37: 3605.5794 | IA37: 3605.5794 | IB37: 3605.5794 | IC37: 6605.5794 | ID37: 3605.5794 | IE37: 3569.8651 | IF37: =+SUBTOTAL(9,HT37:IE37) -> 43942.238 | IH37: 5873.5794 | II37: 6038.5794 | IJ37: 6038.5794 | IK37: 6038.5794 | IL37: 6038.5794 | IM37: 6038.5794 | IN37: 6951.5794 | IO37: 6951.5794 | IP37: 6951.5794 | IQ37: 9951.5794 | IR37: 6951.5794 | IS37: 6915.8651 | IT37: =+SUBTOTAL(9,IH37:IS37) -> 80740.238 | IV37: 26506.056 | IW37: 27661.056 | IX37: 27661.056 | IY37: 27661.056 | IZ37: 27661.056 | JA37: 27661.056 | JB37: 31121.056 | JC37: 31121.056 | JD37: 31121.056 | JE37: 52121.056 | JF37: 31121.056 | JG37: 30871.056 | JH37: =+SUBTOTAL(9,IV37:JG37) -> 372287.67 | JJ37: 33480.373 | JK37: 34965.373 | JL37: 34965.373 | JM37: 34965.373 | JN37: 34965.373 | JO37: 34965.373 | JP37: 39065.373 | JQ37: 39065.373 | JR37: 39065.373 | JS37: 78065.373 | JT37: 39065.373 | JU37: 38672.516 | JV37: =+SUBTOTAL(9,JJ37:JU37) -> 481306.62 | JX37: 16291.897 | JY37: 16951.897 | JZ37: 16951.897 | KA37: 16951.897 | KB37: 16951.897 | KC37: 16951.897 | KD37: 19059.897 | KE37: 19059.897 | KF37: 19059.897 | KG37: 34059.897 | KH37: 19059.897 | KI37: 18881.325 | KJ37: =+SUBTOTAL(9,JX37:KI37) -> 230232.19 | KL37: 27718.159 | KM37: 28213.159 | KN37: 28213.159 | KO37: 28213.159 | KP37: 28213.159 | KQ37: 28213.159 | KR37: 29064.159 | KS37: 29064.159 | KT37: 29064.159 | KU37: 35060.159 | KV37: 29064.159 | KW37: 28992.73 | KX37: =+SUBTOTAL(9,KL37:KW37) -> 349093.48 | KZ37: 10485.579 | LA37: 10485.579 | LB37: 10485.579 | LC37: 10485.579 | LD37: 10485.579 | LE37: 10485.579 | LF37: 10485.579 | LG37: 10485.579 | LH37: 10485.579 | LI37: 13489.579 | LJ37: 10485.579 | LK37: 10449.865 | LL37: =+SUBTOTAL(9,KZ37:LK37) -> 128795.24 | LN37: 0 | LO37: 0 | LP37: 0 | LQ37: 0 | LR37: 0 | LS37: 0 | LT37: 0 | LU37: 0 | LV37: 0 | LW37: 0 | LX37: 0 | LY37: 0 | LZ37: =+SUBTOTAL(9,LN37:LY37) -> 0 | MB37: =SUMIF($D$6:$LY$6,MB$3,$D37:$LY37) -> 654609.02 | MC37: =SUMIF($D$6:$LY$6,MC$3,$D37:$LY37) -> 680514.02 | MD37: =SUMIF($D$6:$LY$6,MD$3,$D37:$LY37) -> 730739.02 | ME37: =SUMIF($D$6:$LY$6,ME$3,$D37:$LY37) -> 730739.02 | MF37: =SUMIF($D$6:$LY$6,MF$3,$D37:$LY37) -> 730739.02 | MG37: =SUMIF($D$6:$LY$6,MG$3,$D37:$LY37) -> 730739.02 | MH37: =SUMIF($D$6:$LY$6,MH$3,$D37:$LY37) -> 792582.02 | MI37: =SUMIF($D$6:$LY$6,MI$3,$D37:$LY37) -> 792582.02 | ... MM37: =SUMIF($D$6:$LY$6,MM$3,$D37:$LY37) -> 786724.87 | MN37: =SUM(MB37:MM37) -> 9511714
B38: Medical Expenses | D38: 0 | E38: 0 | F38: 0 | G38: 0 | H38: 0 | I38: 0 | J38: 0 | K38: 0 | L38: 0 | M38: 0 | N38: 0 | O38: 0 | P38: =+SUBTOTAL(9,D38:O38) -> 0 | R38: 0 | S38: 0 | T38: 0 | U38: 0 | V38: 0 | W38: 0 | X38: 0 | Y38: 0 | Z38: 0 | AA38: 0 | AB38: 0 | AC38: 0 | AD38: =+SUBTOTAL(9,R38:AC38) -> 0 | AF38: 0 | AG38: 0 | AH38: 0 | AI38: 0 | AJ38: 0 | AK38: 0 | AL38: 0 | AM38: 0 | AN38: 0 | AO38: 0 | AP38: 0 | AQ38: 0 | AR38: =+SUBTOTAL(9,AF38:AQ38) -> 0 | AT38: 0 | AU38: 0 | AV38: 0 | AW38: 0 | AX38: 0 | AY38: 0 | AZ38: 0 | BA38: 0 | BB38: 0 | BC38: 0 | BD38: 0 | BE38: 0 | BF38: =+SUBTOTAL(9,AT38:BE38) -> 0 | BH38: 0 | BI38: 0 | BJ38: 0 | BK38: 0 | BL38: 0 | BM38: 0 | BN38: 0 | BO38: 0 | BP38: 0 | BQ38: 0 | BR38: 0 | BS38: 0 | BT38: =+SUBTOTAL(9,BH38:BS38) -> 0 | BV38: 0 | BW38: 0 | BX38: 0 | BY38: 0 | BZ38: 0 | CA38: 0 | CB38: 0 | CC38: 0 | CD38: 0 | CE38: 0 | CF38: 0 | CG38: 0 | CH38: =+SUBTOTAL(9,BV38:CG38) -> 0 | CJ38: 0 | CK38: 0 | CL38: 0 | CM38: 0 | CN38: 0 | CO38: 0 | CP38: 0 | CQ38: 0 | CR38: 0 | CS38: 0 | CT38: 0 | CU38: 0 | CV38: =+SUBTOTAL(9,CJ38:CU38) -> 0 | CX38: 0 | CY38: 0 | CZ38: 0 | DA38: 0 | DB38: 0 | DC38: 0 | DD38: 0 | DE38: 0 | DF38: 0 | DG38: 0 | DH38: 0 | DI38: 0 | DJ38: =+SUBTOTAL(9,CX38:DI38) -> 0 | DL38: 0 | DM38: 0 | DN38: 0 | DO38: 0 | DP38: 0 | DQ38: 0 | DR38: 0 | DS38: 0 | DT38: 0 | DU38: 0 | DV38: 0 | DW38: 0 | DX38: =+SUBTOTAL(9,DL38:DW38) -> 0 | DZ38: 0 | EA38: 0 | EB38: 0 | EC38: 0 | ED38: 0 | EE38: 0 | EF38: 0 | EG38: 0 | EH38: 0 | EI38: 0 | EJ38: 0 | EK38: 0 | EL38: =+SUBTOTAL(9,DZ38:EK38) -> 0 | EN38: 0 | EO38: 0 | EP38: 0 | EQ38: 0 | ER38: 0 | ES38: 0 | ET38: 0 | EU38: 0 | EV38: 0 | EW38: 0 | EX38: 0 | EY38: 0 | EZ38: =+SUBTOTAL(9,EN38:EY38) -> 0 | FB38: 0 | FC38: 0 | FD38: 0 | FE38: 0 | FF38: 0 | FG38: 0 | FH38: 0 | FI38: 0 | FJ38: 0 | FK38: 0 | FL38: 0 | FM38: 0 | FN38: =+SUBTOTAL(9,FB38:FM38) -> 0 | FP38: 0 | FQ38: 0 | FR38: 0 | FS38: 0 | FT38: 0 | FU38: 0 | FV38: 0 | FW38: 0 | FX38: 0 | FY38: 0 | FZ38: 0 | GA38: 0 | GB38: =+SUBTOTAL(9,FP38:GA38) -> 0 | GD38: 0 | GE38: 0 | GF38: 0 | GG38: 0 | GH38: 0 | GI38: 0 | GJ38: 0 | GK38: 0 | GL38: 0 | GM38: 0 | GN38: 0 | GO38: 0 | GP38: =+SUBTOTAL(9,GD38:GO38) -> 0 | GR38: 0 | GS38: 0 | GT38: 0 | GU38: 0 | GV38: 0 | GW38: 0 | GX38: 0 | GY38: 0 | GZ38: 0 | HA38: 0 | HB38: 0 | HC38: 0 | HD38: =+SUBTOTAL(9,GR38:HC38)*0 -> 0 | HF38: 0 | HG38: 0 | HH38: 0 | HI38: 0 | HJ38: 0 | HK38: 0 | HL38: 0 | HM38: 0 | HN38: 0 | HO38: 0 | HP38: 0 | HQ38: 0 | HR38: =+SUBTOTAL(9,HF38:HQ38) -> 0 | HT38: 0 | HU38: 0 | HV38: 0 | HW38: 0 | HX38: 0 | HY38: 0 | HZ38: 0 | IA38: 0 | IB38: 0 | IC38: 0 | ID38: 0 | IE38: 0 | IF38: =+SUBTOTAL(9,HT38:IE38) -> 0 | IH38: 0 | II38: 0 | IJ38: 0 | IK38: 0 | IL38: 0 | IM38: 0 | IN38: 0 | IO38: 0 | IP38: 0 | IQ38: 0 | IR38: 0 | IS38: 0 | IT38: =+SUBTOTAL(9,IH38:IS38) -> 0 | IV38: 0 | IW38: 0 | IX38: 0 | IY38: 0 | IZ38: 0 | JA38: 0 | JB38: 0 | JC38: 0 | JD38: 0 | JE38: 0 | JF38: 0 | JG38: 0 | JH38: =+SUBTOTAL(9,IV38:JG38) -> 0 | JJ38: 0 | JK38: 0 | JL38: 0 | JM38: 0 | JN38: 0 | JO38: 0 | JP38: 0 | JQ38: 0 | JR38: 0 | JS38: 0 | JT38: 0 | JU38: 0 | JV38: =+SUBTOTAL(9,JJ38:JU38) -> 0 | JX38: 0 | JY38: 0 | JZ38: 0 | KA38: 0 | KB38: 0 | KC38: 0 | KD38: 0 | KE38: 0 | KF38: 0 | KG38: 0 | KH38: 0 | KI38: 0 | KJ38: =+SUBTOTAL(9,JX38:KI38) -> 0 | KL38: 0 | KM38: 0 | KN38: 0 | KO38: 0 | KP38: 0 | KQ38: 0 | KR38: 0 | KS38: 0 | KT38: 0 | KU38: 0 | KV38: 0 | KW38: 0 | KX38: =+SUBTOTAL(9,KL38:KW38) -> 0 | KZ38: 0 | LA38: 0 | LB38: 0 | LC38: 0 | LD38: 0 | LE38: 0 | LF38: 0 | LG38: 0 | LH38: 0 | LI38: 0 | LJ38: 0 | LK38: 0 | LL38: =+SUBTOTAL(9,KZ38:LK38) -> 0 | LN38: 0 | LO38: 0 | LP38: 0 | LQ38: 0 | LR38: 0 | LS38: 0 | LT38: 0 | LU38: 0 | LV38: 0 | LW38: 0 | LX38: 0 | LY38: 0 | LZ38: =+SUBTOTAL(9,LN38:LY38) -> 0 | MB38: =SUMIF($D$6:$LY$6,MB$3,$D38:$LY38) -> 0 | MC38: =SUMIF($D$6:$LY$6,MC$3,$D38:$LY38) -> 0 | MD38: =SUMIF($D$6:$LY$6,MD$3,$D38:$LY38) -> 0 | ME38: =SUMIF($D$6:$LY$6,ME$3,$D38:$LY38) -> 0 | MF38: =SUMIF($D$6:$LY$6,MF$3,$D38:$LY38) -> 0 | MG38: =SUMIF($D$6:$LY$6,MG$3,$D38:$LY38) -> 0 | MH38: =SUMIF($D$6:$LY$6,MH$3,$D38:$LY38) -> 0 | MI38: =SUMIF($D$6:$LY$6,MI$3,$D38:$LY38) -> 0 | ... MM38: =SUMIF($D$6:$LY$6,MM$3,$D38:$LY38) -> 0 | MN38: =SUM(MB38:MM38) -> 0
B39: Staff Recruitment / Relocation | D39: 84364.274 | E39: 84364.274 | F39: 84364.274 | G39: 84364.274 | H39: 84364.274 | I39: 84364.274 | J39: 84364.274 | K39: 84364.274 | L39: 84364.274 | M39: 84364.274 | N39: 84364.274 | O39: 84364.274 | P39: =+SUBTOTAL(9,D39:O39) -> 1012371.3 | R39: 8727.3387 | S39: 8727.3387 | T39: 8727.3387 | U39: 8727.3387 | V39: 8727.3387 | W39: 8727.3387 | X39: 8727.3387 | Y39: 8727.3387 | Z39: 8727.3387 | AA39: 8727.3387 | AB39: 8727.3387 | AC39: 8727.3387 | AD39: =+SUBTOTAL(9,R39:AC39) -> 104728.06 | AF39: 8727.3387 | AG39: 8727.3387 | AH39: 8727.3387 | AI39: 8727.3387 | AJ39: 8727.3387 | AK39: 8727.3387 | AL39: 8727.3387 | AM39: 8727.3387 | AN39: 8727.3387 | AO39: 8727.3387 | AP39: 8727.3387 | AQ39: 8727.3387 | AR39: =+SUBTOTAL(9,AF39:AQ39) -> 104728.06 | AT39: 5818.2258 | AU39: 5818.2258 | AV39: 5818.2258 | AW39: 5818.2258 | AX39: 5818.2258 | AY39: 5818.2258 | AZ39: 5818.2258 | BA39: 5818.2258 | BB39: 5818.2258 | BC39: 5818.2258 | BD39: 5818.2258 | BE39: 5818.2258 | BF39: =+SUBTOTAL(9,AT39:BE39) -> 69818.709 | BH39: 43636.693 | BI39: 43636.693 | BJ39: 43636.693 | BK39: 43636.693 | BL39: 43636.693 | BM39: 43636.693 | BN39: 43636.693 | BO39: 43636.693 | BP39: 43636.693 | BQ39: 43636.693 | BR39: 43636.693 | BS39: 43636.693 | BT39: =+SUBTOTAL(9,BH39:BS39) -> 523640.32 | BV39: 2909.1129 | BW39: 2909.1129 | BX39: 2909.1129 | BY39: 2909.1129 | BZ39: 2909.1129 | CA39: 2909.1129 | CB39: 2909.1129 | CC39: 2909.1129 | CD39: 2909.1129 | CE39: 2909.1129 | CF39: 2909.1129 | CG39: 2909.1129 | CH39: =+SUBTOTAL(9,BV39:CG39) -> 34909.355 | CJ39: 32000.242 | CK39: 32000.242 | CL39: 32000.242 | CM39: 32000.242 | CN39: 32000.242 | CO39: 32000.242 | CP39: 32000.242 | CQ39: 32000.242 | CR39: 32000.242 | CS39: 32000.242 | CT39: 32000.242 | CU39: 32000.242 | CV39: =+SUBTOTAL(9,CJ39:CU39) -> 384002.9 | CX39: 81455.161 | CY39: 81455.161 | CZ39: 81455.161 | DA39: 81455.161 | DB39: 81455.161 | DC39: 81455.161 | DD39: 81455.161 | DE39: 81455.161 | DF39: 81455.161 | DG39: 81455.161 | DH39: 81455.161 | DI39: 81455.161 | DJ39: =+SUBTOTAL(9,CX39:DI39) -> 977461.93 | DL39: 81455.161 | DM39: 81455.161 | DN39: 81455.161 | DO39: 81455.161 | DP39: 81455.161 | DQ39: 81455.161 | DR39: 81455.161 | DS39: 81455.161 | DT39: 81455.161 | DU39: 81455.161 | DV39: 81455.161 | DW39: 81455.161 | DX39: =+SUBTOTAL(9,DL39:DW39) -> 977461.93 | DZ39: 2909.1129 | EA39: 2909.1129 | EB39: 2909.1129 | EC39: 2909.1129 | ED39: 2909.1129 | EE39: 2909.1129 | EF39: 2909.1129 | EG39: 2909.1129 | EH39: 2909.1129 | EI39: 2909.1129 | EJ39: 2909.1129 | EK39: 2909.1129 | EL39: =+SUBTOTAL(9,DZ39:EK39) -> 34909.355 | EN39: 5818.2258 | EO39: 5818.2258 | EP39: 5818.2258 | EQ39: 5818.2258 | ER39: 5818.2258 | ES39: 5818.2258 | ET39: 5818.2258 | EU39: 5818.2258 | EV39: 5818.2258 | EW39: 5818.2258 | EX39: 5818.2258 | EY39: 5818.2258 | EZ39: =+SUBTOTAL(9,EN39:EY39) -> 69818.709 | FB39: 2909.1129 | FC39: 2909.1129 | FD39: 2909.1129 | FE39: 2909.1129 | FF39: 2909.1129 | FG39: 2909.1129 | FH39: 2909.1129 | FI39: 2909.1129 | FJ39: 2909.1129 | FK39: 2909.1129 | FL39: 2909.1129 | FM39: 2909.1129 | FN39: =+SUBTOTAL(9,FB39:FM39) -> 34909.355 | FP39: 20363.79 | FQ39: 20363.79 | FR39: 20363.79 | FS39: 20363.79 | FT39: 20363.79 | FU39: 20363.79 | FV39: 20363.79 | FW39: 20363.79 | FX39: 20363.79 | FY39: 20363.79 | FZ39: 20363.79 | GA39: 20363.79 | GB39: =+SUBTOTAL(9,FP39:GA39) -> 244365.48 | GD39: 2909.1129 | GE39: 2909.1129 | GF39: 2909.1129 | GG39: 2909.1129 | GH39: 2909.1129 | GI39: 2909.1129 | GJ39: 2909.1129 | GK39: 2909.1129 | GL39: 2909.1129 | GM39: 2909.1129 | GN39: 2909.1129 | GO39: 2909.1129 | GP39: =+SUBTOTAL(9,GD39:GO39) -> 34909.355 | GR39: -159349.35 | GS39: -159349.35 | GT39: -159349.35 | GU39: -159349.35 | GV39: -159349.35 | GW39: -159349.35 | GX39: -159349.35 | GY39: -159349.35 | GZ39: -159349.35 | HA39: -159349.35 | HB39: -159349.35 | HC39: -159349.35 | HD39: =+SUBTOTAL(9,GR39:HC39)*0 -> 0 | HF39: 11636.452 | HG39: 11636.452 | HH39: 11636.452 | HI39: 11636.452 | HJ39: 11636.452 | HK39: 11636.452 | HL39: 11636.452 | HM39: 11636.452 | HN39: 11636.452 | HO39: 11636.452 | HP39: 11636.452 | HQ39: 11636.452 | HR39: =+SUBTOTAL(9,HF39:HQ39) -> 139637.42 | HT39: 2909.1129 | HU39: 2909.1129 | HV39: 2909.1129 | HW39: 2909.1129 | HX39: 2909.1129 | HY39: 2909.1129 | HZ39: 2909.1129 | IA39: 2909.1129 | IB39: 2909.1129 | IC39: 2909.1129 | ID39: 2909.1129 | IE39: 2909.1129 | IF39: =+SUBTOTAL(9,HT39:IE39) -> 34909.355 | IH39: 2909.1129 | II39: 2909.1129 | IJ39: 2909.1129 | IK39: 2909.1129 | IL39: 2909.1129 | IM39: 2909.1129 | IN39: 2909.1129 | IO39: 2909.1129 | IP39: 2909.1129 | IQ39: 2909.1129 | IR39: 2909.1129 | IS39: 2909.1129 | IT39: =+SUBTOTAL(9,IH39:IS39) -> 34909.355 | IV39: 20363.79 | IW39: 20363.79 | IX39: 20363.79 | IY39: 20363.79 | IZ39: 20363.79 | JA39: 20363.79 | JB39: 20363.79 | JC39: 20363.79 | JD39: 20363.79 | JE39: 20363.79 | JF39: 20363.79 | JG39: 20363.79 | JH39: =+SUBTOTAL(9,IV39:JG39) -> 244365.48 | JJ39: 32000.242 | JK39: 32000.242 | JL39: 32000.242 | JM39: 32000.242 | JN39: 32000.242 | JO39: 32000.242 | JP39: 32000.242 | JQ39: 32000.242 | JR39: 32000.242 | JS39: 32000.242 | JT39: 32000.242 | JU39: 32000.242 | JV39: =+SUBTOTAL(9,JJ39:JU39) -> 384002.9 | JX39: 14545.564 | JY39: 14545.564 | JZ39: 14545.564 | KA39: 14545.564 | KB39: 14545.564 | KC39: 14545.564 | KD39: 14545.564 | KE39: 14545.564 | KF39: 14545.564 | KG39: 14545.564 | KH39: 14545.564 | KI39: 14545.564 | KJ39: =+SUBTOTAL(9,JX39:KI39) -> 174546.77 | KL39: 5818.2258 | KM39: 5818.2258 | KN39: 5818.2258 | KO39: 5818.2258 | KP39: 5818.2258 | KQ39: 5818.2258 | KR39: 5818.2258 | KS39: 5818.2258 | KT39: 5818.2258 | KU39: 5818.2258 | KV39: 5818.2258 | KW39: 5818.2258 | KX39: =+SUBTOTAL(9,KL39:KW39) -> 69818.709 | KZ39: 2909.1129 | LA39: 2909.1129 | LB39: 2909.1129 | LC39: 2909.1129 | LD39: 2909.1129 | LE39: 2909.1129 | LF39: 2909.1129 | LG39: 2909.1129 | LH39: 2909.1129 | LI39: 2909.1129 | LJ39: 2909.1129 | LK39: 2909.1129 | LL39: =+SUBTOTAL(9,KZ39:LK39) -> 34909.355 | LN39: 0 | LO39: 0 | LP39: 0 | LQ39: 0 | LR39: 0 | LS39: 0 | LT39: 0 | LU39: 0 | LV39: 0 | LW39: 0 | LX39: 0 | LY39: 0 | LZ39: =+SUBTOTAL(9,LN39:LY39) -> 0 | MB39: =SUMIF($D$6:$LY$6,MB$3,$D39:$LY39) -> 317745.16 | MC39: =SUMIF($D$6:$LY$6,MC$3,$D39:$LY39) -> 317745.16 | MD39: =SUMIF($D$6:$LY$6,MD$3,$D39:$LY39) -> 317745.16 | ME39: =SUMIF($D$6:$LY$6,ME$3,$D39:$LY39) -> 317745.16 | MF39: =SUMIF($D$6:$LY$6,MF$3,$D39:$LY39) -> 317745.16 | MG39: =SUMIF($D$6:$LY$6,MG$3,$D39:$LY39) -> 317745.16 | MH39: =SUMIF($D$6:$LY$6,MH$3,$D39:$LY39) -> 317745.16 | MI39: =SUMIF($D$6:$LY$6,MI$3,$D39:$LY39) -> 317745.16 | ... MM39: =SUMIF($D$6:$LY$6,MM$3,$D39:$LY39) -> 317745.16 | MN39: =SUM(MB39:MM39) -> 3812942
B40: Staff Functions | D40: 174750 | E40: 12750 | F40: 38250 | G40: 12750 | H40: 12750 | I40: 12750 | J40: 12750 | K40: 117750 | L40: 102750 | M40: 33050 | N40: 38250 | O40: 39750 | P40: =+SUBTOTAL(9,D40:O40) -> 608300 | R40: 17476 | S40: 1276 | T40: 3826 | U40: 1276 | V40: 1276 | W40: 1276 | X40: 1276 | Y40: 11776 | Z40: 10276 | AA40: 3376 | AB40: 3826 | AC40: 3976 | AD40: =+SUBTOTAL(9,R40:AC40) -> 60912 | AF40: 17476 | AG40: 1276 | AH40: 3826 | AI40: 1276 | AJ40: 1276 | AK40: 1276 | AL40: 1276 | AM40: 11776 | AN40: 10276 | AO40: 3376 | AP40: 3826 | AQ40: 3976 | AR40: =+SUBTOTAL(9,AF40:AQ40) -> 60912 | AT40: 11652 | AU40: 852 | AV40: 2552 | AW40: 852 | AX40: 852 | AY40: 852 | AZ40: 852 | BA40: 7852 | BB40: 6852 | BC40: 2252 | BD40: 2552 | BE40: 2652 | BF40: =+SUBTOTAL(9,AT40:BE40) -> 40624 | BH40: 87376 | BI40: 6376 | BJ40: 19126 | BK40: 6376 | BL40: 6376 | BM40: 6376 | BN40: 6376 | BO40: 58876 | BP40: 51376 | BQ40: 15476 | BR40: 19126 | BS40: 19876 | BT40: =+SUBTOTAL(9,BH40:BS40) -> 303112 | BV40: 7326 | BW40: 426 | BX40: 1276 | BY40: 426 | BZ40: 426 | CA40: 426 | CB40: 426 | CC40: 5426 | CD40: 3426 | CE40: 1126 | CF40: 1276 | CG40: 1326 | CH40: =+SUBTOTAL(9,BV40:CG40) -> 23312 | CJ40: 64078 | CK40: 4678 | CL40: 14028 | CM40: 4678 | CN40: 4678 | CO40: 4678 | CP40: 4678 | CQ40: 43178 | CR40: 37678 | CS40: 12378 | CT40: 14028 | CU40: 14578 | CV40: =+SUBTOTAL(9,CJ40:CU40) -> 223336 | CX40: 171178 | CY40: 12328 | CZ40: 36978 | DA40: 12328 | DB40: 12328 | DC40: 12328 | DD40: 12328 | DE40: 116078 | DF40: 99328 | DG40: 32628 | DH40: 36978 | DI40: 38428 | DJ40: =+SUBTOTAL(9,CX40:DI40) -> 593236 | DL40: 163852 | DM40: 11902 | DN40: 35702 | DO40: 11902 | DP40: 11902 | DQ40: 11902 | DR40: 11902 | DS40: 110652 | DT40: 95902 | DU40: 30102 | DV40: 35702 | DW40: 37102 | DX40: =+SUBTOTAL(9,DL40:DW40) -> 568524 | DZ40: 5826 | EA40: 426 | EB40: 1276 | EC40: 426 | ED40: 426 | EE40: 426 | EF40: 426 | EG40: 3926 | EH40: 3426 | EI40: 1126 | EJ40: 1276 | EK40: 1326 | EL40: =+SUBTOTAL(9,DZ40:EK40) -> 20312 | EN40: 11652 | EO40: 852 | EP40: 2552 | EQ40: 852 | ER40: 852 | ES40: 852 | ET40: 852 | EU40: 7852 | EV40: 6852 | EW40: 2252 | EX40: 2552 | EY40: 2652 | EZ40: =+SUBTOTAL(9,EN40:EY40) -> 40624 | FB40: 5826 | FC40: 426 | FD40: 1276 | FE40: 426 | FF40: 426 | FG40: 426 | FH40: 426 | FI40: 3926 | FJ40: 3426 | FK40: 1126 | FL40: 1276 | FM40: 1326 | FN40: =+SUBTOTAL(9,FB40:FM40) -> 20312 | FP40: 46604 | FQ40: 3404 | FR40: 10204 | FS40: 3404 | FT40: 3404 | FU40: 3404 | FV40: 3404 | FW40: 31404 | FX40: 27404 | FY40: 9004 | FZ40: 10204 | GA40: 10604 | GB40: =+SUBTOTAL(9,FP40:GA40) -> 162448 | GD40: 0 | GE40: 0 | GF40: 0 | GG40: 0 | GH40: 0 | GI40: 0 | GJ40: 0 | GK40: 0 | GL40: 0 | GM40: 0 | GN40: 0 | GO40: 0 | GP40: =+SUBTOTAL(9,GD40:GO40) -> 0 | GR40: -120881.11 | GS40: -120881.11 | GT40: -120881.11 | GU40: -120881.11 | GV40: -120881.11 | GW40: -120881.11 | GX40: -120881.11 | GY40: -120881.11 | GZ40: -120881.11 | HA40: -120881.11 | HB40: -120881.11 | HC40: -120881.11 | HD40: =+SUBTOTAL(9,GR40:HC40)*0 -> 0 | HF40: 23304 | HG40: 1704 | HH40: 5104 | HI40: 1704 | HJ40: 1704 | HK40: 1704 | HL40: 1704 | HM40: 15704 | HN40: 13704 | HO40: 4504 | HP40: 5104 | HQ40: 5304 | HR40: =+SUBTOTAL(9,HF40:HQ40) -> 81248 | HT40: 5826 | HU40: 426 | HV40: 1276 | HW40: 426 | HX40: 426 | HY40: 426 | HZ40: 426 | IA40: 3926 | IB40: 3426 | IC40: 1126 | ID40: 1276 | IE40: 1326 | IF40: =+SUBTOTAL(9,HT40:IE40) -> 20312 | IH40: 5826 | II40: 426 | IJ40: 1276 | IK40: 426 | IL40: 426 | IM40: 426 | IN40: 426 | IO40: 3926 | IP40: 3426 | IQ40: 1126 | IR40: 1276 | IS40: 1326 | IT40: =+SUBTOTAL(9,IH40:IS40) -> 20312 | IV40: 40778 | IW40: 2978 | IX40: 8928 | IY40: 2978 | IZ40: 2978 | JA40: 2978 | JB40: 2978 | JC40: 27478 | JD40: 23978 | JE40: 7878 | JF40: 8928 | JG40: 9278 | JH40: =+SUBTOTAL(9,IV40:JG40) -> 142136 | JJ40: 76478 | JK40: 5528 | JL40: 16578 | JM40: 5528 | JN40: 5528 | JO40: 5528 | JP40: 5528 | JQ40: 51778 | JR40: 44528 | JS40: 11828 | JT40: 16578 | JU40: 17228 | JV40: =+SUBTOTAL(9,JJ40:JU40) -> 262636 | JX40: 29126 | JY40: 2126 | JZ40: 6376 | KA40: 2126 | KB40: 2126 | KC40: 2126 | KD40: 2126 | KE40: 19626 | KF40: 17126 | KG40: 4926 | KH40: 6376 | KI40: 6626 | KJ40: =+SUBTOTAL(9,JX40:KI40) -> 100812 | KL40: 11651 | KM40: 851 | KN40: 2551 | KO40: 851 | KP40: 851 | KQ40: 851 | KR40: 851 | KS40: 7851 | KT40: 6851 | KU40: 2251 | KV40: 2551 | KW40: 2651 | KX40: =+SUBTOTAL(9,KL40:KW40) -> 40612 | KZ40: 5825 | LA40: 425 | LB40: 1275 | LC40: 425 | LD40: 425 | LE40: 425 | LF40: 425 | LG40: 3925 | LH40: 3425 | LI40: 1125 | LJ40: 1275 | LK40: 1325 | LL40: =+SUBTOTAL(9,KZ40:LK40) -> 20300 | LN40: 0 | LO40: 0 | LP40: 0 | LQ40: 0 | LR40: 0 | LS40: 0 | LT40: 0 | LU40: 0 | LV40: 0 | LW40: 0 | LX40: 0 | LY40: 0 | LZ40: =+SUBTOTAL(9,LN40:LY40) -> 0 | MB40: =SUMIF($D$6:$LY$6,MB$3,$D40:$LY40) -> 863004.89 | MC40: =SUMIF($D$6:$LY$6,MC$3,$D40:$LY40) -> -49445.113 | MD40: =SUMIF($D$6:$LY$6,MD$3,$D40:$LY40) -> 93354.887 | ME40: =SUMIF($D$6:$LY$6,ME$3,$D40:$LY40) -> -49445.113 | MF40: =SUMIF($D$6:$LY$6,MF$3,$D40:$LY40) -> -49445.113 | MG40: =SUMIF($D$6:$LY$6,MG$3,$D40:$LY40) -> -49445.113 | MH40: =SUMIF($D$6:$LY$6,MH$3,$D40:$LY40) -> -49445.113 | MI40: =SUMIF($D$6:$LY$6,MI$3,$D40:$LY40) -> 543804.89 | ... MM40: =SUMIF($D$6:$LY$6,MM$3,$D40:$LY40) -> 101754.89 | MN40: =SUM(MB40:MM40) -> 1963758.6
B41: Course & Training | D41: 23947 | E41: 23947 | F41: 23947 | G41: 23947 | H41: 23947 | I41: 23947 | J41: 23947 | K41: 23947 | L41: 23947 | M41: 23947 | N41: 23947 | O41: 23947 | P41: =+SUBTOTAL(9,D41:O41) -> 287364 | R41: 1938 | S41: 1938 | T41: 1938 | U41: 1938 | V41: 1938 | W41: 1938 | X41: 1938 | Y41: 1938 | Z41: 1938 | AA41: 1938 | AB41: 1938 | AC41: 1938 | AD41: =+SUBTOTAL(9,R41:AC41) -> 23256 | AF41: 1952 | AG41: 1952 | AH41: 1952 | AI41: 1952 | AJ41: 1952 | AK41: 1952 | AL41: 1952 | AM41: 1952 | AN41: 1952 | AO41: 1952 | AP41: 1952 | AQ41: 1952 | AR41: =+SUBTOTAL(9,AF41:AQ41) -> 23424 | AT41: 6106 | AU41: 6106 | AV41: 6106 | AW41: 6106 | AX41: 6106 | AY41: 6106 | AZ41: 6106 | BA41: 6106 | BB41: 6106 | BC41: 6106 | BD41: 6106 | BE41: 6106 | BF41: =+SUBTOTAL(9,AT41:BE41) -> 73272 | BH41: 35036 | BI41: 35036 | BJ41: 35036 | BK41: 35036 | BL41: 35036 | BM41: 35036 | BN41: 35036 | BO41: 35036 | BP41: 35036 | BQ41: 35036 | BR41: 35036 | BS41: 35036 | BT41: =+SUBTOTAL(9,BH41:BS41) -> 420432 | BV41: 5463 | BW41: 5463 | BX41: 5463 | BY41: 5463 | BZ41: 5463 | CA41: 5463 | CB41: 5463 | CC41: 5463 | CD41: 5463 | CE41: 5463 | CF41: 5463 | CG41: 5463 | CH41: =+SUBTOTAL(9,BV41:CG41) -> 65556 | CJ41: 14146 | CK41: 14146 | CL41: 14146 | CM41: 14146 | CN41: 14146 | CO41: 14146 | CP41: 14146 | CQ41: 14146 | CR41: 14146 | CS41: 14146 | CT41: 14146 | CU41: 14146 | CV41: =+SUBTOTAL(9,CJ41:CU41) -> 169752 | CX41: 31351 | CY41: 31351 | CZ41: 31351 | DA41: 31351 | DB41: 31351 | DC41: 31351 | DD41: 31351 | DE41: 31351 | DF41: 31351 | DG41: 31351 | DH41: 31351 | DI41: 31351 | DJ41: =+SUBTOTAL(9,CX41:DI41) -> 376212 | DL41: 18271 | DM41: 18271 | DN41: 18271 | DO41: 18271 | DP41: 18271 | DQ41: 18271 | DR41: 18271 | DS41: 18271 | DT41: 18271 | DU41: 18271 | DV41: 18271 | DW41: 18271 | DX41: =+SUBTOTAL(9,DL41:DW41) -> 219252 | DZ41: 2961 | EA41: 2961 | EB41: 2961 | EC41: 2961 | ED41: 2961 | EE41: 2961 | EF41: 2961 | EG41: 2961 | EH41: 2961 | EI41: 2961 | EJ41: 2961 | EK41: 2961 | EL41: =+SUBTOTAL(9,DZ41:EK41) -> 35532 | EN41: 4210 | EO41: 4210 | EP41: 4210 | EQ41: 4210 | ER41: 4210 | ES41: 4210 | ET41: 4210 | EU41: 4210 | EV41: 4210 | EW41: 4210 | EX41: 4210 | EY41: 4210 | EZ41: =+SUBTOTAL(9,EN41:EY41) -> 50520 | FB41: 722 | FC41: 722 | FD41: 722 | FE41: 722 | FF41: 722 | FG41: 722 | FH41: 722 | FI41: 722 | FJ41: 722 | FK41: 722 | FL41: 722 | FM41: 722 | FN41: =+SUBTOTAL(9,FB41:FM41) -> 8664 | FP41: 12358 | FQ41: 12358 | FR41: 12358 | FS41: 12358 | FT41: 12358 | FU41: 12358 | FV41: 12358 | FW41: 12358 | FX41: 12358 | FY41: 12358 | FZ41: 12358 | GA41: 12358 | GB41: =+SUBTOTAL(9,FP41:GA41) -> 148296 | GD41: 6580 | GE41: 6580 | GF41: 6580 | GG41: 6580 | GH41: 6580 | GI41: 6580 | GJ41: 6580 | GK41: 6580 | GL41: 6580 | GM41: 6580 | GN41: 6580 | GO41: 6580 | GP41: =+SUBTOTAL(9,GD41:GO41) -> 78960 | GR41: -122636.59 | GS41: -122636.59 | GT41: -122636.59 | GU41: -122636.59 | GV41: -122636.59 | GW41: -122636.59 | GX41: -122636.59 | GY41: -122636.59 | GZ41: -122636.59 | HA41: -122636.59 | HB41: -122636.59 | HC41: -122636.59 | HD41: =+SUBTOTAL(9,GR41:HC41)*0 -> 0 | HF41: 5392 | HG41: 5392 | HH41: 5392 | HI41: 5392 | HJ41: 5392 | HK41: 5392 | HL41: 5392 | HM41: 5392 | HN41: 5392 | HO41: 5392 | HP41: 5392 | HQ41: 5392 | HR41: =+SUBTOTAL(9,HF41:HQ41) -> 64704 | HT41: 1406 | HU41: 1406 | HV41: 1406 | HW41: 1406 | HX41: 1406 | HY41: 1406 | HZ41: 1406 | IA41: 1406 | IB41: 1406 | IC41: 1406 | ID41: 1406 | IE41: 1406 | IF41: =+SUBTOTAL(9,HT41:IE41) -> 16872 | IH41: 4708 | II41: 4708 | IJ41: 4708 | IK41: 4708 | IL41: 4708 | IM41: 4708 | IN41: 4708 | IO41: 4708 | IP41: 4708 | IQ41: 4708 | IR41: 4708 | IS41: 4708 | IT41: =+SUBTOTAL(9,IH41:IS41) -> 56496 | IV41: 13628 | IW41: 13628 | IX41: 13628 | IY41: 13628 | IZ41: 13628 | JA41: 13628 | JB41: 13628 | JC41: 13628 | JD41: 13628 | JE41: 13628 | JF41: 13628 | JG41: 13628 | JH41: =+SUBTOTAL(9,IV41:JG41) -> 163536 | JJ41: 18395 | JK41: 18395 | JL41: 18395 | JM41: 18395 | JN41: 18395 | JO41: 18395 | JP41: 18395 | JQ41: 18395 | JR41: 18395 | JS41: 18395 | JT41: 18395 | JU41: 18395 | JV41: =+SUBTOTAL(9,JJ41:JU41) -> 220740 | JX41: 9936 | JY41: 9936 | JZ41: 9936 | KA41: 9936 | KB41: 9936 | KC41: 9936 | KD41: 9936 | KE41: 9936 | KF41: 9936 | KG41: 9936 | KH41: 9936 | KI41: 9936 | KJ41: =+SUBTOTAL(9,JX41:KI41) -> 119232 | KL41: 1368 | KM41: 1368 | KN41: 1368 | KO41: 1368 | KP41: 1368 | KQ41: 1368 | KR41: 1368 | KS41: 1368 | KT41: 1368 | KU41: 1368 | KV41: 1368 | KW41: 1368 | KX41: =+SUBTOTAL(9,KL41:KW41) -> 16416 | KZ41: 1422 | LA41: 1422 | LB41: 1422 | LC41: 1422 | LD41: 1422 | LE41: 1422 | LF41: 1422 | LG41: 1422 | LH41: 1422 | LI41: 1422 | LJ41: 1422 | LK41: 1422 | LL41: =+SUBTOTAL(9,KZ41:LK41) -> 17064 | LN41: 0 | LO41: 0 | LP41: 0 | LQ41: 0 | LR41: 0 | LS41: 0 | LT41: 0 | LU41: 0 | LV41: 0 | LW41: 0 | LX41: 0 | LY41: 0 | LZ41: =+SUBTOTAL(9,LN41:LY41) -> 0 | MB41: =SUMIF($D$6:$LY$6,MB$3,$D41:$LY41) -> 98659.405 | MC41: =SUMIF($D$6:$LY$6,MC$3,$D41:$LY41) -> 98659.405 | MD41: =SUMIF($D$6:$LY$6,MD$3,$D41:$LY41) -> 98659.405 | ME41: =SUMIF($D$6:$LY$6,ME$3,$D41:$LY41) -> 98659.405 | MF41: =SUMIF($D$6:$LY$6,MF$3,$D41:$LY41) -> 98659.405 | MG41: =SUMIF($D$6:$LY$6,MG$3,$D41:$LY41) -> 98659.405 | MH41: =SUMIF($D$6:$LY$6,MH$3,$D41:$LY41) -> 98659.405 | MI41: =SUMIF($D$6:$LY$6,MI$3,$D41:$LY41) -> 98659.405 | ... MM41: =SUMIF($D$6:$LY$6,MM$3,$D41:$LY41) -> 98659.405 | MN41: =SUM(MB41:MM41) -> 1183912.9
B42: Joint Venture Personnel Cost Recharges | D42: 0 | E42: 0 | F42: 0 | G42: 0 | H42: 0 | I42: 0 | J42: 0 | K42: 0 | L42: 0 | M42: 0 | N42: 0 | O42: 0 | P42: =+SUBTOTAL(9,D42:O42) -> 0 | R42: 0 | S42: 0 | T42: 0 | U42: 0 | V42: 0 | W42: 0 | X42: 0 | Y42: 0 | Z42: 0 | AA42: 0 | AB42: 0 | AC42: 0 | AD42: =+SUBTOTAL(9,R42:AC42) -> 0 | AF42: 0 | AG42: 0 | AH42: 0 | AI42: 0 | AJ42: 0 | AK42: 0 | AL42: 0 | AM42: 0 | AN42: 0 | AO42: 0 | AP42: 0 | AQ42: 0 | AR42: =+SUBTOTAL(9,AF42:AQ42) -> 0 | AT42: 0 | AU42: 0 | AV42: 0 | AW42: 0 | AX42: 0 | AY42: 0 | AZ42: 0 | BA42: 0 | BB42: 0 | BC42: 0 | BD42: 0 | BE42: 0 | BF42: =+SUBTOTAL(9,AT42:BE42) -> 0 | BH42: 0 | BI42: 0 | BJ42: 0 | BK42: 0 | BL42: 0 | BM42: 0 | BN42: 0 | BO42: 0 | BP42: 0 | BQ42: 0 | BR42: 0 | BS42: 0 | BT42: =+SUBTOTAL(9,BH42:BS42) -> 0 | BV42: 0 | BW42: 0 | BX42: 0 | BY42: 0 | BZ42: 0 | CA42: 0 | CB42: 0 | CC42: 0 | CD42: 0 | CE42: 0 | CF42: 0 | CG42: 0 | CH42: =+SUBTOTAL(9,BV42:CG42) -> 0 | CJ42: 0 | CK42: 0 | CL42: 0 | CM42: 0 | CN42: 0 | CO42: 0 | CP42: 0 | CQ42: 0 | CR42: 0 | CS42: 0 | CT42: 0 | CU42: 0 | CV42: =+SUBTOTAL(9,CJ42:CU42) -> 0 | CX42: 0 | CY42: 0 | CZ42: 0 | DA42: 0 | DB42: 0 | DC42: 0 | DD42: 0 | DE42: 0 | DF42: 0 | DG42: 0 | DH42: 0 | DI42: 0 | DJ42: =+SUBTOTAL(9,CX42:DI42) -> 0 | DL42: 0 | DM42: 0 | DN42: 0 | DO42: 0 | DP42: 0 | DQ42: 0 | DR42: 0 | DS42: 0 | DT42: 0 | DU42: 0 | DV42: 0 | DW42: 0 | DX42: =+SUBTOTAL(9,DL42:DW42) -> 0 | DZ42: 0 | EA42: 0 | EB42: 0 | EC42: 0 | ED42: 0 | EE42: 0 | EF42: 0 | EG42: 0 | EH42: 0 | EI42: 0 | EJ42: 0 | EK42: 0 | EL42: =+SUBTOTAL(9,DZ42:EK42) -> 0 | EN42: 0 | EO42: 0 | EP42: 0 | EQ42: 0 | ER42: 0 | ES42: 0 | ET42: 0 | EU42: 0 | EV42: 0 | EW42: 0 | EX42: 0 | EY42: 0 | EZ42: =+SUBTOTAL(9,EN42:EY42) -> 0 | FB42: 0 | FC42: 0 | FD42: 0 | FE42: 0 | FF42: 0 | FG42: 0 | FH42: 0 | FI42: 0 | FJ42: 0 | FK42: 0 | FL42: 0 | FM42: 0 | FN42: =+SUBTOTAL(9,FB42:FM42) -> 0 | FP42: 0 | FQ42: 0 | FR42: 0 | FS42: 0 | FT42: 0 | FU42: 0 | FV42: 0 | FW42: 0 | FX42: 0 | FY42: 0 | FZ42: 0 | GA42: 0 | GB42: =+SUBTOTAL(9,FP42:GA42) -> 0 | GD42: 0 | GE42: 0 | GF42: 0 | GG42: 0 | GH42: 0 | GI42: 0 | GJ42: 0 | GK42: 0 | GL42: 0 | GM42: 0 | GN42: 0 | GO42: 0 | GP42: =+SUBTOTAL(9,GD42:GO42) -> 0 | GR42: 0 | GS42: 0 | GT42: 0 | GU42: 0 | GV42: 0 | GW42: 0 | GX42: 0 | GY42: 0 | GZ42: 0 | HA42: 0 | HB42: 0 | HC42: 0 | HD42: =+SUBTOTAL(9,GR42:HC42)*0 -> 0 | HF42: 0 | HG42: 0 | HH42: 0 | HI42: 0 | HJ42: 0 | HK42: 0 | HL42: 0 | HM42: 0 | HN42: 0 | HO42: 0 | HP42: 0 | HQ42: 0 | HR42: =+SUBTOTAL(9,HF42:HQ42) -> 0 | HT42: 0 | HU42: 0 | HV42: 0 | HW42: 0 | HX42: 0 | HY42: 0 | HZ42: 0 | IA42: 0 | IB42: 0 | IC42: 0 | ID42: 0 | IE42: 0 | IF42: =+SUBTOTAL(9,HT42:IE42) -> 0 | IH42: 0 | II42: 0 | IJ42: 0 | IK42: 0 | IL42: 0 | IM42: 0 | IN42: 0 | IO42: 0 | IP42: 0 | IQ42: 0 | IR42: 0 | IS42: 0 | IT42: =+SUBTOTAL(9,IH42:IS42) -> 0 | IV42: 0 | IW42: 0 | IX42: 0 | IY42: 0 | IZ42: 0 | JA42: 0 | JB42: 0 | JC42: 0 | JD42: 0 | JE42: 0 | JF42: 0 | JG42: 0 | JH42: =+SUBTOTAL(9,IV42:JG42) -> 0 | JJ42: 0 | JK42: 0 | JL42: 0 | JM42: 0 | JN42: 0 | JO42: 0 | JP42: 0 | JQ42: 0 | JR42: 0 | JS42: 0 | JT42: 0 | JU42: 0 | JV42: =+SUBTOTAL(9,JJ42:JU42) -> 0 | JX42: 0 | JY42: 0 | JZ42: 0 | KA42: 0 | KB42: 0 | KC42: 0 | KD42: 0 | KE42: 0 | KF42: 0 | KG42: 0 | KH42: 0 | KI42: 0 | KJ42: =+SUBTOTAL(9,JX42:KI42) -> 0 | KL42: 0 | KM42: 0 | KN42: 0 | KO42: 0 | KP42: 0 | KQ42: 0 | KR42: 0 | KS42: 0 | KT42: 0 | KU42: 0 | KV42: 0 | KW42: 0 | KX42: =+SUBTOTAL(9,KL42:KW42) -> 0 | KZ42: 0 | LA42: 0 | LB42: 0 | LC42: 0 | LD42: 0 | LE42: 0 | LF42: 0 | LG42: 0 | LH42: 0 | LI42: 0 | LJ42: 0 | LK42: 0 | LL42: =+SUBTOTAL(9,KZ42:LK42) -> 0 | LN42: 0 | LO42: 0 | LP42: 0 | LQ42: 0 | LR42: 0 | LS42: 0 | LT42: 0 | LU42: 0 | LV42: 0 | LW42: 0 | LX42: 0 | LY42: 0 | LZ42: =+SUBTOTAL(9,LN42:LY42) -> 0 | MB42: =SUMIF($D$6:$LY$6,MB$3,$D42:$LY42) -> 0 | MC42: =SUMIF($D$6:$LY$6,MC$3,$D42:$LY42) -> 0 | MD42: =SUMIF($D$6:$LY$6,MD$3,$D42:$LY42) -> 0 | ME42: =SUMIF($D$6:$LY$6,ME$3,$D42:$LY42) -> 0 | MF42: =SUMIF($D$6:$LY$6,MF$3,$D42:$LY42) -> 0 | MG42: =SUMIF($D$6:$LY$6,MG$3,$D42:$LY42) -> 0 | MH42: =SUMIF($D$6:$LY$6,MH$3,$D42:$LY42) -> 0 | MI42: =SUMIF($D$6:$LY$6,MI$3,$D42:$LY42) -> 0 | ... MM42: =SUMIF($D$6:$LY$6,MM$3,$D42:$LY42) -> 0 | MN42: =SUM(MB42:MM42) -> 0
B43: Intra-group Personnel Cost Recharges | D43: 0 | E43: 0 | F43: 0 | G43: 0 | H43: 0 | I43: 0 | J43: 0 | K43: 0 | L43: 0 | M43: 0 | N43: 0 | O43: 0 | P43: =+SUBTOTAL(9,D43:O43) -> 0 | R43: 0 | S43: 0 | T43: 0 | U43: 0 | V43: 0 | W43: 0 | X43: 0 | Y43: 0 | Z43: 0 | AA43: 0 | AB43: 0 | AC43: 0 | AD43: =+SUBTOTAL(9,R43:AC43) -> 0 | AF43: 0 | AG43: 0 | AH43: 0 | AI43: 0 | AJ43: 0 | AK43: 0 | AL43: 0 | AM43: 0 | AN43: 0 | AO43: 0 | AP43: 0 | AQ43: 0 | AR43: =+SUBTOTAL(9,AF43:AQ43) -> 0 | AT43: 0 | AU43: 0 | AV43: 0 | AW43: 0 | AX43: 0 | AY43: 0 | AZ43: 0 | BA43: 0 | BB43: 0 | BC43: 0 | BD43: 0 | BE43: 0 | BF43: =+SUBTOTAL(9,AT43:BE43) -> 0 | BH43: 0 | BI43: 0 | BJ43: 0 | BK43: 0 | BL43: 0 | BM43: 0 | BN43: 0 | BO43: 0 | BP43: 0 | BQ43: 0 | BR43: 0 | BS43: 0 | BT43: =+SUBTOTAL(9,BH43:BS43) -> 0 | BV43: 0 | BW43: 0 | BX43: 0 | BY43: 0 | BZ43: 0 | CA43: 0 | CB43: 0 | CC43: 0 | CD43: 0 | CE43: 0 | CF43: 0 | CG43: 0 | CH43: =+SUBTOTAL(9,BV43:CG43) -> 0 | CJ43: 0 | CK43: 0 | CL43: 0 | CM43: 0 | CN43: 0 | CO43: 0 | CP43: 0 | CQ43: 0 | CR43: 0 | CS43: 0 | CT43: 0 | CU43: 0 | CV43: =+SUBTOTAL(9,CJ43:CU43) -> 0 | CX43: 0 | CY43: 0 | CZ43: 0 | DA43: 0 | DB43: 0 | DC43: 0 | DD43: 0 | DE43: 0 | DF43: 0 | DG43: 0 | DH43: 0 | DI43: 0 | DJ43: =+SUBTOTAL(9,CX43:DI43) -> 0 | DL43: 0 | DM43: 0 | DN43: 0 | DO43: 0 | DP43: 0 | DQ43: 0 | DR43: 0 | DS43: 0 | DT43: 0 | DU43: 0 | DV43: 0 | DW43: 0 | DX43: =+SUBTOTAL(9,DL43:DW43) -> 0 | DZ43: 0 | EA43: 0 | EB43: 0 | EC43: 0 | ED43: 0 | EE43: 0 | EF43: 0 | EG43: 0 | EH43: 0 | EI43: 0 | EJ43: 0 | EK43: 0 | EL43: =+SUBTOTAL(9,DZ43:EK43) -> 0 | EN43: 0 | EO43: 0 | EP43: 0 | EQ43: 0 | ER43: 0 | ES43: 0 | ET43: 0 | EU43: 0 | EV43: 0 | EW43: 0 | EX43: 0 | EY43: 0 | EZ43: =+SUBTOTAL(9,EN43:EY43) -> 0 | FB43: 0 | FC43: 0 | FD43: 0 | FE43: 0 | FF43: 0 | FG43: 0 | FH43: 0 | FI43: 0 | FJ43: 0 | FK43: 0 | FL43: 0 | FM43: 0 | FN43: =+SUBTOTAL(9,FB43:FM43) -> 0 | FP43: 0 | FQ43: 0 | FR43: 0 | FS43: 0 | FT43: 0 | FU43: 0 | FV43: 0 | FW43: 0 | FX43: 0 | FY43: 0 | FZ43: 0 | GA43: 0 | GB43: =+SUBTOTAL(9,FP43:GA43) -> 0 | GD43: 0 | GE43: 0 | GF43: 0 | GG43: 0 | GH43: 0 | GI43: 0 | GJ43: 0 | GK43: 0 | GL43: 0 | GM43: 0 | GN43: 0 | GO43: 0 | GP43: =+SUBTOTAL(9,GD43:GO43) -> 0 | GR43: 0 | GS43: 0 | GT43: 0 | GU43: 0 | GV43: 0 | GW43: 0 | GX43: 0 | GY43: 0 | GZ43: 0 | HA43: 0 | HB43: 0 | HC43: 0 | HD43: =+SUBTOTAL(9,GR43:HC43)*0 -> 0 | HF43: 0 | HG43: 0 | HH43: 0 | HI43: 0 | HJ43: 0 | HK43: 0 | HL43: 0 | HM43: 0 | HN43: 0 | HO43: 0 | HP43: 0 | HQ43: 0 | HR43: =+SUBTOTAL(9,HF43:HQ43) -> 0 | HT43: 0 | HU43: 0 | HV43: 0 | HW43: 0 | HX43: 0 | HY43: 0 | HZ43: 0 | IA43: 0 | IB43: 0 | IC43: 0 | ID43: 0 | IE43: 0 | IF43: =+SUBTOTAL(9,HT43:IE43) -> 0 | IH43: 0 | II43: 0 | IJ43: 0 | IK43: 0 | IL43: 0 | IM43: 0 | IN43: 0 | IO43: 0 | IP43: 0 | IQ43: 0 | IR43: 0 | IS43: 0 | IT43: =+SUBTOTAL(9,IH43:IS43) -> 0 | IV43: 0 | IW43: 0 | IX43: 0 | IY43: 0 | IZ43: 0 | JA43: 0 | JB43: 0 | JC43: 0 | JD43: 0 | JE43: 0 | JF43: 0 | JG43: 0 | JH43: =+SUBTOTAL(9,IV43:JG43) -> 0 | JJ43: 0 | JK43: 0 | JL43: 0 | JM43: 0 | JN43: 0 | JO43: 0 | JP43: 0 | JQ43: 0 | JR43: 0 | JS43: 0 | JT43: 0 | JU43: 0 | JV43: =+SUBTOTAL(9,JJ43:JU43) -> 0 | JX43: 0 | JY43: 0 | JZ43: 0 | KA43: 0 | KB43: 0 | KC43: 0 | KD43: 0 | KE43: 0 | KF43: 0 | KG43: 0 | KH43: 0 | KI43: 0 | KJ43: =+SUBTOTAL(9,JX43:KI43) -> 0 | KL43: 0 | KM43: 0 | KN43: 0 | KO43: 0 | KP43: 0 | KQ43: 0 | KR43: 0 | KS43: 0 | KT43: 0 | KU43: 0 | KV43: 0 | KW43: 0 | KX43: =+SUBTOTAL(9,KL43:KW43) -> 0 | KZ43: 0 | LA43: 0 | LB43: 0 | LC43: 0 | LD43: 0 | LE43: 0 | LF43: 0 | LG43: 0 | LH43: 0 | LI43: 0 | LJ43: 0 | LK43: 0 | LL43: =+SUBTOTAL(9,KZ43:LK43) -> 0 | LN43: 0 | LO43: 0 | LP43: 0 | LQ43: 0 | LR43: 0 | LS43: 0 | LT43: 0 | LU43: 0 | LV43: 0 | LW43: 0 | LX43: 0 | LY43: 0 | LZ43: =+SUBTOTAL(9,LN43:LY43) -> 0 | MB43: =SUMIF($D$6:$LY$6,MB$3,$D43:$LY43) -> 0 | MC43: =SUMIF($D$6:$LY$6,MC$3,$D43:$LY43) -> 0 | MD43: =SUMIF($D$6:$LY$6,MD$3,$D43:$LY43) -> 0 | ME43: =SUMIF($D$6:$LY$6,ME$3,$D43:$LY43) -> 0 | MF43: =SUMIF($D$6:$LY$6,MF$3,$D43:$LY43) -> 0 | MG43: =SUMIF($D$6:$LY$6,MG$3,$D43:$LY43) -> 0 | MH43: =SUMIF($D$6:$LY$6,MH$3,$D43:$LY43) -> 0 | MI43: =SUMIF($D$6:$LY$6,MI$3,$D43:$LY43) -> 0 | ... MM43: =SUMIF($D$6:$LY$6,MM$3,$D43:$LY43) -> 0 | MN43: =SUM(MB43:MM43) -> 0
B45: TOTAL PERSONNEL EXPENSES | D45: =SUM(D33:D44) -> 3401211.1 | E45: =SUM(E33:E44) -> 3243996.1 | F45: =SUM(F33:F44) -> 3269496.1 | G45: =SUM(G33:G44) -> 3243996.1 | H45: =SUM(H33:H44) -> 3243996.1 | I45: =SUM(I33:I44) -> 3243996.1 | J45: =SUM(J33:J44) -> 3254121.1 | K45: =SUM(K33:K44) -> 3359121.1 | ... O45: =SUM(O33:O44) -> 3280085.4 | P45: =+SUBTOTAL(9,D45:O45) -> 39528182 | R45: =SUM(R33:R44) -> 281435.08 | S45: =SUM(S33:S44) -> 265730.08 | T45: =SUM(T33:T44) -> 268280.08 | U45: =SUM(U33:U44) -> 265730.08 | V45: =SUM(V33:V44) -> 265730.08 | W45: =SUM(W33:W44) -> 265730.08 | X45: =SUM(X33:X44) -> 266581.08 | Y45: =SUM(Y33:Y44) -> 277081.08 | ... AC45: =SUM(AC33:AC44) -> 269173.93 | AD45: =+SUBTOTAL(9,R45:AC45) -> 3247864.8 | AF45: =SUM(AF33:AF44) -> 283218.08 | AG45: =SUM(AG33:AG44) -> 267513.08 | AH45: =SUM(AH33:AH44) -> 270063.08 | AI45: =SUM(AI33:AI44) -> 267513.08 | AJ45: =SUM(AJ33:AJ44) -> 267513.08 | AK45: =SUM(AK33:AK44) -> 267513.08 | AL45: =SUM(AL33:AL44) -> 268364.08 | AM45: =SUM(AM33:AM44) -> 278864.08 | ... AQ45: =SUM(AQ33:AQ44) -> 270956.93 | AR45: =+SUBTOTAL(9,AF45:AQ45) -> 3269260.8 | AT45: =SUM(AT33:AT44) -> 804423.38 | AU45: =SUM(AU33:AU44) -> 793953.38 | AV45: =SUM(AV33:AV44) -> 795653.38 | AW45: =SUM(AW33:AW44) -> 793953.38 | AX45: =SUM(AX33:AX44) -> 793953.38 | AY45: =SUM(AY33:AY44) -> 793953.38 | AZ45: =SUM(AZ33:AZ44) -> 795186.38 | BA45: =SUM(BA33:BA44) -> 802186.38 | ... BE45: =SUM(BE33:BE44) -> 796914.96 | BF45: =+SUBTOTAL(9,AT45:BE45) -> 9570837.2 | BH45: =SUM(BH33:BH44) -> 4644493.4 | BI45: =SUM(BI33:BI44) -> 4565638.4 | BJ45: =SUM(BJ33:BJ44) -> 4578388.4 | BK45: =SUM(BK33:BK44) -> 4565638.4 | BL45: =SUM(BL33:BL44) -> 4565638.4 | BM45: =SUM(BM33:BM44) -> 4565638.4 | BN45: =SUM(BN33:BN44) -> 4571484.4 | BO45: =SUM(BO33:BO44) -> 4623984.4 | ... BS45: =SUM(BS33:BS44) -> 4584448.7 | BT45: =+SUBTOTAL(9,BH45:BS45) -> 55091656 | BV45: =SUM(BV33:BV44) -> 712393.69 | BW45: =SUM(BW33:BW44) -> 705658.69 | BX45: =SUM(BX33:BX44) -> 706508.69 | BY45: =SUM(BY33:BY44) -> 705658.69 | BZ45: =SUM(BZ33:BZ44) -> 705658.69 | CA45: =SUM(CA33:CA44) -> 705658.69 | CB45: =SUM(CB33:CB44) -> 706571.69 | CC45: =SUM(CC33:CC44) -> 711571.69 | ... CG45: =SUM(CG33:CG44) -> 707435.98 | CH45: =+SUBTOTAL(9,BV45:CG45) -> 8494381.6 | CJ45: =SUM(CJ33:CJ44) -> 2032705.6 | CK45: =SUM(CK33:CK44) -> 1975120.6 | CL45: =SUM(CL33:CL44) -> 1984470.6 | CM45: =SUM(CM33:CM44) -> 1975120.6 | CN45: =SUM(CN33:CN44) -> 1975120.6 | CO45: =SUM(CO33:CO44) -> 1975120.6 | CP45: =SUM(CP33:CP44) -> 1978976.6 | CQ45: =SUM(CQ33:CQ44) -> 2017476.6 | ... CU45: =SUM(CU33:CU44) -> 1988483.8 | CV45: =+SUBTOTAL(9,CJ45:CU45) -> 23922576 | CX45: =SUM(CX33:CX44) -> 4530729.4 | CY45: =SUM(CY33:CY44) -> 4376499.4 | CZ45: =SUM(CZ33:CZ44) -> 4401149.4 | DA45: =SUM(DA33:DA44) -> 4376499.4 | DB45: =SUM(DB33:DB44) -> 4376499.4 | DC45: =SUM(DC33:DC44) -> 4376499.4 | DD45: =SUM(DD33:DD44) -> 4387500.4 | DE45: =SUM(DE33:DE44) -> 4491250.4 | ... DI45: =SUM(DI33:DI44) -> 4412600.4 | DJ45: =+SUBTOTAL(9,CX45:DI45) -> 53110679 | DL45: =SUM(DL33:DL44) -> 2647058.4 | DM45: =SUM(DM33:DM44) -> 2499398.4 | DN45: =SUM(DN33:DN44) -> 2523198.4 | DO45: =SUM(DO33:DO44) -> 2499398.4 | DP45: =SUM(DP33:DP44) -> 2499398.4 | DQ45: =SUM(DQ33:DQ44) -> 2499398.4 | DR45: =SUM(DR33:DR44) -> 2506897.4 | DS45: =SUM(DS33:DS44) -> 2605647.4 | ... DW45: =SUM(DW33:DW44) -> 2531097.4 | DX45: =+SUBTOTAL(9,DL45:DW45) -> 30542185 | DZ45: =SUM(DZ33:DZ44) -> 392311.69 | EA45: =SUM(EA33:EA44) -> 387076.69 | EB45: =SUM(EB33:EB44) -> 387926.69 | EC45: =SUM(EC33:EC44) -> 387076.69 | ED45: =SUM(ED33:ED44) -> 387076.69 | EE45: =SUM(EE33:EE44) -> 387076.69 | EF45: =SUM(EF33:EF44) -> 387695.69 | EG45: =SUM(EG33:EG44) -> 391195.69 | ... EK45: =SUM(EK33:EK44) -> 388559.98 | EL45: =+SUBTOTAL(9,DZ45:EK45) -> 4666633.6 | EN45: =SUM(EN33:EN44) -> 562808.38 | EO45: =SUM(EO33:EO44) -> 552338.38 | EP45: =SUM(EP33:EP44) -> 554038.38 | EQ45: =SUM(EQ33:EQ44) -> 552338.38 | ER45: =SUM(ER33:ER44) -> 552338.38 | ES45: =SUM(ES33:ES44) -> 552338.38 | ET45: =SUM(ET33:ET44) -> 553571.38 | EU45: =SUM(EU33:EU44) -> 560571.38 | ... EY45: =SUM(EY33:EY44) -> 555299.96 | EZ45: =+SUBTOTAL(9,EN45:EY45) -> 6671457.2 | FB45: =SUM(FB33:FB44) -> 103696.69 | FC45: =SUM(FC33:FC44) -> 98461.692 | FD45: =SUM(FD33:FD44) -> 99311.692 | FE45: =SUM(FE33:FE44) -> 98461.692 | FF45: =SUM(FF33:FF44) -> 98461.692 | FG45: =SUM(FG33:FG44) -> 98461.692 | FH45: =SUM(FH33:FH44) -> 98781.692 | FI45: =SUM(FI33:FI44) -> 102281.69 | ... FM45: =SUM(FM33:FM44) -> 99645.978 | FN45: =+SUBTOTAL(9,FB45:FM45) -> 1201459.6 | FP45: =SUM(FP33:FP44) -> 1672302.8 | FQ45: =SUM(FQ33:FQ44) -> 1630422.8 | FR45: =SUM(FR33:FR44) -> 1637222.8 | FS45: =SUM(FS33:FS44) -> 1630422.8 | FT45: =SUM(FT33:FT44) -> 1630422.8 | FU45: =SUM(FU33:FU44) -> 1630422.8 | FV45: =SUM(FV33:FV44) -> 1634368.8 | FW45: =SUM(FW33:FW44) -> 1662368.8 | ... GA45: =SUM(GA33:GA44) -> 1641318.8 | GB45: =+SUBTOTAL(9,FP45:GA45) -> 19732780 | GD45: =SUM(GD33:GD44) -> 841996.69 | GE45: =SUM(GE33:GE44) -> 841996.69 | GF45: =SUM(GF33:GF44) -> 841996.69 | GG45: =SUM(GG33:GG44) -> 841996.69 | GH45: =SUM(GH33:GH44) -> 841996.69 | GI45: =SUM(GI33:GI44) -> 841996.69 | GJ45: =SUM(GJ33:GJ44) -> 841996.69 | GK45: =SUM(GK33:GK44) -> 841996.69 | ... GO45: =SUM(GO33:GO44) -> 841960.98 | GP45: =+SUBTOTAL(9,GD45:GO45) -> 10103925 | GR45: =SUM(GR33:GR44) -> -1857108.3 | GS45: =SUM(GS33:GS44) -> -1857108.3 | GT45: =SUM(GT33:GT44) -> -1806883.3 | GU45: =SUM(GU33:GU44) -> -1806883.3 | GV45: =SUM(GV33:GV44) -> -1806883.3 | GW45: =SUM(GW33:GW44) -> -1806883.3 | GX45: =SUM(GX33:GX44) -> -1806883.3 | GY45: =SUM(GY33:GY44) -> -1806883.3 | ... HC45: =SUM(HC33:HC44) -> -1806883.3 | HD45: =+SUBTOTAL(9,GR45:HC45)*0 -> 0 | HF45: =SUM(HF33:HF44) -> 736181.77 | HG45: =SUM(HG33:HG44) -> 715241.77 | HH45: =SUM(HH33:HH44) -> 718641.77 | HI45: =SUM(HI33:HI44) -> 715241.77 | HJ45: =SUM(HJ33:HJ44) -> 715241.77 | HK45: =SUM(HK33:HK44) -> 715241.77 | HL45: =SUM(HL33:HL44) -> 717005.77 | HM45: =SUM(HM33:HM44) -> 731005.77 | ... HQ45: =SUM(HQ33:HQ44) -> 720462.91 | HR45: =+SUBTOTAL(9,HF45:HQ45) -> 8665482.4 | HT45: =SUM(HT33:HT44) -> 191070.69 | HU45: =SUM(HU33:HU44) -> 185835.69 | HV45: =SUM(HV33:HV44) -> 186685.69 | HW45: =SUM(HW33:HW44) -> 185835.69 | HX45: =SUM(HX33:HX44) -> 185835.69 | HY45: =SUM(HY33:HY44) -> 185835.69 | HZ45: =SUM(HZ33:HZ44) -> 186189.69 | IA45: =SUM(IA33:IA44) -> 189689.69 | ... IE45: =SUM(IE33:IE44) -> 187053.98 | IF45: =+SUBTOTAL(9,HT45:IE45) -> 2250151.6 | IH45: =SUM(IH33:IH44) -> 614659.69 | II45: =SUM(II33:II44) -> 609424.69 | IJ45: =SUM(IJ33:IJ44) -> 610274.69 | IK45: =SUM(IK33:IK44) -> 609424.69 | IL45: =SUM(IL33:IL44) -> 609424.69 | IM45: =SUM(IM33:IM44) -> 609424.69 | IN45: =SUM(IN33:IN44) -> 610337.69 | IO45: =SUM(IO33:IO44) -> 613837.69 | ... IS45: =SUM(IS33:IS44) -> 611201.98 | IT45: =+SUBTOTAL(9,IH45:IS45) -> 7336573.6 | IV45: =SUM(IV33:IV44) -> 1824499.8 | IW45: =SUM(IW33:IW44) -> 1787854.8 | IX45: =SUM(IX33:IX44) -> 1793804.8 | IY45: =SUM(IY33:IY44) -> 1787854.8 | IZ45: =SUM(IZ33:IZ44) -> 1787854.8 | JA45: =SUM(JA33:JA44) -> 1787854.8 | JB45: =SUM(JB33:JB44) -> 1791314.8 | JC45: =SUM(JC33:JC44) -> 1815814.8 | ... JG45: =SUM(JG33:JG44) -> 1797364.8 | JH45: =+SUBTOTAL(9,IV45:JG45) -> 21601013 | JJ45: =SUM(JJ33:JJ44) -> 2486401.6 | JK45: =SUM(JK33:JK44) -> 2416936.6 | JL45: =SUM(JL33:JL44) -> 2427986.6 | JM45: =SUM(JM33:JM44) -> 2416936.6 | JN45: =SUM(JN33:JN44) -> 2416936.6 | JO45: =SUM(JO33:JO44) -> 2416936.6 | JP45: =SUM(JP33:JP44) -> 2421036.6 | JQ45: =SUM(JQ33:JQ44) -> 2467286.6 | ... JU45: =SUM(JU33:JU44) -> 2432343.8 | JV45: =+SUBTOTAL(9,JJ45:JU45) -> 29261262 | JX45: =SUM(JX33:JX44) -> 1326379.5 | JY45: =SUM(JY33:JY44) -> 1300039.5 | JZ45: =SUM(JZ33:JZ44) -> 1304289.5 | KA45: =SUM(KA33:KA44) -> 1300039.5 | KB45: =SUM(KB33:KB44) -> 1300039.5 | KC45: =SUM(KC33:KC44) -> 1300039.5 | KD45: =SUM(KD33:KD44) -> 1302147.5 | KE45: =SUM(KE33:KE44) -> 1319647.5 | ... KI45: =SUM(KI33:KI44) -> 1306468.9 | KJ45: =+SUBTOTAL(9,JX45:KI45) -> 15702583 | KL45: =SUM(KL33:KL44) -> 219448.38 | KM45: =SUM(KM33:KM44) -> 209143.38 | KN45: =SUM(KN33:KN44) -> 210843.38 | KO45: =SUM(KO33:KO44) -> 209143.38 | KP45: =SUM(KP33:KP44) -> 209143.38 | KQ45: =SUM(KQ33:KQ44) -> 209143.38 | KR45: =SUM(KR33:KR44) -> 209994.38 | KS45: =SUM(KS33:KS44) -> 216994.38 | ... KW45: =SUM(KW33:KW44) -> 211722.96 | KX45: =+SUBTOTAL(9,KL45:KW45) -> 2550656.2 | KZ45: =SUM(KZ33:KZ44) -> 200498.69 | LA45: =SUM(LA33:LA44) -> 195098.69 | LB45: =SUM(LB33:LB44) -> 195948.69 | LC45: =SUM(LC33:LC44) -> 195098.69 | LD45: =SUM(LD33:LD44) -> 195098.69 | LE45: =SUM(LE33:LE44) -> 195098.69 | LF45: =SUM(LF33:LF44) -> 195098.69 | LG45: =SUM(LG33:LG44) -> 198598.69 | ... LK45: =SUM(LK33:LK44) -> 195962.98 | LL45: =+SUBTOTAL(9,KZ45:LK45) -> 2359352.6 | LN45: =SUM(LN33:LN44) -> 0 | LO45: =SUM(LO33:LO44) -> 0 | LP45: =SUM(LP33:LP44) -> 0 | LQ45: =SUM(LQ33:LQ44) -> 0 | LR45: =SUM(LR33:LR44) -> 0 | LS45: =SUM(LS33:LS44) -> 0 | LT45: =SUM(LT33:LT44) -> 0 | LU45: =SUM(LU33:LU44) -> 0 | ... LY45: =SUM(LY33:LY44) -> 0 | LZ45: =+SUBTOTAL(9,LN45:LY45) -> 0 | MB45: =SUM(MB33:MB44) -> 28652816 | MC45: =SUM(MC33:MC44) -> 27766271 | MD45: =SUM(MD33:MD44) -> 27959296 | ME45: =SUM(ME33:ME44) -> 27816496 | MF45: =SUM(MF33:MF44) -> 27816496 | MG45: =SUM(MG33:MG44) -> 27816496 | MH45: =SUM(MH33:MH44) -> 27878339 | MI45: =SUM(MI33:MI44) -> 28471589 | ... MN45: =SUM(MN33:MN44) -> 3.370979e+08
GD46: =+GD45+GR45 -> -1015111.6 | GE46: =+GD46/83.92 -> -12096.182 | GF46: =+GE46-'[1]Actual YTD feb'!KL54 -> -20459.144 | MC46: =+MC45/83.92 -> 330865.96
B47: OFFICE EXPENSES
